Workbook
Name Kurs: 'Tumpukan Tool AI'!$D$7
Name PPN_PMSE: 'Tumpukan Tool AI'!$D$8
Name Buffer_Kurs: 'Tumpukan Tool AI'!$D$9
Name GrossUp_PPh26: 'Tumpukan Tool AI'!$D$10
Name Hari_Bulan: 'Tumpukan Tool AI'!$D$11
Name Order_Hari_F0: 'Tumpukan Tool AI'!$D$12
Name Order_Hari_F1: 'Tumpukan Tool AI'!$D$13
Name Order_Hari_F2: 'Tumpukan Tool AI'!$D$14
Name Tiket_Per1000_Th1: 'Tumpukan Tool AI'!$D$15
Name Tiket_Per1000_Th2: 'Tumpukan Tool AI'!$D$16
Name Deflection_CS: 'Tumpukan Tool AI'!$D$17
Name Verif_F0: 'Tumpukan Tool AI'!$D$18
Name Verif_F1: 'Tumpukan Tool AI'!$D$19
Name Verif_F2: 'Tumpukan Tool AI'!$D$20
Name Merchant_F0: 'Tumpukan Tool AI'!$D$21
Name Merchant_F1: 'Tumpukan Tool AI'!$D$22
Name Merchant_F2: 'Tumpukan Tool AI'!$D$23
Name Harga_LLM_In: 'Tumpukan Tool AI'!$D$24
Name Harga_LLM_Out: 'Tumpukan Tool AI'!$D$25
Name Faktor_Token: 'Tumpukan Tool AI'!$D$26
Name Tarif_KYC: 'Tumpukan Tool AI'!$D$27
Name Tarif_WA_Utility: 'Tumpukan Tool AI'!$D$28
Name Porsi_WA: 'Tumpukan Tool AI'!$D$29
Name Faktor_Tool_C: 'Tumpukan Tool AI'!$D$30
Name Faktor_Sembunyi_C: 'Tumpukan Tool AI'!$D$31
Name AI_Satu_Kali: 'Tumpukan Tool AI'!$H$90
Name AI_Var_F0: 'Tumpukan Tool AI'!$H$94
Name AI_Var_F1: 'Tumpukan Tool AI'!$I$94
Name AI_Var_F2: 'Tumpukan Tool AI'!$J$94
Name AI_Tetap_F0: 'Tumpukan Tool AI'!$H$95
Name AI_Tetap_F1: 'Tumpukan Tool AI'!$I$95
Name AI_Tetap_F2: 'Tumpukan Tool AI'!$J$95
Name AI_Sembunyi_F0: 'Tumpukan Tool AI'!$H$96
Name AI_Sembunyi_F1: 'Tumpukan Tool AI'!$I$96
Name AI_Sembunyi_F2: 'Tumpukan Tool AI'!$J$96
Name AI_B_F0: 'Tumpukan Tool AI'!$H$97
Name AI_B_F1: 'Tumpukan Tool AI'!$I$97
Name AI_B_F2: 'Tumpukan Tool AI'!$J$97
Name AI_C_F0: 'Tumpukan Tool AI'!$H$98
Name AI_C_F1: 'Tumpukan Tool AI'!$I$98
Name AI_C_F2: 'Tumpukan Tool AI'!$J$98
Name HC_A_F2: 'Skenario A B C'!$J$44
Name T24_A: 'Perbandingan 24 Bulan'!$D$167
Name T24_B: 'Perbandingan 24 Bulan'!$D$168
Name T24_C: 'Perbandingan 24 Bulan'!$D$169

Sheet Ringkasan Eksekutif
A1: AntarKita - Analisis AI vs SDM: Ringkasan Eksekutif
A2: Disusun 7 September 2026. Turunan dari AntarKita-Model-Biaya-SDM.xlsx v1.0, AntarKita-Manual-Organisasi-dan-SOP.docx, dan DESAIN-ORGANISASI.md.
A3: STATUS: USULAN ANALIS. Tidak satu pun pemangkasan posisi atau pembelian tool pada berkas ini telah diputuskan. Kewenangan ada pada Dewan Komisaris (DESAIN-ORGANISASI 6).
A5: A. REKOMENDASI
A6: 1. Ambil Skenario B (Hibrida): headcount Fase 2 turun dari 42 menjadi 30 orang, dengan tumpukan AI yang dibangun sendiri di atas API LLM, bukan dibeli per-resolusi.
A7: 2. JANGAN mengotomasi pada Fase 0 dan Fase 1. Pada dua fase itu otomasi LEBIH MAHAL daripada manusia karena biaya implementasi terjadi lebih dulu daripada penghematannya. Mulai bangun pada kuartal 2, panen pada kuartal 5.
A8: 3. Penghematan yang jujur adalah sekitar 12-14% biaya terkait SDM, bukan 40-50%. Sebagian besar biaya AntarKita melekat pada peran lapangan, direksi, dan kepatuhan yang TIDAK dapat diotomasi.
A9: 4. Tolak Skenario C. Ia menghapus Treasury/Settlement Officer (melanggar pemisahan tugas DESAIN 6 dan SOP-07) dan menipiskan cakupan shift kanal darurat (SOP-05). Penghematannya nyata, tetapi harganya adalah temuan pada uji tuntas investor.
A11: B. PERBANDINGAN TIGA SKENARIO
A12: Ukuran | B12: Skenario A - Semua manusia | C12: Skenario B - Hibrida (rekomendasi) | D12: Skenario C - AI-maksimal | E12: Sumber angka
A13: Headcount Fase 0 (bulan 1-3) | B13: ='Skenario A B C'!F49 | C13: ='Skenario A B C'!G49 | D13: ='Skenario A B C'!H49 | E13: Lembar 'Skenario A B C'
A14: Headcount Fase 1 (bulan 4-12) | B14: ='Skenario A B C'!I49 | C14: ='Skenario A B C'!J49 | D14: ='Skenario A B C'!K49 | E14: Lembar 'Skenario A B C'
A15: Headcount Fase 2 (bulan 13-24) | B15: ='Skenario A B C'!L49 | C15: ='Skenario A B C'!M49 | D15: ='Skenario A B C'!N49 | E15: Lembar 'Skenario A B C'
A16: Biaya SDM per bulan Fase 2 (Rp) | B16: ='Skenario A B C'!L50 | C16: ='Skenario A B C'!M50 | D16: ='Skenario A B C'!N50 | E16: Model biaya SDM lama (A) & rumus hidup
A17: Biaya non-gaji melekat SDM per bulan Fase 2 (Rp) | B17: ='Skenario A B C'!L51 | C17: ='Skenario A B C'!M51 | D17: ='Skenario A B C'!N51 | E17: Lembar 'Biaya Non-Gaji' model lama
A18: Biaya AI per bulan Fase 2 (Rp) | B18: ='Skenario A B C'!L52 | C18: ='Skenario A B C'!M52 | D18: ='Skenario A B C'!N52 | E18: Lembar 'Tumpukan Tool AI'
A19: TOTAL per bulan Fase 2 (Rp) | B19: ='Skenario A B C'!L53 | C19: ='Skenario A B C'!M53 | D19: ='Skenario A B C'!N53 | E19: Jumlah tiga baris di atas
A20: TOTAL KUMULATIF 24 BULAN (Rp) | B20: =T24_A | C20: =T24_B | D20: =T24_C | E20: Lembar 'Perbandingan 24 Bulan'
A21: Penghematan 24 bulan vs A (Rp) | B21: =0 | C21: =T24_A-T24_B | D21: =T24_A-T24_C | E21: Turunan
A22: Penghematan 24 bulan vs A (%) | B22: =0 | C22: =(T24_A-T24_B)/T24_A | D22: =(T24_A-T24_C)/T24_A | E22: Turunan
A23: Pengurangan headcount bulan 24 (orang) | B23: =0 | C23: ='Perbandingan 24 Bulan'!AA130-'Perbandingan 24 Bulan'!AA131 | D23: ='Perbandingan 24 Bulan'!AA130-'Perbandingan 24 Bulan'!AA132 | E23: Turunan
A24: Titik impas (bulan kumulatif mulai lebih murah dari A) | B24: - | C24: =IFERROR(MATCH(TRUE,INDEX('Perbandingan 24 Bulan'!D153:AA153>0,0),0),"tidak tercapai") | D24: =IFERROR(MATCH(TRUE,INDEX('Perbandingan 24 Bulan'!D154:AA154>0,0),0),"tidak tercapai") | E24: Lembar 'Perbandingan 24 Bulan'
A26: C. APA YANG PECAH LEBIH DULU DAN KAPAN (pada Skenario B yang direkomendasikan)
A27: Urutan | B27: Titik pecah | C27: Pemicu berangka | D27: Perkiraan waktu | E27: Peringatan dini yang harus dipasang | F27: Mitigasi
A28: 1 | B28: Kanal darurat 24 jam (SOP-05) kehilangan penutup shift | C28: Dengan 2 CS Agent Pekanbaru + 1 Padang, shift ketiga di salah satu kota ditutup lintas kota. Satu orang sakit atau resign = shift kosong. | D28: Kapan saja setelah bulan 14 - risiko harian, bukan risiko volume | E28: Persentase peringatan darurat ditangani <=15 menit turun di bawah 95% (target Bab 5) | F28: Anggarkan 1 CS Agent cadangan lintas kota; jangan pangkas di bawah 3 total.
A29: 2 | B29: Agen CS otomatis kewalahan pada kategori di luar naskah baku | C29: Pada 2.400 order/hari, 1.584 tiket/bulan, eskalasi 634/bulan = 21/hari. Aman. Yang pecah lebih dulu adalah KERAGAMAN kasus, bukan jumlahnya: peluncuran AntarTravel/AntarBox memunculkan kategori tiket yang belum ada di basis pengetahuan. | D29: Bulan ke-2 setelah setiap peluncuran layanan baru | E29: Tingkat tiket dibuka ulang naik melewati 8%; deflection turun di bawah 50% | F29: Basis pengetahuan wajib diperbarui SEBELUM rilis layanan baru - masukkan sebagai gerbang di SOP-11.
A30: 3 | B30: Pemelihara otomasi menjadi titik tunggal kegagalan | C30: Satu Backend Engineer (Mid) yang dialihfungsikan memelihara 13 komponen AI sekaligus mengerjakan fitur. Beban lebih dari 1 FTE sejak bulan 16. | D30: Bulan 16-18 | E30: Antrean cacat otomasi > 5 terbuka lebih dari 2 pekan | F30: Kontraktor 0,5 FTE sudah dianggarkan (H-1); naikkan ke 1,0 FTE pada bulan 16 atau kembalikan 1 Backend Mid.
A31: 4 | B31: Beban kepatuhan UU PDP melampaui kapasitas DPO merangkap | C31: Head of Legal & Compliance merangkap DPO sudah memikul perizinan, kontrak, dan hak subjek data. Otomasi menambah DPIA berkala, register keputusan otomatis (Pasal 10), dan uji transfer data (Pasal 56). | D31: Bulan 15-18, atau seketika bila ada insiden data | E31: Permintaan hak subjek data lewat SLA 14 hari; DPIA fitur baru tertunda >1 kuartal | F31: 0,2 FTE sudah dianggarkan (H-3); bila lewat, pisahkan DPO dari Head of Legal - ini konsekuensi biaya, bukan pilihan.
A32: 5 | B32: Gerbang rilis tanpa QA manusia meloloskan cacat pada alur uang | C32: QA Engineer dihapus; hak veto pindah ke Engineering Manager yang juga menulis kode. Pemisahan penulis-penguji hilang. | D32: Rilis besar pertama yang menyentuh dompet setelah bulan 13 | E32: Proporsi rilis tanpa cacat kritikal turun; simulasi e2e tidak 100% lolos | F32: Aturan mutlak: perubahan yang menyentuh dompet WAJIB ditinjau Backend Engineer Senior yang bukan penulisnya. Tuliskan di SOP-11.
A34: D. PERAN YANG TIDAK BOLEH DIOTOMASI (dengan dasarnya)
A35: Peran | B35: Dasar | C35: Jenis dasar
A36: JD-22 Head of Legal & Compliance merangkap DPO | B36: UU 27/2022 Pasal 53 mewajibkan penunjukan pejabat/petugas yang menjalankan fungsi pelindungan data pribadi; Putusan MK 151/PUU-XXII/2024 memperluas tafsirnya. Jabatan melekat pada orang. | F36: Hukum eksplisit
A37: JD-01 Direktur Utama, JD-02 CTO, JD-03 COO, JD-19 Head of Finance | B37: Organ perseroan dan penanggung jawab laporan keuangan serta pajak. Menandatangani perjanjian dan memikul akuntabilitas yang tidak dapat dialihkan ke sistem. | F37: Hukum & tata kelola
A38: JD-18 Trust & Safety Officer - keputusan penangguhan akun | B38: UU 27/2022 Pasal 10: subjek data berhak keberatan atas keputusan yang HANYA didasarkan pemrosesan otomatis dan berdampak signifikan. Penangguhan mitra menghilangkan penghasilan - jelas berdampak signifikan. | F38: Hukum eksplisit
A39: JD-17 CS Agent - penerimaan peringatan darurat | B39: SOP-05: peringatan darurat wajib ditangani manusia dalam 15 menit, kanal aktif 24 jam. CS Agent adalah penerima pertama di luar jam Trust & Safety. | F39: Keselamatan jiwa
A40: JD-21 Treasury/Settlement Officer | B40: DESAIN-ORGANISASI 6 dan SOP-07: penyetuju != pelaksana != perekonsiliasi. Mesin boleh merekonsiliasi; penanggung jawab yang menahan tutup buku harus orang yang berbeda. | F40: Kontrol internal wajib
A41: JD-13 City Manager, JD-14 Ops Supervisor, JD-15 Partner Acquisition, JD-25 Merchant Acquisition | B41: Rekrutmen dan pembinaan mitra, pemeriksaan fisik kendaraan, penanganan kecelakaan, hubungan pemerintah daerah dan pengelola pasar, negosiasi merchant. Risiko R-07 menjadikan pasokan mitra sebagai risiko dengan kemungkinan TERTINGGI pada register risiko - ini posisi terakhir yang boleh dipangkas. | F41: Sifat pekerjaan lapangan

Sheet Tumpukan Tool AI
A1: AntarKita - Tumpukan Tool AI, Volume, dan Biaya Bulanan
A2: Disusun 7 September 2026. Seluruh harga penyedia DIVERIFIKASI pada tanggal tersebut - lihat lembar 'Sumber & Catatan' [S-62] s.d. [S-77]. Angka yang tidak dapat diverifikasi ditandai [ASUMSI] pada kolom Status. Sel berlatar kuning adalah input yang boleh diubah pemilik.
A3: USULAN ANALIS - BUKAN KEPUTUSAN. Seluruh pemilihan tool masih menunggu keputusan Dewan Komisaris.
A5: A. BLOK ASUMSI (bernama - seluruh rumus merujuk ke sel-sel di bawah)
A6: Parameter | D6: Nilai | E6: Satuan | F6: Status data / sumber
A7: Kurs USD/IDR (4 September 2026) | D7: 17631 | E7: Rp/USD | F7: [S-74] exchange-rates.org, diakses 7 Sep 2026
A8: PPN PMSE efektif atas langganan digital luar negeri | D8: 0.11 | E8: % dari nilai | F8: [S-75] 12% x DPP nilai lain 11/12 (UU HPP, PMK 131/2024, PER-12/PJ/2025)
A9: Buffer risiko kurs | D9: 0.08 | E9: % dari nilai | F9: [ASUMSI] penyusun - tidak ada sumber proyeksi kurs yang dapat dipakai
A10: Cadangan gross-up PPh Pasal 26 | D10: 0.1 | E10: % dari nilai | F10: [ASUMSI] tarif umum 20% [S-77]; dicadangkan 10% karena sebagian penyedia berada di negara P3B dan sebagian pembayaran bukan objek royalti
A11: Hari operasi per bulan | D11: 30 | E11: hari | F11: [ASUMSI]
A12: Order selesai per hari - akhir Fase 0 | D12: 30 | E12: order/hari | F12: [ASUMSI] uji tertutup Pekanbaru
A13: Order selesai per hari - akhir Fase 1 | D13: 600 | E13: order/hari | F13: Manual SOP Bab 5, target akhir tahun 1 [ASUMSI penyusun manual]
A14: Order selesai per hari - akhir Fase 2 | D14: 2400 | E14: order/hari | F14: Manual SOP Bab 5, target akhir tahun 2 [ASUMSI penyusun manual]
A15: Tiket per 1.000 order - tahun 1 | D15: 35 | E15: tiket | F15: Manual SOP Bab 5 (batas atas) [ASUMSI]
A16: Tiket per 1.000 order - tahun 2 | D16: 22 | E16: tiket | F16: Manual SOP Bab 5 (batas atas) [ASUMSI]
A17: Tingkat deflection agen CS otomatis | D17: 0.6 | E17: % tiket selesai tanpa manusia | F17: [ASUMSI] rentang wajar 50-70%. JANGAN memakai klaim vendor 90%+
A18: Verifikasi identitas mitra+merchant per bulan - Fase 0 | D18: 40 | E18: verifikasi | F18: [ASUMSI] turunan target mitra Bab 5 & rasio mitra aktif 20% [S-58]
... A31: Faktor biaya tersembunyi Skenario C | D31: 1.8 | E31: x | F31: [ASUMSI] eskalasi & kegagalan lebih sering, beban kepatuhan lebih besar
A33: B. VOLUME TURUNAN PER BULAN (run-rate pada akhir fase)
A34: Ukuran | D34: Fase 0 | E34: Fase 1 | F34: Fase 2 | G34: Rumus / catatan
A35: Order selesai per bulan | D35: =Order_Hari_F0*Hari_Bulan | E35: =Order_Hari_F1*Hari_Bulan | F35: =Order_Hari_F2*Hari_Bulan | G35: order/hari x hari operasi
A36: Tiket masuk per bulan | D36: =D35*Tiket_Per1000_Th1/1000 | E36: =E35*Tiket_Per1000_Th1/1000 | F36: =F35*Tiket_Per1000_Th2/1000 | G36: order/bulan x tiket per 1.000 order
A37: Tiket ditangani agen AI (deflection) | D37: =D36*Deflection_CS | E37: =E36*Deflection_CS | F37: =F36*Deflection_CS | G37: tiket x tingkat deflection
A38: Tiket dieskalasi ke manusia | D38: =D36-D37 | E38: =E36-E37 | F38: =F36-F37 | G38: tiket - tiket yang dideflect
A39: Verifikasi identitas per bulan | D39: =Verif_F0 | E39: =Verif_F1 | F39: =Verif_F2 | G39: blok asumsi
A40: Merchant baru per bulan | D40: =Merchant_F0 | E40: =Merchant_F1 | F40: =Merchant_F2 | G40: blok asumsi
A41: Item katalog diperiksa per bulan | D41: =D40*15 | E41: =E40*15 | F41: =F40*15 | G41: merchant baru x 15 item [ASUMSI]
A42: Kueri analitik bahasa alami per bulan | D42: 30 | E42: 100 | F42: 200 | G42: [ASUMSI] pengganti pekerjaan pelaporan rutin JD-12
A43: Aset konten pemasaran per bulan | D43: 20 | E43: 120 | F43: 300 | G43: [ASUMSI] pengganti pekerjaan produksi konten JD-24
A44: Order ditriase anti-fraud per bulan | D44: =D35*0.03 | E44: =E35*0.03 | F44: =F35*0.03 | G44: 3% order [ASUMSI]
A46: C. PERHITUNGAN VOLUME TOKEN LLM PER BULAN
A47: Kegunaan | B47: Token input per unit | C47: Token output per unit | D47: Basis volume | E47: Token IN Fase 0 | F47: Token IN Fase 1 | G47: Token IN Fase 2 | H47: Token OUT Fase 0 | I47: Token OUT Fase 1 | J47: Token OUT Fase 2
A48: Agen CS tingkat 1 (rata-rata 3 giliran + konteks basis pengetahuan) | B48: 8000 | C48: 900 | D48: baris 37 | E48: =D37*$B48 | F48: =E37*$B48 | G48: =F37*$B48 | H48: =D37*$C48 | I48: =E37*$C48 | J48: =F37*$C48
A49: Triase & ringkasan tiket yang dieskalasi | B49: 3000 | C49: 400 | D49: baris 38 | E49: =D38*$B49 | F49: =E38*$B49 | G49: =F38*$B49 | H49: =D38*$C49 | I49: =E38*$C49 | J49: =F38*$C49
A50: Moderasi katalog & pemeriksaan kewajaran harga | B50: 1200 | C50: 150 | D50: baris 41 | E50: =D41*$B50 | F50: =E41*$B50 | G50: =F41*$B50 | H50: =D41*$C50 | I50: =E41*$C50 | J50: =F41*$C50
A51: Analitik & laporan bahasa alami | B51: 15000 | C51: 2000 | D51: baris 42 | E51: =D42*$B51 | F51: =E42*$B51 | G51: =F42*$B51 | H51: =D42*$C51 | I51: =E42*$C51 | J51: =F42*$C51
A52: Produksi konten pemasaran & naskah kampanye | B52: 3000 | C52: 1500 | D52: baris 43 | E52: =D43*$B52 | F52: =E43*$B52 | G52: =F43*$B52 | H52: =D43*$C52 | I52: =E43*$C52 | J52: =F43*$C52
A53: Triase sinyal anti-fraud (pemeringkatan, bukan keputusan) | B53: 4000 | C53: 500 | D53: baris 44 | E53: =D44*$B53 | F53: =E44*$B53 | G53: =F44*$B53 | H53: =D44*$C53 | I53: =E44*$C53 | J53: =F44*$C53
A54: TOTAL TOKEN PER BULAN | E54: =SUM(E48:E53) | F54: =SUM(F48:F53) | G54: =SUM(G48:G53) | H54: =SUM(H48:H53) | I54: =SUM(I48:I53) | J54: =SUM(J48:J53)
D55: Fase 0 | E55: Fase 1 | F55: Fase 2
D56: =(E54/1000000*Harga_LLM_In+H54/1000000*Harga_LLM_Out)*Faktor_Token*Kurs | E56: =(F54/1000000*Harga_LLM_In+I54/1000000*Harga_LLM_Out)*Faktor_Token*Kurs | F56: =(G54/1000000*Harga_LLM_In+J54/1000000*Harga_LLM_Out)*Faktor_Token*Kurs
A58: D. TUMPUKAN TOOL AI - BIAYA BULANAN PER FASE (Rp)
A59: Kode | B59: Tool / kategori (bernama) | C59: Fungsi | D59: Peran JD yang digantikan / diperkuat | E59: Model harga | F59: Harga satuan terverifikasi | G59: Sifat biaya | H59: Biaya/bulan Fase 0 | I59: Biaya/bulan Fase 1 | J59: Biaya/bulan Fase 2 | K59: Risiko utama | L59: Sumber
A60: T-01 | B60: Claude Haiku 4.5 + Claude Sonnet 5 (API) - LLM produk & internal | C60: Mesin bahasa untuk agen CS, triase tiket & fraud, moderasi katalog, analitik bahasa alami, produksi konten | D60: JD-17 CS Agent; JD-12 Data Analyst; JD-24 Digital Marketing; JD-18 triase | E60: Per juta token | F60: USD 1/5 (Haiku 4.5); USD 2/10 (Sonnet 5) | G60: Variabel - luar negeri | H60: =D56 | I60: =E56 | J60: =F56 | K60: Halusinasi pada pertanyaan saldo/pencairan; prompt WAJIB dimasking dari NIK, alamat, nomor telepon (UU PDP Ps.56) | L60: [S-62]
A61: T-02 | B61: WhatsApp Business Platform (Meta) - kanal omnichannel | C61: Kanal masuk agen CS dan notifikasi order; balasan dalam jendela layanan 24 jam tidak berbiaya | D61: JD-17 CS Agent (kanal); JD-24 (notifikasi) | E61: Per pesan keluar | F61: Rp356,65 Utility; Service gratis | G61: Variabel - lokal | H61: =D35*Porsi_WA*Tarif_WA_Utility | I61: =E35*Porsi_WA*Tarif_WA_Utility | J61: =F35*Porsi_WA*Tarif_WA_Utility | K61: Perubahan kebijakan tarif Meta; pemblokiran nomor bila keluhan spam tinggi | L61: [S-73]
A62: T-03 | B62: Verifikasi identitas + liveness (penyedia LOKAL berizin) | C62: OCR KTP/SIM/STNK, kecocokan wajah 1:1, uji keaktifan (liveness), skor verifikasi otomatis SOP-01 | D62: JD-15 Partner Acquisition (bagian dokumen); admin tinjauan manual SOP-01 | E62: Per verifikasi berhasil | F62: Rp10.000 [ASUMSI]; pembanding Didit USD 0,33 | G62: Variabel - lokal | H62: =D39*Tarif_KYC | I62: =E39*Tarif_KYC | J62: =F39*Tarif_KYC | K62: Bila memakai penyedia luar negeri, foto KTP & swafoto keluar wilayah RI - memicu Pasal 56 UU PDP. WAJIB penyedia lokal. | L62: [S-67][S-37]
A63: T-04 | B63: Intelijen perangkat & skoring fraud (di atas pemicu basis data yang sudah ada) | C63: Sidik jari perangkat, deteksi perangkat dipakai bersama, lompatan lokasi, pemeringkatan risiko pencairan | D63: JD-18 Trust & Safety (triase, bukan keputusan); JD-07 (aturan) | E63: Langganan bulanan | F63: [ASUMSI] - tidak ada daftar harga publik | G63: Tetap - luar negeri | H63: 0 | I63: 4000000 | J63: 8000000 | K63: Positif palsu memblokir mitra yang sah -> UU PDP Pasal 10 memberi hak keberatan atas keputusan otomatis | L63: [ASUMSI]
A64: T-05 | B64: Platform tiket & orkestrasi percakapan (BSP WhatsApp + panel tiket yang sudah ada) | C64: Antrean, penugasan, auto-triage, SLA balas pertama; panel tickets/ticket_messages sudah ada di sistem | D64: JD-16 Head of CX (pengelolaan antrean); JD-17 | E64: Langganan bulanan | F64: [ASUMSI]; pembanding Zendesk Suite Team USD 55/agen/bln | G64: Tetap - campuran | H64: 1000000 | I64: 2000000 | J64: 3000000 | K64: Vendor per-resolusi (Intercom Fin USD 0,99 = Rp17.457) TIDAK ekonomis pada volume AntarKita - lihat catatan C-3 | L64: [S-65][S-66]
A65: T-06 | B65: Claude Team / Claude Code (asisten koding) | C65: Agen koding untuk fitur, perbaikan cakupan uji, sapuan rute otomatis, tinjauan kode tahap pertama | D65: JD-06 Mobile Mid; JD-08 Backend Mid; JD-09 QA; JD-10 Junior SWE | E65: Per kursi per bulan | F65: USD 100 kursi premium; USD 20 kursi standar (tagihan tahunan) | G65: Tetap - luar negeri | H65: =(2*100+2*20)*Kurs | I65: =(3*100+3*20)*Kurs | J65: =(3*100+5*20)*Kurs | K65: Ketergantungan pada mutu tinjauan manusia; kode yang menyentuh dompet WAJIB ditinjau Backend Senior | L65: [S-71][S-70]
A66: T-07 | B66: Metabase Cloud Starter + kueri bahasa alami | C66: Portal Eksekutif, Laba Rugi per bulan & per layanan, audit KPI, penyiapan data uji tuntas | D66: JD-12 Data Analyst (produksi laporan) | E66: Langganan + per pengguna | F66: USD 100/bln (5 pengguna) + USD 6/pengguna; add-on token AI USD 3,75/juta | G66: Tetap - luar negeri | H66: =100*Kurs | I66: =(100+3*6)*Kurs | J66: =(100+7*6)*Kurs | K66: Definisi metrik tanpa pemilik manusia menghasilkan dua versi angka - dilarang Bab 5 manual | L66: [S-69]
A67: T-08 | B67: Moderasi konten & gambar katalog | C67: Penyaringan foto/teks lapak, deteksi harga di luar kewajaran, penyaringan ulasan | D67: JD-25 Merchant Acquisition (mutu katalog); JD-18 | E67: Per permintaan / langganan | F67: [ASUMSI] | G67: Tetap - luar negeri | H67: 0 | I67: 750000 | J67: 1500000 | K67: Salah blokir merchant kecil; wajib jalur banding manusia | L67: [ASUMSI]
A68: T-09 | B68: ElevenLabs (text-to-speech) - panggilan keluar otomatis | C68: Konfirmasi order tak terjawab, pengingat mitra, IVR status tiket. TIDAK dipakai untuk kanal darurat. | D68: JD-17 CS Agent (panggilan rutin); JD-14 Ops Supervisor (pengingat) | E68: Langganan bulanan (kredit) | F68: USD 11 Creator (121rb kredit); USD 99 Pro (600rb kredit) | G68: Tetap - luar negeri | H68: 0 | I68: =11*Kurs | J68: =99*Kurs | K68: Panggilan otomatis pada insiden keselamatan DILARANG - SOP-05 mensyaratkan manusia dalam 15 menit | L68: [S-72]
A69: T-10 | B69: n8n (swakelola) - orkestrator & otomasi alur kerja | C69: Rekonsiliasi dompet harian, laporan bulanan Komisaris, penugasan ulang order tersendat, alur onboarding | D69: JD-21 Treasury (rekonsiliasi); JD-14 (papan order); JD-20 (pembukuan) | E69: Lisensi Community gratis + biaya server | F69: Cloud Pro EUR 50/10.000 eksekusi; Community swakelola gratis | G69: Tetap - campuran | H69: 1000000 | I69: 1750000 | J69: 2500000 | K69: Alur yang gagal diam-diam. Rekonsiliasi WAJIB memunculkan selisih ke manusia, bukan menutupnya. | L69: [S-68]
A70: T-11 | B70: Pipeline uji otomatis (CI) + agen uji | C70: Simulasi ujung-ke-ujung basis data, sapuan rute 3 aplikasi, gerbang rilis SOP-11 | D70: JD-09 QA Engineer (kedua baris) | E70: Langganan CI | F70: [ASUMSI] | G70: Tetap - luar negeri | H70: 1000000 | I70: 1500000 | J70: 2000000 | K70: Gerbang rilis tanpa penahan manusia; hak veto pindah ke Engineering Manager - harus tertulis di SOP-11 | L70: [ASUMSI]
A71: T-12 | B71: Observability & evaluasi LLM + jejak keputusan | C71: Perekaman prompt/keluaran, alasan keputusan otomatis, uji regresi mutu jawaban, pagar pengaman | D71: Kewajiban baru - bukan pengganti peran | E71: Langganan / swakelola | F71: [ASUMSI] | G71: Tetap - campuran | H71: 750000 | I71: 1750000 | J71: 3000000 | K71: Tanpa ini, hak keberatan UU PDP Pasal 10 tidak dapat dilayani karena alasan keputusan tidak terekam | L71: [S-37]
A72: T-13 | B72: Penyimpanan & pemrosesan data pribadi di wilayah Indonesia | C72: Residensi data KYC, log tiket, dan data pribadi yang tidak boleh keluar wilayah RI | D72: Kewajiban baru - bukan pengganti peran | E72: Infrastruktur bulanan | F72: [ASUMSI] | G72: Tetap - lokal | H72: 1000000 | I72: 2500000 | J72: 4000000 | K72: Kegagalan memisahkan data yang boleh & tidak boleh keluar negeri = risiko sanksi hingga 2% pendapatan tahunan | L72: [S-37]
A73: SUBTOTAL biaya tool per bulan | H73: =SUM(H60:H72) | I73: =SUM(I60:I72) | J73: =SUM(J60:J72)
A74: dari itu, dibayar ke penyedia LUAR NEGERI (T-01, T-06, T-07, T-09) | H74: =H60+H65+H66+H68 | I74: =I60+I65+I66+I68 | J74: =J60+J65+J66+J68
A75: Tambahan PPN PMSE + buffer kurs + cadangan gross-up PPh 26 atas porsi luar negeri | H75: =H74*(PPN_PMSE+Buffer_Kurs+GrossUp_PPh26) | I75: =I74*(PPN_PMSE+Buffer_Kurs+GrossUp_PPh26) | J75: =J74*(PPN_PMSE+Buffer_Kurs+GrossUp_PPh26)
A76: TOTAL BIAYA TOOL AI PER BULAN (termasuk pajak & buffer kurs) | H76: =H73+H75 | I76: =I73+I75 | J76: =J73+J75
A78: E. BIAYA TERSEMBUNYI OTOMASI (yang paling sering dilupakan)
A79: Kode | B79: Pos biaya | C79: Basis perhitungan | H79: Fase 0 | I79: Fase 1 | J79: Fase 2 | K79: Catatan / dasar
A80: H-1 | B80: Pemeliharaan otomasi - kontraktor 0,5-1,0 FTE | C80: AI tidak memelihara dirinya: prompt melapuk, API berubah versi, basis pengetahuan basi | H80: 0 | I80: 8000000 | J80: 16000000 | K80: [ASUMSI] setara 0,5 FTE Backend Mid pada Fase 1 dan 1,0 FTE pada Fase 2
A81: H-2 | B81: Biaya kegagalan CS: kompensasi niat baik atas kesalahan agen AI | C81: 2% tiket x Rp50.000 (batas kewenangan CS Agent, SOP-04) | H81: =D36*0.02*50000 | I81: =E36*0.02*50000 | J81: =F36*0.02*50000 | K81: [ASUMSI] 2%; kewenangan Rp50.000 dari JD-17
A82: H-3 | B82: Pengawasan kepatuhan UU PDP oleh DPO atas sistem otomatis | C82: 0,2 FTE Head of Legal & Compliance (Rp17.462.921/bulan) | H82: 0 | I82: =0.2*17462921 | J82: =0.2*17462921 | K82: Beban BARU akibat otomasi: DPIA berkala, register pemrosesan, uji transfer data Pasal 56
A83: H-4 | B83: Audit & jejak keputusan otomatis | C83: 0,1 FTE Trust & Safety (Rp12.421.915/bulan) meninjau keputusan otomatis yang disanggah | H83: 0 | I83: =0.1*12421915 | J83: =0.1*12421915 | K83: Konsekuensi langsung UU PDP Pasal 10 - hak keberatan wajib dapat dilayani manusia
A84: H-5 | B84: Cadangan risiko reputasi bila AI salah menangani keluhan | C84: Perkiraan biaya penanganan krisis Rp150 juta x peluang 15%/tahun / 12 | H84: 0 | I84: 1250000 | J84: 1875000 | K84: [ASUMSI] penyusun. Bukan pengukuran. Turun mendekati nol bila kategori keselamatan selalu dialihkan ke manusia
A85: SUBTOTAL biaya tersembunyi BERULANG per bulan | H85: =SUM(H80:H84) | I85: =SUM(I80:I84) | J85: =SUM(J80:J84)
A87: F. BIAYA SATU KALI (dibebankan pada lembar 'Perbandingan 24 Bulan', bulan 4-15)
B88: Implementasi & integrasi awal (agen CS 320 jam, KYC 160, rekonsiliasi 200, fraud 180, BI 120, konten 80 = 1.060 jam internal + konsultan integrasi) | H88: 250000000 | K88: [ASUMSI] tarif internal Rp97.504/jam diturunkan dari CTC Backend Mid / 160 jam
B89: Penilaian Dampak Pelindungan Data (4 sistem) + perjanjian pemrosesan & kajian kesetaraan negara penerima | H89: 100000000 | K89: [ASUMSI] kewajiban UU PDP untuk pemrosesan berisiko tinggi & transfer lintas negara [S-37]
B90: TOTAL BIAYA SATU KALI | H90: =SUM(H88:H89)
A92: G. REKAP BIAYA AI PER BULAN (run-rate akhir fase)
H93: Fase 0 | I93: Fase 1 | J93: Fase 2
A94: Komponen VARIABEL (ikut volume order): T-01 + T-02 + T-03 | H94: =H60+H61+H62 | I94: =I60+I61+I62 | J94: =J60+J61+J62
A95: Komponen TETAP tool (T-04 s.d. T-13) + pajak & buffer kurs | H95: =H76-(H60+H61+H62) | I95: =I76-(I60+I61+I62) | J95: =J76-(J60+J61+J62)
A96: Biaya tersembunyi berulang | H96: =H85 | I96: =I85 | J96: =J85
A97: TOTAL BIAYA AI PER BULAN - SKENARIO B (Hibrida) | H97: =H94+H95+H96 | I97: =I94+I95+I96 | J97: =J94+J95+J96
A98: TOTAL BIAYA AI PER BULAN - SKENARIO C (AI-maksimal) | H98: =(H94+H95)*Faktor_Tool_C+H96*Faktor_Sembunyi_C | I98: =(I94+I95)*Faktor_Tool_C+I96*Faktor_Sembunyi_C | J98: =(J94+J95)*Faktor_Tool_C+J96*Faktor_Sembunyi_C
A100: Catatan C-3: agen CS berbayar per resolusi (Intercom Fin USD 0,99 = Rp17.457 [S-65]) menghasilkan biaya per tiket yang SETARA dengan biaya CS Agent manusia pada volume AntarKita (1.584 tiket/bulan dibagi 5 agen = Rp19.593/tiket). Karena itu rekomendasi adalah MEMBANGUN agen CS di atas API LLM (T-01) yang berbiaya sekitar Rp170/tiket, bukan membeli platform per-resolusi. Penghematan CS berasal dari pengurangan CAKUPAN SHIFT, bukan dari biaya per tiket.

Sheet Penilaian Peran
A1: AntarKita - Penilaian Otomatisasi 26 Uraian Jabatan (JD-01 s.d. JD-26)
A2: Metode: tiap peran dibongkar menjadi tugas, lalu dinilai pada empat sumbu. Skor = 0,35xA + 0,25xB + 0,25x(100-C) + 0,15x(100-D). Kategori otomatis dari skor, KECUALI bila kolom 'Pembatas' memuat syarat hukum atau keselamatan - kolom 'Kategori final' adalah yang mengikat.
A3: USULAN ANALIS - keputusan mengurangi atau menghapus posisi ada pada Dewan Komisaris (DESAIN-ORGANISASI 6).
A5: Kode | B5: Jabatan | C5: Tugas inti (ringkas, dari Bab 3 manual) | D5: A. Sifat tugas rutin/terstruktur (0-100) | E5: B. Volume & prediktabilitas (0-100) | F5: C. Risiko bila salah (0-100) | G5: D. Syarat hukum/keselamatan yang mengharuskan manusia (0-100) | H5: Skor otomatisasi (0-100) | I5: Kategori dari skor | J5: Pembatas hukum / operasional | K5: KATEGORI FINAL (mengikat) | L5: Tindakan yang diusulkan
A6: JD-01 | B6: Direktur Utama (CEO) | C6: RKAT, kas & runway, hubungan investor, tanda tangan perjanjian kemitraan & PJP, persetujuan >Rp50 jt ke Komisaris | D6: 15 | E6: 20 | F6: 95 | G6: 95 | H6: =0.35*D6+0.25*E6+0.25*(100-F6)+0.15*(100-G6) | I6: =IF(G6>=80,"WAJIB MANUSIA",IF(H6>=70,"OTOMATIS PENUH",IF(H6>=50,"AUGMENTASI TINGGI",IF(H6>=35,"AUGMENTASI RENDAH","WAJIB MANUSIA")))) | J6: Organ perseroan; menandatangani perjanjian; akuntabilitas hukum tidak dapat didelegasikan ke sistem | K6: WAJIB MANUSIA | L6: Tetap 1 orang. AI dipakai untuk penyusunan paket laporan & analisis skenario.
A7: JD-02 | B7: Direktur Teknologi (CTO) | C7: Peta jalan, keandalan, pengendali teknis kepatuhan UU PDP, incident commander S1, hak akses & PIN admin | D7: 25 | E7: 30 | F7: 90 | G7: 90 | H7: =0.35*D7+0.25*E7+0.25*(100-F7)+0.15*(100-G7) | I7: =IF(G7>=80,"WAJIB MANUSIA",IF(H7>=70,"OTOMATIS PENUH",IF(H7>=50,"AUGMENTASI TINGGI",IF(H7>=35,"AUGMENTASI RENDAH","WAJIB MANUSIA")))) | J7: Pengendali teknis UU PDP; penetapan keparahan insiden; direksi | K7: WAJIB MANUSIA | L7: Tetap 1 orang. Rentang kendali teknis naik karena agen koding; tetap pemilik akuntabilitas.
A8: JD-03 | B8: Direktur Operasi (COO) | C8: Target kota, sakelar layanan darurat, pemilik SOP-03/SOP-05, eskalasi tingkat 3, playbook kota | D8: 25 | E8: 35 | F8: 90 | G8: 90 | H8: =0.35*D8+0.25*E8+0.25*(100-F8)+0.15*(100-G8) | I8: =IF(G8>=80,"WAJIB MANUSIA",IF(H8>=70,"OTOMATIS PENUH",IF(H8>=50,"AUGMENTASI TINGGI",IF(H8>=35,"AUGMENTASI RENDAH","WAJIB MANUSIA")))) | J8: Keputusan darurat operasional & keselamatan; direksi | K8: WAJIB MANUSIA | L8: Tetap 1 orang. Pada Skenario C merangkap Head of CX - inilah titik pecah pertama.
A9: JD-04 | B9: Engineering Manager | C9: Siklus rilis, migrasi bernomor, tinjauan kode, wakil incident commander, pembinaan | D9: 40 | E9: 45 | F9: 70 | G9: 25 | H9: =0.35*D9+0.25*E9+0.25*(100-F9)+0.15*(100-G9) | I9: =IF(G9>=80,"WAJIB MANUSIA",IF(H9>=70,"OTOMATIS PENUH",IF(H9>=50,"AUGMENTASI TINGGI",IF(H9>=35,"AUGMENTASI RENDAH","WAJIB MANUSIA")))) | J9: Pemilik postmortem & gerbang penggabungan kode | K9: AUGMENTASI RENDAH | L9: Tetap 1 orang, mengambil alih gerbang rilis dari QA Engineer.
A10: JD-05 | B10: Mobile Engineer - Senior | C10: Arsitektur aplikasi, ErrorBoundary, langganan realtime, alur kritikal yang menyentuh uang | D10: 55 | E10: 60 | F10: 55 | G10: 10 | H10: =0.35*D10+0.25*E10+0.25*(100-F10)+0.15*(100-G10) | I10: =IF(G10>=80,"WAJIB MANUSIA",IF(H10>=70,"OTOMATIS PENUH",IF(H10>=50,"AUGMENTASI TINGGI",IF(H10>=35,"AUGMENTASI RENDAH","WAJIB MANUSIA")))) | J10: - | K10: AUGMENTASI TINGGI | L10: Tetap 1 orang; menyerap pekerjaan 1 Mobile Mid dengan agen koding.
A11: JD-06 | B11: Mobile Engineer - Mid | C11: Membangun layar & alur baru, memperbaiki cacat, skenario sapuan rute, teks antarmuka | D11: 65 | E11: 68 | F11: 45 | G11: 5 | H11: =0.35*D11+0.25*E11+0.25*(100-F11)+0.15*(100-G11) | I11: =IF(G11>=80,"WAJIB MANUSIA",IF(H11>=70,"OTOMATIS PENUH",IF(H11>=50,"AUGMENTASI TINGGI",IF(H11>=35,"AUGMENTASI RENDAH","WAJIB MANUSIA")))) | J11: - | K11: AUGMENTASI TINGGI | L11: Kedua baris (dasar + gelombang 2) dihapus pada Skenario B.
A12: JD-07 | B12: Backend Engineer - Senior | C12: Skema dompet & pembagian hasil, RLS, idempotensi, aturan anti-fraud, simulasi ujung-ke-ujung | D12: 45 | E12: 50 | F12: 85 | G12: 15 | H12: =0.35*D12+0.25*E12+0.25*(100-F12)+0.15*(100-G12) | I12: =IF(G12>=80,"WAJIB MANUSIA",IF(H12>=70,"OTOMATIS PENUH",IF(H12>=50,"AUGMENTASI TINGGI",IF(H12>=35,"AUGMENTASI RENDAH","WAJIB MANUSIA")))) | J12: Perubahan yang menyentuh uang wajib ditinjau manusia (SOP-11, DESAIN 6) | K12: AUGMENTASI RENDAH | L12: Tetap. Gelombang 2 dipertahankan di Skenario B (titik tunggal kegagalan bila dihapus).
A13: JD-08 | B13: Backend Engineer - Mid | C13: Fungsi panel admin non-keuangan, tiket, notifikasi, indeks, temuan advisor | D13: 65 | E13: 65 | F13: 55 | G13: 10 | H13: =0.35*D13+0.25*E13+0.25*(100-F13)+0.15*(100-G13) | I13: =IF(G13>=80,"WAJIB MANUSIA",IF(H13>=70,"OTOMATIS PENUH",IF(H13>=50,"AUGMENTASI TINGGI",IF(H13>=35,"AUGMENTASI RENDAH","WAJIB MANUSIA")))) | J13: - | K13: AUGMENTASI TINGGI | L13: Baris dasar dipertahankan & dialihfungsikan jadi pemelihara otomasi; gelombang 2 dihapus.
A14: JD-09 | B14: QA Engineer | C14: Menjalankan simulasi e2e, sapuan rute otomatis, uji alur uang, daftar periksa rilis, bukti uji | D14: 80 | E14: 85 | F14: 50 | G14: 10 | H14: =0.35*D14+0.25*E14+0.25*(100-F14)+0.15*(100-G14) | I14: =IF(G14>=80,"WAJIB MANUSIA",IF(H14>=70,"OTOMATIS PENUH",IF(H14>=50,"AUGMENTASI TINGGI",IF(H14>=35,"AUGMENTASI RENDAH","WAJIB MANUSIA")))) | J14: Hak menahan rilis (SOP-11) berpindah ke Engineering Manager | K14: OTOMATIS PENUH | L14: Kedua baris dihapus; gerbang rilis dijalankan pipeline uji + Engineering Manager.
A15: JD-10 | B15: Junior Software Engineer | C15: Perbaikan cacat kecil, pengujian dasar, membantu QA, pembinaan, catatan teknis | D15: 85 | E15: 85 | F15: 35 | G15: 0 | H15: =0.35*D15+0.25*E15+0.25*(100-F15)+0.15*(100-G15) | I15: =IF(G15>=80,"WAJIB MANUSIA",IF(H15>=70,"OTOMATIS PENUH",IF(H15>=50,"AUGMENTASI TINGGI",IF(H15>=35,"AUGMENTASI RENDAH","WAJIB MANUSIA")))) | J15: Nilai kaderisasi lokal (keputusan strategis, bukan teknis) | K15: OTOMATIS PENUH | L15: Baris Pekanbaru dihapus; baris Padang dipertahankan sebagai keputusan kaderisasi - MENUNGGU KOMISARIS.
A16: JD-11 | B16: Product Designer (UI/UX) | C16: Sistem desain, alur pemesanan, panel admin, teks antarmuka, uji 5 pengguna per kota | D16: 50 | E16: 55 | F16: 45 | G16: 5 | H16: =0.35*D16+0.25*E16+0.25*(100-F16)+0.15*(100-G16) | I16: =IF(G16>=80,"WAJIB MANUSIA",IF(H16>=70,"OTOMATIS PENUH",IF(H16>=50,"AUGMENTASI TINGGI",IF(H16>=35,"AUGMENTASI RENDAH","WAJIB MANUSIA")))) | J16: Uji dengan pengguna nyata tidak dapat disimulasikan | K16: AUGMENTASI TINGGI | L16: Baris dasar tetap; gelombang 2 dihapus.
A17: JD-12 | B17: Data Analyst | C17: Portal Eksekutif & Laba Rugi, audit KPI bulanan, rasio mitra aktif, data uji tuntas, definisi metrik | D17: 75 | E17: 80 | F17: 45 | G17: 10 | H17: =0.35*D17+0.25*E17+0.25*(100-F17)+0.15*(100-G17) | I17: =IF(G17>=80,"WAJIB MANUSIA",IF(H17>=70,"OTOMATIS PENUH",IF(H17>=50,"AUGMENTASI TINGGI",IF(H17>=35,"AUGMENTASI RENDAH","WAJIB MANUSIA")))) | J17: Definisi resmi metrik butuh pemilik manusia yang dapat dimintai pertanggungjawaban | K17: OTOMATIS PENUH | L17: Posisi dihapus; kepemilikan definisi metrik pindah ke Head of Finance, produksi laporan ke BI bahasa alami.
... A31: JD-26 | B31: HR & GA Generalist | C31: Rekrutmen bertahap, dua struktur payroll, pendaftaran BPJS, THR, kontrak & arsip, kantor 2 kota, pelatihan PDP | D31: 60 | E31: 65 | F31: 70 | G31: 55 | H31: =0.35*D31+0.25*E31+0.25*(100-F31)+0.15*(100-G31) | I31: =IF(G31>=80,"WAJIB MANUSIA",IF(H31>=70,"OTOMATIS PENUH",IF(H31>=50,"AUGMENTASI TINGGI",IF(H31>=35,"AUGMENTASI RENDAH","WAJIB MANUSIA")))) | J31: Penanggung jawab kepatuhan pengupahan & pelaporan jaminan sosial | K31: AUGMENTASI TINGGI | L31: Tetap 1 orang (tidak dapat dipangkas lebih jauh); payroll & administrasi diotomasi.
B32: Rekap jumlah peran per kategori final
B33: OTOMATIS PENUH | H33: =COUNTIF($K$6:$K$31,B33)
B34: AUGMENTASI TINGGI | H34: =COUNTIF($K$6:$K$31,B34)
B35: AUGMENTASI RENDAH | H35: =COUNTIF($K$6:$K$31,B35)
B36: WAJIB MANUSIA | H36: =COUNTIF($K$6:$K$31,B36)
B37: TOTAL | H37: =SUM(H33:H36)
A39: Catatan sumbu D (syarat manusia): 95-100 = kewajiban hukum eksplisit (UU 27/2022 Pasal 53 untuk DPO; organ perseroan; penanggung jawab laporan keuangan & pajak). 60-90 = keputusan yang menimbulkan akibat hukum atau berdampak signifikan pada subjek data (UU 27/2022 Pasal 10 - hak keberatan atas keputusan yang hanya berdasar pemrosesan otomatis), atau keselamatan jiwa (SOP-05). 20-55 = kontrol internal wajib (pemisahan tugas keuangan DESAIN 6 / SOP-07). 0-15 = tidak ada syarat manusia.

Sheet Skenario A B C
A1: AntarKita - Skenario A (semua manusia) / B (hibrida - rekomendasi) / C (AI-maksimal)
A2: Baris posisi, CTC per orang, bulan mulai, dan jumlah orang per fase adalah SALINAN PERSIS dari AntarKita-Model-Biaya-SDM.xlsx lembar 'Biaya Bulanan' baris 26-63. Kolom 'Potong B' dan 'Potong C' adalah INPUT yang boleh diubah pemilik; seluruh angka lain adalah rumus hidup.
A3: Uji A vs model lama harus menghasilkan 0 pada baris UJI di bawah.
A5: No | B5: Direktorat | C5: Posisi | D5: Level | E5: Bulan Mulai | F5: CTC per orang (Rp) | G5: Bulan aktif per orang (bln 1-24) | H5: Orang A F0 | I5: Orang A F1 | J5: Orang A F2 | K5: POTONG B | L5: POTONG C | M5: Orang B F0 | N5: Orang B F1 | O5: Orang B F2 | P5: Orang C F0 | Q5: Orang C F1 | R5: Orang C F2 | S5: Biaya A F0 | T5: Biaya A F1 | U5: Biaya A F2 | V5: Biaya B F0 | W5: Biaya B F1 | X5: Biaya B F2 | Y5: Biaya C F0 | Z5: Biaya C F1 | AA5: Biaya C F2 | AB5: Kum 24 bln A | AC5: Kum 24 bln B | AD5: Kum 24 bln C
A6: 1 | B6: Direksi & Tata Kelola | C6: Direktur Utama (CEO) | D6: C-Level | E6: 1 | F6: 44156676 | G6: 24 | H6: 1 | I6: 1 | J6: 1 | K6: 0 | L6: 0 | M6: =MAX(0,H6-$K6) | N6: =MAX(0,I6-$K6) | O6: =MAX(0,J6-$K6) | P6: =MAX(0,H6-$L6) | Q6: =MAX(0,I6-$L6) | R6: =MAX(0,J6-$L6) | S6: =$F6*H6 | T6: =$F6*I6 | U6: =$F6*J6 | V6: =$F6*M6 | W6: =$F6*N6 | X6: =$F6*O6 | Y6: =$F6*P6 | Z6: =$F6*Q6 | AA6: =$F6*R6 | AB6: =$F6*$G6*$J6 | AC6: =$F6*$G6*MAX(0,$J6-$K6) | AD6: =$F6*$G6*MAX(0,$J6-$L6)
A7: 2 | B7: Direksi & Tata Kelola | C7: HR & GA Generalist | D7: Staf Senior | E7: 3 | F7: 11114345 | G7: 22 | H7: 1 | I7: 1 | J7: 1 | K7: 0 | L7: 0 | M7: =MAX(0,H7-$K7) | N7: =MAX(0,I7-$K7) | O7: =MAX(0,J7-$K7) | P7: =MAX(0,H7-$L7) | Q7: =MAX(0,I7-$L7) | R7: =MAX(0,J7-$L7) | S7: =$F7*H7 | T7: =$F7*I7 | U7: =$F7*J7 | V7: =$F7*M7 | W7: =$F7*N7 | X7: =$F7*O7 | Y7: =$F7*P7 | Z7: =$F7*Q7 | AA7: =$F7*R7 | AB7: =$F7*$G7*$J7 | AC7: =$F7*$G7*MAX(0,$J7-$K7) | AD7: =$F7*$G7*MAX(0,$J7-$L7)
A8: 3 | B8: Teknologi | C8: Direktur Teknologi (CTO) | D8: C-Level | E8: 1 | F8: 37948826 | G8: 24 | H8: 1 | I8: 1 | J8: 1 | K8: 0 | L8: 0 | M8: =MAX(0,H8-$K8) | N8: =MAX(0,I8-$K8) | O8: =MAX(0,J8-$K8) | P8: =MAX(0,H8-$L8) | Q8: =MAX(0,I8-$L8) | R8: =MAX(0,J8-$L8) | S8: =$F8*H8 | T8: =$F8*I8 | U8: =$F8*J8 | V8: =$F8*M8 | W8: =$F8*N8 | X8: =$F8*O8 | Y8: =$F8*P8 | Z8: =$F8*Q8 | AA8: =$F8*R8 | AB8: =$F8*$G8*$J8 | AC8: =$F8*$G8*MAX(0,$J8-$K8) | AD8: =$F8*$G8*MAX(0,$J8-$L8)
A9: 4 | B9: Teknologi | C9: Engineering Manager | D9: Manajer | E9: 4 | F9: 34844901 | G9: 21 | H9: 0 | I9: 1 | J9: 1 | K9: 0 | L9: 0 | M9: =MAX(0,H9-$K9) | N9: =MAX(0,I9-$K9) | O9: =MAX(0,J9-$K9) | P9: =MAX(0,H9-$L9) | Q9: =MAX(0,I9-$L9) | R9: =MAX(0,J9-$L9) | S9: =$F9*H9 | T9: =$F9*I9 | U9: =$F9*J9 | V9: =$F9*M9 | W9: =$F9*N9 | X9: =$F9*O9 | Y9: =$F9*P9 | Z9: =$F9*Q9 | AA9: =$F9*R9 | AB9: =$F9*$G9*$J9 | AC9: =$F9*$G9*MAX(0,$J9-$K9) | AD9: =$F9*$G9*MAX(0,$J9-$L9)
A10: 5 | B10: Teknologi | C10: Mobile Engineer (Senior) | D10: Senior | E10: 1 | F10: 25533126 | G10: 24 | H10: 1 | I10: 1 | J10: 1 | K10: 0 | L10: 0 | M10: =MAX(0,H10-$K10) | N10: =MAX(0,I10-$K10) | O10: =MAX(0,J10-$K10) | P10: =MAX(0,H10-$L10) | Q10: =MAX(0,I10-$L10) | R10: =MAX(0,J10-$L10) | S10: =$F10*H10 | T10: =$F10*I10 | U10: =$F10*J10 | V10: =$F10*M10 | W10: =$F10*N10 | X10: =$F10*O10 | Y10: =$F10*P10 | Z10: =$F10*Q10 | AA10: =$F10*R10 | AB10: =$F10*$G10*$J10 | AC10: =$F10*$G10*MAX(0,$J10-$K10) | AD10: =$F10*$G10*MAX(0,$J10-$L10)
A11: 6 | B11: Teknologi | C11: Mobile Engineer (Mid) | D11: Mid | E11: 5 | F11: 15600566 | G11: 20 | H11: 0 | I11: 1 | J11: 1 | K11: 1 | L11: 1 | M11: =MAX(0,H11-$K11) | N11: =MAX(0,I11-$K11) | O11: =MAX(0,J11-$K11) | P11: =MAX(0,H11-$L11) | Q11: =MAX(0,I11-$L11) | R11: =MAX(0,J11-$L11) | S11: =$F11*H11 | T11: =$F11*I11 | U11: =$F11*J11 | V11: =$F11*M11 | W11: =$F11*N11 | X11: =$F11*O11 | Y11: =$F11*P11 | Z11: =$F11*Q11 | AA11: =$F11*R11 | AB11: =$F11*$G11*$J11 | AC11: =$F11*$G11*MAX(0,$J11-$K11) | AD11: =$F11*$G11*MAX(0,$J11-$L11)
A12: 7 | B12: Teknologi | C12: Mobile Engineer (Mid) - gelombang 2 | D12: Mid | E12: 14 | F12: 15600566 | G12: 11 | H12: 0 | I12: 0 | J12: 1 | K12: 1 | L12: 1 | M12: =MAX(0,H12-$K12) | N12: =MAX(0,I12-$K12) | O12: =MAX(0,J12-$K12) | P12: =MAX(0,H12-$L12) | Q12: =MAX(0,I12-$L12) | R12: =MAX(0,J12-$L12) | S12: =$F12*H12 | T12: =$F12*I12 | U12: =$F12*J12 | V12: =$F12*M12 | W12: =$F12*N12 | X12: =$F12*O12 | Y12: =$F12*P12 | Z12: =$F12*Q12 | AA12: =$F12*R12 | AB12: =$F12*$G12*$J12 | AC12: =$F12*$G12*MAX(0,$J12-$K12) | AD12: =$F12*$G12*MAX(0,$J12-$L12)
A13: 8 | B13: Teknologi | C13: Backend Engineer (Senior) | D13: Senior | E13: 1 | F13: 25533126 | G13: 24 | H13: 1 | I13: 1 | J13: 1 | K13: 0 | L13: 0 | M13: =MAX(0,H13-$K13) | N13: =MAX(0,I13-$K13) | O13: =MAX(0,J13-$K13) | P13: =MAX(0,H13-$L13) | Q13: =MAX(0,I13-$L13) | R13: =MAX(0,J13-$L13) | S13: =$F13*H13 | T13: =$F13*I13 | U13: =$F13*J13 | V13: =$F13*M13 | W13: =$F13*N13 | X13: =$F13*O13 | Y13: =$F13*P13 | Z13: =$F13*Q13 | AA13: =$F13*R13 | AB13: =$F13*$G13*$J13 | AC13: =$F13*$G13*MAX(0,$J13-$K13) | AD13: =$F13*$G13*MAX(0,$J13-$L13)
A14: 9 | B14: Teknologi | C14: Backend Engineer (Senior) - gelombang 2 | D14: Senior | E14: 19 | F14: 25533126 | G14: 6 | H14: 0 | I14: 0 | J14: 1 | K14: 0 | L14: 1 | M14: =MAX(0,H14-$K14) | N14: =MAX(0,I14-$K14) | O14: =MAX(0,J14-$K14) | P14: =MAX(0,H14-$L14) | Q14: =MAX(0,I14-$L14) | R14: =MAX(0,J14-$L14) | S14: =$F14*H14 | T14: =$F14*I14 | U14: =$F14*J14 | V14: =$F14*M14 | W14: =$F14*N14 | X14: =$F14*O14 | Y14: =$F14*P14 | Z14: =$F14*Q14 | AA14: =$F14*R14 | AB14: =$F14*$G14*$J14 | AC14: =$F14*$G14*MAX(0,$J14-$K14) | AD14: =$F14*$G14*MAX(0,$J14-$L14)
A15: 10 | B15: Teknologi | C15: Backend Engineer (Mid) | D15: Mid | E15: 4 | F15: 15600566 | G15: 21 | H15: 0 | I15: 1 | J15: 1 | K15: 0 | L15: 1 | M15: =MAX(0,H15-$K15) | N15: =MAX(0,I15-$K15) | O15: =MAX(0,J15-$K15) | P15: =MAX(0,H15-$L15) | Q15: =MAX(0,I15-$L15) | R15: =MAX(0,J15-$L15) | S15: =$F15*H15 | T15: =$F15*I15 | U15: =$F15*J15 | V15: =$F15*M15 | W15: =$F15*N15 | X15: =$F15*O15 | Y15: =$F15*P15 | Z15: =$F15*Q15 | AA15: =$F15*R15 | AB15: =$F15*$G15*$J15 | AC15: =$F15*$G15*MAX(0,$J15-$K15) | AD15: =$F15*$G15*MAX(0,$J15-$L15)
A16: 11 | B16: Teknologi | C16: Backend Engineer (Mid) - gelombang 2 | D16: Mid | E16: 13 | F16: 15600566 | G16: 12 | H16: 0 | I16: 0 | J16: 1 | K16: 1 | L16: 1 | M16: =MAX(0,H16-$K16) | N16: =MAX(0,I16-$K16) | O16: =MAX(0,J16-$K16) | P16: =MAX(0,H16-$L16) | Q16: =MAX(0,I16-$L16) | R16: =MAX(0,J16-$L16) | S16: =$F16*H16 | T16: =$F16*I16 | U16: =$F16*J16 | V16: =$F16*M16 | W16: =$F16*N16 | X16: =$F16*O16 | Y16: =$F16*P16 | Z16: =$F16*Q16 | AA16: =$F16*R16 | AB16: =$F16*$G16*$J16 | AC16: =$F16*$G16*MAX(0,$J16-$K16) | AD16: =$F16*$G16*MAX(0,$J16-$L16)
A17: 12 | B17: Teknologi | C17: QA Engineer | D17: Mid | E17: 6 | F17: 13075700 | G17: 19 | H17: 0 | I17: 1 | J17: 1 | K17: 1 | L17: 1 | M17: =MAX(0,H17-$K17) | N17: =MAX(0,I17-$K17) | O17: =MAX(0,J17-$K17) | P17: =MAX(0,H17-$L17) | Q17: =MAX(0,I17-$L17) | R17: =MAX(0,J17-$L17) | S17: =$F17*H17 | T17: =$F17*I17 | U17: =$F17*J17 | V17: =$F17*M17 | W17: =$F17*N17 | X17: =$F17*O17 | Y17: =$F17*P17 | Z17: =$F17*Q17 | AA17: =$F17*R17 | AB17: =$F17*$G17*$J17 | AC17: =$F17*$G17*MAX(0,$J17-$K17) | AD17: =$F17*$G17*MAX(0,$J17-$L17)
... A43: 38 | B43: Legal & Kepatuhan | C43: Head of Legal & Compliance (merangkap DPO) | D43: Head | E43: 4 | F43: 17462921 | G43: 21 | H43: 0 | I43: 1 | J43: 1 | K43: 0 | L43: 0 | M43: =MAX(0,H43-$K43) | N43: =MAX(0,I43-$K43) | O43: =MAX(0,J43-$K43) | P43: =MAX(0,H43-$L43) | Q43: =MAX(0,I43-$L43) | R43: =MAX(0,J43-$L43) | S43: =$F43*H43 | T43: =$F43*I43 | U43: =$F43*J43 | V43: =$F43*M43 | W43: =$F43*N43 | X43: =$F43*O43 | Y43: =$F43*P43 | Z43: =$F43*Q43 | AA43: =$F43*R43 | AB43: =$F43*$G43*$J43 | AC43: =$F43*$G43*MAX(0,$J43-$K43) | AD43: =$F43*$G43*MAX(0,$J43-$L43)
C44: TOTAL | H44: =SUM(H6:H43) | I44: =SUM(I6:I43) | J44: =SUM(J6:J43) | M44: =SUM(M6:M43) | N44: =SUM(N6:N43) | O44: =SUM(O6:O43) | P44: =SUM(P6:P43) | Q44: =SUM(Q6:Q43) | R44: =SUM(R6:R43) | S44: =SUM(S6:S43) | T44: =SUM(T6:T43) | ... AD44: =SUM(AD6:AD43)
C45: UJI vs model lama (harus 0) | J45: =J44-42 | U45: =U44-636272061.75 | AB45: =AB44-11689208853
A47: PERBANDINGAN TIGA SKENARIO (run-rate per bulan pada akhir tiap fase)
A48: Pos | F48: Fase 0 - A | G48: Fase 0 - B | H48: Fase 0 - C | I48: Fase 1 - A | J48: Fase 1 - B | K48: Fase 1 - C | L48: Fase 2 - A | M48: Fase 2 - B | N48: Fase 2 - C
A49: Jumlah karyawan (headcount) | F49: =H44 | G49: =M44 | H49: =P44 | I49: =I44 | J49: =N44 | K49: =Q44 | L49: =J44 | M49: =O44 | N49: =R44
A50: Biaya SDM per bulan (gaji + iuran + THR), Rp | F50: =S44 | G50: =V44 | H50: =Y44 | I50: =T44 | J50: =W44 | K50: =Z44 | L50: =U44 | M50: =X44 | N50: =AA44
A51: Biaya non-gaji melekat SDM per bulan, Rp (kursi, lisensi dasar, asuransi, pelatihan) | F51: =F49*2150000.000000 | G51: =G49*2150000.000000 | H51: =H49*2150000.000000 | I51: =I49*2000000.000000 | J51: =J49*2000000.000000 | K51: =K49*2000000.000000 | L51: =L49*1864285.714286 | M51: =M49*1864285.714286 | N51: =N49*1864285.714286
A52: Biaya AI per bulan (tool + biaya tersembunyi berulang), Rp | F52: 0 | G52: =AI_B_F0 | H52: =AI_C_F0 | I52: 0 | J52: =AI_B_F1 | K52: =AI_C_F1 | L52: 0 | M52: =AI_B_F2 | N52: =AI_C_F2
A53: TOTAL BIAYA TERKAIT SDM + AI PER BULAN, Rp | F53: =F50+F51+F52 | G53: =G50+G51+G52 | H53: =H50+H51+H52 | I53: =I50+I51+I52 | J53: =J50+J51+J52 | K53: =K50+K51+K52 | L53: =L50+L51+L52 | M53: =M50+M51+M52 | N53: =N50+N51+N52
A54: Penghematan terhadap Skenario A per bulan, Rp (negatif = lebih mahal) | F54: =F53-F53 | G54: =F53-G53 | H54: =F53-H53 | I54: =I53-I53 | J54: =I53-J53 | K54: =I53-K53 | L54: =L53-L53 | M54: =L53-M53 | N54: =L53-N53
A55: Penghematan terhadap Skenario A, % | F55: =IF(F53=0,0,(F53-F53)/F53) | G55: =IF(F53=0,0,(F53-G53)/F53) | H55: =IF(F53=0,0,(F53-H53)/F53) | I55: =IF(I53=0,0,(I53-I53)/I53) | J55: =IF(I53=0,0,(I53-J53)/I53) | K55: =IF(I53=0,0,(I53-K53)/I53) | L55: =IF(L53=0,0,(L53-L53)/L53) | M55: =IF(L53=0,0,(L53-M53)/L53) | N55: =IF(L53=0,0,(L53-N53)/L53)
A56: Pengurangan headcount terhadap Skenario A (orang) | F56: =F49-F49 | G56: =F49-G49 | H56: =F49-H49 | I56: =I49-I49 | J56: =I49-J49 | K56: =I49-K49 | L56: =L49-L49 | M56: =L49-M49 | N56: =L49-N49
A58: Risiko utama tiap skenario
A59: A - Semua manusia | B59: Biaya tetap tertinggi; runway terpendek. Perpres 27/2026 membatasi potongan roda dua 8% [S-25] sehingga pendapatan per order tertekan - struktur biaya ini paling rentan bila likuiditas pasar terlambat terbentuk. Tidak ada risiko baru dari otomasi.
A60: B - Hibrida (REKOMENDASI) | B60: Ketergantungan pada 1 kontraktor pemelihara otomasi; kewajiban baru UU PDP (DPIA, Pasal 10, Pasal 56); mutu jawaban CS turun bila basis pengetahuan tidak dirawat. Pemisahan tugas keuangan TETAP utuh.
A61: C - AI-maksimal | B61: MELANGGAR pemisahan tugas keuangan (Treasury/Settlement dihapus - DESAIN 6 & SOP-07). Kanal darurat 24 jam tidak lagi terjamin (SOP-05). Backend Senior menjadi titik tunggal kegagalan pada modul dompet. Tidak layak diajukan ke uji tuntas investor.

Sheet Perbandingan 24 Bulan
A1: AntarKita - Perbandingan Bulan 1-24: Skenario A / B / C
A2: Aturan aktivasi posisi identik dengan model lama: orang(bulan m) = 0 bila m < Bulan Mulai; selain itu = jumlah orang fase yang berlaku pada bulan m (Fase 0 = bulan 1-3, Fase 1 = bulan 4-12, Fase 2 = bulan 13-24), dikurangi kolom POTONG pada lembar 'Skenario A B C'.
C4: BULAN KE- | D4: 1 | E4: 2 | F4: 3 | G4: 4 | H4: 5 | I4: 6 | J4: 7 | K4: 8 | L4: 9 | M4: 10 | N4: 11 | O4: 12 | P4: 13 | Q4: 14 | R4: 15 | S4: 16 | T4: 17 | U4: 18 | V4: 19 | W4: 20 | X4: 21 | Y4: 22 | Z4: 23 | AA4: 24
A5: Order selesai per hari (jalur pertumbuhan) | B5: [ASUMSI] jalur naik ke 600 pada bulan 12 dan 2.400 pada bulan 24 (target Bab 5) | D5: 0 | E5: 10 | F5: 30 | G5: 60 | H5: 100 | I5: 150 | J5: 210 | K5: 280 | L5: 350 | M5: 430 | N5: 510 | O5: 600 | P5: 700 | Q5: 820 | R5: 950 | S5: 1090 | T5: 1240 | U5: 1400 | V5: 1570 | W5: 1750 | X5: 1940 | Y5: 2100 | Z5: 2250 | AA5: 2400
A6: Order selesai per bulan | D6: =D5*Hari_Bulan | E6: =E5*Hari_Bulan | F6: =F5*Hari_Bulan | G6: =G5*Hari_Bulan | H6: =H5*Hari_Bulan | I6: =I5*Hari_Bulan | J6: =J5*Hari_Bulan | K6: =K5*Hari_Bulan | ... AA6: =AA5*Hari_Bulan
A7: Tiket masuk per bulan | D7: =D6*Tiket_Per1000_Th1/1000 | E7: =E6*Tiket_Per1000_Th1/1000 | F7: =F6*Tiket_Per1000_Th1/1000 | G7: =G6*Tiket_Per1000_Th1/1000 | H7: =H6*Tiket_Per1000_Th1/1000 | I7: =I6*Tiket_Per1000_Th1/1000 | J7: =J6*Tiket_Per1000_Th1/1000 | K7: =K6*Tiket_Per1000_Th1/1000 | ... O7: =O6*Tiket_Per1000_Th1/1000 | P7: =P6*Tiket_Per1000_Th2/1000 | Q7: =Q6*Tiket_Per1000_Th2/1000 | R7: =R6*Tiket_Per1000_Th2/1000 | S7: =S6*Tiket_Per1000_Th2/1000 | T7: =T6*Tiket_Per1000_Th2/1000 | U7: =U6*Tiket_Per1000_Th2/1000 | V7: =V6*Tiket_Per1000_Th2/1000 | W7: =W6*Tiket_Per1000_Th2/1000 | ... AA7: =AA6*Tiket_Per1000_Th2/1000
A9: A. JUMLAH ORANG AKTIF PER BULAN - SKENARIO A (semua manusia)
A10: Direktur Utama (CEO) | B10: ='Skenario A B C'!$F$6 | D10: =IF(1<'Skenario A B C'!$E$6,0,MAX(0,'Skenario A B C'!$H$6-'Skenario A B C'!$AE$6)) | E10: =IF(2<'Skenario A B C'!$E$6,0,MAX(0,'Skenario A B C'!$H$6-'Skenario A B C'!$AE$6)) | F10: =IF(3<'Skenario A B C'!$E$6,0,MAX(0,'Skenario A B C'!$H$6-'Skenario A B C'!$AE$6)) | G10: =IF(4<'Skenario A B C'!$E$6,0,MAX(0,'Skenario A B C'!$I$6-'Skenario A B C'!$AE$6)) | H10: =IF(5<'Skenario A B C'!$E$6,0,MAX(0,'Skenario A B C'!$I$6-'Skenario A B C'!$AE$6)) | I10: =IF(6<'Skenario A B C'!$E$6,0,MAX(0,'Skenario A B C'!$I$6-'Skenario A B C'!$AE$6)) | J10: =IF(7<'Skenario A B C'!$E$6,0,MAX(0,'Skenario A B C'!$I$6-'Skenario A B C'!$AE$6)) | K10: =IF(8<'Skenario A B C'!$E$6,0,MAX(0,'Skenario A B C'!$I$6-'Skenario A B C'!$AE$6)) | L10: =IF(9<'Skenario A B C'!$E$6,0,MAX(0,'Skenario A B C'!$I$6-'Skenario A B C'!$AE$6)) | M10: =IF(10<'Skenario A B C'!$E$6,0,MAX(0,'Skenario A B C'!$I$6-'Skenario A B C'!$AE$6)) | N10: =IF(11<'Skenario A B C'!$E$6,0,MAX(0,'Skenario A B C'!$I$6-'Skenario A B C'!$AE$6)) | O10: =IF(12<'Skenario A B C'!$E$6,0,MAX(0,'Skenario A B C'!$I$6-'Skenario A B C'!$AE$6)) | P10: =IF(13<'Skenario A B C'!$E$6,0,MAX(0,'Skenario A B C'!$J$6-'Skenario A B C'!$AE$6)) | Q10: =IF(14<'Skenario A B C'!$E$6,0,MAX(0,'Skenario A B C'!$J$6-'Skenario A B C'!$AE$6)) | R10: =IF(15<'Skenario A B C'!$E$6,0,MAX(0,'Skenario A B C'!$J$6-'Skenario A B C'!$AE$6)) | S10: =IF(16<'Skenario A B C'!$E$6,0,MAX(0,'Skenario A B C'!$J$6-'Skenario A B C'!$AE$6)) | T10: =IF(17<'Skenario A B C'!$E$6,0,MAX(0,'Skenario A B C'!$J$6-'Skenario A B C'!$AE$6)) | U10: =IF(18<'Skenario A B C'!$E$6,0,MAX(0,'Skenario A B C'!$J$6-'Skenario A B C'!$AE$6)) | V10: =IF(19<'Skenario A B C'!$E$6,0,MAX(0,'Skenario A B C'!$J$6-'Skenario A B C'!$AE$6)) | W10: =IF(20<'Skenario A B C'!$E$6,0,MAX(0,'Skenario A B C'!$J$6-'Skenario A B C'!$AE$6)) | X10: =IF(21<'Skenario A B C'!$E$6,0,MAX(0,'Skenario A B C'!$J$6-'Skenario A B C'!$AE$6)) | Y10: =IF(22<'Skenario A B C'!$E$6,0,MAX(0,'Skenario A B C'!$J$6-'Skenario A B C'!$AE$6)) | Z10: =IF(23<'Skenario A B C'!$E$6,0,MAX(0,'Skenario A B C'!$J$6-'Skenario A B C'!$AE$6)) | AA10: =IF(24<'Skenario A B C'!$E$6,0,MAX(0,'Skenario A B C'!$J$6-'Skenario A B C'!$AE$6))
A11: HR & GA Generalist | B11: ='Skenario A B C'!$F$7 | D11: =IF(1<'Skenario A B C'!$E$7,0,MAX(0,'Skenario A B C'!$H$7-'Skenario A B C'!$AE$7)) | E11: =IF(2<'Skenario A B C'!$E$7,0,MAX(0,'Skenario A B C'!$H$7-'Skenario A B C'!$AE$7)) | F11: =IF(3<'Skenario A B C'!$E$7,0,MAX(0,'Skenario A B C'!$H$7-'Skenario A B C'!$AE$7)) | G11: =IF(4<'Skenario A B C'!$E$7,0,MAX(0,'Skenario A B C'!$I$7-'Skenario A B C'!$AE$7)) | H11: =IF(5<'Skenario A B C'!$E$7,0,MAX(0,'Skenario A B C'!$I$7-'Skenario A B C'!$AE$7)) | I11: =IF(6<'Skenario A B C'!$E$7,0,MAX(0,'Skenario A B C'!$I$7-'Skenario A B C'!$AE$7)) | J11: =IF(7<'Skenario A B C'!$E$7,0,MAX(0,'Skenario A B C'!$I$7-'Skenario A B C'!$AE$7)) | K11: =IF(8<'Skenario A B C'!$E$7,0,MAX(0,'Skenario A B C'!$I$7-'Skenario A B C'!$AE$7)) | L11: =IF(9<'Skenario A B C'!$E$7,0,MAX(0,'Skenario A B C'!$I$7-'Skenario A B C'!$AE$7)) | M11: =IF(10<'Skenario A B C'!$E$7,0,MAX(0,'Skenario A B C'!$I$7-'Skenario A B C'!$AE$7)) | N11: =IF(11<'Skenario A B C'!$E$7,0,MAX(0,'Skenario A B C'!$I$7-'Skenario A B C'!$AE$7)) | O11: =IF(12<'Skenario A B C'!$E$7,0,MAX(0,'Skenario A B C'!$I$7-'Skenario A B C'!$AE$7)) | P11: =IF(13<'Skenario A B C'!$E$7,0,MAX(0,'Skenario A B C'!$J$7-'Skenario A B C'!$AE$7)) | Q11: =IF(14<'Skenario A B C'!$E$7,0,MAX(0,'Skenario A B C'!$J$7-'Skenario A B C'!$AE$7)) | R11: =IF(15<'Skenario A B C'!$E$7,0,MAX(0,'Skenario A B C'!$J$7-'Skenario A B C'!$AE$7)) | S11: =IF(16<'Skenario A B C'!$E$7,0,MAX(0,'Skenario A B C'!$J$7-'Skenario A B C'!$AE$7)) | T11: =IF(17<'Skenario A B C'!$E$7,0,MAX(0,'Skenario A B C'!$J$7-'Skenario A B C'!$AE$7)) | U11: =IF(18<'Skenario A B C'!$E$7,0,MAX(0,'Skenario A B C'!$J$7-'Skenario A B C'!$AE$7)) | V11: =IF(19<'Skenario A B C'!$E$7,0,MAX(0,'Skenario A B C'!$J$7-'Skenario A B C'!$AE$7)) | W11: =IF(20<'Skenario A B C'!$E$7,0,MAX(0,'Skenario A B C'!$J$7-'Skenario A B C'!$AE$7)) | X11: =IF(21<'Skenario A B C'!$E$7,0,MAX(0,'Skenario A B C'!$J$7-'Skenario A B C'!$AE$7)) | Y11: =IF(22<'Skenario A B C'!$E$7,0,MAX(0,'Skenario A B C'!$J$7-'Skenario A B C'!$AE$7)) | Z11: =IF(23<'Skenario A B C'!$E$7,0,MAX(0,'Skenario A B C'!$J$7-'Skenario A B C'!$AE$7)) | AA11: =IF(24<'Skenario A B C'!$E$7,0,MAX(0,'Skenario A B C'!$J$7-'Skenario A B C'!$AE$7))
A12: Direktur Teknologi (CTO) | B12: ='Skenario A B C'!$F$8 | D12: =IF(1<'Skenario A B C'!$E$8,0,MAX(0,'Skenario A B C'!$H$8-'Skenario A B C'!$AE$8)) | E12: =IF(2<'Skenario A B C'!$E$8,0,MAX(0,'Skenario A B C'!$H$8-'Skenario A B C'!$AE$8)) | F12: =IF(3<'Skenario A B C'!$E$8,0,MAX(0,'Skenario A B C'!$H$8-'Skenario A B C'!$AE$8)) | G12: =IF(4<'Skenario A B C'!$E$8,0,MAX(0,'Skenario A B C'!$I$8-'Skenario A B C'!$AE$8)) | H12: =IF(5<'Skenario A B C'!$E$8,0,MAX(0,'Skenario A B C'!$I$8-'Skenario A B C'!$AE$8)) | I12: =IF(6<'Skenario A B C'!$E$8,0,MAX(0,'Skenario A B C'!$I$8-'Skenario A B C'!$AE$8)) | J12: =IF(7<'Skenario A B C'!$E$8,0,MAX(0,'Skenario A B C'!$I$8-'Skenario A B C'!$AE$8)) | K12: =IF(8<'Skenario A B C'!$E$8,0,MAX(0,'Skenario A B C'!$I$8-'Skenario A B C'!$AE$8)) | L12: =IF(9<'Skenario A B C'!$E$8,0,MAX(0,'Skenario A B C'!$I$8-'Skenario A B C'!$AE$8)) | M12: =IF(10<'Skenario A B C'!$E$8,0,MAX(0,'Skenario A B C'!$I$8-'Skenario A B C'!$AE$8)) | N12: =IF(11<'Skenario A B C'!$E$8,0,MAX(0,'Skenario A B C'!$I$8-'Skenario A B C'!$AE$8)) | O12: =IF(12<'Skenario A B C'!$E$8,0,MAX(0,'Skenario A B C'!$I$8-'Skenario A B C'!$AE$8)) | P12: =IF(13<'Skenario A B C'!$E$8,0,MAX(0,'Skenario A B C'!$J$8-'Skenario A B C'!$AE$8)) | Q12: =IF(14<'Skenario A B C'!$E$8,0,MAX(0,'Skenario A B C'!$J$8-'Skenario A B C'!$AE$8)) | R12: =IF(15<'Skenario A B C'!$E$8,0,MAX(0,'Skenario A B C'!$J$8-'Skenario A B C'!$AE$8)) | S12: =IF(16<'Skenario A B C'!$E$8,0,MAX(0,'Skenario A B C'!$J$8-'Skenario A B C'!$AE$8)) | T12: =IF(17<'Skenario A B C'!$E$8,0,MAX(0,'Skenario A B C'!$J$8-'Skenario A B C'!$AE$8)) | U12: =IF(18<'Skenario A B C'!$E$8,0,MAX(0,'Skenario A B C'!$J$8-'Skenario A B C'!$AE$8)) | V12: =IF(19<'Skenario A B C'!$E$8,0,MAX(0,'Skenario A B C'!$J$8-'Skenario A B C'!$AE$8)) | W12: =IF(20<'Skenario A B C'!$E$8,0,MAX(0,'Skenario A B C'!$J$8-'Skenario A B C'!$AE$8)) | X12: =IF(21<'Skenario A B C'!$E$8,0,MAX(0,'Skenario A B C'!$J$8-'Skenario A B C'!$AE$8)) | Y12: =IF(22<'Skenario A B C'!$E$8,0,MAX(0,'Skenario A B C'!$J$8-'Skenario A B C'!$AE$8)) | Z12: =IF(23<'Skenario A B C'!$E$8,0,MAX(0,'Skenario A B C'!$J$8-'Skenario A B C'!$AE$8)) | AA12: =IF(24<'Skenario A B C'!$E$8,0,MAX(0,'Skenario A B C'!$J$8-'Skenario A B C'!$AE$8))
A13: Engineering Manager | B13: ='Skenario A B C'!$F$9 | D13: =IF(1<'Skenario A B C'!$E$9,0,MAX(0,'Skenario A B C'!$H$9-'Skenario A B C'!$AE$9)) | E13: =IF(2<'Skenario A B C'!$E$9,0,MAX(0,'Skenario A B C'!$H$9-'Skenario A B C'!$AE$9)) | F13: =IF(3<'Skenario A B C'!$E$9,0,MAX(0,'Skenario A B C'!$H$9-'Skenario A B C'!$AE$9)) | G13: =IF(4<'Skenario A B C'!$E$9,0,MAX(0,'Skenario A B C'!$I$9-'Skenario A B C'!$AE$9)) | H13: =IF(5<'Skenario A B C'!$E$9,0,MAX(0,'Skenario A B C'!$I$9-'Skenario A B C'!$AE$9)) | I13: =IF(6<'Skenario A B C'!$E$9,0,MAX(0,'Skenario A B C'!$I$9-'Skenario A B C'!$AE$9)) | J13: =IF(7<'Skenario A B C'!$E$9,0,MAX(0,'Skenario A B C'!$I$9-'Skenario A B C'!$AE$9)) | K13: =IF(8<'Skenario A B C'!$E$9,0,MAX(0,'Skenario A B C'!$I$9-'Skenario A B C'!$AE$9)) | L13: =IF(9<'Skenario A B C'!$E$9,0,MAX(0,'Skenario A B C'!$I$9-'Skenario A B C'!$AE$9)) | M13: =IF(10<'Skenario A B C'!$E$9,0,MAX(0,'Skenario A B C'!$I$9-'Skenario A B C'!$AE$9)) | N13: =IF(11<'Skenario A B C'!$E$9,0,MAX(0,'Skenario A B C'!$I$9-'Skenario A B C'!$AE$9)) | O13: =IF(12<'Skenario A B C'!$E$9,0,MAX(0,'Skenario A B C'!$I$9-'Skenario A B C'!$AE$9)) | P13: =IF(13<'Skenario A B C'!$E$9,0,MAX(0,'Skenario A B C'!$J$9-'Skenario A B C'!$AE$9)) | Q13: =IF(14<'Skenario A B C'!$E$9,0,MAX(0,'Skenario A B C'!$J$9-'Skenario A B C'!$AE$9)) | R13: =IF(15<'Skenario A B C'!$E$9,0,MAX(0,'Skenario A B C'!$J$9-'Skenario A B C'!$AE$9)) | S13: =IF(16<'Skenario A B C'!$E$9,0,MAX(0,'Skenario A B C'!$J$9-'Skenario A B C'!$AE$9)) | T13: =IF(17<'Skenario A B C'!$E$9,0,MAX(0,'Skenario A B C'!$J$9-'Skenario A B C'!$AE$9)) | U13: =IF(18<'Skenario A B C'!$E$9,0,MAX(0,'Skenario A B C'!$J$9-'Skenario A B C'!$AE$9)) | V13: =IF(19<'Skenario A B C'!$E$9,0,MAX(0,'Skenario A B C'!$J$9-'Skenario A B C'!$AE$9)) | W13: =IF(20<'Skenario A B C'!$E$9,0,MAX(0,'Skenario A B C'!$J$9-'Skenario A B C'!$AE$9)) | X13: =IF(21<'Skenario A B C'!$E$9,0,MAX(0,'Skenario A B C'!$J$9-'Skenario A B C'!$AE$9)) | Y13: =IF(22<'Skenario A B C'!$E$9,0,MAX(0,'Skenario A B C'!$J$9-'Skenario A B C'!$AE$9)) | Z13: =IF(23<'Skenario A B C'!$E$9,0,MAX(0,'Skenario A B C'!$J$9-'Skenario A B C'!$AE$9)) | AA13: =IF(24<'Skenario A B C'!$E$9,0,MAX(0,'Skenario A B C'!$J$9-'Skenario A B C'!$AE$9))
A14: Mobile Engineer (Senior) | B14: ='Skenario A B C'!$F$10 | D14: =IF(1<'Skenario A B C'!$E$10,0,MAX(0,'Skenario A B C'!$H$10-'Skenario A B C'!$AE$10)) | E14: =IF(2<'Skenario A B C'!$E$10,0,MAX(0,'Skenario A B C'!$H$10-'Skenario A B C'!$AE$10)) | F14: =IF(3<'Skenario A B C'!$E$10,0,MAX(0,'Skenario A B C'!$H$10-'Skenario A B C'!$AE$10)) | G14: =IF(4<'Skenario A B C'!$E$10,0,MAX(0,'Skenario A B C'!$I$10-'Skenario A B C'!$AE$10)) | H14: =IF(5<'Skenario A B C'!$E$10,0,MAX(0,'Skenario A B C'!$I$10-'Skenario A B C'!$AE$10)) | I14: =IF(6<'Skenario A B C'!$E$10,0,MAX(0,'Skenario A B C'!$I$10-'Skenario A B C'!$AE$10)) | J14: =IF(7<'Skenario A B C'!$E$10,0,MAX(0,'Skenario A B C'!$I$10-'Skenario A B C'!$AE$10)) | K14: =IF(8<'Skenario A B C'!$E$10,0,MAX(0,'Skenario A B C'!$I$10-'Skenario A B C'!$AE$10)) | L14: =IF(9<'Skenario A B C'!$E$10,0,MAX(0,'Skenario A B C'!$I$10-'Skenario A B C'!$AE$10)) | M14: =IF(10<'Skenario A B C'!$E$10,0,MAX(0,'Skenario A B C'!$I$10-'Skenario A B C'!$AE$10)) | N14: =IF(11<'Skenario A B C'!$E$10,0,MAX(0,'Skenario A B C'!$I$10-'Skenario A B C'!$AE$10)) | O14: =IF(12<'Skenario A B C'!$E$10,0,MAX(0,'Skenario A B C'!$I$10-'Skenario A B C'!$AE$10)) | P14: =IF(13<'Skenario A B C'!$E$10,0,MAX(0,'Skenario A B C'!$J$10-'Skenario A B C'!$AE$10)) | Q14: =IF(14<'Skenario A B C'!$E$10,0,MAX(0,'Skenario A B C'!$J$10-'Skenario A B C'!$AE$10)) | R14: =IF(15<'Skenario A B C'!$E$10,0,MAX(0,'Skenario A B C'!$J$10-'Skenario A B C'!$AE$10)) | S14: =IF(16<'Skenario A B C'!$E$10,0,MAX(0,'Skenario A B C'!$J$10-'Skenario A B C'!$AE$10)) | T14: =IF(17<'Skenario A B C'!$E$10,0,MAX(0,'Skenario A B C'!$J$10-'Skenario A B C'!$AE$10)) | U14: =IF(18<'Skenario A B C'!$E$10,0,MAX(0,'Skenario A B C'!$J$10-'Skenario A B C'!$AE$10)) | V14: =IF(19<'Skenario A B C'!$E$10,0,MAX(0,'Skenario A B C'!$J$10-'Skenario A B C'!$AE$10)) | W14: =IF(20<'Skenario A B C'!$E$10,0,MAX(0,'Skenario A B C'!$J$10-'Skenario A B C'!$AE$10)) | X14: =IF(21<'Skenario A B C'!$E$10,0,MAX(0,'Skenario A B C'!$J$10-'Skenario A B C'!$AE$10)) | Y14: =IF(22<'Skenario A B C'!$E$10,0,MAX(0,'Skenario A B C'!$J$10-'Skenario A B C'!$AE$10)) | Z14: =IF(23<'Skenario A B C'!$E$10,0,MAX(0,'Skenario A B C'!$J$10-'Skenario A B C'!$AE$10)) | AA14: =IF(24<'Skenario A B C'!$E$10,0,MAX(0,'Skenario A B C'!$J$10-'Skenario A B C'!$AE$10))
A15: Mobile Engineer (Mid) | B15: ='Skenario A B C'!$F$11 | D15: =IF(1<'Skenario A B C'!$E$11,0,MAX(0,'Skenario A B C'!$H$11-'Skenario A B C'!$AE$11)) | E15: =IF(2<'Skenario A B C'!$E$11,0,MAX(0,'Skenario A B C'!$H$11-'Skenario A B C'!$AE$11)) | F15: =IF(3<'Skenario A B C'!$E$11,0,MAX(0,'Skenario A B C'!$H$11-'Skenario A B C'!$AE$11)) | G15: =IF(4<'Skenario A B C'!$E$11,0,MAX(0,'Skenario A B C'!$I$11-'Skenario A B C'!$AE$11)) | H15: =IF(5<'Skenario A B C'!$E$11,0,MAX(0,'Skenario A B C'!$I$11-'Skenario A B C'!$AE$11)) | I15: =IF(6<'Skenario A B C'!$E$11,0,MAX(0,'Skenario A B C'!$I$11-'Skenario A B C'!$AE$11)) | J15: =IF(7<'Skenario A B C'!$E$11,0,MAX(0,'Skenario A B C'!$I$11-'Skenario A B C'!$AE$11)) | K15: =IF(8<'Skenario A B C'!$E$11,0,MAX(0,'Skenario A B C'!$I$11-'Skenario A B C'!$AE$11)) | L15: =IF(9<'Skenario A B C'!$E$11,0,MAX(0,'Skenario A B C'!$I$11-'Skenario A B C'!$AE$11)) | M15: =IF(10<'Skenario A B C'!$E$11,0,MAX(0,'Skenario A B C'!$I$11-'Skenario A B C'!$AE$11)) | N15: =IF(11<'Skenario A B C'!$E$11,0,MAX(0,'Skenario A B C'!$I$11-'Skenario A B C'!$AE$11)) | O15: =IF(12<'Skenario A B C'!$E$11,0,MAX(0,'Skenario A B C'!$I$11-'Skenario A B C'!$AE$11)) | P15: =IF(13<'Skenario A B C'!$E$11,0,MAX(0,'Skenario A B C'!$J$11-'Skenario A B C'!$AE$11)) | Q15: =IF(14<'Skenario A B C'!$E$11,0,MAX(0,'Skenario A B C'!$J$11-'Skenario A B C'!$AE$11)) | R15: =IF(15<'Skenario A B C'!$E$11,0,MAX(0,'Skenario A B C'!$J$11-'Skenario A B C'!$AE$11)) | S15: =IF(16<'Skenario A B C'!$E$11,0,MAX(0,'Skenario A B C'!$J$11-'Skenario A B C'!$AE$11)) | T15: =IF(17<'Skenario A B C'!$E$11,0,MAX(0,'Skenario A B C'!$J$11-'Skenario A B C'!$AE$11)) | U15: =IF(18<'Skenario A B C'!$E$11,0,MAX(0,'Skenario A B C'!$J$11-'Skenario A B C'!$AE$11)) | V15: =IF(19<'Skenario A B C'!$E$11,0,MAX(0,'Skenario A B C'!$J$11-'Skenario A B C'!$AE$11)) | W15: =IF(20<'Skenario A B C'!$E$11,0,MAX(0,'Skenario A B C'!$J$11-'Skenario A B C'!$AE$11)) | X15: =IF(21<'Skenario A B C'!$E$11,0,MAX(0,'Skenario A B C'!$J$11-'Skenario A B C'!$AE$11)) | Y15: =IF(22<'Skenario A B C'!$E$11,0,MAX(0,'Skenario A B C'!$J$11-'Skenario A B C'!$AE$11)) | Z15: =IF(23<'Skenario A B C'!$E$11,0,MAX(0,'Skenario A B C'!$J$11-'Skenario A B C'!$AE$11)) | AA15: =IF(24<'Skenario A B C'!$E$11,0,MAX(0,'Skenario A B C'!$J$11-'Skenario A B C'!$AE$11))
A16: Mobile Engineer (Mid) - gelombang 2 | B16: ='Skenario A B C'!$F$12 | D16: =IF(1<'Skenario A B C'!$E$12,0,MAX(0,'Skenario A B C'!$H$12-'Skenario A B C'!$AE$12)) | E16: =IF(2<'Skenario A B C'!$E$12,0,MAX(0,'Skenario A B C'!$H$12-'Skenario A B C'!$AE$12)) | F16: =IF(3<'Skenario A B C'!$E$12,0,MAX(0,'Skenario A B C'!$H$12-'Skenario A B C'!$AE$12)) | G16: =IF(4<'Skenario A B C'!$E$12,0,MAX(0,'Skenario A B C'!$I$12-'Skenario A B C'!$AE$12)) | H16: =IF(5<'Skenario A B C'!$E$12,0,MAX(0,'Skenario A B C'!$I$12-'Skenario A B C'!$AE$12)) | I16: =IF(6<'Skenario A B C'!$E$12,0,MAX(0,'Skenario A B C'!$I$12-'Skenario A B C'!$AE$12)) | J16: =IF(7<'Skenario A B C'!$E$12,0,MAX(0,'Skenario A B C'!$I$12-'Skenario A B C'!$AE$12)) | K16: =IF(8<'Skenario A B C'!$E$12,0,MAX(0,'Skenario A B C'!$I$12-'Skenario A B C'!$AE$12)) | L16: =IF(9<'Skenario A B C'!$E$12,0,MAX(0,'Skenario A B C'!$I$12-'Skenario A B C'!$AE$12)) | M16: =IF(10<'Skenario A B C'!$E$12,0,MAX(0,'Skenario A B C'!$I$12-'Skenario A B C'!$AE$12)) | N16: =IF(11<'Skenario A B C'!$E$12,0,MAX(0,'Skenario A B C'!$I$12-'Skenario A B C'!$AE$12)) | O16: =IF(12<'Skenario A B C'!$E$12,0,MAX(0,'Skenario A B C'!$I$12-'Skenario A B C'!$AE$12)) | P16: =IF(13<'Skenario A B C'!$E$12,0,MAX(0,'Skenario A B C'!$J$12-'Skenario A B C'!$AE$12)) | Q16: =IF(14<'Skenario A B C'!$E$12,0,MAX(0,'Skenario A B C'!$J$12-'Skenario A B C'!$AE$12)) | R16: =IF(15<'Skenario A B C'!$E$12,0,MAX(0,'Skenario A B C'!$J$12-'Skenario A B C'!$AE$12)) | S16: =IF(16<'Skenario A B C'!$E$12,0,MAX(0,'Skenario A B C'!$J$12-'Skenario A B C'!$AE$12)) | T16: =IF(17<'Skenario A B C'!$E$12,0,MAX(0,'Skenario A B C'!$J$12-'Skenario A B C'!$AE$12)) | U16: =IF(18<'Skenario A B C'!$E$12,0,MAX(0,'Skenario A B C'!$J$12-'Skenario A B C'!$AE$12)) | V16: =IF(19<'Skenario A B C'!$E$12,0,MAX(0,'Skenario A B C'!$J$12-'Skenario A B C'!$AE$12)) | W16: =IF(20<'Skenario A B C'!$E$12,0,MAX(0,'Skenario A B C'!$J$12-'Skenario A B C'!$AE$12)) | X16: =IF(21<'Skenario A B C'!$E$12,0,MAX(0,'Skenario A B C'!$J$12-'Skenario A B C'!$AE$12)) | Y16: =IF(22<'Skenario A B C'!$E$12,0,MAX(0,'Skenario A B C'!$J$12-'Skenario A B C'!$AE$12)) | Z16: =IF(23<'Skenario A B C'!$E$12,0,MAX(0,'Skenario A B C'!$J$12-'Skenario A B C'!$AE$12)) | AA16: =IF(24<'Skenario A B C'!$E$12,0,MAX(0,'Skenario A B C'!$J$12-'Skenario A B C'!$AE$12))
A17: Backend Engineer (Senior) | B17: ='Skenario A B C'!$F$13 | D17: =IF(1<'Skenario A B C'!$E$13,0,MAX(0,'Skenario A B C'!$H$13-'Skenario A B C'!$AE$13)) | E17: =IF(2<'Skenario A B C'!$E$13,0,MAX(0,'Skenario A B C'!$H$13-'Skenario A B C'!$AE$13)) | F17: =IF(3<'Skenario A B C'!$E$13,0,MAX(0,'Skenario A B C'!$H$13-'Skenario A B C'!$AE$13)) | G17: =IF(4<'Skenario A B C'!$E$13,0,MAX(0,'Skenario A B C'!$I$13-'Skenario A B C'!$AE$13)) | H17: =IF(5<'Skenario A B C'!$E$13,0,MAX(0,'Skenario A B C'!$I$13-'Skenario A B C'!$AE$13)) | I17: =IF(6<'Skenario A B C'!$E$13,0,MAX(0,'Skenario A B C'!$I$13-'Skenario A B C'!$AE$13)) | J17: =IF(7<'Skenario A B C'!$E$13,0,MAX(0,'Skenario A B C'!$I$13-'Skenario A B C'!$AE$13)) | K17: =IF(8<'Skenario A B C'!$E$13,0,MAX(0,'Skenario A B C'!$I$13-'Skenario A B C'!$AE$13)) | L17: =IF(9<'Skenario A B C'!$E$13,0,MAX(0,'Skenario A B C'!$I$13-'Skenario A B C'!$AE$13)) | M17: =IF(10<'Skenario A B C'!$E$13,0,MAX(0,'Skenario A B C'!$I$13-'Skenario A B C'!$AE$13)) | N17: =IF(11<'Skenario A B C'!$E$13,0,MAX(0,'Skenario A B C'!$I$13-'Skenario A B C'!$AE$13)) | O17: =IF(12<'Skenario A B C'!$E$13,0,MAX(0,'Skenario A B C'!$I$13-'Skenario A B C'!$AE$13)) | P17: =IF(13<'Skenario A B C'!$E$13,0,MAX(0,'Skenario A B C'!$J$13-'Skenario A B C'!$AE$13)) | Q17: =IF(14<'Skenario A B C'!$E$13,0,MAX(0,'Skenario A B C'!$J$13-'Skenario A B C'!$AE$13)) | R17: =IF(15<'Skenario A B C'!$E$13,0,MAX(0,'Skenario A B C'!$J$13-'Skenario A B C'!$AE$13)) | S17: =IF(16<'Skenario A B C'!$E$13,0,MAX(0,'Skenario A B C'!$J$13-'Skenario A B C'!$AE$13)) | T17: =IF(17<'Skenario A B C'!$E$13,0,MAX(0,'Skenario A B C'!$J$13-'Skenario A B C'!$AE$13)) | U17: =IF(18<'Skenario A B C'!$E$13,0,MAX(0,'Skenario A B C'!$J$13-'Skenario A B C'!$AE$13)) | V17: =IF(19<'Skenario A B C'!$E$13,0,MAX(0,'Skenario A B C'!$J$13-'Skenario A B C'!$AE$13)) | W17: =IF(20<'Skenario A B C'!$E$13,0,MAX(0,'Skenario A B C'!$J$13-'Skenario A B C'!$AE$13)) | X17: =IF(21<'Skenario A B C'!$E$13,0,MAX(0,'Skenario A B C'!$J$13-'Skenario A B C'!$AE$13)) | Y17: =IF(22<'Skenario A B C'!$E$13,0,MAX(0,'Skenario A B C'!$J$13-'Skenario A B C'!$AE$13)) | Z17: =IF(23<'Skenario A B C'!$E$13,0,MAX(0,'Skenario A B C'!$J$13-'Skenario A B C'!$AE$13)) | AA17: =IF(24<'Skenario A B C'!$E$13,0,MAX(0,'Skenario A B C'!$J$13-'Skenario A B C'!$AE$13))
A18: Backend Engineer (Senior) - gelombang 2 | B18: ='Skenario A B C'!$F$14 | D18: =IF(1<'Skenario A B C'!$E$14,0,MAX(0,'Skenario A B C'!$H$14-'Skenario A B C'!$AE$14)) | E18: =IF(2<'Skenario A B C'!$E$14,0,MAX(0,'Skenario A B C'!$H$14-'Skenario A B C'!$AE$14)) | F18: =IF(3<'Skenario A B C'!$E$14,0,MAX(0,'Skenario A B C'!$H$14-'Skenario A B C'!$AE$14)) | G18: =IF(4<'Skenario A B C'!$E$14,0,MAX(0,'Skenario A B C'!$I$14-'Skenario A B C'!$AE$14)) | H18: =IF(5<'Skenario A B C'!$E$14,0,MAX(0,'Skenario A B C'!$I$14-'Skenario A B C'!$AE$14)) | I18: =IF(6<'Skenario A B C'!$E$14,0,MAX(0,'Skenario A B C'!$I$14-'Skenario A B C'!$AE$14)) | J18: =IF(7<'Skenario A B C'!$E$14,0,MAX(0,'Skenario A B C'!$I$14-'Skenario A B C'!$AE$14)) | K18: =IF(8<'Skenario A B C'!$E$14,0,MAX(0,'Skenario A B C'!$I$14-'Skenario A B C'!$AE$14)) | L18: =IF(9<'Skenario A B C'!$E$14,0,MAX(0,'Skenario A B C'!$I$14-'Skenario A B C'!$AE$14)) | M18: =IF(10<'Skenario A B C'!$E$14,0,MAX(0,'Skenario A B C'!$I$14-'Skenario A B C'!$AE$14)) | N18: =IF(11<'Skenario A B C'!$E$14,0,MAX(0,'Skenario A B C'!$I$14-'Skenario A B C'!$AE$14)) | O18: =IF(12<'Skenario A B C'!$E$14,0,MAX(0,'Skenario A B C'!$I$14-'Skenario A B C'!$AE$14)) | P18: =IF(13<'Skenario A B C'!$E$14,0,MAX(0,'Skenario A B C'!$J$14-'Skenario A B C'!$AE$14)) | Q18: =IF(14<'Skenario A B C'!$E$14,0,MAX(0,'Skenario A B C'!$J$14-'Skenario A B C'!$AE$14)) | R18: =IF(15<'Skenario A B C'!$E$14,0,MAX(0,'Skenario A B C'!$J$14-'Skenario A B C'!$AE$14)) | S18: =IF(16<'Skenario A B C'!$E$14,0,MAX(0,'Skenario A B C'!$J$14-'Skenario A B C'!$AE$14)) | T18: =IF(17<'Skenario A B C'!$E$14,0,MAX(0,'Skenario A B C'!$J$14-'Skenario A B C'!$AE$14)) | U18: =IF(18<'Skenario A B C'!$E$14,0,MAX(0,'Skenario A B C'!$J$14-'Skenario A B C'!$AE$14)) | V18: =IF(19<'Skenario A B C'!$E$14,0,MAX(0,'Skenario A B C'!$J$14-'Skenario A B C'!$AE$14)) | W18: =IF(20<'Skenario A B C'!$E$14,0,MAX(0,'Skenario A B C'!$J$14-'Skenario A B C'!$AE$14)) | X18: =IF(21<'Skenario A B C'!$E$14,0,MAX(0,'Skenario A B C'!$J$14-'Skenario A B C'!$AE$14)) | Y18: =IF(22<'Skenario A B C'!$E$14,0,MAX(0,'Skenario A B C'!$J$14-'Skenario A B C'!$AE$14)) | Z18: =IF(23<'Skenario A B C'!$E$14,0,MAX(0,'Skenario A B C'!$J$14-'Skenario A B C'!$AE$14)) | AA18: =IF(24<'Skenario A B C'!$E$14,0,MAX(0,'Skenario A B C'!$J$14-'Skenario A B C'!$AE$14))
A19: Backend Engineer (Mid) | B19: ='Skenario A B C'!$F$15 | D19: =IF(1<'Skenario A B C'!$E$15,0,MAX(0,'Skenario A B C'!$H$15-'Skenario A B C'!$AE$15)) | E19: =IF(2<'Skenario A B C'!$E$15,0,MAX(0,'Skenario A B C'!$H$15-'Skenario A B C'!$AE$15)) | F19: =IF(3<'Skenario A B C'!$E$15,0,MAX(0,'Skenario A B C'!$H$15-'Skenario A B C'!$AE$15)) | G19: =IF(4<'Skenario A B C'!$E$15,0,MAX(0,'Skenario A B C'!$I$15-'Skenario A B C'!$AE$15)) | H19: =IF(5<'Skenario A B C'!$E$15,0,MAX(0,'Skenario A B C'!$I$15-'Skenario A B C'!$AE$15)) | I19: =IF(6<'Skenario A B C'!$E$15,0,MAX(0,'Skenario A B C'!$I$15-'Skenario A B C'!$AE$15)) | J19: =IF(7<'Skenario A B C'!$E$15,0,MAX(0,'Skenario A B C'!$I$15-'Skenario A B C'!$AE$15)) | K19: =IF(8<'Skenario A B C'!$E$15,0,MAX(0,'Skenario A B C'!$I$15-'Skenario A B C'!$AE$15)) | L19: =IF(9<'Skenario A B C'!$E$15,0,MAX(0,'Skenario A B C'!$I$15-'Skenario A B C'!$AE$15)) | M19: =IF(10<'Skenario A B C'!$E$15,0,MAX(0,'Skenario A B C'!$I$15-'Skenario A B C'!$AE$15)) | N19: =IF(11<'Skenario A B C'!$E$15,0,MAX(0,'Skenario A B C'!$I$15-'Skenario A B C'!$AE$15)) | O19: =IF(12<'Skenario A B C'!$E$15,0,MAX(0,'Skenario A B C'!$I$15-'Skenario A B C'!$AE$15)) | P19: =IF(13<'Skenario A B C'!$E$15,0,MAX(0,'Skenario A B C'!$J$15-'Skenario A B C'!$AE$15)) | Q19: =IF(14<'Skenario A B C'!$E$15,0,MAX(0,'Skenario A B C'!$J$15-'Skenario A B C'!$AE$15)) | R19: =IF(15<'Skenario A B C'!$E$15,0,MAX(0,'Skenario A B C'!$J$15-'Skenario A B C'!$AE$15)) | S19: =IF(16<'Skenario A B C'!$E$15,0,MAX(0,'Skenario A B C'!$J$15-'Skenario A B C'!$AE$15)) | T19: =IF(17<'Skenario A B C'!$E$15,0,MAX(0,'Skenario A B C'!$J$15-'Skenario A B C'!$AE$15)) | U19: =IF(18<'Skenario A B C'!$E$15,0,MAX(0,'Skenario A B C'!$J$15-'Skenario A B C'!$AE$15)) | V19: =IF(19<'Skenario A B C'!$E$15,0,MAX(0,'Skenario A B C'!$J$15-'Skenario A B C'!$AE$15)) | W19: =IF(20<'Skenario A B C'!$E$15,0,MAX(0,'Skenario A B C'!$J$15-'Skenario A B C'!$AE$15)) | X19: =IF(21<'Skenario A B C'!$E$15,0,MAX(0,'Skenario A B C'!$J$15-'Skenario A B C'!$AE$15)) | Y19: =IF(22<'Skenario A B C'!$E$15,0,MAX(0,'Skenario A B C'!$J$15-'Skenario A B C'!$AE$15)) | Z19: =IF(23<'Skenario A B C'!$E$15,0,MAX(0,'Skenario A B C'!$J$15-'Skenario A B C'!$AE$15)) | AA19: =IF(24<'Skenario A B C'!$E$15,0,MAX(0,'Skenario A B C'!$J$15-'Skenario A B C'!$AE$15))
A20: Backend Engineer (Mid) - gelombang 2 | B20: ='Skenario A B C'!$F$16 | D20: =IF(1<'Skenario A B C'!$E$16,0,MAX(0,'Skenario A B C'!$H$16-'Skenario A B C'!$AE$16)) | E20: =IF(2<'Skenario A B C'!$E$16,0,MAX(0,'Skenario A B C'!$H$16-'Skenario A B C'!$AE$16)) | F20: =IF(3<'Skenario A B C'!$E$16,0,MAX(0,'Skenario A B C'!$H$16-'Skenario A B C'!$AE$16)) | G20: =IF(4<'Skenario A B C'!$E$16,0,MAX(0,'Skenario A B C'!$I$16-'Skenario A B C'!$AE$16)) | H20: =IF(5<'Skenario A B C'!$E$16,0,MAX(0,'Skenario A B C'!$I$16-'Skenario A B C'!$AE$16)) | I20: =IF(6<'Skenario A B C'!$E$16,0,MAX(0,'Skenario A B C'!$I$16-'Skenario A B C'!$AE$16)) | J20: =IF(7<'Skenario A B C'!$E$16,0,MAX(0,'Skenario A B C'!$I$16-'Skenario A B C'!$AE$16)) | K20: =IF(8<'Skenario A B C'!$E$16,0,MAX(0,'Skenario A B C'!$I$16-'Skenario A B C'!$AE$16)) | L20: =IF(9<'Skenario A B C'!$E$16,0,MAX(0,'Skenario A B C'!$I$16-'Skenario A B C'!$AE$16)) | M20: =IF(10<'Skenario A B C'!$E$16,0,MAX(0,'Skenario A B C'!$I$16-'Skenario A B C'!$AE$16)) | N20: =IF(11<'Skenario A B C'!$E$16,0,MAX(0,'Skenario A B C'!$I$16-'Skenario A B C'!$AE$16)) | O20: =IF(12<'Skenario A B C'!$E$16,0,MAX(0,'Skenario A B C'!$I$16-'Skenario A B C'!$AE$16)) | P20: =IF(13<'Skenario A B C'!$E$16,0,MAX(0,'Skenario A B C'!$J$16-'Skenario A B C'!$AE$16)) | Q20: =IF(14<'Skenario A B C'!$E$16,0,MAX(0,'Skenario A B C'!$J$16-'Skenario A B C'!$AE$16)) | R20: =IF(15<'Skenario A B C'!$E$16,0,MAX(0,'Skenario A B C'!$J$16-'Skenario A B C'!$AE$16)) | S20: =IF(16<'Skenario A B C'!$E$16,0,MAX(0,'Skenario A B C'!$J$16-'Skenario A B C'!$AE$16)) | T20: =IF(17<'Skenario A B C'!$E$16,0,MAX(0,'Skenario A B C'!$J$16-'Skenario A B C'!$AE$16)) | U20: =IF(18<'Skenario A B C'!$E$16,0,MAX(0,'Skenario A B C'!$J$16-'Skenario A B C'!$AE$16)) | V20: =IF(19<'Skenario A B C'!$E$16,0,MAX(0,'Skenario A B C'!$J$16-'Skenario A B C'!$AE$16)) | W20: =IF(20<'Skenario A B C'!$E$16,0,MAX(0,'Skenario A B C'!$J$16-'Skenario A B C'!$AE$16)) | X20: =IF(21<'Skenario A B C'!$E$16,0,MAX(0,'Skenario A B C'!$J$16-'Skenario A B C'!$AE$16)) | Y20: =IF(22<'Skenario A B C'!$E$16,0,MAX(0,'Skenario A B C'!$J$16-'Skenario A B C'!$AE$16)) | Z20: =IF(23<'Skenario A B C'!$E$16,0,MAX(0,'Skenario A B C'!$J$16-'Skenario A B C'!$AE$16)) | AA20: =IF(24<'Skenario A B C'!$E$16,0,MAX(0,'Skenario A B C'!$J$16-'Skenario A B C'!$AE$16))
A21: QA Engineer | B21: ='Skenario A B C'!$F$17 | D21: =IF(1<'Skenario A B C'!$E$17,0,MAX(0,'Skenario A B C'!$H$17-'Skenario A B C'!$AE$17)) | E21: =IF(2<'Skenario A B C'!$E$17,0,MAX(0,'Skenario A B C'!$H$17-'Skenario A B C'!$AE$17)) | F21: =IF(3<'Skenario A B C'!$E$17,0,MAX(0,'Skenario A B C'!$H$17-'Skenario A B C'!$AE$17)) | G21: =IF(4<'Skenario A B C'!$E$17,0,MAX(0,'Skenario A B C'!$I$17-'Skenario A B C'!$AE$17)) | H21: =IF(5<'Skenario A B C'!$E$17,0,MAX(0,'Skenario A B C'!$I$17-'Skenario A B C'!$AE$17)) | I21: =IF(6<'Skenario A B C'!$E$17,0,MAX(0,'Skenario A B C'!$I$17-'Skenario A B C'!$AE$17)) | J21: =IF(7<'Skenario A B C'!$E$17,0,MAX(0,'Skenario A B C'!$I$17-'Skenario A B C'!$AE$17)) | K21: =IF(8<'Skenario A B C'!$E$17,0,MAX(0,'Skenario A B C'!$I$17-'Skenario A B C'!$AE$17)) | L21: =IF(9<'Skenario A B C'!$E$17,0,MAX(0,'Skenario A B C'!$I$17-'Skenario A B C'!$AE$17)) | M21: =IF(10<'Skenario A B C'!$E$17,0,MAX(0,'Skenario A B C'!$I$17-'Skenario A B C'!$AE$17)) | N21: =IF(11<'Skenario A B C'!$E$17,0,MAX(0,'Skenario A B C'!$I$17-'Skenario A B C'!$AE$17)) | O21: =IF(12<'Skenario A B C'!$E$17,0,MAX(0,'Skenario A B C'!$I$17-'Skenario A B C'!$AE$17)) | P21: =IF(13<'Skenario A B C'!$E$17,0,MAX(0,'Skenario A B C'!$J$17-'Skenario A B C'!$AE$17)) | Q21: =IF(14<'Skenario A B C'!$E$17,0,MAX(0,'Skenario A B C'!$J$17-'Skenario A B C'!$AE$17)) | R21: =IF(15<'Skenario A B C'!$E$17,0,MAX(0,'Skenario A B C'!$J$17-'Skenario A B C'!$AE$17)) | S21: =IF(16<'Skenario A B C'!$E$17,0,MAX(0,'Skenario A B C'!$J$17-'Skenario A B C'!$AE$17)) | T21: =IF(17<'Skenario A B C'!$E$17,0,MAX(0,'Skenario A B C'!$J$17-'Skenario A B C'!$AE$17)) | U21: =IF(18<'Skenario A B C'!$E$17,0,MAX(0,'Skenario A B C'!$J$17-'Skenario A B C'!$AE$17)) | V21: =IF(19<'Skenario A B C'!$E$17,0,MAX(0,'Skenario A B C'!$J$17-'Skenario A B C'!$AE$17)) | W21: =IF(20<'Skenario A B C'!$E$17,0,MAX(0,'Skenario A B C'!$J$17-'Skenario A B C'!$AE$17)) | X21: =IF(21<'Skenario A B C'!$E$17,0,MAX(0,'Skenario A B C'!$J$17-'Skenario A B C'!$AE$17)) | Y21: =IF(22<'Skenario A B C'!$E$17,0,MAX(0,'Skenario A B C'!$J$17-'Skenario A B C'!$AE$17)) | Z21: =IF(23<'Skenario A B C'!$E$17,0,MAX(0,'Skenario A B C'!$J$17-'Skenario A B C'!$AE$17)) | AA21: =IF(24<'Skenario A B C'!$E$17,0,MAX(0,'Skenario A B C'!$J$17-'Skenario A B C'!$AE$17))
A22: QA Engineer - gelombang 2 | B22: ='Skenario A B C'!$F$18 | D22: =IF(1<'Skenario A B C'!$E$18,0,MAX(0,'Skenario A B C'!$H$18-'Skenario A B C'!$AE$18)) | E22: =IF(2<'Skenario A B C'!$E$18,0,MAX(0,'Skenario A B C'!$H$18-'Skenario A B C'!$AE$18)) | F22: =IF(3<'Skenario A B C'!$E$18,0,MAX(0,'Skenario A B C'!$H$18-'Skenario A B C'!$AE$18)) | G22: =IF(4<'Skenario A B C'!$E$18,0,MAX(0,'Skenario A B C'!$I$18-'Skenario A B C'!$AE$18)) | H22: =IF(5<'Skenario A B C'!$E$18,0,MAX(0,'Skenario A B C'!$I$18-'Skenario A B C'!$AE$18)) | I22: =IF(6<'Skenario A B C'!$E$18,0,MAX(0,'Skenario A B C'!$I$18-'Skenario A B C'!$AE$18)) | J22: =IF(7<'Skenario A B C'!$E$18,0,MAX(0,'Skenario A B C'!$I$18-'Skenario A B C'!$AE$18)) | K22: =IF(8<'Skenario A B C'!$E$18,0,MAX(0,'Skenario A B C'!$I$18-'Skenario A B C'!$AE$18)) | L22: =IF(9<'Skenario A B C'!$E$18,0,MAX(0,'Skenario A B C'!$I$18-'Skenario A B C'!$AE$18)) | M22: =IF(10<'Skenario A B C'!$E$18,0,MAX(0,'Skenario A B C'!$I$18-'Skenario A B C'!$AE$18)) | N22: =IF(11<'Skenario A B C'!$E$18,0,MAX(0,'Skenario A B C'!$I$18-'Skenario A B C'!$AE$18)) | O22: =IF(12<'Skenario A B C'!$E$18,0,MAX(0,'Skenario A B C'!$I$18-'Skenario A B C'!$AE$18)) | P22: =IF(13<'Skenario A B C'!$E$18,0,MAX(0,'Skenario A B C'!$J$18-'Skenario A B C'!$AE$18)) | Q22: =IF(14<'Skenario A B C'!$E$18,0,MAX(0,'Skenario A B C'!$J$18-'Skenario A B C'!$AE$18)) | R22: =IF(15<'Skenario A B C'!$E$18,0,MAX(0,'Skenario A B C'!$J$18-'Skenario A B C'!$AE$18)) | S22: =IF(16<'Skenario A B C'!$E$18,0,MAX(0,'Skenario A B C'!$J$18-'Skenario A B C'!$AE$18)) | T22: =IF(17<'Skenario A B C'!$E$18,0,MAX(0,'Skenario A B C'!$J$18-'Skenario A B C'!$AE$18)) | U22: =IF(18<'Skenario A B C'!$E$18,0,MAX(0,'Skenario A B C'!$J$18-'Skenario A B C'!$AE$18)) | V22: =IF(19<'Skenario A B C'!$E$18,0,MAX(0,'Skenario A B C'!$J$18-'Skenario A B C'!$AE$18)) | W22: =IF(20<'Skenario A B C'!$E$18,0,MAX(0,'Skenario A B C'!$J$18-'Skenario A B C'!$AE$18)) | X22: =IF(21<'Skenario A B C'!$E$18,0,MAX(0,'Skenario A B C'!$J$18-'Skenario A B C'!$AE$18)) | Y22: =IF(22<'Skenario A B C'!$E$18,0,MAX(0,'Skenario A B C'!$J$18-'Skenario A B C'!$AE$18)) | Z22: =IF(23<'Skenario A B C'!$E$18,0,MAX(0,'Skenario A B C'!$J$18-'Skenario A B C'!$AE$18)) | AA22: =IF(24<'Skenario A B C'!$E$18,0,MAX(0,'Skenario A B C'!$J$18-'Skenario A B C'!$AE$18))
A23: Junior Software Engineer | B23: ='Skenario A B C'!$F$19 | D23: =IF(1<'Skenario A B C'!$E$19,0,MAX(0,'Skenario A B C'!$H$19-'Skenario A B C'!$AE$19)) | E23: =IF(2<'Skenario A B C'!$E$19,0,MAX(0,'Skenario A B C'!$H$19-'Skenario A B C'!$AE$19)) | F23: =IF(3<'Skenario A B C'!$E$19,0,MAX(0,'Skenario A B C'!$H$19-'Skenario A B C'!$AE$19)) | G23: =IF(4<'Skenario A B C'!$E$19,0,MAX(0,'Skenario A B C'!$I$19-'Skenario A B C'!$AE$19)) | H23: =IF(5<'Skenario A B C'!$E$19,0,MAX(0,'Skenario A B C'!$I$19-'Skenario A B C'!$AE$19)) | I23: =IF(6<'Skenario A B C'!$E$19,0,MAX(0,'Skenario A B C'!$I$19-'Skenario A B C'!$AE$19)) | J23: =IF(7<'Skenario A B C'!$E$19,0,MAX(0,'Skenario A B C'!$I$19-'Skenario A B C'!$AE$19)) | K23: =IF(8<'Skenario A B C'!$E$19,0,MAX(0,'Skenario A B C'!$I$19-'Skenario A B C'!$AE$19)) | L23: =IF(9<'Skenario A B C'!$E$19,0,MAX(0,'Skenario A B C'!$I$19-'Skenario A B C'!$AE$19)) | M23: =IF(10<'Skenario A B C'!$E$19,0,MAX(0,'Skenario A B C'!$I$19-'Skenario A B C'!$AE$19)) | N23: =IF(11<'Skenario A B C'!$E$19,0,MAX(0,'Skenario A B C'!$I$19-'Skenario A B C'!$AE$19)) | O23: =IF(12<'Skenario A B C'!$E$19,0,MAX(0,'Skenario A B C'!$I$19-'Skenario A B C'!$AE$19)) | P23: =IF(13<'Skenario A B C'!$E$19,0,MAX(0,'Skenario A B C'!$J$19-'Skenario A B C'!$AE$19)) | Q23: =IF(14<'Skenario A B C'!$E$19,0,MAX(0,'Skenario A B C'!$J$19-'Skenario A B C'!$AE$19)) | R23: =IF(15<'Skenario A B C'!$E$19,0,MAX(0,'Skenario A B C'!$J$19-'Skenario A B C'!$AE$19)) | S23: =IF(16<'Skenario A B C'!$E$19,0,MAX(0,'Skenario A B C'!$J$19-'Skenario A B C'!$AE$19)) | T23: =IF(17<'Skenario A B C'!$E$19,0,MAX(0,'Skenario A B C'!$J$19-'Skenario A B C'!$AE$19)) | U23: =IF(18<'Skenario A B C'!$E$19,0,MAX(0,'Skenario A B C'!$J$19-'Skenario A B C'!$AE$19)) | V23: =IF(19<'Skenario A B C'!$E$19,0,MAX(0,'Skenario A B C'!$J$19-'Skenario A B C'!$AE$19)) | W23: =IF(20<'Skenario A B C'!$E$19,0,MAX(0,'Skenario A B C'!$J$19-'Skenario A B C'!$AE$19)) | X23: =IF(21<'Skenario A B C'!$E$19,0,MAX(0,'Skenario A B C'!$J$19-'Skenario A B C'!$AE$19)) | Y23: =IF(22<'Skenario A B C'!$E$19,0,MAX(0,'Skenario A B C'!$J$19-'Skenario A B C'!$AE$19)) | Z23: =IF(23<'Skenario A B C'!$E$19,0,MAX(0,'Skenario A B C'!$J$19-'Skenario A B C'!$AE$19)) | AA23: =IF(24<'Skenario A B C'!$E$19,0,MAX(0,'Skenario A B C'!$J$19-'Skenario A B C'!$AE$19))
A24: Junior Software Engineer - Padang | B24: ='Skenario A B C'!$F$20 | D24: =IF(1<'Skenario A B C'!$E$20,0,MAX(0,'Skenario A B C'!$H$20-'Skenario A B C'!$AE$20)) | E24: =IF(2<'Skenario A B C'!$E$20,0,MAX(0,'Skenario A B C'!$H$20-'Skenario A B C'!$AE$20)) | F24: =IF(3<'Skenario A B C'!$E$20,0,MAX(0,'Skenario A B C'!$H$20-'Skenario A B C'!$AE$20)) | G24: =IF(4<'Skenario A B C'!$E$20,0,MAX(0,'Skenario A B C'!$I$20-'Skenario A B C'!$AE$20)) | H24: =IF(5<'Skenario A B C'!$E$20,0,MAX(0,'Skenario A B C'!$I$20-'Skenario A B C'!$AE$20)) | I24: =IF(6<'Skenario A B C'!$E$20,0,MAX(0,'Skenario A B C'!$I$20-'Skenario A B C'!$AE$20)) | J24: =IF(7<'Skenario A B C'!$E$20,0,MAX(0,'Skenario A B C'!$I$20-'Skenario A B C'!$AE$20)) | K24: =IF(8<'Skenario A B C'!$E$20,0,MAX(0,'Skenario A B C'!$I$20-'Skenario A B C'!$AE$20)) | L24: =IF(9<'Skenario A B C'!$E$20,0,MAX(0,'Skenario A B C'!$I$20-'Skenario A B C'!$AE$20)) | M24: =IF(10<'Skenario A B C'!$E$20,0,MAX(0,'Skenario A B C'!$I$20-'Skenario A B C'!$AE$20)) | N24: =IF(11<'Skenario A B C'!$E$20,0,MAX(0,'Skenario A B C'!$I$20-'Skenario A B C'!$AE$20)) | O24: =IF(12<'Skenario A B C'!$E$20,0,MAX(0,'Skenario A B C'!$I$20-'Skenario A B C'!$AE$20)) | P24: =IF(13<'Skenario A B C'!$E$20,0,MAX(0,'Skenario A B C'!$J$20-'Skenario A B C'!$AE$20)) | Q24: =IF(14<'Skenario A B C'!$E$20,0,MAX(0,'Skenario A B C'!$J$20-'Skenario A B C'!$AE$20)) | R24: =IF(15<'Skenario A B C'!$E$20,0,MAX(0,'Skenario A B C'!$J$20-'Skenario A B C'!$AE$20)) | S24: =IF(16<'Skenario A B C'!$E$20,0,MAX(0,'Skenario A B C'!$J$20-'Skenario A B C'!$AE$20)) | T24: =IF(17<'Skenario A B C'!$E$20,0,MAX(0,'Skenario A B C'!$J$20-'Skenario A B C'!$AE$20)) | U24: =IF(18<'Skenario A B C'!$E$20,0,MAX(0,'Skenario A B C'!$J$20-'Skenario A B C'!$AE$20)) | V24: =IF(19<'Skenario A B C'!$E$20,0,MAX(0,'Skenario A B C'!$J$20-'Skenario A B C'!$AE$20)) | W24: =IF(20<'Skenario A B C'!$E$20,0,MAX(0,'Skenario A B C'!$J$20-'Skenario A B C'!$AE$20)) | X24: =IF(21<'Skenario A B C'!$E$20,0,MAX(0,'Skenario A B C'!$J$20-'Skenario A B C'!$AE$20)) | Y24: =IF(22<'Skenario A B C'!$E$20,0,MAX(0,'Skenario A B C'!$J$20-'Skenario A B C'!$AE$20)) | Z24: =IF(23<'Skenario A B C'!$E$20,0,MAX(0,'Skenario A B C'!$J$20-'Skenario A B C'!$AE$20)) | AA24: =IF(24<'Skenario A B C'!$E$20,0,MAX(0,'Skenario A B C'!$J$20-'Skenario A B C'!$AE$20))
A25: Product Designer (UI/UX) | B25: ='Skenario A B C'!$F$21 | D25: =IF(1<'Skenario A B C'!$E$21,0,MAX(0,'Skenario A B C'!$H$21-'Skenario A B C'!$AE$21)) | E25: =IF(2<'Skenario A B C'!$E$21,0,MAX(0,'Skenario A B C'!$H$21-'Skenario A B C'!$AE$21)) | F25: =IF(3<'Skenario A B C'!$E$21,0,MAX(0,'Skenario A B C'!$H$21-'Skenario A B C'!$AE$21)) | G25: =IF(4<'Skenario A B C'!$E$21,0,MAX(0,'Skenario A B C'!$I$21-'Skenario A B C'!$AE$21)) | H25: =IF(5<'Skenario A B C'!$E$21,0,MAX(0,'Skenario A B C'!$I$21-'Skenario A B C'!$AE$21)) | I25: =IF(6<'Skenario A B C'!$E$21,0,MAX(0,'Skenario A B C'!$I$21-'Skenario A B C'!$AE$21)) | J25: =IF(7<'Skenario A B C'!$E$21,0,MAX(0,'Skenario A B C'!$I$21-'Skenario A B C'!$AE$21)) | K25: =IF(8<'Skenario A B C'!$E$21,0,MAX(0,'Skenario A B C'!$I$21-'Skenario A B C'!$AE$21)) | L25: =IF(9<'Skenario A B C'!$E$21,0,MAX(0,'Skenario A B C'!$I$21-'Skenario A B C'!$AE$21)) | M25: =IF(10<'Skenario A B C'!$E$21,0,MAX(0,'Skenario A B C'!$I$21-'Skenario A B C'!$AE$21)) | N25: =IF(11<'Skenario A B C'!$E$21,0,MAX(0,'Skenario A B C'!$I$21-'Skenario A B C'!$AE$21)) | O25: =IF(12<'Skenario A B C'!$E$21,0,MAX(0,'Skenario A B C'!$I$21-'Skenario A B C'!$AE$21)) | P25: =IF(13<'Skenario A B C'!$E$21,0,MAX(0,'Skenario A B C'!$J$21-'Skenario A B C'!$AE$21)) | Q25: =IF(14<'Skenario A B C'!$E$21,0,MAX(0,'Skenario A B C'!$J$21-'Skenario A B C'!$AE$21)) | R25: =IF(15<'Skenario A B C'!$E$21,0,MAX(0,'Skenario A B C'!$J$21-'Skenario A B C'!$AE$21)) | S25: =IF(16<'Skenario A B C'!$E$21,0,MAX(0,'Skenario A B C'!$J$21-'Skenario A B C'!$AE$21)) | T25: =IF(17<'Skenario A B C'!$E$21,0,MAX(0,'Skenario A B C'!$J$21-'Skenario A B C'!$AE$21)) | U25: =IF(18<'Skenario A B C'!$E$21,0,MAX(0,'Skenario A B C'!$J$21-'Skenario A B C'!$AE$21)) | V25: =IF(19<'Skenario A B C'!$E$21,0,MAX(0,'Skenario A B C'!$J$21-'Skenario A B C'!$AE$21)) | W25: =IF(20<'Skenario A B C'!$E$21,0,MAX(0,'Skenario A B C'!$J$21-'Skenario A B C'!$AE$21)) | X25: =IF(21<'Skenario A B C'!$E$21,0,MAX(0,'Skenario A B C'!$J$21-'Skenario A B C'!$AE$21)) | Y25: =IF(22<'Skenario A B C'!$E$21,0,MAX(0,'Skenario A B C'!$J$21-'Skenario A B C'!$AE$21)) | Z25: =IF(23<'Skenario A B C'!$E$21,0,MAX(0,'Skenario A B C'!$J$21-'Skenario A B C'!$AE$21)) | AA25: =IF(24<'Skenario A B C'!$E$21,0,MAX(0,'Skenario A B C'!$J$21-'Skenario A B C'!$AE$21))
A26: Product Designer (UI/UX) - gelombang 2 | B26: ='Skenario A B C'!$F$22 | D26: =IF(1<'Skenario A B C'!$E$22,0,MAX(0,'Skenario A B C'!$H$22-'Skenario A B C'!$AE$22)) | E26: =IF(2<'Skenario A B C'!$E$22,0,MAX(0,'Skenario A B C'!$H$22-'Skenario A B C'!$AE$22)) | F26: =IF(3<'Skenario A B C'!$E$22,0,MAX(0,'Skenario A B C'!$H$22-'Skenario A B C'!$AE$22)) | G26: =IF(4<'Skenario A B C'!$E$22,0,MAX(0,'Skenario A B C'!$I$22-'Skenario A B C'!$AE$22)) | H26: =IF(5<'Skenario A B C'!$E$22,0,MAX(0,'Skenario A B C'!$I$22-'Skenario A B C'!$AE$22)) | I26: =IF(6<'Skenario A B C'!$E$22,0,MAX(0,'Skenario A B C'!$I$22-'Skenario A B C'!$AE$22)) | J26: =IF(7<'Skenario A B C'!$E$22,0,MAX(0,'Skenario A B C'!$I$22-'Skenario A B C'!$AE$22)) | K26: =IF(8<'Skenario A B C'!$E$22,0,MAX(0,'Skenario A B C'!$I$22-'Skenario A B C'!$AE$22)) | L26: =IF(9<'Skenario A B C'!$E$22,0,MAX(0,'Skenario A B C'!$I$22-'Skenario A B C'!$AE$22)) | M26: =IF(10<'Skenario A B C'!$E$22,0,MAX(0,'Skenario A B C'!$I$22-'Skenario A B C'!$AE$22)) | N26: =IF(11<'Skenario A B C'!$E$22,0,MAX(0,'Skenario A B C'!$I$22-'Skenario A B C'!$AE$22)) | O26: =IF(12<'Skenario A B C'!$E$22,0,MAX(0,'Skenario A B C'!$I$22-'Skenario A B C'!$AE$22)) | P26: =IF(13<'Skenario A B C'!$E$22,0,MAX(0,'Skenario A B C'!$J$22-'Skenario A B C'!$AE$22)) | Q26: =IF(14<'Skenario A B C'!$E$22,0,MAX(0,'Skenario A B C'!$J$22-'Skenario A B C'!$AE$22)) | R26: =IF(15<'Skenario A B C'!$E$22,0,MAX(0,'Skenario A B C'!$J$22-'Skenario A B C'!$AE$22)) | S26: =IF(16<'Skenario A B C'!$E$22,0,MAX(0,'Skenario A B C'!$J$22-'Skenario A B C'!$AE$22)) | T26: =IF(17<'Skenario A B C'!$E$22,0,MAX(0,'Skenario A B C'!$J$22-'Skenario A B C'!$AE$22)) | U26: =IF(18<'Skenario A B C'!$E$22,0,MAX(0,'Skenario A B C'!$J$22-'Skenario A B C'!$AE$22)) | V26: =IF(19<'Skenario A B C'!$E$22,0,MAX(0,'Skenario A B C'!$J$22-'Skenario A B C'!$AE$22)) | W26: =IF(20<'Skenario A B C'!$E$22,0,MAX(0,'Skenario A B C'!$J$22-'Skenario A B C'!$AE$22)) | X26: =IF(21<'Skenario A B C'!$E$22,0,MAX(0,'Skenario A B C'!$J$22-'Skenario A B C'!$AE$22)) | Y26: =IF(22<'Skenario A B C'!$E$22,0,MAX(0,'Skenario A B C'!$J$22-'Skenario A B C'!$AE$22)) | Z26: =IF(23<'Skenario A B C'!$E$22,0,MAX(0,'Skenario A B C'!$J$22-'Skenario A B C'!$AE$22)) | AA26: =IF(24<'Skenario A B C'!$E$22,0,MAX(0,'Skenario A B C'!$J$22-'Skenario A B C'!$AE$22))
A27: Data Analyst | B27: ='Skenario A B C'!$F$23 | D27: =IF(1<'Skenario A B C'!$E$23,0,MAX(0,'Skenario A B C'!$H$23-'Skenario A B C'!$AE$23)) | E27: =IF(2<'Skenario A B C'!$E$23,0,MAX(0,'Skenario A B C'!$H$23-'Skenario A B C'!$AE$23)) | F27: =IF(3<'Skenario A B C'!$E$23,0,MAX(0,'Skenario A B C'!$H$23-'Skenario A B C'!$AE$23)) | G27: =IF(4<'Skenario A B C'!$E$23,0,MAX(0,'Skenario A B C'!$I$23-'Skenario A B C'!$AE$23)) | H27: =IF(5<'Skenario A B C'!$E$23,0,MAX(0,'Skenario A B C'!$I$23-'Skenario A B C'!$AE$23)) | I27: =IF(6<'Skenario A B C'!$E$23,0,MAX(0,'Skenario A B C'!$I$23-'Skenario A B C'!$AE$23)) | J27: =IF(7<'Skenario A B C'!$E$23,0,MAX(0,'Skenario A B C'!$I$23-'Skenario A B C'!$AE$23)) | K27: =IF(8<'Skenario A B C'!$E$23,0,MAX(0,'Skenario A B C'!$I$23-'Skenario A B C'!$AE$23)) | L27: =IF(9<'Skenario A B C'!$E$23,0,MAX(0,'Skenario A B C'!$I$23-'Skenario A B C'!$AE$23)) | M27: =IF(10<'Skenario A B C'!$E$23,0,MAX(0,'Skenario A B C'!$I$23-'Skenario A B C'!$AE$23)) | N27: =IF(11<'Skenario A B C'!$E$23,0,MAX(0,'Skenario A B C'!$I$23-'Skenario A B C'!$AE$23)) | O27: =IF(12<'Skenario A B C'!$E$23,0,MAX(0,'Skenario A B C'!$I$23-'Skenario A B C'!$AE$23)) | P27: =IF(13<'Skenario A B C'!$E$23,0,MAX(0,'Skenario A B C'!$J$23-'Skenario A B C'!$AE$23)) | Q27: =IF(14<'Skenario A B C'!$E$23,0,MAX(0,'Skenario A B C'!$J$23-'Skenario A B C'!$AE$23)) | R27: =IF(15<'Skenario A B C'!$E$23,0,MAX(0,'Skenario A B C'!$J$23-'Skenario A B C'!$AE$23)) | S27: =IF(16<'Skenario A B C'!$E$23,0,MAX(0,'Skenario A B C'!$J$23-'Skenario A B C'!$AE$23)) | T27: =IF(17<'Skenario A B C'!$E$23,0,MAX(0,'Skenario A B C'!$J$23-'Skenario A B C'!$AE$23)) | U27: =IF(18<'Skenario A B C'!$E$23,0,MAX(0,'Skenario A B C'!$J$23-'Skenario A B C'!$AE$23)) | V27: =IF(19<'Skenario A B C'!$E$23,0,MAX(0,'Skenario A B C'!$J$23-'Skenario A B C'!$AE$23)) | W27: =IF(20<'Skenario A B C'!$E$23,0,MAX(0,'Skenario A B C'!$J$23-'Skenario A B C'!$AE$23)) | X27: =IF(21<'Skenario A B C'!$E$23,0,MAX(0,'Skenario A B C'!$J$23-'Skenario A B C'!$AE$23)) | Y27: =IF(22<'Skenario A B C'!$E$23,0,MAX(0,'Skenario A B C'!$J$23-'Skenario A B C'!$AE$23)) | Z27: =IF(23<'Skenario A B C'!$E$23,0,MAX(0,'Skenario A B C'!$J$23-'Skenario A B C'!$AE$23)) | AA27: =IF(24<'Skenario A B C'!$E$23,0,MAX(0,'Skenario A B C'!$J$23-'Skenario A B C'!$AE$23))
A28: Direktur Operasi (COO) | B28: ='Skenario A B C'!$F$24 | D28: =IF(1<'Skenario A B C'!$E$24,0,MAX(0,'Skenario A B C'!$H$24-'Skenario A B C'!$AE$24)) | E28: =IF(2<'Skenario A B C'!$E$24,0,MAX(0,'Skenario A B C'!$H$24-'Skenario A B C'!$AE$24)) | F28: =IF(3<'Skenario A B C'!$E$24,0,MAX(0,'Skenario A B C'!$H$24-'Skenario A B C'!$AE$24)) | G28: =IF(4<'Skenario A B C'!$E$24,0,MAX(0,'Skenario A B C'!$I$24-'Skenario A B C'!$AE$24)) | H28: =IF(5<'Skenario A B C'!$E$24,0,MAX(0,'Skenario A B C'!$I$24-'Skenario A B C'!$AE$24)) | I28: =IF(6<'Skenario A B C'!$E$24,0,MAX(0,'Skenario A B C'!$I$24-'Skenario A B C'!$AE$24)) | J28: =IF(7<'Skenario A B C'!$E$24,0,MAX(0,'Skenario A B C'!$I$24-'Skenario A B C'!$AE$24)) | K28: =IF(8<'Skenario A B C'!$E$24,0,MAX(0,'Skenario A B C'!$I$24-'Skenario A B C'!$AE$24)) | L28: =IF(9<'Skenario A B C'!$E$24,0,MAX(0,'Skenario A B C'!$I$24-'Skenario A B C'!$AE$24)) | M28: =IF(10<'Skenario A B C'!$E$24,0,MAX(0,'Skenario A B C'!$I$24-'Skenario A B C'!$AE$24)) | N28: =IF(11<'Skenario A B C'!$E$24,0,MAX(0,'Skenario A B C'!$I$24-'Skenario A B C'!$AE$24)) | O28: =IF(12<'Skenario A B C'!$E$24,0,MAX(0,'Skenario A B C'!$I$24-'Skenario A B C'!$AE$24)) | P28: =IF(13<'Skenario A B C'!$E$24,0,MAX(0,'Skenario A B C'!$J$24-'Skenario A B C'!$AE$24)) | Q28: =IF(14<'Skenario A B C'!$E$24,0,MAX(0,'Skenario A B C'!$J$24-'Skenario A B C'!$AE$24)) | R28: =IF(15<'Skenario A B C'!$E$24,0,MAX(0,'Skenario A B C'!$J$24-'Skenario A B C'!$AE$24)) | S28: =IF(16<'Skenario A B C'!$E$24,0,MAX(0,'Skenario A B C'!$J$24-'Skenario A B C'!$AE$24)) | T28: =IF(17<'Skenario A B C'!$E$24,0,MAX(0,'Skenario A B C'!$J$24-'Skenario A B C'!$AE$24)) | U28: =IF(18<'Skenario A B C'!$E$24,0,MAX(0,'Skenario A B C'!$J$24-'Skenario A B C'!$AE$24)) | V28: =IF(19<'Skenario A B C'!$E$24,0,MAX(0,'Skenario A B C'!$J$24-'Skenario A B C'!$AE$24)) | W28: =IF(20<'Skenario A B C'!$E$24,0,MAX(0,'Skenario A B C'!$J$24-'Skenario A B C'!$AE$24)) | X28: =IF(21<'Skenario A B C'!$E$24,0,MAX(0,'Skenario A B C'!$J$24-'Skenario A B C'!$AE$24)) | Y28: =IF(22<'Skenario A B C'!$E$24,0,MAX(0,'Skenario A B C'!$J$24-'Skenario A B C'!$AE$24)) | Z28: =IF(23<'Skenario A B C'!$E$24,0,MAX(0,'Skenario A B C'!$J$24-'Skenario A B C'!$AE$24)) | AA28: =IF(24<'Skenario A B C'!$E$24,0,MAX(0,'Skenario A B C'!$J$24-'Skenario A B C'!$AE$24))
A29: City Manager Pekanbaru | B29: ='Skenario A B C'!$F$25 | D29: =IF(1<'Skenario A B C'!$E$25,0,MAX(0,'Skenario A B C'!$H$25-'Skenario A B C'!$AE$25)) | E29: =IF(2<'Skenario A B C'!$E$25,0,MAX(0,'Skenario A B C'!$H$25-'Skenario A B C'!$AE$25)) | F29: =IF(3<'Skenario A B C'!$E$25,0,MAX(0,'Skenario A B C'!$H$25-'Skenario A B C'!$AE$25)) | G29: =IF(4<'Skenario A B C'!$E$25,0,MAX(0,'Skenario A B C'!$I$25-'Skenario A B C'!$AE$25)) | H29: =IF(5<'Skenario A B C'!$E$25,0,MAX(0,'Skenario A B C'!$I$25-'Skenario A B C'!$AE$25)) | I29: =IF(6<'Skenario A B C'!$E$25,0,MAX(0,'Skenario A B C'!$I$25-'Skenario A B C'!$AE$25)) | J29: =IF(7<'Skenario A B C'!$E$25,0,MAX(0,'Skenario A B C'!$I$25-'Skenario A B C'!$AE$25)) | K29: =IF(8<'Skenario A B C'!$E$25,0,MAX(0,'Skenario A B C'!$I$25-'Skenario A B C'!$AE$25)) | L29: =IF(9<'Skenario A B C'!$E$25,0,MAX(0,'Skenario A B C'!$I$25-'Skenario A B C'!$AE$25)) | M29: =IF(10<'Skenario A B C'!$E$25,0,MAX(0,'Skenario A B C'!$I$25-'Skenario A B C'!$AE$25)) | N29: =IF(11<'Skenario A B C'!$E$25,0,MAX(0,'Skenario A B C'!$I$25-'Skenario A B C'!$AE$25)) | O29: =IF(12<'Skenario A B C'!$E$25,0,MAX(0,'Skenario A B C'!$I$25-'Skenario A B C'!$AE$25)) | P29: =IF(13<'Skenario A B C'!$E$25,0,MAX(0,'Skenario A B C'!$J$25-'Skenario A B C'!$AE$25)) | Q29: =IF(14<'Skenario A B C'!$E$25,0,MAX(0,'Skenario A B C'!$J$25-'Skenario A B C'!$AE$25)) | R29: =IF(15<'Skenario A B C'!$E$25,0,MAX(0,'Skenario A B C'!$J$25-'Skenario A B C'!$AE$25)) | S29: =IF(16<'Skenario A B C'!$E$25,0,MAX(0,'Skenario A B C'!$J$25-'Skenario A B C'!$AE$25)) | T29: =IF(17<'Skenario A B C'!$E$25,0,MAX(0,'Skenario A B C'!$J$25-'Skenario A B C'!$AE$25)) | U29: =IF(18<'Skenario A B C'!$E$25,0,MAX(0,'Skenario A B C'!$J$25-'Skenario A B C'!$AE$25)) | V29: =IF(19<'Skenario A B C'!$E$25,0,MAX(0,'Skenario A B C'!$J$25-'Skenario A B C'!$AE$25)) | W29: =IF(20<'Skenario A B C'!$E$25,0,MAX(0,'Skenario A B C'!$J$25-'Skenario A B C'!$AE$25)) | X29: =IF(21<'Skenario A B C'!$E$25,0,MAX(0,'Skenario A B C'!$J$25-'Skenario A B C'!$AE$25)) | Y29: =IF(22<'Skenario A B C'!$E$25,0,MAX(0,'Skenario A B C'!$J$25-'Skenario A B C'!$AE$25)) | Z29: =IF(23<'Skenario A B C'!$E$25,0,MAX(0,'Skenario A B C'!$J$25-'Skenario A B C'!$AE$25)) | AA29: =IF(24<'Skenario A B C'!$E$25,0,MAX(0,'Skenario A B C'!$J$25-'Skenario A B C'!$AE$25))
A30: Ops Supervisor Pekanbaru | B30: ='Skenario A B C'!$F$26 | D30: =IF(1<'Skenario A B C'!$E$26,0,MAX(0,'Skenario A B C'!$H$26-'Skenario A B C'!$AE$26)) | E30: =IF(2<'Skenario A B C'!$E$26,0,MAX(0,'Skenario A B C'!$H$26-'Skenario A B C'!$AE$26)) | F30: =IF(3<'Skenario A B C'!$E$26,0,MAX(0,'Skenario A B C'!$H$26-'Skenario A B C'!$AE$26)) | G30: =IF(4<'Skenario A B C'!$E$26,0,MAX(0,'Skenario A B C'!$I$26-'Skenario A B C'!$AE$26)) | H30: =IF(5<'Skenario A B C'!$E$26,0,MAX(0,'Skenario A B C'!$I$26-'Skenario A B C'!$AE$26)) | I30: =IF(6<'Skenario A B C'!$E$26,0,MAX(0,'Skenario A B C'!$I$26-'Skenario A B C'!$AE$26)) | J30: =IF(7<'Skenario A B C'!$E$26,0,MAX(0,'Skenario A B C'!$I$26-'Skenario A B C'!$AE$26)) | K30: =IF(8<'Skenario A B C'!$E$26,0,MAX(0,'Skenario A B C'!$I$26-'Skenario A B C'!$AE$26)) | L30: =IF(9<'Skenario A B C'!$E$26,0,MAX(0,'Skenario A B C'!$I$26-'Skenario A B C'!$AE$26)) | M30: =IF(10<'Skenario A B C'!$E$26,0,MAX(0,'Skenario A B C'!$I$26-'Skenario A B C'!$AE$26)) | N30: =IF(11<'Skenario A B C'!$E$26,0,MAX(0,'Skenario A B C'!$I$26-'Skenario A B C'!$AE$26)) | O30: =IF(12<'Skenario A B C'!$E$26,0,MAX(0,'Skenario A B C'!$I$26-'Skenario A B C'!$AE$26)) | P30: =IF(13<'Skenario A B C'!$E$26,0,MAX(0,'Skenario A B C'!$J$26-'Skenario A B C'!$AE$26)) | Q30: =IF(14<'Skenario A B C'!$E$26,0,MAX(0,'Skenario A B C'!$J$26-'Skenario A B C'!$AE$26)) | R30: =IF(15<'Skenario A B C'!$E$26,0,MAX(0,'Skenario A B C'!$J$26-'Skenario A B C'!$AE$26)) | S30: =IF(16<'Skenario A B C'!$E$26,0,MAX(0,'Skenario A B C'!$J$26-'Skenario A B C'!$AE$26)) | T30: =IF(17<'Skenario A B C'!$E$26,0,MAX(0,'Skenario A B C'!$J$26-'Skenario A B C'!$AE$26)) | U30: =IF(18<'Skenario A B C'!$E$26,0,MAX(0,'Skenario A B C'!$J$26-'Skenario A B C'!$AE$26)) | V30: =IF(19<'Skenario A B C'!$E$26,0,MAX(0,'Skenario A B C'!$J$26-'Skenario A B C'!$AE$26)) | W30: =IF(20<'Skenario A B C'!$E$26,0,MAX(0,'Skenario A B C'!$J$26-'Skenario A B C'!$AE$26)) | X30: =IF(21<'Skenario A B C'!$E$26,0,MAX(0,'Skenario A B C'!$J$26-'Skenario A B C'!$AE$26)) | Y30: =IF(22<'Skenario A B C'!$E$26,0,MAX(0,'Skenario A B C'!$J$26-'Skenario A B C'!$AE$26)) | Z30: =IF(23<'Skenario A B C'!$E$26,0,MAX(0,'Skenario A B C'!$J$26-'Skenario A B C'!$AE$26)) | AA30: =IF(24<'Skenario A B C'!$E$26,0,MAX(0,'Skenario A B C'!$J$26-'Skenario A B C'!$AE$26))
A31: Partner Acquisition Pekanbaru | B31: ='Skenario A B C'!$F$27 | D31: =IF(1<'Skenario A B C'!$E$27,0,MAX(0,'Skenario A B C'!$H$27-'Skenario A B C'!$AE$27)) | E31: =IF(2<'Skenario A B C'!$E$27,0,MAX(0,'Skenario A B C'!$H$27-'Skenario A B C'!$AE$27)) | F31: =IF(3<'Skenario A B C'!$E$27,0,MAX(0,'Skenario A B C'!$H$27-'Skenario A B C'!$AE$27)) | G31: =IF(4<'Skenario A B C'!$E$27,0,MAX(0,'Skenario A B C'!$I$27-'Skenario A B C'!$AE$27)) | H31: =IF(5<'Skenario A B C'!$E$27,0,MAX(0,'Skenario A B C'!$I$27-'Skenario A B C'!$AE$27)) | I31: =IF(6<'Skenario A B C'!$E$27,0,MAX(0,'Skenario A B C'!$I$27-'Skenario A B C'!$AE$27)) | J31: =IF(7<'Skenario A B C'!$E$27,0,MAX(0,'Skenario A B C'!$I$27-'Skenario A B C'!$AE$27)) | K31: =IF(8<'Skenario A B C'!$E$27,0,MAX(0,'Skenario A B C'!$I$27-'Skenario A B C'!$AE$27)) | L31: =IF(9<'Skenario A B C'!$E$27,0,MAX(0,'Skenario A B C'!$I$27-'Skenario A B C'!$AE$27)) | M31: =IF(10<'Skenario A B C'!$E$27,0,MAX(0,'Skenario A B C'!$I$27-'Skenario A B C'!$AE$27)) | N31: =IF(11<'Skenario A B C'!$E$27,0,MAX(0,'Skenario A B C'!$I$27-'Skenario A B C'!$AE$27)) | O31: =IF(12<'Skenario A B C'!$E$27,0,MAX(0,'Skenario A B C'!$I$27-'Skenario A B C'!$AE$27)) | P31: =IF(13<'Skenario A B C'!$E$27,0,MAX(0,'Skenario A B C'!$J$27-'Skenario A B C'!$AE$27)) | Q31: =IF(14<'Skenario A B C'!$E$27,0,MAX(0,'Skenario A B C'!$J$27-'Skenario A B C'!$AE$27)) | R31: =IF(15<'Skenario A B C'!$E$27,0,MAX(0,'Skenario A B C'!$J$27-'Skenario A B C'!$AE$27)) | S31: =IF(16<'Skenario A B C'!$E$27,0,MAX(0,'Skenario A B C'!$J$27-'Skenario A B C'!$AE$27)) | T31: =IF(17<'Skenario A B C'!$E$27,0,MAX(0,'Skenario A B C'!$J$27-'Skenario A B C'!$AE$27)) | U31: =IF(18<'Skenario A B C'!$E$27,0,MAX(0,'Skenario A B C'!$J$27-'Skenario A B C'!$AE$27)) | V31: =IF(19<'Skenario A B C'!$E$27,0,MAX(0,'Skenario A B C'!$J$27-'Skenario A B C'!$AE$27)) | W31: =IF(20<'Skenario A B C'!$E$27,0,MAX(0,'Skenario A B C'!$J$27-'Skenario A B C'!$AE$27)) | X31: =IF(21<'Skenario A B C'!$E$27,0,MAX(0,'Skenario A B C'!$J$27-'Skenario A B C'!$AE$27)) | Y31: =IF(22<'Skenario A B C'!$E$27,0,MAX(0,'Skenario A B C'!$J$27-'Skenario A B C'!$AE$27)) | Z31: =IF(23<'Skenario A B C'!$E$27,0,MAX(0,'Skenario A B C'!$J$27-'Skenario A B C'!$AE$27)) | AA31: =IF(24<'Skenario A B C'!$E$27,0,MAX(0,'Skenario A B C'!$J$27-'Skenario A B C'!$AE$27))
A32: Head of Customer Experience | B32: ='Skenario A B C'!$F$28 | D32: =IF(1<'Skenario A B C'!$E$28,0,MAX(0,'Skenario A B C'!$H$28-'Skenario A B C'!$AE$28)) | E32: =IF(2<'Skenario A B C'!$E$28,0,MAX(0,'Skenario A B C'!$H$28-'Skenario A B C'!$AE$28)) | F32: =IF(3<'Skenario A B C'!$E$28,0,MAX(0,'Skenario A B C'!$H$28-'Skenario A B C'!$AE$28)) | G32: =IF(4<'Skenario A B C'!$E$28,0,MAX(0,'Skenario A B C'!$I$28-'Skenario A B C'!$AE$28)) | H32: =IF(5<'Skenario A B C'!$E$28,0,MAX(0,'Skenario A B C'!$I$28-'Skenario A B C'!$AE$28)) | I32: =IF(6<'Skenario A B C'!$E$28,0,MAX(0,'Skenario A B C'!$I$28-'Skenario A B C'!$AE$28)) | J32: =IF(7<'Skenario A B C'!$E$28,0,MAX(0,'Skenario A B C'!$I$28-'Skenario A B C'!$AE$28)) | K32: =IF(8<'Skenario A B C'!$E$28,0,MAX(0,'Skenario A B C'!$I$28-'Skenario A B C'!$AE$28)) | L32: =IF(9<'Skenario A B C'!$E$28,0,MAX(0,'Skenario A B C'!$I$28-'Skenario A B C'!$AE$28)) | M32: =IF(10<'Skenario A B C'!$E$28,0,MAX(0,'Skenario A B C'!$I$28-'Skenario A B C'!$AE$28)) | N32: =IF(11<'Skenario A B C'!$E$28,0,MAX(0,'Skenario A B C'!$I$28-'Skenario A B C'!$AE$28)) | O32: =IF(12<'Skenario A B C'!$E$28,0,MAX(0,'Skenario A B C'!$I$28-'Skenario A B C'!$AE$28)) | P32: =IF(13<'Skenario A B C'!$E$28,0,MAX(0,'Skenario A B C'!$J$28-'Skenario A B C'!$AE$28)) | Q32: =IF(14<'Skenario A B C'!$E$28,0,MAX(0,'Skenario A B C'!$J$28-'Skenario A B C'!$AE$28)) | R32: =IF(15<'Skenario A B C'!$E$28,0,MAX(0,'Skenario A B C'!$J$28-'Skenario A B C'!$AE$28)) | S32: =IF(16<'Skenario A B C'!$E$28,0,MAX(0,'Skenario A B C'!$J$28-'Skenario A B C'!$AE$28)) | T32: =IF(17<'Skenario A B C'!$E$28,0,MAX(0,'Skenario A B C'!$J$28-'Skenario A B C'!$AE$28)) | U32: =IF(18<'Skenario A B C'!$E$28,0,MAX(0,'Skenario A B C'!$J$28-'Skenario A B C'!$AE$28)) | V32: =IF(19<'Skenario A B C'!$E$28,0,MAX(0,'Skenario A B C'!$J$28-'Skenario A B C'!$AE$28)) | W32: =IF(20<'Skenario A B C'!$E$28,0,MAX(0,'Skenario A B C'!$J$28-'Skenario A B C'!$AE$28)) | X32: =IF(21<'Skenario A B C'!$E$28,0,MAX(0,'Skenario A B C'!$J$28-'Skenario A B C'!$AE$28)) | Y32: =IF(22<'Skenario A B C'!$E$28,0,MAX(0,'Skenario A B C'!$J$28-'Skenario A B C'!$AE$28)) | Z32: =IF(23<'Skenario A B C'!$E$28,0,MAX(0,'Skenario A B C'!$J$28-'Skenario A B C'!$AE$28)) | AA32: =IF(24<'Skenario A B C'!$E$28,0,MAX(0,'Skenario A B C'!$J$28-'Skenario A B C'!$AE$28))
A33: CS Agent Pekanbaru (shift) | B33: ='Skenario A B C'!$F$29 | D33: =IF(1<'Skenario A B C'!$E$29,0,MAX(0,'Skenario A B C'!$H$29-'Skenario A B C'!$AE$29)) | E33: =IF(2<'Skenario A B C'!$E$29,0,MAX(0,'Skenario A B C'!$H$29-'Skenario A B C'!$AE$29)) | F33: =IF(3<'Skenario A B C'!$E$29,0,MAX(0,'Skenario A B C'!$H$29-'Skenario A B C'!$AE$29)) | G33: =IF(4<'Skenario A B C'!$E$29,0,MAX(0,'Skenario A B C'!$I$29-'Skenario A B C'!$AE$29)) | H33: =IF(5<'Skenario A B C'!$E$29,0,MAX(0,'Skenario A B C'!$I$29-'Skenario A B C'!$AE$29)) | I33: =IF(6<'Skenario A B C'!$E$29,0,MAX(0,'Skenario A B C'!$I$29-'Skenario A B C'!$AE$29)) | J33: =IF(7<'Skenario A B C'!$E$29,0,MAX(0,'Skenario A B C'!$I$29-'Skenario A B C'!$AE$29)) | K33: =IF(8<'Skenario A B C'!$E$29,0,MAX(0,'Skenario A B C'!$I$29-'Skenario A B C'!$AE$29)) | L33: =IF(9<'Skenario A B C'!$E$29,0,MAX(0,'Skenario A B C'!$I$29-'Skenario A B C'!$AE$29)) | M33: =IF(10<'Skenario A B C'!$E$29,0,MAX(0,'Skenario A B C'!$I$29-'Skenario A B C'!$AE$29)) | N33: =IF(11<'Skenario A B C'!$E$29,0,MAX(0,'Skenario A B C'!$I$29-'Skenario A B C'!$AE$29)) | O33: =IF(12<'Skenario A B C'!$E$29,0,MAX(0,'Skenario A B C'!$I$29-'Skenario A B C'!$AE$29)) | P33: =IF(13<'Skenario A B C'!$E$29,0,MAX(0,'Skenario A B C'!$J$29-'Skenario A B C'!$AE$29)) | Q33: =IF(14<'Skenario A B C'!$E$29,0,MAX(0,'Skenario A B C'!$J$29-'Skenario A B C'!$AE$29)) | R33: =IF(15<'Skenario A B C'!$E$29,0,MAX(0,'Skenario A B C'!$J$29-'Skenario A B C'!$AE$29)) | S33: =IF(16<'Skenario A B C'!$E$29,0,MAX(0,'Skenario A B C'!$J$29-'Skenario A B C'!$AE$29)) | T33: =IF(17<'Skenario A B C'!$E$29,0,MAX(0,'Skenario A B C'!$J$29-'Skenario A B C'!$AE$29)) | U33: =IF(18<'Skenario A B C'!$E$29,0,MAX(0,'Skenario A B C'!$J$29-'Skenario A B C'!$AE$29)) | V33: =IF(19<'Skenario A B C'!$E$29,0,MAX(0,'Skenario A B C'!$J$29-'Skenario A B C'!$AE$29)) | W33: =IF(20<'Skenario A B C'!$E$29,0,MAX(0,'Skenario A B C'!$J$29-'Skenario A B C'!$AE$29)) | X33: =IF(21<'Skenario A B C'!$E$29,0,MAX(0,'Skenario A B C'!$J$29-'Skenario A B C'!$AE$29)) | Y33: =IF(22<'Skenario A B C'!$E$29,0,MAX(0,'Skenario A B C'!$J$29-'Skenario A B C'!$AE$29)) | Z33: =IF(23<'Skenario A B C'!$E$29,0,MAX(0,'Skenario A B C'!$J$29-'Skenario A B C'!$AE$29)) | AA33: =IF(24<'Skenario A B C'!$E$29,0,MAX(0,'Skenario A B C'!$J$29-'Skenario A B C'!$AE$29))
A34: Trust & Safety Officer | B34: ='Skenario A B C'!$F$30 | D34: =IF(1<'Skenario A B C'!$E$30,0,MAX(0,'Skenario A B C'!$H$30-'Skenario A B C'!$AE$30)) | E34: =IF(2<'Skenario A B C'!$E$30,0,MAX(0,'Skenario A B C'!$H$30-'Skenario A B C'!$AE$30)) | F34: =IF(3<'Skenario A B C'!$E$30,0,MAX(0,'Skenario A B C'!$H$30-'Skenario A B C'!$AE$30)) | G34: =IF(4<'Skenario A B C'!$E$30,0,MAX(0,'Skenario A B C'!$I$30-'Skenario A B C'!$AE$30)) | H34: =IF(5<'Skenario A B C'!$E$30,0,MAX(0,'Skenario A B C'!$I$30-'Skenario A B C'!$AE$30)) | I34: =IF(6<'Skenario A B C'!$E$30,0,MAX(0,'Skenario A B C'!$I$30-'Skenario A B C'!$AE$30)) | J34: =IF(7<'Skenario A B C'!$E$30,0,MAX(0,'Skenario A B C'!$I$30-'Skenario A B C'!$AE$30)) | K34: =IF(8<'Skenario A B C'!$E$30,0,MAX(0,'Skenario A B C'!$I$30-'Skenario A B C'!$AE$30)) | L34: =IF(9<'Skenario A B C'!$E$30,0,MAX(0,'Skenario A B C'!$I$30-'Skenario A B C'!$AE$30)) | M34: =IF(10<'Skenario A B C'!$E$30,0,MAX(0,'Skenario A B C'!$I$30-'Skenario A B C'!$AE$30)) | N34: =IF(11<'Skenario A B C'!$E$30,0,MAX(0,'Skenario A B C'!$I$30-'Skenario A B C'!$AE$30)) | O34: =IF(12<'Skenario A B C'!$E$30,0,MAX(0,'Skenario A B C'!$I$30-'Skenario A B C'!$AE$30)) | P34: =IF(13<'Skenario A B C'!$E$30,0,MAX(0,'Skenario A B C'!$J$30-'Skenario A B C'!$AE$30)) | Q34: =IF(14<'Skenario A B C'!$E$30,0,MAX(0,'Skenario A B C'!$J$30-'Skenario A B C'!$AE$30)) | R34: =IF(15<'Skenario A B C'!$E$30,0,MAX(0,'Skenario A B C'!$J$30-'Skenario A B C'!$AE$30)) | S34: =IF(16<'Skenario A B C'!$E$30,0,MAX(0,'Skenario A B C'!$J$30-'Skenario A B C'!$AE$30)) | T34: =IF(17<'Skenario A B C'!$E$30,0,MAX(0,'Skenario A B C'!$J$30-'Skenario A B C'!$AE$30)) | U34: =IF(18<'Skenario A B C'!$E$30,0,MAX(0,'Skenario A B C'!$J$30-'Skenario A B C'!$AE$30)) | V34: =IF(19<'Skenario A B C'!$E$30,0,MAX(0,'Skenario A B C'!$J$30-'Skenario A B C'!$AE$30)) | W34: =IF(20<'Skenario A B C'!$E$30,0,MAX(0,'Skenario A B C'!$J$30-'Skenario A B C'!$AE$30)) | X34: =IF(21<'Skenario A B C'!$E$30,0,MAX(0,'Skenario A B C'!$J$30-'Skenario A B C'!$AE$30)) | Y34: =IF(22<'Skenario A B C'!$E$30,0,MAX(0,'Skenario A B C'!$J$30-'Skenario A B C'!$AE$30)) | Z34: =IF(23<'Skenario A B C'!$E$30,0,MAX(0,'Skenario A B C'!$J$30-'Skenario A B C'!$AE$30)) | AA34: =IF(24<'Skenario A B C'!$E$30,0,MAX(0,'Skenario A B C'!$J$30-'Skenario A B C'!$AE$30))
A35: City Manager Padang | B35: ='Skenario A B C'!$F$31 | D35: =IF(1<'Skenario A B C'!$E$31,0,MAX(0,'Skenario A B C'!$H$31-'Skenario A B C'!$AE$31)) | E35: =IF(2<'Skenario A B C'!$E$31,0,MAX(0,'Skenario A B C'!$H$31-'Skenario A B C'!$AE$31)) | F35: =IF(3<'Skenario A B C'!$E$31,0,MAX(0,'Skenario A B C'!$H$31-'Skenario A B C'!$AE$31)) | G35: =IF(4<'Skenario A B C'!$E$31,0,MAX(0,'Skenario A B C'!$I$31-'Skenario A B C'!$AE$31)) | H35: =IF(5<'Skenario A B C'!$E$31,0,MAX(0,'Skenario A B C'!$I$31-'Skenario A B C'!$AE$31)) | I35: =IF(6<'Skenario A B C'!$E$31,0,MAX(0,'Skenario A B C'!$I$31-'Skenario A B C'!$AE$31)) | J35: =IF(7<'Skenario A B C'!$E$31,0,MAX(0,'Skenario A B C'!$I$31-'Skenario A B C'!$AE$31)) | K35: =IF(8<'Skenario A B C'!$E$31,0,MAX(0,'Skenario A B C'!$I$31-'Skenario A B C'!$AE$31)) | L35: =IF(9<'Skenario A B C'!$E$31,0,MAX(0,'Skenario A B C'!$I$31-'Skenario A B C'!$AE$31)) | M35: =IF(10<'Skenario A B C'!$E$31,0,MAX(0,'Skenario A B C'!$I$31-'Skenario A B C'!$AE$31)) | N35: =IF(11<'Skenario A B C'!$E$31,0,MAX(0,'Skenario A B C'!$I$31-'Skenario A B C'!$AE$31)) | O35: =IF(12<'Skenario A B C'!$E$31,0,MAX(0,'Skenario A B C'!$I$31-'Skenario A B C'!$AE$31)) | P35: =IF(13<'Skenario A B C'!$E$31,0,MAX(0,'Skenario A B C'!$J$31-'Skenario A B C'!$AE$31)) | Q35: =IF(14<'Skenario A B C'!$E$31,0,MAX(0,'Skenario A B C'!$J$31-'Skenario A B C'!$AE$31)) | R35: =IF(15<'Skenario A B C'!$E$31,0,MAX(0,'Skenario A B C'!$J$31-'Skenario A B C'!$AE$31)) | S35: =IF(16<'Skenario A B C'!$E$31,0,MAX(0,'Skenario A B C'!$J$31-'Skenario A B C'!$AE$31)) | T35: =IF(17<'Skenario A B C'!$E$31,0,MAX(0,'Skenario A B C'!$J$31-'Skenario A B C'!$AE$31)) | U35: =IF(18<'Skenario A B C'!$E$31,0,MAX(0,'Skenario A B C'!$J$31-'Skenario A B C'!$AE$31)) | V35: =IF(19<'Skenario A B C'!$E$31,0,MAX(0,'Skenario A B C'!$J$31-'Skenario A B C'!$AE$31)) | W35: =IF(20<'Skenario A B C'!$E$31,0,MAX(0,'Skenario A B C'!$J$31-'Skenario A B C'!$AE$31)) | X35: =IF(21<'Skenario A B C'!$E$31,0,MAX(0,'Skenario A B C'!$J$31-'Skenario A B C'!$AE$31)) | Y35: =IF(22<'Skenario A B C'!$E$31,0,MAX(0,'Skenario A B C'!$J$31-'Skenario A B C'!$AE$31)) | Z35: =IF(23<'Skenario A B C'!$E$31,0,MAX(0,'Skenario A B C'!$J$31-'Skenario A B C'!$AE$31)) | AA35: =IF(24<'Skenario A B C'!$E$31,0,MAX(0,'Skenario A B C'!$J$31-'Skenario A B C'!$AE$31))
A36: Partner Acquisition Padang | B36: ='Skenario A B C'!$F$32 | D36: =IF(1<'Skenario A B C'!$E$32,0,MAX(0,'Skenario A B C'!$H$32-'Skenario A B C'!$AE$32)) | E36: =IF(2<'Skenario A B C'!$E$32,0,MAX(0,'Skenario A B C'!$H$32-'Skenario A B C'!$AE$32)) | F36: =IF(3<'Skenario A B C'!$E$32,0,MAX(0,'Skenario A B C'!$H$32-'Skenario A B C'!$AE$32)) | G36: =IF(4<'Skenario A B C'!$E$32,0,MAX(0,'Skenario A B C'!$I$32-'Skenario A B C'!$AE$32)) | H36: =IF(5<'Skenario A B C'!$E$32,0,MAX(0,'Skenario A B C'!$I$32-'Skenario A B C'!$AE$32)) | I36: =IF(6<'Skenario A B C'!$E$32,0,MAX(0,'Skenario A B C'!$I$32-'Skenario A B C'!$AE$32)) | J36: =IF(7<'Skenario A B C'!$E$32,0,MAX(0,'Skenario A B C'!$I$32-'Skenario A B C'!$AE$32)) | K36: =IF(8<'Skenario A B C'!$E$32,0,MAX(0,'Skenario A B C'!$I$32-'Skenario A B C'!$AE$32)) | L36: =IF(9<'Skenario A B C'!$E$32,0,MAX(0,'Skenario A B C'!$I$32-'Skenario A B C'!$AE$32)) | M36: =IF(10<'Skenario A B C'!$E$32,0,MAX(0,'Skenario A B C'!$I$32-'Skenario A B C'!$AE$32)) | N36: =IF(11<'Skenario A B C'!$E$32,0,MAX(0,'Skenario A B C'!$I$32-'Skenario A B C'!$AE$32)) | O36: =IF(12<'Skenario A B C'!$E$32,0,MAX(0,'Skenario A B C'!$I$32-'Skenario A B C'!$AE$32)) | P36: =IF(13<'Skenario A B C'!$E$32,0,MAX(0,'Skenario A B C'!$J$32-'Skenario A B C'!$AE$32)) | Q36: =IF(14<'Skenario A B C'!$E$32,0,MAX(0,'Skenario A B C'!$J$32-'Skenario A B C'!$AE$32)) | R36: =IF(15<'Skenario A B C'!$E$32,0,MAX(0,'Skenario A B C'!$J$32-'Skenario A B C'!$AE$32)) | S36: =IF(16<'Skenario A B C'!$E$32,0,MAX(0,'Skenario A B C'!$J$32-'Skenario A B C'!$AE$32)) | T36: =IF(17<'Skenario A B C'!$E$32,0,MAX(0,'Skenario A B C'!$J$32-'Skenario A B C'!$AE$32)) | U36: =IF(18<'Skenario A B C'!$E$32,0,MAX(0,'Skenario A B C'!$J$32-'Skenario A B C'!$AE$32)) | V36: =IF(19<'Skenario A B C'!$E$32,0,MAX(0,'Skenario A B C'!$J$32-'Skenario A B C'!$AE$32)) | W36: =IF(20<'Skenario A B C'!$E$32,0,MAX(0,'Skenario A B C'!$J$32-'Skenario A B C'!$AE$32)) | X36: =IF(21<'Skenario A B C'!$E$32,0,MAX(0,'Skenario A B C'!$J$32-'Skenario A B C'!$AE$32)) | Y36: =IF(22<'Skenario A B C'!$E$32,0,MAX(0,'Skenario A B C'!$J$32-'Skenario A B C'!$AE$32)) | Z36: =IF(23<'Skenario A B C'!$E$32,0,MAX(0,'Skenario A B C'!$J$32-'Skenario A B C'!$AE$32)) | AA36: =IF(24<'Skenario A B C'!$E$32,0,MAX(0,'Skenario A B C'!$J$32-'Skenario A B C'!$AE$32))
A37: Ops Supervisor Padang | B37: ='Skenario A B C'!$F$33 | D37: =IF(1<'Skenario A B C'!$E$33,0,MAX(0,'Skenario A B C'!$H$33-'Skenario A B C'!$AE$33)) | E37: =IF(2<'Skenario A B C'!$E$33,0,MAX(0,'Skenario A B C'!$H$33-'Skenario A B C'!$AE$33)) | F37: =IF(3<'Skenario A B C'!$E$33,0,MAX(0,'Skenario A B C'!$H$33-'Skenario A B C'!$AE$33)) | G37: =IF(4<'Skenario A B C'!$E$33,0,MAX(0,'Skenario A B C'!$I$33-'Skenario A B C'!$AE$33)) | H37: =IF(5<'Skenario A B C'!$E$33,0,MAX(0,'Skenario A B C'!$I$33-'Skenario A B C'!$AE$33)) | I37: =IF(6<'Skenario A B C'!$E$33,0,MAX(0,'Skenario A B C'!$I$33-'Skenario A B C'!$AE$33)) | J37: =IF(7<'Skenario A B C'!$E$33,0,MAX(0,'Skenario A B C'!$I$33-'Skenario A B C'!$AE$33)) | K37: =IF(8<'Skenario A B C'!$E$33,0,MAX(0,'Skenario A B C'!$I$33-'Skenario A B C'!$AE$33)) | L37: =IF(9<'Skenario A B C'!$E$33,0,MAX(0,'Skenario A B C'!$I$33-'Skenario A B C'!$AE$33)) | M37: =IF(10<'Skenario A B C'!$E$33,0,MAX(0,'Skenario A B C'!$I$33-'Skenario A B C'!$AE$33)) | N37: =IF(11<'Skenario A B C'!$E$33,0,MAX(0,'Skenario A B C'!$I$33-'Skenario A B C'!$AE$33)) | O37: =IF(12<'Skenario A B C'!$E$33,0,MAX(0,'Skenario A B C'!$I$33-'Skenario A B C'!$AE$33)) | P37: =IF(13<'Skenario A B C'!$E$33,0,MAX(0,'Skenario A B C'!$J$33-'Skenario A B C'!$AE$33)) | Q37: =IF(14<'Skenario A B C'!$E$33,0,MAX(0,'Skenario A B C'!$J$33-'Skenario A B C'!$AE$33)) | R37: =IF(15<'Skenario A B C'!$E$33,0,MAX(0,'Skenario A B C'!$J$33-'Skenario A B C'!$AE$33)) | S37: =IF(16<'Skenario A B C'!$E$33,0,MAX(0,'Skenario A B C'!$J$33-'Skenario A B C'!$AE$33)) | T37: =IF(17<'Skenario A B C'!$E$33,0,MAX(0,'Skenario A B C'!$J$33-'Skenario A B C'!$AE$33)) | U37: =IF(18<'Skenario A B C'!$E$33,0,MAX(0,'Skenario A B C'!$J$33-'Skenario A B C'!$AE$33)) | V37: =IF(19<'Skenario A B C'!$E$33,0,MAX(0,'Skenario A B C'!$J$33-'Skenario A B C'!$AE$33)) | W37: =IF(20<'Skenario A B C'!$E$33,0,MAX(0,'Skenario A B C'!$J$33-'Skenario A B C'!$AE$33)) | X37: =IF(21<'Skenario A B C'!$E$33,0,MAX(0,'Skenario A B C'!$J$33-'Skenario A B C'!$AE$33)) | Y37: =IF(22<'Skenario A B C'!$E$33,0,MAX(0,'Skenario A B C'!$J$33-'Skenario A B C'!$AE$33)) | Z37: =IF(23<'Skenario A B C'!$E$33,0,MAX(0,'Skenario A B C'!$J$33-'Skenario A B C'!$AE$33)) | AA37: =IF(24<'Skenario A B C'!$E$33,0,MAX(0,'Skenario A B C'!$J$33-'Skenario A B C'!$AE$33))
A38: CS Agent Padang (shift) | B38: ='Skenario A B C'!$F$34 | D38: =IF(1<'Skenario A B C'!$E$34,0,MAX(0,'Skenario A B C'!$H$34-'Skenario A B C'!$AE$34)) | E38: =IF(2<'Skenario A B C'!$E$34,0,MAX(0,'Skenario A B C'!$H$34-'Skenario A B C'!$AE$34)) | F38: =IF(3<'Skenario A B C'!$E$34,0,MAX(0,'Skenario A B C'!$H$34-'Skenario A B C'!$AE$34)) | G38: =IF(4<'Skenario A B C'!$E$34,0,MAX(0,'Skenario A B C'!$I$34-'Skenario A B C'!$AE$34)) | H38: =IF(5<'Skenario A B C'!$E$34,0,MAX(0,'Skenario A B C'!$I$34-'Skenario A B C'!$AE$34)) | I38: =IF(6<'Skenario A B C'!$E$34,0,MAX(0,'Skenario A B C'!$I$34-'Skenario A B C'!$AE$34)) | J38: =IF(7<'Skenario A B C'!$E$34,0,MAX(0,'Skenario A B C'!$I$34-'Skenario A B C'!$AE$34)) | K38: =IF(8<'Skenario A B C'!$E$34,0,MAX(0,'Skenario A B C'!$I$34-'Skenario A B C'!$AE$34)) | L38: =IF(9<'Skenario A B C'!$E$34,0,MAX(0,'Skenario A B C'!$I$34-'Skenario A B C'!$AE$34)) | M38: =IF(10<'Skenario A B C'!$E$34,0,MAX(0,'Skenario A B C'!$I$34-'Skenario A B C'!$AE$34)) | N38: =IF(11<'Skenario A B C'!$E$34,0,MAX(0,'Skenario A B C'!$I$34-'Skenario A B C'!$AE$34)) | O38: =IF(12<'Skenario A B C'!$E$34,0,MAX(0,'Skenario A B C'!$I$34-'Skenario A B C'!$AE$34)) | P38: =IF(13<'Skenario A B C'!$E$34,0,MAX(0,'Skenario A B C'!$J$34-'Skenario A B C'!$AE$34)) | Q38: =IF(14<'Skenario A B C'!$E$34,0,MAX(0,'Skenario A B C'!$J$34-'Skenario A B C'!$AE$34)) | R38: =IF(15<'Skenario A B C'!$E$34,0,MAX(0,'Skenario A B C'!$J$34-'Skenario A B C'!$AE$34)) | S38: =IF(16<'Skenario A B C'!$E$34,0,MAX(0,'Skenario A B C'!$J$34-'Skenario A B C'!$AE$34)) | T38: =IF(17<'Skenario A B C'!$E$34,0,MAX(0,'Skenario A B C'!$J$34-'Skenario A B C'!$AE$34)) | U38: =IF(18<'Skenario A B C'!$E$34,0,MAX(0,'Skenario A B C'!$J$34-'Skenario A B C'!$AE$34)) | V38: =IF(19<'Skenario A B C'!$E$34,0,MAX(0,'Skenario A B C'!$J$34-'Skenario A B C'!$AE$34)) | W38: =IF(20<'Skenario A B C'!$E$34,0,MAX(0,'Skenario A B C'!$J$34-'Skenario A B C'!$AE$34)) | X38: =IF(21<'Skenario A B C'!$E$34,0,MAX(0,'Skenario A B C'!$J$34-'Skenario A B C'!$AE$34)) | Y38: =IF(22<'Skenario A B C'!$E$34,0,MAX(0,'Skenario A B C'!$J$34-'Skenario A B C'!$AE$34)) | Z38: =IF(23<'Skenario A B C'!$E$34,0,MAX(0,'Skenario A B C'!$J$34-'Skenario A B C'!$AE$34)) | AA38: =IF(24<'Skenario A B C'!$E$34,0,MAX(0,'Skenario A B C'!$J$34-'Skenario A B C'!$AE$34))
A39: Partner Acquisition Padang - gelombang 2 | B39: ='Skenario A B C'!$F$35 | D39: =IF(1<'Skenario A B C'!$E$35,0,MAX(0,'Skenario A B C'!$H$35-'Skenario A B C'!$AE$35)) | E39: =IF(2<'Skenario A B C'!$E$35,0,MAX(0,'Skenario A B C'!$H$35-'Skenario A B C'!$AE$35)) | F39: =IF(3<'Skenario A B C'!$E$35,0,MAX(0,'Skenario A B C'!$H$35-'Skenario A B C'!$AE$35)) | G39: =IF(4<'Skenario A B C'!$E$35,0,MAX(0,'Skenario A B C'!$I$35-'Skenario A B C'!$AE$35)) | H39: =IF(5<'Skenario A B C'!$E$35,0,MAX(0,'Skenario A B C'!$I$35-'Skenario A B C'!$AE$35)) | I39: =IF(6<'Skenario A B C'!$E$35,0,MAX(0,'Skenario A B C'!$I$35-'Skenario A B C'!$AE$35)) | J39: =IF(7<'Skenario A B C'!$E$35,0,MAX(0,'Skenario A B C'!$I$35-'Skenario A B C'!$AE$35)) | K39: =IF(8<'Skenario A B C'!$E$35,0,MAX(0,'Skenario A B C'!$I$35-'Skenario A B C'!$AE$35)) | L39: =IF(9<'Skenario A B C'!$E$35,0,MAX(0,'Skenario A B C'!$I$35-'Skenario A B C'!$AE$35)) | M39: =IF(10<'Skenario A B C'!$E$35,0,MAX(0,'Skenario A B C'!$I$35-'Skenario A B C'!$AE$35)) | N39: =IF(11<'Skenario A B C'!$E$35,0,MAX(0,'Skenario A B C'!$I$35-'Skenario A B C'!$AE$35)) | O39: =IF(12<'Skenario A B C'!$E$35,0,MAX(0,'Skenario A B C'!$I$35-'Skenario A B C'!$AE$35)) | P39: =IF(13<'Skenario A B C'!$E$35,0,MAX(0,'Skenario A B C'!$J$35-'Skenario A B C'!$AE$35)) | Q39: =IF(14<'Skenario A B C'!$E$35,0,MAX(0,'Skenario A B C'!$J$35-'Skenario A B C'!$AE$35)) | R39: =IF(15<'Skenario A B C'!$E$35,0,MAX(0,'Skenario A B C'!$J$35-'Skenario A B C'!$AE$35)) | S39: =IF(16<'Skenario A B C'!$E$35,0,MAX(0,'Skenario A B C'!$J$35-'Skenario A B C'!$AE$35)) | T39: =IF(17<'Skenario A B C'!$E$35,0,MAX(0,'Skenario A B C'!$J$35-'Skenario A B C'!$AE$35)) | U39: =IF(18<'Skenario A B C'!$E$35,0,MAX(0,'Skenario A B C'!$J$35-'Skenario A B C'!$AE$35)) | V39: =IF(19<'Skenario A B C'!$E$35,0,MAX(0,'Skenario A B C'!$J$35-'Skenario A B C'!$AE$35)) | W39: =IF(20<'Skenario A B C'!$E$35,0,MAX(0,'Skenario A B C'!$J$35-'Skenario A B C'!$AE$35)) | X39: =IF(21<'Skenario A B C'!$E$35,0,MAX(0,'Skenario A B C'!$J$35-'Skenario A B C'!$AE$35)) | Y39: =IF(22<'Skenario A B C'!$E$35,0,MAX(0,'Skenario A B C'!$J$35-'Skenario A B C'!$AE$35)) | Z39: =IF(23<'Skenario A B C'!$E$35,0,MAX(0,'Skenario A B C'!$J$35-'Skenario A B C'!$AE$35)) | AA39: =IF(24<'Skenario A B C'!$E$35,0,MAX(0,'Skenario A B C'!$J$35-'Skenario A B C'!$AE$35))
A40: Head of Growth & Partnership | B40: ='Skenario A B C'!$F$36 | D40: =IF(1<'Skenario A B C'!$E$36,0,MAX(0,'Skenario A B C'!$H$36-'Skenario A B C'!$AE$36)) | E40: =IF(2<'Skenario A B C'!$E$36,0,MAX(0,'Skenario A B C'!$H$36-'Skenario A B C'!$AE$36)) | F40: =IF(3<'Skenario A B C'!$E$36,0,MAX(0,'Skenario A B C'!$H$36-'Skenario A B C'!$AE$36)) | G40: =IF(4<'Skenario A B C'!$E$36,0,MAX(0,'Skenario A B C'!$I$36-'Skenario A B C'!$AE$36)) | H40: =IF(5<'Skenario A B C'!$E$36,0,MAX(0,'Skenario A B C'!$I$36-'Skenario A B C'!$AE$36)) | I40: =IF(6<'Skenario A B C'!$E$36,0,MAX(0,'Skenario A B C'!$I$36-'Skenario A B C'!$AE$36)) | J40: =IF(7<'Skenario A B C'!$E$36,0,MAX(0,'Skenario A B C'!$I$36-'Skenario A B C'!$AE$36)) | K40: =IF(8<'Skenario A B C'!$E$36,0,MAX(0,'Skenario A B C'!$I$36-'Skenario A B C'!$AE$36)) | L40: =IF(9<'Skenario A B C'!$E$36,0,MAX(0,'Skenario A B C'!$I$36-'Skenario A B C'!$AE$36)) | M40: =IF(10<'Skenario A B C'!$E$36,0,MAX(0,'Skenario A B C'!$I$36-'Skenario A B C'!$AE$36)) | N40: =IF(11<'Skenario A B C'!$E$36,0,MAX(0,'Skenario A B C'!$I$36-'Skenario A B C'!$AE$36)) | O40: =IF(12<'Skenario A B C'!$E$36,0,MAX(0,'Skenario A B C'!$I$36-'Skenario A B C'!$AE$36)) | P40: =IF(13<'Skenario A B C'!$E$36,0,MAX(0,'Skenario A B C'!$J$36-'Skenario A B C'!$AE$36)) | Q40: =IF(14<'Skenario A B C'!$E$36,0,MAX(0,'Skenario A B C'!$J$36-'Skenario A B C'!$AE$36)) | R40: =IF(15<'Skenario A B C'!$E$36,0,MAX(0,'Skenario A B C'!$J$36-'Skenario A B C'!$AE$36)) | S40: =IF(16<'Skenario A B C'!$E$36,0,MAX(0,'Skenario A B C'!$J$36-'Skenario A B C'!$AE$36)) | T40: =IF(17<'Skenario A B C'!$E$36,0,MAX(0,'Skenario A B C'!$J$36-'Skenario A B C'!$AE$36)) | U40: =IF(18<'Skenario A B C'!$E$36,0,MAX(0,'Skenario A B C'!$J$36-'Skenario A B C'!$AE$36)) | V40: =IF(19<'Skenario A B C'!$E$36,0,MAX(0,'Skenario A B C'!$J$36-'Skenario A B C'!$AE$36)) | W40: =IF(20<'Skenario A B C'!$E$36,0,MAX(0,'Skenario A B C'!$J$36-'Skenario A B C'!$AE$36)) | X40: =IF(21<'Skenario A B C'!$E$36,0,MAX(0,'Skenario A B C'!$J$36-'Skenario A B C'!$AE$36)) | Y40: =IF(22<'Skenario A B C'!$E$36,0,MAX(0,'Skenario A B C'!$J$36-'Skenario A B C'!$AE$36)) | Z40: =IF(23<'Skenario A B C'!$E$36,0,MAX(0,'Skenario A B C'!$J$36-'Skenario A B C'!$AE$36)) | AA40: =IF(24<'Skenario A B C'!$E$36,0,MAX(0,'Skenario A B C'!$J$36-'Skenario A B C'!$AE$36))
A41: Digital Marketing Staff | B41: ='Skenario A B C'!$F$37 | D41: =IF(1<'Skenario A B C'!$E$37,0,MAX(0,'Skenario A B C'!$H$37-'Skenario A B C'!$AE$37)) | E41: =IF(2<'Skenario A B C'!$E$37,0,MAX(0,'Skenario A B C'!$H$37-'Skenario A B C'!$AE$37)) | F41: =IF(3<'Skenario A B C'!$E$37,0,MAX(0,'Skenario A B C'!$H$37-'Skenario A B C'!$AE$37)) | G41: =IF(4<'Skenario A B C'!$E$37,0,MAX(0,'Skenario A B C'!$I$37-'Skenario A B C'!$AE$37)) | H41: =IF(5<'Skenario A B C'!$E$37,0,MAX(0,'Skenario A B C'!$I$37-'Skenario A B C'!$AE$37)) | I41: =IF(6<'Skenario A B C'!$E$37,0,MAX(0,'Skenario A B C'!$I$37-'Skenario A B C'!$AE$37)) | J41: =IF(7<'Skenario A B C'!$E$37,0,MAX(0,'Skenario A B C'!$I$37-'Skenario A B C'!$AE$37)) | K41: =IF(8<'Skenario A B C'!$E$37,0,MAX(0,'Skenario A B C'!$I$37-'Skenario A B C'!$AE$37)) | L41: =IF(9<'Skenario A B C'!$E$37,0,MAX(0,'Skenario A B C'!$I$37-'Skenario A B C'!$AE$37)) | M41: =IF(10<'Skenario A B C'!$E$37,0,MAX(0,'Skenario A B C'!$I$37-'Skenario A B C'!$AE$37)) | N41: =IF(11<'Skenario A B C'!$E$37,0,MAX(0,'Skenario A B C'!$I$37-'Skenario A B C'!$AE$37)) | O41: =IF(12<'Skenario A B C'!$E$37,0,MAX(0,'Skenario A B C'!$I$37-'Skenario A B C'!$AE$37)) | P41: =IF(13<'Skenario A B C'!$E$37,0,MAX(0,'Skenario A B C'!$J$37-'Skenario A B C'!$AE$37)) | Q41: =IF(14<'Skenario A B C'!$E$37,0,MAX(0,'Skenario A B C'!$J$37-'Skenario A B C'!$AE$37)) | R41: =IF(15<'Skenario A B C'!$E$37,0,MAX(0,'Skenario A B C'!$J$37-'Skenario A B C'!$AE$37)) | S41: =IF(16<'Skenario A B C'!$E$37,0,MAX(0,'Skenario A B C'!$J$37-'Skenario A B C'!$AE$37)) | T41: =IF(17<'Skenario A B C'!$E$37,0,MAX(0,'Skenario A B C'!$J$37-'Skenario A B C'!$AE$37)) | U41: =IF(18<'Skenario A B C'!$E$37,0,MAX(0,'Skenario A B C'!$J$37-'Skenario A B C'!$AE$37)) | V41: =IF(19<'Skenario A B C'!$E$37,0,MAX(0,'Skenario A B C'!$J$37-'Skenario A B C'!$AE$37)) | W41: =IF(20<'Skenario A B C'!$E$37,0,MAX(0,'Skenario A B C'!$J$37-'Skenario A B C'!$AE$37)) | X41: =IF(21<'Skenario A B C'!$E$37,0,MAX(0,'Skenario A B C'!$J$37-'Skenario A B C'!$AE$37)) | Y41: =IF(22<'Skenario A B C'!$E$37,0,MAX(0,'Skenario A B C'!$J$37-'Skenario A B C'!$AE$37)) | Z41: =IF(23<'Skenario A B C'!$E$37,0,MAX(0,'Skenario A B C'!$J$37-'Skenario A B C'!$AE$37)) | AA41: =IF(24<'Skenario A B C'!$E$37,0,MAX(0,'Skenario A B C'!$J$37-'Skenario A B C'!$AE$37))
A42: Merchant Acquisition Officer | B42: ='Skenario A B C'!$F$38 | D42: =IF(1<'Skenario A B C'!$E$38,0,MAX(0,'Skenario A B C'!$H$38-'Skenario A B C'!$AE$38)) | E42: =IF(2<'Skenario A B C'!$E$38,0,MAX(0,'Skenario A B C'!$H$38-'Skenario A B C'!$AE$38)) | F42: =IF(3<'Skenario A B C'!$E$38,0,MAX(0,'Skenario A B C'!$H$38-'Skenario A B C'!$AE$38)) | G42: =IF(4<'Skenario A B C'!$E$38,0,MAX(0,'Skenario A B C'!$I$38-'Skenario A B C'!$AE$38)) | H42: =IF(5<'Skenario A B C'!$E$38,0,MAX(0,'Skenario A B C'!$I$38-'Skenario A B C'!$AE$38)) | I42: =IF(6<'Skenario A B C'!$E$38,0,MAX(0,'Skenario A B C'!$I$38-'Skenario A B C'!$AE$38)) | J42: =IF(7<'Skenario A B C'!$E$38,0,MAX(0,'Skenario A B C'!$I$38-'Skenario A B C'!$AE$38)) | K42: =IF(8<'Skenario A B C'!$E$38,0,MAX(0,'Skenario A B C'!$I$38-'Skenario A B C'!$AE$38)) | L42: =IF(9<'Skenario A B C'!$E$38,0,MAX(0,'Skenario A B C'!$I$38-'Skenario A B C'!$AE$38)) | M42: =IF(10<'Skenario A B C'!$E$38,0,MAX(0,'Skenario A B C'!$I$38-'Skenario A B C'!$AE$38)) | N42: =IF(11<'Skenario A B C'!$E$38,0,MAX(0,'Skenario A B C'!$I$38-'Skenario A B C'!$AE$38)) | O42: =IF(12<'Skenario A B C'!$E$38,0,MAX(0,'Skenario A B C'!$I$38-'Skenario A B C'!$AE$38)) | P42: =IF(13<'Skenario A B C'!$E$38,0,MAX(0,'Skenario A B C'!$J$38-'Skenario A B C'!$AE$38)) | Q42: =IF(14<'Skenario A B C'!$E$38,0,MAX(0,'Skenario A B C'!$J$38-'Skenario A B C'!$AE$38)) | R42: =IF(15<'Skenario A B C'!$E$38,0,MAX(0,'Skenario A B C'!$J$38-'Skenario A B C'!$AE$38)) | S42: =IF(16<'Skenario A B C'!$E$38,0,MAX(0,'Skenario A B C'!$J$38-'Skenario A B C'!$AE$38)) | T42: =IF(17<'Skenario A B C'!$E$38,0,MAX(0,'Skenario A B C'!$J$38-'Skenario A B C'!$AE$38)) | U42: =IF(18<'Skenario A B C'!$E$38,0,MAX(0,'Skenario A B C'!$J$38-'Skenario A B C'!$AE$38)) | V42: =IF(19<'Skenario A B C'!$E$38,0,MAX(0,'Skenario A B C'!$J$38-'Skenario A B C'!$AE$38)) | W42: =IF(20<'Skenario A B C'!$E$38,0,MAX(0,'Skenario A B C'!$J$38-'Skenario A B C'!$AE$38)) | X42: =IF(21<'Skenario A B C'!$E$38,0,MAX(0,'Skenario A B C'!$J$38-'Skenario A B C'!$AE$38)) | Y42: =IF(22<'Skenario A B C'!$E$38,0,MAX(0,'Skenario A B C'!$J$38-'Skenario A B C'!$AE$38)) | Z42: =IF(23<'Skenario A B C'!$E$38,0,MAX(0,'Skenario A B C'!$J$38-'Skenario A B C'!$AE$38)) | AA42: =IF(24<'Skenario A B C'!$E$38,0,MAX(0,'Skenario A B C'!$J$38-'Skenario A B C'!$AE$38))
A43: Head of Finance | B43: ='Skenario A B C'!$F$39 | D43: =IF(1<'Skenario A B C'!$E$39,0,MAX(0,'Skenario A B C'!$H$39-'Skenario A B C'!$AE$39)) | E43: =IF(2<'Skenario A B C'!$E$39,0,MAX(0,'Skenario A B C'!$H$39-'Skenario A B C'!$AE$39)) | F43: =IF(3<'Skenario A B C'!$E$39,0,MAX(0,'Skenario A B C'!$H$39-'Skenario A B C'!$AE$39)) | G43: =IF(4<'Skenario A B C'!$E$39,0,MAX(0,'Skenario A B C'!$I$39-'Skenario A B C'!$AE$39)) | H43: =IF(5<'Skenario A B C'!$E$39,0,MAX(0,'Skenario A B C'!$I$39-'Skenario A B C'!$AE$39)) | I43: =IF(6<'Skenario A B C'!$E$39,0,MAX(0,'Skenario A B C'!$I$39-'Skenario A B C'!$AE$39)) | J43: =IF(7<'Skenario A B C'!$E$39,0,MAX(0,'Skenario A B C'!$I$39-'Skenario A B C'!$AE$39)) | K43: =IF(8<'Skenario A B C'!$E$39,0,MAX(0,'Skenario A B C'!$I$39-'Skenario A B C'!$AE$39)) | L43: =IF(9<'Skenario A B C'!$E$39,0,MAX(0,'Skenario A B C'!$I$39-'Skenario A B C'!$AE$39)) | M43: =IF(10<'Skenario A B C'!$E$39,0,MAX(0,'Skenario A B C'!$I$39-'Skenario A B C'!$AE$39)) | N43: =IF(11<'Skenario A B C'!$E$39,0,MAX(0,'Skenario A B C'!$I$39-'Skenario A B C'!$AE$39)) | O43: =IF(12<'Skenario A B C'!$E$39,0,MAX(0,'Skenario A B C'!$I$39-'Skenario A B C'!$AE$39)) | P43: =IF(13<'Skenario A B C'!$E$39,0,MAX(0,'Skenario A B C'!$J$39-'Skenario A B C'!$AE$39)) | Q43: =IF(14<'Skenario A B C'!$E$39,0,MAX(0,'Skenario A B C'!$J$39-'Skenario A B C'!$AE$39)) | R43: =IF(15<'Skenario A B C'!$E$39,0,MAX(0,'Skenario A B C'!$J$39-'Skenario A B C'!$AE$39)) | S43: =IF(16<'Skenario A B C'!$E$39,0,MAX(0,'Skenario A B C'!$J$39-'Skenario A B C'!$AE$39)) | T43: =IF(17<'Skenario A B C'!$E$39,0,MAX(0,'Skenario A B C'!$J$39-'Skenario A B C'!$AE$39)) | U43: =IF(18<'Skenario A B C'!$E$39,0,MAX(0,'Skenario A B C'!$J$39-'Skenario A B C'!$AE$39)) | V43: =IF(19<'Skenario A B C'!$E$39,0,MAX(0,'Skenario A B C'!$J$39-'Skenario A B C'!$AE$39)) | W43: =IF(20<'Skenario A B C'!$E$39,0,MAX(0,'Skenario A B C'!$J$39-'Skenario A B C'!$AE$39)) | X43: =IF(21<'Skenario A B C'!$E$39,0,MAX(0,'Skenario A B C'!$J$39-'Skenario A B C'!$AE$39)) | Y43: =IF(22<'Skenario A B C'!$E$39,0,MAX(0,'Skenario A B C'!$J$39-'Skenario A B C'!$AE$39)) | Z43: =IF(23<'Skenario A B C'!$E$39,0,MAX(0,'Skenario A B C'!$J$39-'Skenario A B C'!$AE$39)) | AA43: =IF(24<'Skenario A B C'!$E$39,0,MAX(0,'Skenario A B C'!$J$39-'Skenario A B C'!$AE$39))
A44: Finance & Accounting Staff | B44: ='Skenario A B C'!$F$40 | D44: =IF(1<'Skenario A B C'!$E$40,0,MAX(0,'Skenario A B C'!$H$40-'Skenario A B C'!$AE$40)) | E44: =IF(2<'Skenario A B C'!$E$40,0,MAX(0,'Skenario A B C'!$H$40-'Skenario A B C'!$AE$40)) | F44: =IF(3<'Skenario A B C'!$E$40,0,MAX(0,'Skenario A B C'!$H$40-'Skenario A B C'!$AE$40)) | G44: =IF(4<'Skenario A B C'!$E$40,0,MAX(0,'Skenario A B C'!$I$40-'Skenario A B C'!$AE$40)) | H44: =IF(5<'Skenario A B C'!$E$40,0,MAX(0,'Skenario A B C'!$I$40-'Skenario A B C'!$AE$40)) | I44: =IF(6<'Skenario A B C'!$E$40,0,MAX(0,'Skenario A B C'!$I$40-'Skenario A B C'!$AE$40)) | J44: =IF(7<'Skenario A B C'!$E$40,0,MAX(0,'Skenario A B C'!$I$40-'Skenario A B C'!$AE$40)) | K44: =IF(8<'Skenario A B C'!$E$40,0,MAX(0,'Skenario A B C'!$I$40-'Skenario A B C'!$AE$40)) | L44: =IF(9<'Skenario A B C'!$E$40,0,MAX(0,'Skenario A B C'!$I$40-'Skenario A B C'!$AE$40)) | M44: =IF(10<'Skenario A B C'!$E$40,0,MAX(0,'Skenario A B C'!$I$40-'Skenario A B C'!$AE$40)) | N44: =IF(11<'Skenario A B C'!$E$40,0,MAX(0,'Skenario A B C'!$I$40-'Skenario A B C'!$AE$40)) | O44: =IF(12<'Skenario A B C'!$E$40,0,MAX(0,'Skenario A B C'!$I$40-'Skenario A B C'!$AE$40)) | P44: =IF(13<'Skenario A B C'!$E$40,0,MAX(0,'Skenario A B C'!$J$40-'Skenario A B C'!$AE$40)) | Q44: =IF(14<'Skenario A B C'!$E$40,0,MAX(0,'Skenario A B C'!$J$40-'Skenario A B C'!$AE$40)) | R44: =IF(15<'Skenario A B C'!$E$40,0,MAX(0,'Skenario A B C'!$J$40-'Skenario A B C'!$AE$40)) | S44: =IF(16<'Skenario A B C'!$E$40,0,MAX(0,'Skenario A B C'!$J$40-'Skenario A B C'!$AE$40)) | T44: =IF(17<'Skenario A B C'!$E$40,0,MAX(0,'Skenario A B C'!$J$40-'Skenario A B C'!$AE$40)) | U44: =IF(18<'Skenario A B C'!$E$40,0,MAX(0,'Skenario A B C'!$J$40-'Skenario A B C'!$AE$40)) | V44: =IF(19<'Skenario A B C'!$E$40,0,MAX(0,'Skenario A B C'!$J$40-'Skenario A B C'!$AE$40)) | W44: =IF(20<'Skenario A B C'!$E$40,0,MAX(0,'Skenario A B C'!$J$40-'Skenario A B C'!$AE$40)) | X44: =IF(21<'Skenario A B C'!$E$40,0,MAX(0,'Skenario A B C'!$J$40-'Skenario A B C'!$AE$40)) | Y44: =IF(22<'Skenario A B C'!$E$40,0,MAX(0,'Skenario A B C'!$J$40-'Skenario A B C'!$AE$40)) | Z44: =IF(23<'Skenario A B C'!$E$40,0,MAX(0,'Skenario A B C'!$J$40-'Skenario A B C'!$AE$40)) | AA44: =IF(24<'Skenario A B C'!$E$40,0,MAX(0,'Skenario A B C'!$J$40-'Skenario A B C'!$AE$40))
A45: Treasury/Settlement Officer | B45: ='Skenario A B C'!$F$41 | D45: =IF(1<'Skenario A B C'!$E$41,0,MAX(0,'Skenario A B C'!$H$41-'Skenario A B C'!$AE$41)) | E45: =IF(2<'Skenario A B C'!$E$41,0,MAX(0,'Skenario A B C'!$H$41-'Skenario A B C'!$AE$41)) | F45: =IF(3<'Skenario A B C'!$E$41,0,MAX(0,'Skenario A B C'!$H$41-'Skenario A B C'!$AE$41)) | G45: =IF(4<'Skenario A B C'!$E$41,0,MAX(0,'Skenario A B C'!$I$41-'Skenario A B C'!$AE$41)) | H45: =IF(5<'Skenario A B C'!$E$41,0,MAX(0,'Skenario A B C'!$I$41-'Skenario A B C'!$AE$41)) | I45: =IF(6<'Skenario A B C'!$E$41,0,MAX(0,'Skenario A B C'!$I$41-'Skenario A B C'!$AE$41)) | J45: =IF(7<'Skenario A B C'!$E$41,0,MAX(0,'Skenario A B C'!$I$41-'Skenario A B C'!$AE$41)) | K45: =IF(8<'Skenario A B C'!$E$41,0,MAX(0,'Skenario A B C'!$I$41-'Skenario A B C'!$AE$41)) | L45: =IF(9<'Skenario A B C'!$E$41,0,MAX(0,'Skenario A B C'!$I$41-'Skenario A B C'!$AE$41)) | M45: =IF(10<'Skenario A B C'!$E$41,0,MAX(0,'Skenario A B C'!$I$41-'Skenario A B C'!$AE$41)) | N45: =IF(11<'Skenario A B C'!$E$41,0,MAX(0,'Skenario A B C'!$I$41-'Skenario A B C'!$AE$41)) | O45: =IF(12<'Skenario A B C'!$E$41,0,MAX(0,'Skenario A B C'!$I$41-'Skenario A B C'!$AE$41)) | P45: =IF(13<'Skenario A B C'!$E$41,0,MAX(0,'Skenario A B C'!$J$41-'Skenario A B C'!$AE$41)) | Q45: =IF(14<'Skenario A B C'!$E$41,0,MAX(0,'Skenario A B C'!$J$41-'Skenario A B C'!$AE$41)) | R45: =IF(15<'Skenario A B C'!$E$41,0,MAX(0,'Skenario A B C'!$J$41-'Skenario A B C'!$AE$41)) | S45: =IF(16<'Skenario A B C'!$E$41,0,MAX(0,'Skenario A B C'!$J$41-'Skenario A B C'!$AE$41)) | T45: =IF(17<'Skenario A B C'!$E$41,0,MAX(0,'Skenario A B C'!$J$41-'Skenario A B C'!$AE$41)) | U45: =IF(18<'Skenario A B C'!$E$41,0,MAX(0,'Skenario A B C'!$J$41-'Skenario A B C'!$AE$41)) | V45: =IF(19<'Skenario A B C'!$E$41,0,MAX(0,'Skenario A B C'!$J$41-'Skenario A B C'!$AE$41)) | W45: =IF(20<'Skenario A B C'!$E$41,0,MAX(0,'Skenario A B C'!$J$41-'Skenario A B C'!$AE$41)) | X45: =IF(21<'Skenario A B C'!$E$41,0,MAX(0,'Skenario A B C'!$J$41-'Skenario A B C'!$AE$41)) | Y45: =IF(22<'Skenario A B C'!$E$41,0,MAX(0,'Skenario A B C'!$J$41-'Skenario A B C'!$AE$41)) | Z45: =IF(23<'Skenario A B C'!$E$41,0,MAX(0,'Skenario A B C'!$J$41-'Skenario A B C'!$AE$41)) | AA45: =IF(24<'Skenario A B C'!$E$41,0,MAX(0,'Skenario A B C'!$J$41-'Skenario A B C'!$AE$41))
A46: Finance & Accounting Staff - Padang | B46: ='Skenario A B C'!$F$42 | D46: =IF(1<'Skenario A B C'!$E$42,0,MAX(0,'Skenario A B C'!$H$42-'Skenario A B C'!$AE$42)) | E46: =IF(2<'Skenario A B C'!$E$42,0,MAX(0,'Skenario A B C'!$H$42-'Skenario A B C'!$AE$42)) | F46: =IF(3<'Skenario A B C'!$E$42,0,MAX(0,'Skenario A B C'!$H$42-'Skenario A B C'!$AE$42)) | G46: =IF(4<'Skenario A B C'!$E$42,0,MAX(0,'Skenario A B C'!$I$42-'Skenario A B C'!$AE$42)) | H46: =IF(5<'Skenario A B C'!$E$42,0,MAX(0,'Skenario A B C'!$I$42-'Skenario A B C'!$AE$42)) | I46: =IF(6<'Skenario A B C'!$E$42,0,MAX(0,'Skenario A B C'!$I$42-'Skenario A B C'!$AE$42)) | J46: =IF(7<'Skenario A B C'!$E$42,0,MAX(0,'Skenario A B C'!$I$42-'Skenario A B C'!$AE$42)) | K46: =IF(8<'Skenario A B C'!$E$42,0,MAX(0,'Skenario A B C'!$I$42-'Skenario A B C'!$AE$42)) | L46: =IF(9<'Skenario A B C'!$E$42,0,MAX(0,'Skenario A B C'!$I$42-'Skenario A B C'!$AE$42)) | M46: =IF(10<'Skenario A B C'!$E$42,0,MAX(0,'Skenario A B C'!$I$42-'Skenario A B C'!$AE$42)) | N46: =IF(11<'Skenario A B C'!$E$42,0,MAX(0,'Skenario A B C'!$I$42-'Skenario A B C'!$AE$42)) | O46: =IF(12<'Skenario A B C'!$E$42,0,MAX(0,'Skenario A B C'!$I$42-'Skenario A B C'!$AE$42)) | P46: =IF(13<'Skenario A B C'!$E$42,0,MAX(0,'Skenario A B C'!$J$42-'Skenario A B C'!$AE$42)) | Q46: =IF(14<'Skenario A B C'!$E$42,0,MAX(0,'Skenario A B C'!$J$42-'Skenario A B C'!$AE$42)) | R46: =IF(15<'Skenario A B C'!$E$42,0,MAX(0,'Skenario A B C'!$J$42-'Skenario A B C'!$AE$42)) | S46: =IF(16<'Skenario A B C'!$E$42,0,MAX(0,'Skenario A B C'!$J$42-'Skenario A B C'!$AE$42)) | T46: =IF(17<'Skenario A B C'!$E$42,0,MAX(0,'Skenario A B C'!$J$42-'Skenario A B C'!$AE$42)) | U46: =IF(18<'Skenario A B C'!$E$42,0,MAX(0,'Skenario A B C'!$J$42-'Skenario A B C'!$AE$42)) | V46: =IF(19<'Skenario A B C'!$E$42,0,MAX(0,'Skenario A B C'!$J$42-'Skenario A B C'!$AE$42)) | W46: =IF(20<'Skenario A B C'!$E$42,0,MAX(0,'Skenario A B C'!$J$42-'Skenario A B C'!$AE$42)) | X46: =IF(21<'Skenario A B C'!$E$42,0,MAX(0,'Skenario A B C'!$J$42-'Skenario A B C'!$AE$42)) | Y46: =IF(22<'Skenario A B C'!$E$42,0,MAX(0,'Skenario A B C'!$J$42-'Skenario A B C'!$AE$42)) | Z46: =IF(23<'Skenario A B C'!$E$42,0,MAX(0,'Skenario A B C'!$J$42-'Skenario A B C'!$AE$42)) | AA46: =IF(24<'Skenario A B C'!$E$42,0,MAX(0,'Skenario A B C'!$J$42-'Skenario A B C'!$AE$42))
A47: Head of Legal & Compliance (merangkap DPO) | B47: ='Skenario A B C'!$F$43 | D47: =IF(1<'Skenario A B C'!$E$43,0,MAX(0,'Skenario A B C'!$H$43-'Skenario A B C'!$AE$43)) | E47: =IF(2<'Skenario A B C'!$E$43,0,MAX(0,'Skenario A B C'!$H$43-'Skenario A B C'!$AE$43)) | F47: =IF(3<'Skenario A B C'!$E$43,0,MAX(0,'Skenario A B C'!$H$43-'Skenario A B C'!$AE$43)) | G47: =IF(4<'Skenario A B C'!$E$43,0,MAX(0,'Skenario A B C'!$I$43-'Skenario A B C'!$AE$43)) | H47: =IF(5<'Skenario A B C'!$E$43,0,MAX(0,'Skenario A B C'!$I$43-'Skenario A B C'!$AE$43)) | I47: =IF(6<'Skenario A B C'!$E$43,0,MAX(0,'Skenario A B C'!$I$43-'Skenario A B C'!$AE$43)) | J47: =IF(7<'Skenario A B C'!$E$43,0,MAX(0,'Skenario A B C'!$I$43-'Skenario A B C'!$AE$43)) | K47: =IF(8<'Skenario A B C'!$E$43,0,MAX(0,'Skenario A B C'!$I$43-'Skenario A B C'!$AE$43)) | L47: =IF(9<'Skenario A B C'!$E$43,0,MAX(0,'Skenario A B C'!$I$43-'Skenario A B C'!$AE$43)) | M47: =IF(10<'Skenario A B C'!$E$43,0,MAX(0,'Skenario A B C'!$I$43-'Skenario A B C'!$AE$43)) | N47: =IF(11<'Skenario A B C'!$E$43,0,MAX(0,'Skenario A B C'!$I$43-'Skenario A B C'!$AE$43)) | O47: =IF(12<'Skenario A B C'!$E$43,0,MAX(0,'Skenario A B C'!$I$43-'Skenario A B C'!$AE$43)) | P47: =IF(13<'Skenario A B C'!$E$43,0,MAX(0,'Skenario A B C'!$J$43-'Skenario A B C'!$AE$43)) | Q47: =IF(14<'Skenario A B C'!$E$43,0,MAX(0,'Skenario A B C'!$J$43-'Skenario A B C'!$AE$43)) | R47: =IF(15<'Skenario A B C'!$E$43,0,MAX(0,'Skenario A B C'!$J$43-'Skenario A B C'!$AE$43)) | S47: =IF(16<'Skenario A B C'!$E$43,0,MAX(0,'Skenario A B C'!$J$43-'Skenario A B C'!$AE$43)) | T47: =IF(17<'Skenario A B C'!$E$43,0,MAX(0,'Skenario A B C'!$J$43-'Skenario A B C'!$AE$43)) | U47: =IF(18<'Skenario A B C'!$E$43,0,MAX(0,'Skenario A B C'!$J$43-'Skenario A B C'!$AE$43)) | V47: =IF(19<'Skenario A B C'!$E$43,0,MAX(0,'Skenario A B C'!$J$43-'Skenario A B C'!$AE$43)) | W47: =IF(20<'Skenario A B C'!$E$43,0,MAX(0,'Skenario A B C'!$J$43-'Skenario A B C'!$AE$43)) | X47: =IF(21<'Skenario A B C'!$E$43,0,MAX(0,'Skenario A B C'!$J$43-'Skenario A B C'!$AE$43)) | Y47: =IF(22<'Skenario A B C'!$E$43,0,MAX(0,'Skenario A B C'!$J$43-'Skenario A B C'!$AE$43)) | Z47: =IF(23<'Skenario A B C'!$E$43,0,MAX(0,'Skenario A B C'!$J$43-'Skenario A B C'!$AE$43)) | AA47: =IF(24<'Skenario A B C'!$E$43,0,MAX(0,'Skenario A B C'!$J$43-'Skenario A B C'!$AE$43))
A49: B. JUMLAH ORANG AKTIF PER BULAN - SKENARIO B (hibrida)
A50: Direktur Utama (CEO) | B50: ='Skenario A B C'!$F$6 | D50: =IF(1<'Skenario A B C'!$E$6,0,MAX(0,'Skenario A B C'!$H$6-'Skenario A B C'!$K$6)) | E50: =IF(2<'Skenario A B C'!$E$6,0,MAX(0,'Skenario A B C'!$H$6-'Skenario A B C'!$K$6)) | F50: =IF(3<'Skenario A B C'!$E$6,0,MAX(0,'Skenario A B C'!$H$6-'Skenario A B C'!$K$6)) | G50: =IF(4<'Skenario A B C'!$E$6,0,MAX(0,'Skenario A B C'!$I$6-'Skenario A B C'!$K$6)) | H50: =IF(5<'Skenario A B C'!$E$6,0,MAX(0,'Skenario A B C'!$I$6-'Skenario A B C'!$K$6)) | I50: =IF(6<'Skenario A B C'!$E$6,0,MAX(0,'Skenario A B C'!$I$6-'Skenario A B C'!$K$6)) | J50: =IF(7<'Skenario A B C'!$E$6,0,MAX(0,'Skenario A B C'!$I$6-'Skenario A B C'!$K$6)) | K50: =IF(8<'Skenario A B C'!$E$6,0,MAX(0,'Skenario A B C'!$I$6-'Skenario A B C'!$K$6)) | L50: =IF(9<'Skenario A B C'!$E$6,0,MAX(0,'Skenario A B C'!$I$6-'Skenario A B C'!$K$6)) | M50: =IF(10<'Skenario A B C'!$E$6,0,MAX(0,'Skenario A B C'!$I$6-'Skenario A B C'!$K$6)) | N50: =IF(11<'Skenario A B C'!$E$6,0,MAX(0,'Skenario A B C'!$I$6-'Skenario A B C'!$K$6)) | O50: =IF(12<'Skenario A B C'!$E$6,0,MAX(0,'Skenario A B C'!$I$6-'Skenario A B C'!$K$6)) | P50: =IF(13<'Skenario A B C'!$E$6,0,MAX(0,'Skenario A B C'!$J$6-'Skenario A B C'!$K$6)) | Q50: =IF(14<'Skenario A B C'!$E$6,0,MAX(0,'Skenario A B C'!$J$6-'Skenario A B C'!$K$6)) | R50: =IF(15<'Skenario A B C'!$E$6,0,MAX(0,'Skenario A B C'!$J$6-'Skenario A B C'!$K$6)) | S50: =IF(16<'Skenario A B C'!$E$6,0,MAX(0,'Skenario A B C'!$J$6-'Skenario A B C'!$K$6)) | T50: =IF(17<'Skenario A B C'!$E$6,0,MAX(0,'Skenario A B C'!$J$6-'Skenario A B C'!$K$6)) | U50: =IF(18<'Skenario A B C'!$E$6,0,MAX(0,'Skenario A B C'!$J$6-'Skenario A B C'!$K$6)) | V50: =IF(19<'Skenario A B C'!$E$6,0,MAX(0,'Skenario A B C'!$J$6-'Skenario A B C'!$K$6)) | W50: =IF(20<'Skenario A B C'!$E$6,0,MAX(0,'Skenario A B C'!$J$6-'Skenario A B C'!$K$6)) | X50: =IF(21<'Skenario A B C'!$E$6,0,MAX(0,'Skenario A B C'!$J$6-'Skenario A B C'!$K$6)) | Y50: =IF(22<'Skenario A B C'!$E$6,0,MAX(0,'Skenario A B C'!$J$6-'Skenario A B C'!$K$6)) | Z50: =IF(23<'Skenario A B C'!$E$6,0,MAX(0,'Skenario A B C'!$J$6-'Skenario A B C'!$K$6)) | AA50: =IF(24<'Skenario A B C'!$E$6,0,MAX(0,'Skenario A B C'!$J$6-'Skenario A B C'!$K$6))
A51: HR & GA Generalist | B51: ='Skenario A B C'!$F$7 | D51: =IF(1<'Skenario A B C'!$E$7,0,MAX(0,'Skenario A B C'!$H$7-'Skenario A B C'!$K$7)) | E51: =IF(2<'Skenario A B C'!$E$7,0,MAX(0,'Skenario A B C'!$H$7-'Skenario A B C'!$K$7)) | F51: =IF(3<'Skenario A B C'!$E$7,0,MAX(0,'Skenario A B C'!$H$7-'Skenario A B C'!$K$7)) | G51: =IF(4<'Skenario A B C'!$E$7,0,MAX(0,'Skenario A B C'!$I$7-'Skenario A B C'!$K$7)) | H51: =IF(5<'Skenario A B C'!$E$7,0,MAX(0,'Skenario A B C'!$I$7-'Skenario A B C'!$K$7)) | I51: =IF(6<'Skenario A B C'!$E$7,0,MAX(0,'Skenario A B C'!$I$7-'Skenario A B C'!$K$7)) | J51: =IF(7<'Skenario A B C'!$E$7,0,MAX(0,'Skenario A B C'!$I$7-'Skenario A B C'!$K$7)) | K51: =IF(8<'Skenario A B C'!$E$7,0,MAX(0,'Skenario A B C'!$I$7-'Skenario A B C'!$K$7)) | L51: =IF(9<'Skenario A B C'!$E$7,0,MAX(0,'Skenario A B C'!$I$7-'Skenario A B C'!$K$7)) | M51: =IF(10<'Skenario A B C'!$E$7,0,MAX(0,'Skenario A B C'!$I$7-'Skenario A B C'!$K$7)) | N51: =IF(11<'Skenario A B C'!$E$7,0,MAX(0,'Skenario A B C'!$I$7-'Skenario A B C'!$K$7)) | O51: =IF(12<'Skenario A B C'!$E$7,0,MAX(0,'Skenario A B C'!$I$7-'Skenario A B C'!$K$7)) | P51: =IF(13<'Skenario A B C'!$E$7,0,MAX(0,'Skenario A B C'!$J$7-'Skenario A B C'!$K$7)) | Q51: =IF(14<'Skenario A B C'!$E$7,0,MAX(0,'Skenario A B C'!$J$7-'Skenario A B C'!$K$7)) | R51: =IF(15<'Skenario A B C'!$E$7,0,MAX(0,'Skenario A B C'!$J$7-'Skenario A B C'!$K$7)) | S51: =IF(16<'Skenario A B C'!$E$7,0,MAX(0,'Skenario A B C'!$J$7-'Skenario A B C'!$K$7)) | T51: =IF(17<'Skenario A B C'!$E$7,0,MAX(0,'Skenario A B C'!$J$7-'Skenario A B C'!$K$7)) | U51: =IF(18<'Skenario A B C'!$E$7,0,MAX(0,'Skenario A B C'!$J$7-'Skenario A B C'!$K$7)) | V51: =IF(19<'Skenario A B C'!$E$7,0,MAX(0,'Skenario A B C'!$J$7-'Skenario A B C'!$K$7)) | W51: =IF(20<'Skenario A B C'!$E$7,0,MAX(0,'Skenario A B C'!$J$7-'Skenario A B C'!$K$7)) | X51: =IF(21<'Skenario A B C'!$E$7,0,MAX(0,'Skenario A B C'!$J$7-'Skenario A B C'!$K$7)) | Y51: =IF(22<'Skenario A B C'!$E$7,0,MAX(0,'Skenario A B C'!$J$7-'Skenario A B C'!$K$7)) | Z51: =IF(23<'Skenario A B C'!$E$7,0,MAX(0,'Skenario A B C'!$J$7-'Skenario A B C'!$K$7)) | AA51: =IF(24<'Skenario A B C'!$E$7,0,MAX(0,'Skenario A B C'!$J$7-'Skenario A B C'!$K$7))
A52: Direktur Teknologi (CTO) | B52: ='Skenario A B C'!$F$8 | D52: =IF(1<'Skenario A B C'!$E$8,0,MAX(0,'Skenario A B C'!$H$8-'Skenario A B C'!$K$8)) | E52: =IF(2<'Skenario A B C'!$E$8,0,MAX(0,'Skenario A B C'!$H$8-'Skenario A B C'!$K$8)) | F52: =IF(3<'Skenario A B C'!$E$8,0,MAX(0,'Skenario A B C'!$H$8-'Skenario A B C'!$K$8)) | G52: =IF(4<'Skenario A B C'!$E$8,0,MAX(0,'Skenario A B C'!$I$8-'Skenario A B C'!$K$8)) | H52: =IF(5<'Skenario A B C'!$E$8,0,MAX(0,'Skenario A B C'!$I$8-'Skenario A B C'!$K$8)) | I52: =IF(6<'Skenario A B C'!$E$8,0,MAX(0,'Skenario A B C'!$I$8-'Skenario A B C'!$K$8)) | J52: =IF(7<'Skenario A B C'!$E$8,0,MAX(0,'Skenario A B C'!$I$8-'Skenario A B C'!$K$8)) | K52: =IF(8<'Skenario A B C'!$E$8,0,MAX(0,'Skenario A B C'!$I$8-'Skenario A B C'!$K$8)) | L52: =IF(9<'Skenario A B C'!$E$8,0,MAX(0,'Skenario A B C'!$I$8-'Skenario A B C'!$K$8)) | M52: =IF(10<'Skenario A B C'!$E$8,0,MAX(0,'Skenario A B C'!$I$8-'Skenario A B C'!$K$8)) | N52: =IF(11<'Skenario A B C'!$E$8,0,MAX(0,'Skenario A B C'!$I$8-'Skenario A B C'!$K$8)) | O52: =IF(12<'Skenario A B C'!$E$8,0,MAX(0,'Skenario A B C'!$I$8-'Skenario A B C'!$K$8)) | P52: =IF(13<'Skenario A B C'!$E$8,0,MAX(0,'Skenario A B C'!$J$8-'Skenario A B C'!$K$8)) | Q52: =IF(14<'Skenario A B C'!$E$8,0,MAX(0,'Skenario A B C'!$J$8-'Skenario A B C'!$K$8)) | R52: =IF(15<'Skenario A B C'!$E$8,0,MAX(0,'Skenario A B C'!$J$8-'Skenario A B C'!$K$8)) | S52: =IF(16<'Skenario A B C'!$E$8,0,MAX(0,'Skenario A B C'!$J$8-'Skenario A B C'!$K$8)) | T52: =IF(17<'Skenario A B C'!$E$8,0,MAX(0,'Skenario A B C'!$J$8-'Skenario A B C'!$K$8)) | U52: =IF(18<'Skenario A B C'!$E$8,0,MAX(0,'Skenario A B C'!$J$8-'Skenario A B C'!$K$8)) | V52: =IF(19<'Skenario A B C'!$E$8,0,MAX(0,'Skenario A B C'!$J$8-'Skenario A B C'!$K$8)) | W52: =IF(20<'Skenario A B C'!$E$8,0,MAX(0,'Skenario A B C'!$J$8-'Skenario A B C'!$K$8)) | X52: =IF(21<'Skenario A B C'!$E$8,0,MAX(0,'Skenario A B C'!$J$8-'Skenario A B C'!$K$8)) | Y52: =IF(22<'Skenario A B C'!$E$8,0,MAX(0,'Skenario A B C'!$J$8-'Skenario A B C'!$K$8)) | Z52: =IF(23<'Skenario A B C'!$E$8,0,MAX(0,'Skenario A B C'!$J$8-'Skenario A B C'!$K$8)) | AA52: =IF(24<'Skenario A B C'!$E$8,0,MAX(0,'Skenario A B C'!$J$8-'Skenario A B C'!$K$8))
A53: Engineering Manager | B53: ='Skenario A B C'!$F$9 | D53: =IF(1<'Skenario A B C'!$E$9,0,MAX(0,'Skenario A B C'!$H$9-'Skenario A B C'!$K$9)) | E53: =IF(2<'Skenario A B C'!$E$9,0,MAX(0,'Skenario A B C'!$H$9-'Skenario A B C'!$K$9)) | F53: =IF(3<'Skenario A B C'!$E$9,0,MAX(0,'Skenario A B C'!$H$9-'Skenario A B C'!$K$9)) | G53: =IF(4<'Skenario A B C'!$E$9,0,MAX(0,'Skenario A B C'!$I$9-'Skenario A B C'!$K$9)) | H53: =IF(5<'Skenario A B C'!$E$9,0,MAX(0,'Skenario A B C'!$I$9-'Skenario A B C'!$K$9)) | I53: =IF(6<'Skenario A B C'!$E$9,0,MAX(0,'Skenario A B C'!$I$9-'Skenario A B C'!$K$9)) | J53: =IF(7<'Skenario A B C'!$E$9,0,MAX(0,'Skenario A B C'!$I$9-'Skenario A B C'!$K$9)) | K53: =IF(8<'Skenario A B C'!$E$9,0,MAX(0,'Skenario A B C'!$I$9-'Skenario A B C'!$K$9)) | L53: =IF(9<'Skenario A B C'!$E$9,0,MAX(0,'Skenario A B C'!$I$9-'Skenario A B C'!$K$9)) | M53: =IF(10<'Skenario A B C'!$E$9,0,MAX(0,'Skenario A B C'!$I$9-'Skenario A B C'!$K$9)) | N53: =IF(11<'Skenario A B C'!$E$9,0,MAX(0,'Skenario A B C'!$I$9-'Skenario A B C'!$K$9)) | O53: =IF(12<'Skenario A B C'!$E$9,0,MAX(0,'Skenario A B C'!$I$9-'Skenario A B C'!$K$9)) | P53: =IF(13<'Skenario A B C'!$E$9,0,MAX(0,'Skenario A B C'!$J$9-'Skenario A B C'!$K$9)) | Q53: =IF(14<'Skenario A B C'!$E$9,0,MAX(0,'Skenario A B C'!$J$9-'Skenario A B C'!$K$9)) | R53: =IF(15<'Skenario A B C'!$E$9,0,MAX(0,'Skenario A B C'!$J$9-'Skenario A B C'!$K$9)) | S53: =IF(16<'Skenario A B C'!$E$9,0,MAX(0,'Skenario A B C'!$J$9-'Skenario A B C'!$K$9)) | T53: =IF(17<'Skenario A B C'!$E$9,0,MAX(0,'Skenario A B C'!$J$9-'Skenario A B C'!$K$9)) | U53: =IF(18<'Skenario A B C'!$E$9,0,MAX(0,'Skenario A B C'!$J$9-'Skenario A B C'!$K$9)) | V53: =IF(19<'Skenario A B C'!$E$9,0,MAX(0,'Skenario A B C'!$J$9-'Skenario A B C'!$K$9)) | W53: =IF(20<'Skenario A B C'!$E$9,0,MAX(0,'Skenario A B C'!$J$9-'Skenario A B C'!$K$9)) | X53: =IF(21<'Skenario A B C'!$E$9,0,MAX(0,'Skenario A B C'!$J$9-'Skenario A B C'!$K$9)) | Y53: =IF(22<'Skenario A B C'!$E$9,0,MAX(0,'Skenario A B C'!$J$9-'Skenario A B C'!$K$9)) | Z53: =IF(23<'Skenario A B C'!$E$9,0,MAX(0,'Skenario A B C'!$J$9-'Skenario A B C'!$K$9)) | AA53: =IF(24<'Skenario A B C'!$E$9,0,MAX(0,'Skenario A B C'!$J$9-'Skenario A B C'!$K$9))
A54: Mobile Engineer (Senior) | B54: ='Skenario A B C'!$F$10 | D54: =IF(1<'Skenario A B C'!$E$10,0,MAX(0,'Skenario A B C'!$H$10-'Skenario A B C'!$K$10)) | E54: =IF(2<'Skenario A B C'!$E$10,0,MAX(0,'Skenario A B C'!$H$10-'Skenario A B C'!$K$10)) | F54: =IF(3<'Skenario A B C'!$E$10,0,MAX(0,'Skenario A B C'!$H$10-'Skenario A B C'!$K$10)) | G54: =IF(4<'Skenario A B C'!$E$10,0,MAX(0,'Skenario A B C'!$I$10-'Skenario A B C'!$K$10)) | H54: =IF(5<'Skenario A B C'!$E$10,0,MAX(0,'Skenario A B C'!$I$10-'Skenario A B C'!$K$10)) | I54: =IF(6<'Skenario A B C'!$E$10,0,MAX(0,'Skenario A B C'!$I$10-'Skenario A B C'!$K$10)) | J54: =IF(7<'Skenario A B C'!$E$10,0,MAX(0,'Skenario A B C'!$I$10-'Skenario A B C'!$K$10)) | K54: =IF(8<'Skenario A B C'!$E$10,0,MAX(0,'Skenario A B C'!$I$10-'Skenario A B C'!$K$10)) | L54: =IF(9<'Skenario A B C'!$E$10,0,MAX(0,'Skenario A B C'!$I$10-'Skenario A B C'!$K$10)) | M54: =IF(10<'Skenario A B C'!$E$10,0,MAX(0,'Skenario A B C'!$I$10-'Skenario A B C'!$K$10)) | N54: =IF(11<'Skenario A B C'!$E$10,0,MAX(0,'Skenario A B C'!$I$10-'Skenario A B C'!$K$10)) | O54: =IF(12<'Skenario A B C'!$E$10,0,MAX(0,'Skenario A B C'!$I$10-'Skenario A B C'!$K$10)) | P54: =IF(13<'Skenario A B C'!$E$10,0,MAX(0,'Skenario A B C'!$J$10-'Skenario A B C'!$K$10)) | Q54: =IF(14<'Skenario A B C'!$E$10,0,MAX(0,'Skenario A B C'!$J$10-'Skenario A B C'!$K$10)) | R54: =IF(15<'Skenario A B C'!$E$10,0,MAX(0,'Skenario A B C'!$J$10-'Skenario A B C'!$K$10)) | S54: =IF(16<'Skenario A B C'!$E$10,0,MAX(0,'Skenario A B C'!$J$10-'Skenario A B C'!$K$10)) | T54: =IF(17<'Skenario A B C'!$E$10,0,MAX(0,'Skenario A B C'!$J$10-'Skenario A B C'!$K$10)) | U54: =IF(18<'Skenario A B C'!$E$10,0,MAX(0,'Skenario A B C'!$J$10-'Skenario A B C'!$K$10)) | V54: =IF(19<'Skenario A B C'!$E$10,0,MAX(0,'Skenario A B C'!$J$10-'Skenario A B C'!$K$10)) | W54: =IF(20<'Skenario A B C'!$E$10,0,MAX(0,'Skenario A B C'!$J$10-'Skenario A B C'!$K$10)) | X54: =IF(21<'Skenario A B C'!$E$10,0,MAX(0,'Skenario A B C'!$J$10-'Skenario A B C'!$K$10)) | Y54: =IF(22<'Skenario A B C'!$E$10,0,MAX(0,'Skenario A B C'!$J$10-'Skenario A B C'!$K$10)) | Z54: =IF(23<'Skenario A B C'!$E$10,0,MAX(0,'Skenario A B C'!$J$10-'Skenario A B C'!$K$10)) | AA54: =IF(24<'Skenario A B C'!$E$10,0,MAX(0,'Skenario A B C'!$J$10-'Skenario A B C'!$K$10))
A55: Mobile Engineer (Mid) | B55: ='Skenario A B C'!$F$11 | D55: =IF(1<'Skenario A B C'!$E$11,0,MAX(0,'Skenario A B C'!$H$11-'Skenario A B C'!$K$11)) | E55: =IF(2<'Skenario A B C'!$E$11,0,MAX(0,'Skenario A B C'!$H$11-'Skenario A B C'!$K$11)) | F55: =IF(3<'Skenario A B C'!$E$11,0,MAX(0,'Skenario A B C'!$H$11-'Skenario A B C'!$K$11)) | G55: =IF(4<'Skenario A B C'!$E$11,0,MAX(0,'Skenario A B C'!$I$11-'Skenario A B C'!$K$11)) | H55: =IF(5<'Skenario A B C'!$E$11,0,MAX(0,'Skenario A B C'!$I$11-'Skenario A B C'!$K$11)) | I55: =IF(6<'Skenario A B C'!$E$11,0,MAX(0,'Skenario A B C'!$I$11-'Skenario A B C'!$K$11)) | J55: =IF(7<'Skenario A B C'!$E$11,0,MAX(0,'Skenario A B C'!$I$11-'Skenario A B C'!$K$11)) | K55: =IF(8<'Skenario A B C'!$E$11,0,MAX(0,'Skenario A B C'!$I$11-'Skenario A B C'!$K$11)) | L55: =IF(9<'Skenario A B C'!$E$11,0,MAX(0,'Skenario A B C'!$I$11-'Skenario A B C'!$K$11)) | M55: =IF(10<'Skenario A B C'!$E$11,0,MAX(0,'Skenario A B C'!$I$11-'Skenario A B C'!$K$11)) | N55: =IF(11<'Skenario A B C'!$E$11,0,MAX(0,'Skenario A B C'!$I$11-'Skenario A B C'!$K$11)) | O55: =IF(12<'Skenario A B C'!$E$11,0,MAX(0,'Skenario A B C'!$I$11-'Skenario A B C'!$K$11)) | P55: =IF(13<'Skenario A B C'!$E$11,0,MAX(0,'Skenario A B C'!$J$11-'Skenario A B C'!$K$11)) | Q55: =IF(14<'Skenario A B C'!$E$11,0,MAX(0,'Skenario A B C'!$J$11-'Skenario A B C'!$K$11)) | R55: =IF(15<'Skenario A B C'!$E$11,0,MAX(0,'Skenario A B C'!$J$11-'Skenario A B C'!$K$11)) | S55: =IF(16<'Skenario A B C'!$E$11,0,MAX(0,'Skenario A B C'!$J$11-'Skenario A B C'!$K$11)) | T55: =IF(17<'Skenario A B C'!$E$11,0,MAX(0,'Skenario A B C'!$J$11-'Skenario A B C'!$K$11)) | U55: =IF(18<'Skenario A B C'!$E$11,0,MAX(0,'Skenario A B C'!$J$11-'Skenario A B C'!$K$11)) | V55: =IF(19<'Skenario A B C'!$E$11,0,MAX(0,'Skenario A B C'!$J$11-'Skenario A B C'!$K$11)) | W55: =IF(20<'Skenario A B C'!$E$11,0,MAX(0,'Skenario A B C'!$J$11-'Skenario A B C'!$K$11)) | X55: =IF(21<'Skenario A B C'!$E$11,0,MAX(0,'Skenario A B C'!$J$11-'Skenario A B C'!$K$11)) | Y55: =IF(22<'Skenario A B C'!$E$11,0,MAX(0,'Skenario A B C'!$J$11-'Skenario A B C'!$K$11)) | Z55: =IF(23<'Skenario A B C'!$E$11,0,MAX(0,'Skenario A B C'!$J$11-'Skenario A B C'!$K$11)) | AA55: =IF(24<'Skenario A B C'!$E$11,0,MAX(0,'Skenario A B C'!$J$11-'Skenario A B C'!$K$11))
A56: Mobile Engineer (Mid) - gelombang 2 | B56: ='Skenario A B C'!$F$12 | D56: =IF(1<'Skenario A B C'!$E$12,0,MAX(0,'Skenario A B C'!$H$12-'Skenario A B C'!$K$12)) | E56: =IF(2<'Skenario A B C'!$E$12,0,MAX(0,'Skenario A B C'!$H$12-'Skenario A B C'!$K$12)) | F56: =IF(3<'Skenario A B C'!$E$12,0,MAX(0,'Skenario A B C'!$H$12-'Skenario A B C'!$K$12)) | G56: =IF(4<'Skenario A B C'!$E$12,0,MAX(0,'Skenario A B C'!$I$12-'Skenario A B C'!$K$12)) | H56: =IF(5<'Skenario A B C'!$E$12,0,MAX(0,'Skenario A B C'!$I$12-'Skenario A B C'!$K$12)) | I56: =IF(6<'Skenario A B C'!$E$12,0,MAX(0,'Skenario A B C'!$I$12-'Skenario A B C'!$K$12)) | J56: =IF(7<'Skenario A B C'!$E$12,0,MAX(0,'Skenario A B C'!$I$12-'Skenario A B C'!$K$12)) | K56: =IF(8<'Skenario A B C'!$E$12,0,MAX(0,'Skenario A B C'!$I$12-'Skenario A B C'!$K$12)) | L56: =IF(9<'Skenario A B C'!$E$12,0,MAX(0,'Skenario A B C'!$I$12-'Skenario A B C'!$K$12)) | M56: =IF(10<'Skenario A B C'!$E$12,0,MAX(0,'Skenario A B C'!$I$12-'Skenario A B C'!$K$12)) | N56: =IF(11<'Skenario A B C'!$E$12,0,MAX(0,'Skenario A B C'!$I$12-'Skenario A B C'!$K$12)) | O56: =IF(12<'Skenario A B C'!$E$12,0,MAX(0,'Skenario A B C'!$I$12-'Skenario A B C'!$K$12)) | P56: =IF(13<'Skenario A B C'!$E$12,0,MAX(0,'Skenario A B C'!$J$12-'Skenario A B C'!$K$12)) | Q56: =IF(14<'Skenario A B C'!$E$12,0,MAX(0,'Skenario A B C'!$J$12-'Skenario A B C'!$K$12)) | R56: =IF(15<'Skenario A B C'!$E$12,0,MAX(0,'Skenario A B C'!$J$12-'Skenario A B C'!$K$12)) | S56: =IF(16<'Skenario A B C'!$E$12,0,MAX(0,'Skenario A B C'!$J$12-'Skenario A B C'!$K$12)) | T56: =IF(17<'Skenario A B C'!$E$12,0,MAX(0,'Skenario A B C'!$J$12-'Skenario A B C'!$K$12)) | U56: =IF(18<'Skenario A B C'!$E$12,0,MAX(0,'Skenario A B C'!$J$12-'Skenario A B C'!$K$12)) | V56: =IF(19<'Skenario A B C'!$E$12,0,MAX(0,'Skenario A B C'!$J$12-'Skenario A B C'!$K$12)) | W56: =IF(20<'Skenario A B C'!$E$12,0,MAX(0,'Skenario A B C'!$J$12-'Skenario A B C'!$K$12)) | X56: =IF(21<'Skenario A B C'!$E$12,0,MAX(0,'Skenario A B C'!$J$12-'Skenario A B C'!$K$12)) | Y56: =IF(22<'Skenario A B C'!$E$12,0,MAX(0,'Skenario A B C'!$J$12-'Skenario A B C'!$K$12)) | Z56: =IF(23<'Skenario A B C'!$E$12,0,MAX(0,'Skenario A B C'!$J$12-'Skenario A B C'!$K$12)) | AA56: =IF(24<'Skenario A B C'!$E$12,0,MAX(0,'Skenario A B C'!$J$12-'Skenario A B C'!$K$12))
A57: Backend Engineer (Senior) | B57: ='Skenario A B C'!$F$13 | D57: =IF(1<'Skenario A B C'!$E$13,0,MAX(0,'Skenario A B C'!$H$13-'Skenario A B C'!$K$13)) | E57: =IF(2<'Skenario A B C'!$E$13,0,MAX(0,'Skenario A B C'!$H$13-'Skenario A B C'!$K$13)) | F57: =IF(3<'Skenario A B C'!$E$13,0,MAX(0,'Skenario A B C'!$H$13-'Skenario A B C'!$K$13)) | G57: =IF(4<'Skenario A B C'!$E$13,0,MAX(0,'Skenario A B C'!$I$13-'Skenario A B C'!$K$13)) | H57: =IF(5<'Skenario A B C'!$E$13,0,MAX(0,'Skenario A B C'!$I$13-'Skenario A B C'!$K$13)) | I57: =IF(6<'Skenario A B C'!$E$13,0,MAX(0,'Skenario A B C'!$I$13-'Skenario A B C'!$K$13)) | J57: =IF(7<'Skenario A B C'!$E$13,0,MAX(0,'Skenario A B C'!$I$13-'Skenario A B C'!$K$13)) | K57: =IF(8<'Skenario A B C'!$E$13,0,MAX(0,'Skenario A B C'!$I$13-'Skenario A B C'!$K$13)) | L57: =IF(9<'Skenario A B C'!$E$13,0,MAX(0,'Skenario A B C'!$I$13-'Skenario A B C'!$K$13)) | M57: =IF(10<'Skenario A B C'!$E$13,0,MAX(0,'Skenario A B C'!$I$13-'Skenario A B C'!$K$13)) | N57: =IF(11<'Skenario A B C'!$E$13,0,MAX(0,'Skenario A B C'!$I$13-'Skenario A B C'!$K$13)) | O57: =IF(12<'Skenario A B C'!$E$13,0,MAX(0,'Skenario A B C'!$I$13-'Skenario A B C'!$K$13)) | P57: =IF(13<'Skenario A B C'!$E$13,0,MAX(0,'Skenario A B C'!$J$13-'Skenario A B C'!$K$13)) | Q57: =IF(14<'Skenario A B C'!$E$13,0,MAX(0,'Skenario A B C'!$J$13-'Skenario A B C'!$K$13)) | R57: =IF(15<'Skenario A B C'!$E$13,0,MAX(0,'Skenario A B C'!$J$13-'Skenario A B C'!$K$13)) | S57: =IF(16<'Skenario A B C'!$E$13,0,MAX(0,'Skenario A B C'!$J$13-'Skenario A B C'!$K$13)) | T57: =IF(17<'Skenario A B C'!$E$13,0,MAX(0,'Skenario A B C'!$J$13-'Skenario A B C'!$K$13)) | U57: =IF(18<'Skenario A B C'!$E$13,0,MAX(0,'Skenario A B C'!$J$13-'Skenario A B C'!$K$13)) | V57: =IF(19<'Skenario A B C'!$E$13,0,MAX(0,'Skenario A B C'!$J$13-'Skenario A B C'!$K$13)) | W57: =IF(20<'Skenario A B C'!$E$13,0,MAX(0,'Skenario A B C'!$J$13-'Skenario A B C'!$K$13)) | X57: =IF(21<'Skenario A B C'!$E$13,0,MAX(0,'Skenario A B C'!$J$13-'Skenario A B C'!$K$13)) | Y57: =IF(22<'Skenario A B C'!$E$13,0,MAX(0,'Skenario A B C'!$J$13-'Skenario A B C'!$K$13)) | Z57: =IF(23<'Skenario A B C'!$E$13,0,MAX(0,'Skenario A B C'!$J$13-'Skenario A B C'!$K$13)) | AA57: =IF(24<'Skenario A B C'!$E$13,0,MAX(0,'Skenario A B C'!$J$13-'Skenario A B C'!$K$13))
A58: Backend Engineer (Senior) - gelombang 2 | B58: ='Skenario A B C'!$F$14 | D58: =IF(1<'Skenario A B C'!$E$14,0,MAX(0,'Skenario A B C'!$H$14-'Skenario A B C'!$K$14)) | E58: =IF(2<'Skenario A B C'!$E$14,0,MAX(0,'Skenario A B C'!$H$14-'Skenario A B C'!$K$14)) | F58: =IF(3<'Skenario A B C'!$E$14,0,MAX(0,'Skenario A B C'!$H$14-'Skenario A B C'!$K$14)) | G58: =IF(4<'Skenario A B C'!$E$14,0,MAX(0,'Skenario A B C'!$I$14-'Skenario A B C'!$K$14)) | H58: =IF(5<'Skenario A B C'!$E$14,0,MAX(0,'Skenario A B C'!$I$14-'Skenario A B C'!$K$14)) | I58: =IF(6<'Skenario A B C'!$E$14,0,MAX(0,'Skenario A B C'!$I$14-'Skenario A B C'!$K$14)) | J58: =IF(7<'Skenario A B C'!$E$14,0,MAX(0,'Skenario A B C'!$I$14-'Skenario A B C'!$K$14)) | K58: =IF(8<'Skenario A B C'!$E$14,0,MAX(0,'Skenario A B C'!$I$14-'Skenario A B C'!$K$14)) | L58: =IF(9<'Skenario A B C'!$E$14,0,MAX(0,'Skenario A B C'!$I$14-'Skenario A B C'!$K$14)) | M58: =IF(10<'Skenario A B C'!$E$14,0,MAX(0,'Skenario A B C'!$I$14-'Skenario A B C'!$K$14)) | N58: =IF(11<'Skenario A B C'!$E$14,0,MAX(0,'Skenario A B C'!$I$14-'Skenario A B C'!$K$14)) | O58: =IF(12<'Skenario A B C'!$E$14,0,MAX(0,'Skenario A B C'!$I$14-'Skenario A B C'!$K$14)) | P58: =IF(13<'Skenario A B C'!$E$14,0,MAX(0,'Skenario A B C'!$J$14-'Skenario A B C'!$K$14)) | Q58: =IF(14<'Skenario A B C'!$E$14,0,MAX(0,'Skenario A B C'!$J$14-'Skenario A B C'!$K$14)) | R58: =IF(15<'Skenario A B C'!$E$14,0,MAX(0,'Skenario A B C'!$J$14-'Skenario A B C'!$K$14)) | S58: =IF(16<'Skenario A B C'!$E$14,0,MAX(0,'Skenario A B C'!$J$14-'Skenario A B C'!$K$14)) | T58: =IF(17<'Skenario A B C'!$E$14,0,MAX(0,'Skenario A B C'!$J$14-'Skenario A B C'!$K$14)) | U58: =IF(18<'Skenario A B C'!$E$14,0,MAX(0,'Skenario A B C'!$J$14-'Skenario A B C'!$K$14)) | V58: =IF(19<'Skenario A B C'!$E$14,0,MAX(0,'Skenario A B C'!$J$14-'Skenario A B C'!$K$14)) | W58: =IF(20<'Skenario A B C'!$E$14,0,MAX(0,'Skenario A B C'!$J$14-'Skenario A B C'!$K$14)) | X58: =IF(21<'Skenario A B C'!$E$14,0,MAX(0,'Skenario A B C'!$J$14-'Skenario A B C'!$K$14)) | Y58: =IF(22<'Skenario A B C'!$E$14,0,MAX(0,'Skenario A B C'!$J$14-'Skenario A B C'!$K$14)) | Z58: =IF(23<'Skenario A B C'!$E$14,0,MAX(0,'Skenario A B C'!$J$14-'Skenario A B C'!$K$14)) | AA58: =IF(24<'Skenario A B C'!$E$14,0,MAX(0,'Skenario A B C'!$J$14-'Skenario A B C'!$K$14))
A59: Backend Engineer (Mid) | B59: ='Skenario A B C'!$F$15 | D59: =IF(1<'Skenario A B C'!$E$15,0,MAX(0,'Skenario A B C'!$H$15-'Skenario A B C'!$K$15)) | E59: =IF(2<'Skenario A B C'!$E$15,0,MAX(0,'Skenario A B C'!$H$15-'Skenario A B C'!$K$15)) | F59: =IF(3<'Skenario A B C'!$E$15,0,MAX(0,'Skenario A B C'!$H$15-'Skenario A B C'!$K$15)) | G59: =IF(4<'Skenario A B C'!$E$15,0,MAX(0,'Skenario A B C'!$I$15-'Skenario A B C'!$K$15)) | H59: =IF(5<'Skenario A B C'!$E$15,0,MAX(0,'Skenario A B C'!$I$15-'Skenario A B C'!$K$15)) | I59: =IF(6<'Skenario A B C'!$E$15,0,MAX(0,'Skenario A B C'!$I$15-'Skenario A B C'!$K$15)) | J59: =IF(7<'Skenario A B C'!$E$15,0,MAX(0,'Skenario A B C'!$I$15-'Skenario A B C'!$K$15)) | K59: =IF(8<'Skenario A B C'!$E$15,0,MAX(0,'Skenario A B C'!$I$15-'Skenario A B C'!$K$15)) | L59: =IF(9<'Skenario A B C'!$E$15,0,MAX(0,'Skenario A B C'!$I$15-'Skenario A B C'!$K$15)) | M59: =IF(10<'Skenario A B C'!$E$15,0,MAX(0,'Skenario A B C'!$I$15-'Skenario A B C'!$K$15)) | N59: =IF(11<'Skenario A B C'!$E$15,0,MAX(0,'Skenario A B C'!$I$15-'Skenario A B C'!$K$15)) | O59: =IF(12<'Skenario A B C'!$E$15,0,MAX(0,'Skenario A B C'!$I$15-'Skenario A B C'!$K$15)) | P59: =IF(13<'Skenario A B C'!$E$15,0,MAX(0,'Skenario A B C'!$J$15-'Skenario A B C'!$K$15)) | Q59: =IF(14<'Skenario A B C'!$E$15,0,MAX(0,'Skenario A B C'!$J$15-'Skenario A B C'!$K$15)) | R59: =IF(15<'Skenario A B C'!$E$15,0,MAX(0,'Skenario A B C'!$J$15-'Skenario A B C'!$K$15)) | S59: =IF(16<'Skenario A B C'!$E$15,0,MAX(0,'Skenario A B C'!$J$15-'Skenario A B C'!$K$15)) | T59: =IF(17<'Skenario A B C'!$E$15,0,MAX(0,'Skenario A B C'!$J$15-'Skenario A B C'!$K$15)) | U59: =IF(18<'Skenario A B C'!$E$15,0,MAX(0,'Skenario A B C'!$J$15-'Skenario A B C'!$K$15)) | V59: =IF(19<'Skenario A B C'!$E$15,0,MAX(0,'Skenario A B C'!$J$15-'Skenario A B C'!$K$15)) | W59: =IF(20<'Skenario A B C'!$E$15,0,MAX(0,'Skenario A B C'!$J$15-'Skenario A B C'!$K$15)) | X59: =IF(21<'Skenario A B C'!$E$15,0,MAX(0,'Skenario A B C'!$J$15-'Skenario A B C'!$K$15)) | Y59: =IF(22<'Skenario A B C'!$E$15,0,MAX(0,'Skenario A B C'!$J$15-'Skenario A B C'!$K$15)) | Z59: =IF(23<'Skenario A B C'!$E$15,0,MAX(0,'Skenario A B C'!$J$15-'Skenario A B C'!$K$15)) | AA59: =IF(24<'Skenario A B C'!$E$15,0,MAX(0,'Skenario A B C'!$J$15-'Skenario A B C'!$K$15))
A60: Backend Engineer (Mid) - gelombang 2 | B60: ='Skenario A B C'!$F$16 | D60: =IF(1<'Skenario A B C'!$E$16,0,MAX(0,'Skenario A B C'!$H$16-'Skenario A B C'!$K$16)) | E60: =IF(2<'Skenario A B C'!$E$16,0,MAX(0,'Skenario A B C'!$H$16-'Skenario A B C'!$K$16)) | F60: =IF(3<'Skenario A B C'!$E$16,0,MAX(0,'Skenario A B C'!$H$16-'Skenario A B C'!$K$16)) | G60: =IF(4<'Skenario A B C'!$E$16,0,MAX(0,'Skenario A B C'!$I$16-'Skenario A B C'!$K$16)) | H60: =IF(5<'Skenario A B C'!$E$16,0,MAX(0,'Skenario A B C'!$I$16-'Skenario A B C'!$K$16)) | I60: =IF(6<'Skenario A B C'!$E$16,0,MAX(0,'Skenario A B C'!$I$16-'Skenario A B C'!$K$16)) | J60: =IF(7<'Skenario A B C'!$E$16,0,MAX(0,'Skenario A B C'!$I$16-'Skenario A B C'!$K$16)) | K60: =IF(8<'Skenario A B C'!$E$16,0,MAX(0,'Skenario A B C'!$I$16-'Skenario A B C'!$K$16)) | L60: =IF(9<'Skenario A B C'!$E$16,0,MAX(0,'Skenario A B C'!$I$16-'Skenario A B C'!$K$16)) | M60: =IF(10<'Skenario A B C'!$E$16,0,MAX(0,'Skenario A B C'!$I$16-'Skenario A B C'!$K$16)) | N60: =IF(11<'Skenario A B C'!$E$16,0,MAX(0,'Skenario A B C'!$I$16-'Skenario A B C'!$K$16)) | O60: =IF(12<'Skenario A B C'!$E$16,0,MAX(0,'Skenario A B C'!$I$16-'Skenario A B C'!$K$16)) | P60: =IF(13<'Skenario A B C'!$E$16,0,MAX(0,'Skenario A B C'!$J$16-'Skenario A B C'!$K$16)) | Q60: =IF(14<'Skenario A B C'!$E$16,0,MAX(0,'Skenario A B C'!$J$16-'Skenario A B C'!$K$16)) | R60: =IF(15<'Skenario A B C'!$E$16,0,MAX(0,'Skenario A B C'!$J$16-'Skenario A B C'!$K$16)) | S60: =IF(16<'Skenario A B C'!$E$16,0,MAX(0,'Skenario A B C'!$J$16-'Skenario A B C'!$K$16)) | T60: =IF(17<'Skenario A B C'!$E$16,0,MAX(0,'Skenario A B C'!$J$16-'Skenario A B C'!$K$16)) | U60: =IF(18<'Skenario A B C'!$E$16,0,MAX(0,'Skenario A B C'!$J$16-'Skenario A B C'!$K$16)) | V60: =IF(19<'Skenario A B C'!$E$16,0,MAX(0,'Skenario A B C'!$J$16-'Skenario A B C'!$K$16)) | W60: =IF(20<'Skenario A B C'!$E$16,0,MAX(0,'Skenario A B C'!$J$16-'Skenario A B C'!$K$16)) | X60: =IF(21<'Skenario A B C'!$E$16,0,MAX(0,'Skenario A B C'!$J$16-'Skenario A B C'!$K$16)) | Y60: =IF(22<'Skenario A B C'!$E$16,0,MAX(0,'Skenario A B C'!$J$16-'Skenario A B C'!$K$16)) | Z60: =IF(23<'Skenario A B C'!$E$16,0,MAX(0,'Skenario A B C'!$J$16-'Skenario A B C'!$K$16)) | AA60: =IF(24<'Skenario A B C'!$E$16,0,MAX(0,'Skenario A B C'!$J$16-'Skenario A B C'!$K$16))
A61: QA Engineer | B61: ='Skenario A B C'!$F$17 | D61: =IF(1<'Skenario A B C'!$E$17,0,MAX(0,'Skenario A B C'!$H$17-'Skenario A B C'!$K$17)) | E61: =IF(2<'Skenario A B C'!$E$17,0,MAX(0,'Skenario A B C'!$H$17-'Skenario A B C'!$K$17)) | F61: =IF(3<'Skenario A B C'!$E$17,0,MAX(0,'Skenario A B C'!$H$17-'Skenario A B C'!$K$17)) | G61: =IF(4<'Skenario A B C'!$E$17,0,MAX(0,'Skenario A B C'!$I$17-'Skenario A B C'!$K$17)) | H61: =IF(5<'Skenario A B C'!$E$17,0,MAX(0,'Skenario A B C'!$I$17-'Skenario A B C'!$K$17)) | I61: =IF(6<'Skenario A B C'!$E$17,0,MAX(0,'Skenario A B C'!$I$17-'Skenario A B C'!$K$17)) | J61: =IF(7<'Skenario A B C'!$E$17,0,MAX(0,'Skenario A B C'!$I$17-'Skenario A B C'!$K$17)) | K61: =IF(8<'Skenario A B C'!$E$17,0,MAX(0,'Skenario A B C'!$I$17-'Skenario A B C'!$K$17)) | L61: =IF(9<'Skenario A B C'!$E$17,0,MAX(0,'Skenario A B C'!$I$17-'Skenario A B C'!$K$17)) | M61: =IF(10<'Skenario A B C'!$E$17,0,MAX(0,'Skenario A B C'!$I$17-'Skenario A B C'!$K$17)) | N61: =IF(11<'Skenario A B C'!$E$17,0,MAX(0,'Skenario A B C'!$I$17-'Skenario A B C'!$K$17)) | O61: =IF(12<'Skenario A B C'!$E$17,0,MAX(0,'Skenario A B C'!$I$17-'Skenario A B C'!$K$17)) | P61: =IF(13<'Skenario A B C'!$E$17,0,MAX(0,'Skenario A B C'!$J$17-'Skenario A B C'!$K$17)) | Q61: =IF(14<'Skenario A B C'!$E$17,0,MAX(0,'Skenario A B C'!$J$17-'Skenario A B C'!$K$17)) | R61: =IF(15<'Skenario A B C'!$E$17,0,MAX(0,'Skenario A B C'!$J$17-'Skenario A B C'!$K$17)) | S61: =IF(16<'Skenario A B C'!$E$17,0,MAX(0,'Skenario A B C'!$J$17-'Skenario A B C'!$K$17)) | T61: =IF(17<'Skenario A B C'!$E$17,0,MAX(0,'Skenario A B C'!$J$17-'Skenario A B C'!$K$17)) | U61: =IF(18<'Skenario A B C'!$E$17,0,MAX(0,'Skenario A B C'!$J$17-'Skenario A B C'!$K$17)) | V61: =IF(19<'Skenario A B C'!$E$17,0,MAX(0,'Skenario A B C'!$J$17-'Skenario A B C'!$K$17)) | W61: =IF(20<'Skenario A B C'!$E$17,0,MAX(0,'Skenario A B C'!$J$17-'Skenario A B C'!$K$17)) | X61: =IF(21<'Skenario A B C'!$E$17,0,MAX(0,'Skenario A B C'!$J$17-'Skenario A B C'!$K$17)) | Y61: =IF(22<'Skenario A B C'!$E$17,0,MAX(0,'Skenario A B C'!$J$17-'Skenario A B C'!$K$17)) | Z61: =IF(23<'Skenario A B C'!$E$17,0,MAX(0,'Skenario A B C'!$J$17-'Skenario A B C'!$K$17)) | AA61: =IF(24<'Skenario A B C'!$E$17,0,MAX(0,'Skenario A B C'!$J$17-'Skenario A B C'!$K$17))
A62: QA Engineer - gelombang 2 | B62: ='Skenario A B C'!$F$18 | D62: =IF(1<'Skenario A B C'!$E$18,0,MAX(0,'Skenario A B C'!$H$18-'Skenario A B C'!$K$18)) | E62: =IF(2<'Skenario A B C'!$E$18,0,MAX(0,'Skenario A B C'!$H$18-'Skenario A B C'!$K$18)) | F62: =IF(3<'Skenario A B C'!$E$18,0,MAX(0,'Skenario A B C'!$H$18-'Skenario A B C'!$K$18)) | G62: =IF(4<'Skenario A B C'!$E$18,0,MAX(0,'Skenario A B C'!$I$18-'Skenario A B C'!$K$18)) | H62: =IF(5<'Skenario A B C'!$E$18,0,MAX(0,'Skenario A B C'!$I$18-'Skenario A B C'!$K$18)) | I62: =IF(6<'Skenario A B C'!$E$18,0,MAX(0,'Skenario A B C'!$I$18-'Skenario A B C'!$K$18)) | J62: =IF(7<'Skenario A B C'!$E$18,0,MAX(0,'Skenario A B C'!$I$18-'Skenario A B C'!$K$18)) | K62: =IF(8<'Skenario A B C'!$E$18,0,MAX(0,'Skenario A B C'!$I$18-'Skenario A B C'!$K$18)) | L62: =IF(9<'Skenario A B C'!$E$18,0,MAX(0,'Skenario A B C'!$I$18-'Skenario A B C'!$K$18)) | M62: =IF(10<'Skenario A B C'!$E$18,0,MAX(0,'Skenario A B C'!$I$18-'Skenario A B C'!$K$18)) | N62: =IF(11<'Skenario A B C'!$E$18,0,MAX(0,'Skenario A B C'!$I$18-'Skenario A B C'!$K$18)) | O62: =IF(12<'Skenario A B C'!$E$18,0,MAX(0,'Skenario A B C'!$I$18-'Skenario A B C'!$K$18)) | P62: =IF(13<'Skenario A B C'!$E$18,0,MAX(0,'Skenario A B C'!$J$18-'Skenario A B C'!$K$18)) | Q62: =IF(14<'Skenario A B C'!$E$18,0,MAX(0,'Skenario A B C'!$J$18-'Skenario A B C'!$K$18)) | R62: =IF(15<'Skenario A B C'!$E$18,0,MAX(0,'Skenario A B C'!$J$18-'Skenario A B C'!$K$18)) | S62: =IF(16<'Skenario A B C'!$E$18,0,MAX(0,'Skenario A B C'!$J$18-'Skenario A B C'!$K$18)) | T62: =IF(17<'Skenario A B C'!$E$18,0,MAX(0,'Skenario A B C'!$J$18-'Skenario A B C'!$K$18)) | U62: =IF(18<'Skenario A B C'!$E$18,0,MAX(0,'Skenario A B C'!$J$18-'Skenario A B C'!$K$18)) | V62: =IF(19<'Skenario A B C'!$E$18,0,MAX(0,'Skenario A B C'!$J$18-'Skenario A B C'!$K$18)) | W62: =IF(20<'Skenario A B C'!$E$18,0,MAX(0,'Skenario A B C'!$J$18-'Skenario A B C'!$K$18)) | X62: =IF(21<'Skenario A B C'!$E$18,0,MAX(0,'Skenario A B C'!$J$18-'Skenario A B C'!$K$18)) | Y62: =IF(22<'Skenario A B C'!$E$18,0,MAX(0,'Skenario A B C'!$J$18-'Skenario A B C'!$K$18)) | Z62: =IF(23<'Skenario A B C'!$E$18,0,MAX(0,'Skenario A B C'!$J$18-'Skenario A B C'!$K$18)) | AA62: =IF(24<'Skenario A B C'!$E$18,0,MAX(0,'Skenario A B C'!$J$18-'Skenario A B C'!$K$18))
A63: Junior Software Engineer | B63: ='Skenario A B C'!$F$19 | D63: =IF(1<'Skenario A B C'!$E$19,0,MAX(0,'Skenario A B C'!$H$19-'Skenario A B C'!$K$19)) | E63: =IF(2<'Skenario A B C'!$E$19,0,MAX(0,'Skenario A B C'!$H$19-'Skenario A B C'!$K$19)) | F63: =IF(3<'Skenario A B C'!$E$19,0,MAX(0,'Skenario A B C'!$H$19-'Skenario A B C'!$K$19)) | G63: =IF(4<'Skenario A B C'!$E$19,0,MAX(0,'Skenario A B C'!$I$19-'Skenario A B C'!$K$19)) | H63: =IF(5<'Skenario A B C'!$E$19,0,MAX(0,'Skenario A B C'!$I$19-'Skenario A B C'!$K$19)) | I63: =IF(6<'Skenario A B C'!$E$19,0,MAX(0,'Skenario A B C'!$I$19-'Skenario A B C'!$K$19)) | J63: =IF(7<'Skenario A B C'!$E$19,0,MAX(0,'Skenario A B C'!$I$19-'Skenario A B C'!$K$19)) | K63: =IF(8<'Skenario A B C'!$E$19,0,MAX(0,'Skenario A B C'!$I$19-'Skenario A B C'!$K$19)) | L63: =IF(9<'Skenario A B C'!$E$19,0,MAX(0,'Skenario A B C'!$I$19-'Skenario A B C'!$K$19)) | M63: =IF(10<'Skenario A B C'!$E$19,0,MAX(0,'Skenario A B C'!$I$19-'Skenario A B C'!$K$19)) | N63: =IF(11<'Skenario A B C'!$E$19,0,MAX(0,'Skenario A B C'!$I$19-'Skenario A B C'!$K$19)) | O63: =IF(12<'Skenario A B C'!$E$19,0,MAX(0,'Skenario A B C'!$I$19-'Skenario A B C'!$K$19)) | P63: =IF(13<'Skenario A B C'!$E$19,0,MAX(0,'Skenario A B C'!$J$19-'Skenario A B C'!$K$19)) | Q63: =IF(14<'Skenario A B C'!$E$19,0,MAX(0,'Skenario A B C'!$J$19-'Skenario A B C'!$K$19)) | R63: =IF(15<'Skenario A B C'!$E$19,0,MAX(0,'Skenario A B C'!$J$19-'Skenario A B C'!$K$19)) | S63: =IF(16<'Skenario A B C'!$E$19,0,MAX(0,'Skenario A B C'!$J$19-'Skenario A B C'!$K$19)) | T63: =IF(17<'Skenario A B C'!$E$19,0,MAX(0,'Skenario A B C'!$J$19-'Skenario A B C'!$K$19)) | U63: =IF(18<'Skenario A B C'!$E$19,0,MAX(0,'Skenario A B C'!$J$19-'Skenario A B C'!$K$19)) | V63: =IF(19<'Skenario A B C'!$E$19,0,MAX(0,'Skenario A B C'!$J$19-'Skenario A B C'!$K$19)) | W63: =IF(20<'Skenario A B C'!$E$19,0,MAX(0,'Skenario A B C'!$J$19-'Skenario A B C'!$K$19)) | X63: =IF(21<'Skenario A B C'!$E$19,0,MAX(0,'Skenario A B C'!$J$19-'Skenario A B C'!$K$19)) | Y63: =IF(22<'Skenario A B C'!$E$19,0,MAX(0,'Skenario A B C'!$J$19-'Skenario A B C'!$K$19)) | Z63: =IF(23<'Skenario A B C'!$E$19,0,MAX(0,'Skenario A B C'!$J$19-'Skenario A B C'!$K$19)) | AA63: =IF(24<'Skenario A B C'!$E$19,0,MAX(0,'Skenario A B C'!$J$19-'Skenario A B C'!$K$19))
A64: Junior Software Engineer - Padang | B64: ='Skenario A B C'!$F$20 | D64: =IF(1<'Skenario A B C'!$E$20,0,MAX(0,'Skenario A B C'!$H$20-'Skenario A B C'!$K$20)) | E64: =IF(2<'Skenario A B C'!$E$20,0,MAX(0,'Skenario A B C'!$H$20-'Skenario A B C'!$K$20)) | F64: =IF(3<'Skenario A B C'!$E$20,0,MAX(0,'Skenario A B C'!$H$20-'Skenario A B C'!$K$20)) | G64: =IF(4<'Skenario A B C'!$E$20,0,MAX(0,'Skenario A B C'!$I$20-'Skenario A B C'!$K$20)) | H64: =IF(5<'Skenario A B C'!$E$20,0,MAX(0,'Skenario A B C'!$I$20-'Skenario A B C'!$K$20)) | I64: =IF(6<'Skenario A B C'!$E$20,0,MAX(0,'Skenario A B C'!$I$20-'Skenario A B C'!$K$20)) | J64: =IF(7<'Skenario A B C'!$E$20,0,MAX(0,'Skenario A B C'!$I$20-'Skenario A B C'!$K$20)) | K64: =IF(8<'Skenario A B C'!$E$20,0,MAX(0,'Skenario A B C'!$I$20-'Skenario A B C'!$K$20)) | L64: =IF(9<'Skenario A B C'!$E$20,0,MAX(0,'Skenario A B C'!$I$20-'Skenario A B C'!$K$20)) | M64: =IF(10<'Skenario A B C'!$E$20,0,MAX(0,'Skenario A B C'!$I$20-'Skenario A B C'!$K$20)) | N64: =IF(11<'Skenario A B C'!$E$20,0,MAX(0,'Skenario A B C'!$I$20-'Skenario A B C'!$K$20)) | O64: =IF(12<'Skenario A B C'!$E$20,0,MAX(0,'Skenario A B C'!$I$20-'Skenario A B C'!$K$20)) | P64: =IF(13<'Skenario A B C'!$E$20,0,MAX(0,'Skenario A B C'!$J$20-'Skenario A B C'!$K$20)) | Q64: =IF(14<'Skenario A B C'!$E$20,0,MAX(0,'Skenario A B C'!$J$20-'Skenario A B C'!$K$20)) | R64: =IF(15<'Skenario A B C'!$E$20,0,MAX(0,'Skenario A B C'!$J$20-'Skenario A B C'!$K$20)) | S64: =IF(16<'Skenario A B C'!$E$20,0,MAX(0,'Skenario A B C'!$J$20-'Skenario A B C'!$K$20)) | T64: =IF(17<'Skenario A B C'!$E$20,0,MAX(0,'Skenario A B C'!$J$20-'Skenario A B C'!$K$20)) | U64: =IF(18<'Skenario A B C'!$E$20,0,MAX(0,'Skenario A B C'!$J$20-'Skenario A B C'!$K$20)) | V64: =IF(19<'Skenario A B C'!$E$20,0,MAX(0,'Skenario A B C'!$J$20-'Skenario A B C'!$K$20)) | W64: =IF(20<'Skenario A B C'!$E$20,0,MAX(0,'Skenario A B C'!$J$20-'Skenario A B C'!$K$20)) | X64: =IF(21<'Skenario A B C'!$E$20,0,MAX(0,'Skenario A B C'!$J$20-'Skenario A B C'!$K$20)) | Y64: =IF(22<'Skenario A B C'!$E$20,0,MAX(0,'Skenario A B C'!$J$20-'Skenario A B C'!$K$20)) | Z64: =IF(23<'Skenario A B C'!$E$20,0,MAX(0,'Skenario A B C'!$J$20-'Skenario A B C'!$K$20)) | AA64: =IF(24<'Skenario A B C'!$E$20,0,MAX(0,'Skenario A B C'!$J$20-'Skenario A B C'!$K$20))
A65: Product Designer (UI/UX) | B65: ='Skenario A B C'!$F$21 | D65: =IF(1<'Skenario A B C'!$E$21,0,MAX(0,'Skenario A B C'!$H$21-'Skenario A B C'!$K$21)) | E65: =IF(2<'Skenario A B C'!$E$21,0,MAX(0,'Skenario A B C'!$H$21-'Skenario A B C'!$K$21)) | F65: =IF(3<'Skenario A B C'!$E$21,0,MAX(0,'Skenario A B C'!$H$21-'Skenario A B C'!$K$21)) | G65: =IF(4<'Skenario A B C'!$E$21,0,MAX(0,'Skenario A B C'!$I$21-'Skenario A B C'!$K$21)) | H65: =IF(5<'Skenario A B C'!$E$21,0,MAX(0,'Skenario A B C'!$I$21-'Skenario A B C'!$K$21)) | I65: =IF(6<'Skenario A B C'!$E$21,0,MAX(0,'Skenario A B C'!$I$21-'Skenario A B C'!$K$21)) | J65: =IF(7<'Skenario A B C'!$E$21,0,MAX(0,'Skenario A B C'!$I$21-'Skenario A B C'!$K$21)) | K65: =IF(8<'Skenario A B C'!$E$21,0,MAX(0,'Skenario A B C'!$I$21-'Skenario A B C'!$K$21)) | L65: =IF(9<'Skenario A B C'!$E$21,0,MAX(0,'Skenario A B C'!$I$21-'Skenario A B C'!$K$21)) | M65: =IF(10<'Skenario A B C'!$E$21,0,MAX(0,'Skenario A B C'!$I$21-'Skenario A B C'!$K$21)) | N65: =IF(11<'Skenario A B C'!$E$21,0,MAX(0,'Skenario A B C'!$I$21-'Skenario A B C'!$K$21)) | O65: =IF(12<'Skenario A B C'!$E$21,0,MAX(0,'Skenario A B C'!$I$21-'Skenario A B C'!$K$21)) | P65: =IF(13<'Skenario A B C'!$E$21,0,MAX(0,'Skenario A B C'!$J$21-'Skenario A B C'!$K$21)) | Q65: =IF(14<'Skenario A B C'!$E$21,0,MAX(0,'Skenario A B C'!$J$21-'Skenario A B C'!$K$21)) | R65: =IF(15<'Skenario A B C'!$E$21,0,MAX(0,'Skenario A B C'!$J$21-'Skenario A B C'!$K$21)) | S65: =IF(16<'Skenario A B C'!$E$21,0,MAX(0,'Skenario A B C'!$J$21-'Skenario A B C'!$K$21)) | T65: =IF(17<'Skenario A B C'!$E$21,0,MAX(0,'Skenario A B C'!$J$21-'Skenario A B C'!$K$21)) | U65: =IF(18<'Skenario A B C'!$E$21,0,MAX(0,'Skenario A B C'!$J$21-'Skenario A B C'!$K$21)) | V65: =IF(19<'Skenario A B C'!$E$21,0,MAX(0,'Skenario A B C'!$J$21-'Skenario A B C'!$K$21)) | W65: =IF(20<'Skenario A B C'!$E$21,0,MAX(0,'Skenario A B C'!$J$21-'Skenario A B C'!$K$21)) | X65: =IF(21<'Skenario A B C'!$E$21,0,MAX(0,'Skenario A B C'!$J$21-'Skenario A B C'!$K$21)) | Y65: =IF(22<'Skenario A B C'!$E$21,0,MAX(0,'Skenario A B C'!$J$21-'Skenario A B C'!$K$21)) | Z65: =IF(23<'Skenario A B C'!$E$21,0,MAX(0,'Skenario A B C'!$J$21-'Skenario A B C'!$K$21)) | AA65: =IF(24<'Skenario A B C'!$E$21,0,MAX(0,'Skenario A B C'!$J$21-'Skenario A B C'!$K$21))
A66: Product Designer (UI/UX) - gelombang 2 | B66: ='Skenario A B C'!$F$22 | D66: =IF(1<'Skenario A B C'!$E$22,0,MAX(0,'Skenario A B C'!$H$22-'Skenario A B C'!$K$22)) | E66: =IF(2<'Skenario A B C'!$E$22,0,MAX(0,'Skenario A B C'!$H$22-'Skenario A B C'!$K$22)) | F66: =IF(3<'Skenario A B C'!$E$22,0,MAX(0,'Skenario A B C'!$H$22-'Skenario A B C'!$K$22)) | G66: =IF(4<'Skenario A B C'!$E$22,0,MAX(0,'Skenario A B C'!$I$22-'Skenario A B C'!$K$22)) | H66: =IF(5<'Skenario A B C'!$E$22,0,MAX(0,'Skenario A B C'!$I$22-'Skenario A B C'!$K$22)) | I66: =IF(6<'Skenario A B C'!$E$22,0,MAX(0,'Skenario A B C'!$I$22-'Skenario A B C'!$K$22)) | J66: =IF(7<'Skenario A B C'!$E$22,0,MAX(0,'Skenario A B C'!$I$22-'Skenario A B C'!$K$22)) | K66: =IF(8<'Skenario A B C'!$E$22,0,MAX(0,'Skenario A B C'!$I$22-'Skenario A B C'!$K$22)) | L66: =IF(9<'Skenario A B C'!$E$22,0,MAX(0,'Skenario A B C'!$I$22-'Skenario A B C'!$K$22)) | M66: =IF(10<'Skenario A B C'!$E$22,0,MAX(0,'Skenario A B C'!$I$22-'Skenario A B C'!$K$22)) | N66: =IF(11<'Skenario A B C'!$E$22,0,MAX(0,'Skenario A B C'!$I$22-'Skenario A B C'!$K$22)) | O66: =IF(12<'Skenario A B C'!$E$22,0,MAX(0,'Skenario A B C'!$I$22-'Skenario A B C'!$K$22)) | P66: =IF(13<'Skenario A B C'!$E$22,0,MAX(0,'Skenario A B C'!$J$22-'Skenario A B C'!$K$22)) | Q66: =IF(14<'Skenario A B C'!$E$22,0,MAX(0,'Skenario A B C'!$J$22-'Skenario A B C'!$K$22)) | R66: =IF(15<'Skenario A B C'!$E$22,0,MAX(0,'Skenario A B C'!$J$22-'Skenario A B C'!$K$22)) | S66: =IF(16<'Skenario A B C'!$E$22,0,MAX(0,'Skenario A B C'!$J$22-'Skenario A B C'!$K$22)) | T66: =IF(17<'Skenario A B C'!$E$22,0,MAX(0,'Skenario A B C'!$J$22-'Skenario A B C'!$K$22)) | U66: =IF(18<'Skenario A B C'!$E$22,0,MAX(0,'Skenario A B C'!$J$22-'Skenario A B C'!$K$22)) | V66: =IF(19<'Skenario A B C'!$E$22,0,MAX(0,'Skenario A B C'!$J$22-'Skenario A B C'!$K$22)) | W66: =IF(20<'Skenario A B C'!$E$22,0,MAX(0,'Skenario A B C'!$J$22-'Skenario A B C'!$K$22)) | X66: =IF(21<'Skenario A B C'!$E$22,0,MAX(0,'Skenario A B C'!$J$22-'Skenario A B C'!$K$22)) | Y66: =IF(22<'Skenario A B C'!$E$22,0,MAX(0,'Skenario A B C'!$J$22-'Skenario A B C'!$K$22)) | Z66: =IF(23<'Skenario A B C'!$E$22,0,MAX(0,'Skenario A B C'!$J$22-'Skenario A B C'!$K$22)) | AA66: =IF(24<'Skenario A B C'!$E$22,0,MAX(0,'Skenario A B C'!$J$22-'Skenario A B C'!$K$22))
A67: Data Analyst | B67: ='Skenario A B C'!$F$23 | D67: =IF(1<'Skenario A B C'!$E$23,0,MAX(0,'Skenario A B C'!$H$23-'Skenario A B C'!$K$23)) | E67: =IF(2<'Skenario A B C'!$E$23,0,MAX(0,'Skenario A B C'!$H$23-'Skenario A B C'!$K$23)) | F67: =IF(3<'Skenario A B C'!$E$23,0,MAX(0,'Skenario A B C'!$H$23-'Skenario A B C'!$K$23)) | G67: =IF(4<'Skenario A B C'!$E$23,0,MAX(0,'Skenario A B C'!$I$23-'Skenario A B C'!$K$23)) | H67: =IF(5<'Skenario A B C'!$E$23,0,MAX(0,'Skenario A B C'!$I$23-'Skenario A B C'!$K$23)) | I67: =IF(6<'Skenario A B C'!$E$23,0,MAX(0,'Skenario A B C'!$I$23-'Skenario A B C'!$K$23)) | J67: =IF(7<'Skenario A B C'!$E$23,0,MAX(0,'Skenario A B C'!$I$23-'Skenario A B C'!$K$23)) | K67: =IF(8<'Skenario A B C'!$E$23,0,MAX(0,'Skenario A B C'!$I$23-'Skenario A B C'!$K$23)) | L67: =IF(9<'Skenario A B C'!$E$23,0,MAX(0,'Skenario A B C'!$I$23-'Skenario A B C'!$K$23)) | M67: =IF(10<'Skenario A B C'!$E$23,0,MAX(0,'Skenario A B C'!$I$23-'Skenario A B C'!$K$23)) | N67: =IF(11<'Skenario A B C'!$E$23,0,MAX(0,'Skenario A B C'!$I$23-'Skenario A B C'!$K$23)) | O67: =IF(12<'Skenario A B C'!$E$23,0,MAX(0,'Skenario A B C'!$I$23-'Skenario A B C'!$K$23)) | P67: =IF(13<'Skenario A B C'!$E$23,0,MAX(0,'Skenario A B C'!$J$23-'Skenario A B C'!$K$23)) | Q67: =IF(14<'Skenario A B C'!$E$23,0,MAX(0,'Skenario A B C'!$J$23-'Skenario A B C'!$K$23)) | R67: =IF(15<'Skenario A B C'!$E$23,0,MAX(0,'Skenario A B C'!$J$23-'Skenario A B C'!$K$23)) | S67: =IF(16<'Skenario A B C'!$E$23,0,MAX(0,'Skenario A B C'!$J$23-'Skenario A B C'!$K$23)) | T67: =IF(17<'Skenario A B C'!$E$23,0,MAX(0,'Skenario A B C'!$J$23-'Skenario A B C'!$K$23)) | U67: =IF(18<'Skenario A B C'!$E$23,0,MAX(0,'Skenario A B C'!$J$23-'Skenario A B C'!$K$23)) | V67: =IF(19<'Skenario A B C'!$E$23,0,MAX(0,'Skenario A B C'!$J$23-'Skenario A B C'!$K$23)) | W67: =IF(20<'Skenario A B C'!$E$23,0,MAX(0,'Skenario A B C'!$J$23-'Skenario A B C'!$K$23)) | X67: =IF(21<'Skenario A B C'!$E$23,0,MAX(0,'Skenario A B C'!$J$23-'Skenario A B C'!$K$23)) | Y67: =IF(22<'Skenario A B C'!$E$23,0,MAX(0,'Skenario A B C'!$J$23-'Skenario A B C'!$K$23)) | Z67: =IF(23<'Skenario A B C'!$E$23,0,MAX(0,'Skenario A B C'!$J$23-'Skenario A B C'!$K$23)) | AA67: =IF(24<'Skenario A B C'!$E$23,0,MAX(0,'Skenario A B C'!$J$23-'Skenario A B C'!$K$23))
A68: Direktur Operasi (COO) | B68: ='Skenario A B C'!$F$24 | D68: =IF(1<'Skenario A B C'!$E$24,0,MAX(0,'Skenario A B C'!$H$24-'Skenario A B C'!$K$24)) | E68: =IF(2<'Skenario A B C'!$E$24,0,MAX(0,'Skenario A B C'!$H$24-'Skenario A B C'!$K$24)) | F68: =IF(3<'Skenario A B C'!$E$24,0,MAX(0,'Skenario A B C'!$H$24-'Skenario A B C'!$K$24)) | G68: =IF(4<'Skenario A B C'!$E$24,0,MAX(0,'Skenario A B C'!$I$24-'Skenario A B C'!$K$24)) | H68: =IF(5<'Skenario A B C'!$E$24,0,MAX(0,'Skenario A B C'!$I$24-'Skenario A B C'!$K$24)) | I68: =IF(6<'Skenario A B C'!$E$24,0,MAX(0,'Skenario A B C'!$I$24-'Skenario A B C'!$K$24)) | J68: =IF(7<'Skenario A B C'!$E$24,0,MAX(0,'Skenario A B C'!$I$24-'Skenario A B C'!$K$24)) | K68: =IF(8<'Skenario A B C'!$E$24,0,MAX(0,'Skenario A B C'!$I$24-'Skenario A B C'!$K$24)) | L68: =IF(9<'Skenario A B C'!$E$24,0,MAX(0,'Skenario A B C'!$I$24-'Skenario A B C'!$K$24)) | M68: =IF(10<'Skenario A B C'!$E$24,0,MAX(0,'Skenario A B C'!$I$24-'Skenario A B C'!$K$24)) | N68: =IF(11<'Skenario A B C'!$E$24,0,MAX(0,'Skenario A B C'!$I$24-'Skenario A B C'!$K$24)) | O68: =IF(12<'Skenario A B C'!$E$24,0,MAX(0,'Skenario A B C'!$I$24-'Skenario A B C'!$K$24)) | P68: =IF(13<'Skenario A B C'!$E$24,0,MAX(0,'Skenario A B C'!$J$24-'Skenario A B C'!$K$24)) | Q68: =IF(14<'Skenario A B C'!$E$24,0,MAX(0,'Skenario A B C'!$J$24-'Skenario A B C'!$K$24)) | R68: =IF(15<'Skenario A B C'!$E$24,0,MAX(0,'Skenario A B C'!$J$24-'Skenario A B C'!$K$24)) | S68: =IF(16<'Skenario A B C'!$E$24,0,MAX(0,'Skenario A B C'!$J$24-'Skenario A B C'!$K$24)) | T68: =IF(17<'Skenario A B C'!$E$24,0,MAX(0,'Skenario A B C'!$J$24-'Skenario A B C'!$K$24)) | U68: =IF(18<'Skenario A B C'!$E$24,0,MAX(0,'Skenario A B C'!$J$24-'Skenario A B C'!$K$24)) | V68: =IF(19<'Skenario A B C'!$E$24,0,MAX(0,'Skenario A B C'!$J$24-'Skenario A B C'!$K$24)) | W68: =IF(20<'Skenario A B C'!$E$24,0,MAX(0,'Skenario A B C'!$J$24-'Skenario A B C'!$K$24)) | X68: =IF(21<'Skenario A B C'!$E$24,0,MAX(0,'Skenario A B C'!$J$24-'Skenario A B C'!$K$24)) | Y68: =IF(22<'Skenario A B C'!$E$24,0,MAX(0,'Skenario A B C'!$J$24-'Skenario A B C'!$K$24)) | Z68: =IF(23<'Skenario A B C'!$E$24,0,MAX(0,'Skenario A B C'!$J$24-'Skenario A B C'!$K$24)) | AA68: =IF(24<'Skenario A B C'!$E$24,0,MAX(0,'Skenario A B C'!$J$24-'Skenario A B C'!$K$24))
A69: City Manager Pekanbaru | B69: ='Skenario A B C'!$F$25 | D69: =IF(1<'Skenario A B C'!$E$25,0,MAX(0,'Skenario A B C'!$H$25-'Skenario A B C'!$K$25)) | E69: =IF(2<'Skenario A B C'!$E$25,0,MAX(0,'Skenario A B C'!$H$25-'Skenario A B C'!$K$25)) | F69: =IF(3<'Skenario A B C'!$E$25,0,MAX(0,'Skenario A B C'!$H$25-'Skenario A B C'!$K$25)) | G69: =IF(4<'Skenario A B C'!$E$25,0,MAX(0,'Skenario A B C'!$I$25-'Skenario A B C'!$K$25)) | H69: =IF(5<'Skenario A B C'!$E$25,0,MAX(0,'Skenario A B C'!$I$25-'Skenario A B C'!$K$25)) | I69: =IF(6<'Skenario A B C'!$E$25,0,MAX(0,'Skenario A B C'!$I$25-'Skenario A B C'!$K$25)) | J69: =IF(7<'Skenario A B C'!$E$25,0,MAX(0,'Skenario A B C'!$I$25-'Skenario A B C'!$K$25)) | K69: =IF(8<'Skenario A B C'!$E$25,0,MAX(0,'Skenario A B C'!$I$25-'Skenario A B C'!$K$25)) | L69: =IF(9<'Skenario A B C'!$E$25,0,MAX(0,'Skenario A B C'!$I$25-'Skenario A B C'!$K$25)) | M69: =IF(10<'Skenario A B C'!$E$25,0,MAX(0,'Skenario A B C'!$I$25-'Skenario A B C'!$K$25)) | N69: =IF(11<'Skenario A B C'!$E$25,0,MAX(0,'Skenario A B C'!$I$25-'Skenario A B C'!$K$25)) | O69: =IF(12<'Skenario A B C'!$E$25,0,MAX(0,'Skenario A B C'!$I$25-'Skenario A B C'!$K$25)) | P69: =IF(13<'Skenario A B C'!$E$25,0,MAX(0,'Skenario A B C'!$J$25-'Skenario A B C'!$K$25)) | Q69: =IF(14<'Skenario A B C'!$E$25,0,MAX(0,'Skenario A B C'!$J$25-'Skenario A B C'!$K$25)) | R69: =IF(15<'Skenario A B C'!$E$25,0,MAX(0,'Skenario A B C'!$J$25-'Skenario A B C'!$K$25)) | S69: =IF(16<'Skenario A B C'!$E$25,0,MAX(0,'Skenario A B C'!$J$25-'Skenario A B C'!$K$25)) | T69: =IF(17<'Skenario A B C'!$E$25,0,MAX(0,'Skenario A B C'!$J$25-'Skenario A B C'!$K$25)) | U69: =IF(18<'Skenario A B C'!$E$25,0,MAX(0,'Skenario A B C'!$J$25-'Skenario A B C'!$K$25)) | V69: =IF(19<'Skenario A B C'!$E$25,0,MAX(0,'Skenario A B C'!$J$25-'Skenario A B C'!$K$25)) | W69: =IF(20<'Skenario A B C'!$E$25,0,MAX(0,'Skenario A B C'!$J$25-'Skenario A B C'!$K$25)) | X69: =IF(21<'Skenario A B C'!$E$25,0,MAX(0,'Skenario A B C'!$J$25-'Skenario A B C'!$K$25)) | Y69: =IF(22<'Skenario A B C'!$E$25,0,MAX(0,'Skenario A B C'!$J$25-'Skenario A B C'!$K$25)) | Z69: =IF(23<'Skenario A B C'!$E$25,0,MAX(0,'Skenario A B C'!$J$25-'Skenario A B C'!$K$25)) | AA69: =IF(24<'Skenario A B C'!$E$25,0,MAX(0,'Skenario A B C'!$J$25-'Skenario A B C'!$K$25))
A70: Ops Supervisor Pekanbaru | B70: ='Skenario A B C'!$F$26 | D70: =IF(1<'Skenario A B C'!$E$26,0,MAX(0,'Skenario A B C'!$H$26-'Skenario A B C'!$K$26)) | E70: =IF(2<'Skenario A B C'!$E$26,0,MAX(0,'Skenario A B C'!$H$26-'Skenario A B C'!$K$26)) | F70: =IF(3<'Skenario A B C'!$E$26,0,MAX(0,'Skenario A B C'!$H$26-'Skenario A B C'!$K$26)) | G70: =IF(4<'Skenario A B C'!$E$26,0,MAX(0,'Skenario A B C'!$I$26-'Skenario A B C'!$K$26)) | H70: =IF(5<'Skenario A B C'!$E$26,0,MAX(0,'Skenario A B C'!$I$26-'Skenario A B C'!$K$26)) | I70: =IF(6<'Skenario A B C'!$E$26,0,MAX(0,'Skenario A B C'!$I$26-'Skenario A B C'!$K$26)) | J70: =IF(7<'Skenario A B C'!$E$26,0,MAX(0,'Skenario A B C'!$I$26-'Skenario A B C'!$K$26)) | K70: =IF(8<'Skenario A B C'!$E$26,0,MAX(0,'Skenario A B C'!$I$26-'Skenario A B C'!$K$26)) | L70: =IF(9<'Skenario A B C'!$E$26,0,MAX(0,'Skenario A B C'!$I$26-'Skenario A B C'!$K$26)) | M70: =IF(10<'Skenario A B C'!$E$26,0,MAX(0,'Skenario A B C'!$I$26-'Skenario A B C'!$K$26)) | N70: =IF(11<'Skenario A B C'!$E$26,0,MAX(0,'Skenario A B C'!$I$26-'Skenario A B C'!$K$26)) | O70: =IF(12<'Skenario A B C'!$E$26,0,MAX(0,'Skenario A B C'!$I$26-'Skenario A B C'!$K$26)) | P70: =IF(13<'Skenario A B C'!$E$26,0,MAX(0,'Skenario A B C'!$J$26-'Skenario A B C'!$K$26)) | Q70: =IF(14<'Skenario A B C'!$E$26,0,MAX(0,'Skenario A B C'!$J$26-'Skenario A B C'!$K$26)) | R70: =IF(15<'Skenario A B C'!$E$26,0,MAX(0,'Skenario A B C'!$J$26-'Skenario A B C'!$K$26)) | S70: =IF(16<'Skenario A B C'!$E$26,0,MAX(0,'Skenario A B C'!$J$26-'Skenario A B C'!$K$26)) | T70: =IF(17<'Skenario A B C'!$E$26,0,MAX(0,'Skenario A B C'!$J$26-'Skenario A B C'!$K$26)) | U70: =IF(18<'Skenario A B C'!$E$26,0,MAX(0,'Skenario A B C'!$J$26-'Skenario A B C'!$K$26)) | V70: =IF(19<'Skenario A B C'!$E$26,0,MAX(0,'Skenario A B C'!$J$26-'Skenario A B C'!$K$26)) | W70: =IF(20<'Skenario A B C'!$E$26,0,MAX(0,'Skenario A B C'!$J$26-'Skenario A B C'!$K$26)) | X70: =IF(21<'Skenario A B C'!$E$26,0,MAX(0,'Skenario A B C'!$J$26-'Skenario A B C'!$K$26)) | Y70: =IF(22<'Skenario A B C'!$E$26,0,MAX(0,'Skenario A B C'!$J$26-'Skenario A B C'!$K$26)) | Z70: =IF(23<'Skenario A B C'!$E$26,0,MAX(0,'Skenario A B C'!$J$26-'Skenario A B C'!$K$26)) | AA70: =IF(24<'Skenario A B C'!$E$26,0,MAX(0,'Skenario A B C'!$J$26-'Skenario A B C'!$K$26))
A71: Partner Acquisition Pekanbaru | B71: ='Skenario A B C'!$F$27 | D71: =IF(1<'Skenario A B C'!$E$27,0,MAX(0,'Skenario A B C'!$H$27-'Skenario A B C'!$K$27)) | E71: =IF(2<'Skenario A B C'!$E$27,0,MAX(0,'Skenario A B C'!$H$27-'Skenario A B C'!$K$27)) | F71: =IF(3<'Skenario A B C'!$E$27,0,MAX(0,'Skenario A B C'!$H$27-'Skenario A B C'!$K$27)) | G71: =IF(4<'Skenario A B C'!$E$27,0,MAX(0,'Skenario A B C'!$I$27-'Skenario A B C'!$K$27)) | H71: =IF(5<'Skenario A B C'!$E$27,0,MAX(0,'Skenario A B C'!$I$27-'Skenario A B C'!$K$27)) | I71: =IF(6<'Skenario A B C'!$E$27,0,MAX(0,'Skenario A B C'!$I$27-'Skenario A B C'!$K$27)) | J71: =IF(7<'Skenario A B C'!$E$27,0,MAX(0,'Skenario A B C'!$I$27-'Skenario A B C'!$K$27)) | K71: =IF(8<'Skenario A B C'!$E$27,0,MAX(0,'Skenario A B C'!$I$27-'Skenario A B C'!$K$27)) | L71: =IF(9<'Skenario A B C'!$E$27,0,MAX(0,'Skenario A B C'!$I$27-'Skenario A B C'!$K$27)) | M71: =IF(10<'Skenario A B C'!$E$27,0,MAX(0,'Skenario A B C'!$I$27-'Skenario A B C'!$K$27)) | N71: =IF(11<'Skenario A B C'!$E$27,0,MAX(0,'Skenario A B C'!$I$27-'Skenario A B C'!$K$27)) | O71: =IF(12<'Skenario A B C'!$E$27,0,MAX(0,'Skenario A B C'!$I$27-'Skenario A B C'!$K$27)) | P71: =IF(13<'Skenario A B C'!$E$27,0,MAX(0,'Skenario A B C'!$J$27-'Skenario A B C'!$K$27)) | Q71: =IF(14<'Skenario A B C'!$E$27,0,MAX(0,'Skenario A B C'!$J$27-'Skenario A B C'!$K$27)) | R71: =IF(15<'Skenario A B C'!$E$27,0,MAX(0,'Skenario A B C'!$J$27-'Skenario A B C'!$K$27)) | S71: =IF(16<'Skenario A B C'!$E$27,0,MAX(0,'Skenario A B C'!$J$27-'Skenario A B C'!$K$27)) | T71: =IF(17<'Skenario A B C'!$E$27,0,MAX(0,'Skenario A B C'!$J$27-'Skenario A B C'!$K$27)) | U71: =IF(18<'Skenario A B C'!$E$27,0,MAX(0,'Skenario A B C'!$J$27-'Skenario A B C'!$K$27)) | V71: =IF(19<'Skenario A B C'!$E$27,0,MAX(0,'Skenario A B C'!$J$27-'Skenario A B C'!$K$27)) | W71: =IF(20<'Skenario A B C'!$E$27,0,MAX(0,'Skenario A B C'!$J$27-'Skenario A B C'!$K$27)) | X71: =IF(21<'Skenario A B C'!$E$27,0,MAX(0,'Skenario A B C'!$J$27-'Skenario A B C'!$K$27)) | Y71: =IF(22<'Skenario A B C'!$E$27,0,MAX(0,'Skenario A B C'!$J$27-'Skenario A B C'!$K$27)) | Z71: =IF(23<'Skenario A B C'!$E$27,0,MAX(0,'Skenario A B C'!$J$27-'Skenario A B C'!$K$27)) | AA71: =IF(24<'Skenario A B C'!$E$27,0,MAX(0,'Skenario A B C'!$J$27-'Skenario A B C'!$K$27))
A72: Head of Customer Experience | B72: ='Skenario A B C'!$F$28 | D72: =IF(1<'Skenario A B C'!$E$28,0,MAX(0,'Skenario A B C'!$H$28-'Skenario A B C'!$K$28)) | E72: =IF(2<'Skenario A B C'!$E$28,0,MAX(0,'Skenario A B C'!$H$28-'Skenario A B C'!$K$28)) | F72: =IF(3<'Skenario A B C'!$E$28,0,MAX(0,'Skenario A B C'!$H$28-'Skenario A B C'!$K$28)) | G72: =IF(4<'Skenario A B C'!$E$28,0,MAX(0,'Skenario A B C'!$I$28-'Skenario A B C'!$K$28)) | H72: =IF(5<'Skenario A B C'!$E$28,0,MAX(0,'Skenario A B C'!$I$28-'Skenario A B C'!$K$28)) | I72: =IF(6<'Skenario A B C'!$E$28,0,MAX(0,'Skenario A B C'!$I$28-'Skenario A B C'!$K$28)) | J72: =IF(7<'Skenario A B C'!$E$28,0,MAX(0,'Skenario A B C'!$I$28-'Skenario A B C'!$K$28)) | K72: =IF(8<'Skenario A B C'!$E$28,0,MAX(0,'Skenario A B C'!$I$28-'Skenario A B C'!$K$28)) | L72: =IF(9<'Skenario A B C'!$E$28,0,MAX(0,'Skenario A B C'!$I$28-'Skenario A B C'!$K$28)) | M72: =IF(10<'Skenario A B C'!$E$28,0,MAX(0,'Skenario A B C'!$I$28-'Skenario A B C'!$K$28)) | N72: =IF(11<'Skenario A B C'!$E$28,0,MAX(0,'Skenario A B C'!$I$28-'Skenario A B C'!$K$28)) | O72: =IF(12<'Skenario A B C'!$E$28,0,MAX(0,'Skenario A B C'!$I$28-'Skenario A B C'!$K$28)) | P72: =IF(13<'Skenario A B C'!$E$28,0,MAX(0,'Skenario A B C'!$J$28-'Skenario A B C'!$K$28)) | Q72: =IF(14<'Skenario A B C'!$E$28,0,MAX(0,'Skenario A B C'!$J$28-'Skenario A B C'!$K$28)) | R72: =IF(15<'Skenario A B C'!$E$28,0,MAX(0,'Skenario A B C'!$J$28-'Skenario A B C'!$K$28)) | S72: =IF(16<'Skenario A B C'!$E$28,0,MAX(0,'Skenario A B C'!$J$28-'Skenario A B C'!$K$28)) | T72: =IF(17<'Skenario A B C'!$E$28,0,MAX(0,'Skenario A B C'!$J$28-'Skenario A B C'!$K$28)) | U72: =IF(18<'Skenario A B C'!$E$28,0,MAX(0,'Skenario A B C'!$J$28-'Skenario A B C'!$K$28)) | V72: =IF(19<'Skenario A B C'!$E$28,0,MAX(0,'Skenario A B C'!$J$28-'Skenario A B C'!$K$28)) | W72: =IF(20<'Skenario A B C'!$E$28,0,MAX(0,'Skenario A B C'!$J$28-'Skenario A B C'!$K$28)) | X72: =IF(21<'Skenario A B C'!$E$28,0,MAX(0,'Skenario A B C'!$J$28-'Skenario A B C'!$K$28)) | Y72: =IF(22<'Skenario A B C'!$E$28,0,MAX(0,'Skenario A B C'!$J$28-'Skenario A B C'!$K$28)) | Z72: =IF(23<'Skenario A B C'!$E$28,0,MAX(0,'Skenario A B C'!$J$28-'Skenario A B C'!$K$28)) | AA72: =IF(24<'Skenario A B C'!$E$28,0,MAX(0,'Skenario A B C'!$J$28-'Skenario A B C'!$K$28))
A73: CS Agent Pekanbaru (shift) | B73: ='Skenario A B C'!$F$29 | D73: =IF(1<'Skenario A B C'!$E$29,0,MAX(0,'Skenario A B C'!$H$29-'Skenario A B C'!$K$29)) | E73: =IF(2<'Skenario A B C'!$E$29,0,MAX(0,'Skenario A B C'!$H$29-'Skenario A B C'!$K$29)) | F73: =IF(3<'Skenario A B C'!$E$29,0,MAX(0,'Skenario A B C'!$H$29-'Skenario A B C'!$K$29)) | G73: =IF(4<'Skenario A B C'!$E$29,0,MAX(0,'Skenario A B C'!$I$29-'Skenario A B C'!$K$29)) | H73: =IF(5<'Skenario A B C'!$E$29,0,MAX(0,'Skenario A B C'!$I$29-'Skenario A B C'!$K$29)) | I73: =IF(6<'Skenario A B C'!$E$29,0,MAX(0,'Skenario A B C'!$I$29-'Skenario A B C'!$K$29)) | J73: =IF(7<'Skenario A B C'!$E$29,0,MAX(0,'Skenario A B C'!$I$29-'Skenario A B C'!$K$29)) | K73: =IF(8<'Skenario A B C'!$E$29,0,MAX(0,'Skenario A B C'!$I$29-'Skenario A B C'!$K$29)) | L73: =IF(9<'Skenario A B C'!$E$29,0,MAX(0,'Skenario A B C'!$I$29-'Skenario A B C'!$K$29)) | M73: =IF(10<'Skenario A B C'!$E$29,0,MAX(0,'Skenario A B C'!$I$29-'Skenario A B C'!$K$29)) | N73: =IF(11<'Skenario A B C'!$E$29,0,MAX(0,'Skenario A B C'!$I$29-'Skenario A B C'!$K$29)) | O73: =IF(12<'Skenario A B C'!$E$29,0,MAX(0,'Skenario A B C'!$I$29-'Skenario A B C'!$K$29)) | P73: =IF(13<'Skenario A B C'!$E$29,0,MAX(0,'Skenario A B C'!$J$29-'Skenario A B C'!$K$29)) | Q73: =IF(14<'Skenario A B C'!$E$29,0,MAX(0,'Skenario A B C'!$J$29-'Skenario A B C'!$K$29)) | R73: =IF(15<'Skenario A B C'!$E$29,0,MAX(0,'Skenario A B C'!$J$29-'Skenario A B C'!$K$29)) | S73: =IF(16<'Skenario A B C'!$E$29,0,MAX(0,'Skenario A B C'!$J$29-'Skenario A B C'!$K$29)) | T73: =IF(17<'Skenario A B C'!$E$29,0,MAX(0,'Skenario A B C'!$J$29-'Skenario A B C'!$K$29)) | U73: =IF(18<'Skenario A B C'!$E$29,0,MAX(0,'Skenario A B C'!$J$29-'Skenario A B C'!$K$29)) | V73: =IF(19<'Skenario A B C'!$E$29,0,MAX(0,'Skenario A B C'!$J$29-'Skenario A B C'!$K$29)) | W73: =IF(20<'Skenario A B C'!$E$29,0,MAX(0,'Skenario A B C'!$J$29-'Skenario A B C'!$K$29)) | X73: =IF(21<'Skenario A B C'!$E$29,0,MAX(0,'Skenario A B C'!$J$29-'Skenario A B C'!$K$29)) | Y73: =IF(22<'Skenario A B C'!$E$29,0,MAX(0,'Skenario A B C'!$J$29-'Skenario A B C'!$K$29)) | Z73: =IF(23<'Skenario A B C'!$E$29,0,MAX(0,'Skenario A B C'!$J$29-'Skenario A B C'!$K$29)) | AA73: =IF(24<'Skenario A B C'!$E$29,0,MAX(0,'Skenario A B C'!$J$29-'Skenario A B C'!$K$29))
A74: Trust & Safety Officer | B74: ='Skenario A B C'!$F$30 | D74: =IF(1<'Skenario A B C'!$E$30,0,MAX(0,'Skenario A B C'!$H$30-'Skenario A B C'!$K$30)) | E74: =IF(2<'Skenario A B C'!$E$30,0,MAX(0,'Skenario A B C'!$H$30-'Skenario A B C'!$K$30)) | F74: =IF(3<'Skenario A B C'!$E$30,0,MAX(0,'Skenario A B C'!$H$30-'Skenario A B C'!$K$30)) | G74: =IF(4<'Skenario A B C'!$E$30,0,MAX(0,'Skenario A B C'!$I$30-'Skenario A B C'!$K$30)) | H74: =IF(5<'Skenario A B C'!$E$30,0,MAX(0,'Skenario A B C'!$I$30-'Skenario A B C'!$K$30)) | I74: =IF(6<'Skenario A B C'!$E$30,0,MAX(0,'Skenario A B C'!$I$30-'Skenario A B C'!$K$30)) | J74: =IF(7<'Skenario A B C'!$E$30,0,MAX(0,'Skenario A B C'!$I$30-'Skenario A B C'!$K$30)) | K74: =IF(8<'Skenario A B C'!$E$30,0,MAX(0,'Skenario A B C'!$I$30-'Skenario A B C'!$K$30)) | L74: =IF(9<'Skenario A B C'!$E$30,0,MAX(0,'Skenario A B C'!$I$30-'Skenario A B C'!$K$30)) | M74: =IF(10<'Skenario A B C'!$E$30,0,MAX(0,'Skenario A B C'!$I$30-'Skenario A B C'!$K$30)) | N74: =IF(11<'Skenario A B C'!$E$30,0,MAX(0,'Skenario A B C'!$I$30-'Skenario A B C'!$K$30)) | O74: =IF(12<'Skenario A B C'!$E$30,0,MAX(0,'Skenario A B C'!$I$30-'Skenario A B C'!$K$30)) | P74: =IF(13<'Skenario A B C'!$E$30,0,MAX(0,'Skenario A B C'!$J$30-'Skenario A B C'!$K$30)) | Q74: =IF(14<'Skenario A B C'!$E$30,0,MAX(0,'Skenario A B C'!$J$30-'Skenario A B C'!$K$30)) | R74: =IF(15<'Skenario A B C'!$E$30,0,MAX(0,'Skenario A B C'!$J$30-'Skenario A B C'!$K$30)) | S74: =IF(16<'Skenario A B C'!$E$30,0,MAX(0,'Skenario A B C'!$J$30-'Skenario A B C'!$K$30)) | T74: =IF(17<'Skenario A B C'!$E$30,0,MAX(0,'Skenario A B C'!$J$30-'Skenario A B C'!$K$30)) | U74: =IF(18<'Skenario A B C'!$E$30,0,MAX(0,'Skenario A B C'!$J$30-'Skenario A B C'!$K$30)) | V74: =IF(19<'Skenario A B C'!$E$30,0,MAX(0,'Skenario A B C'!$J$30-'Skenario A B C'!$K$30)) | W74: =IF(20<'Skenario A B C'!$E$30,0,MAX(0,'Skenario A B C'!$J$30-'Skenario A B C'!$K$30)) | X74: =IF(21<'Skenario A B C'!$E$30,0,MAX(0,'Skenario A B C'!$J$30-'Skenario A B C'!$K$30)) | Y74: =IF(22<'Skenario A B C'!$E$30,0,MAX(0,'Skenario A B C'!$J$30-'Skenario A B C'!$K$30)) | Z74: =IF(23<'Skenario A B C'!$E$30,0,MAX(0,'Skenario A B C'!$J$30-'Skenario A B C'!$K$30)) | AA74: =IF(24<'Skenario A B C'!$E$30,0,MAX(0,'Skenario A B C'!$J$30-'Skenario A B C'!$K$30))
A75: City Manager Padang | B75: ='Skenario A B C'!$F$31 | D75: =IF(1<'Skenario A B C'!$E$31,0,MAX(0,'Skenario A B C'!$H$31-'Skenario A B C'!$K$31)) | E75: =IF(2<'Skenario A B C'!$E$31,0,MAX(0,'Skenario A B C'!$H$31-'Skenario A B C'!$K$31)) | F75: =IF(3<'Skenario A B C'!$E$31,0,MAX(0,'Skenario A B C'!$H$31-'Skenario A B C'!$K$31)) | G75: =IF(4<'Skenario A B C'!$E$31,0,MAX(0,'Skenario A B C'!$I$31-'Skenario A B C'!$K$31)) | H75: =IF(5<'Skenario A B C'!$E$31,0,MAX(0,'Skenario A B C'!$I$31-'Skenario A B C'!$K$31)) | I75: =IF(6<'Skenario A B C'!$E$31,0,MAX(0,'Skenario A B C'!$I$31-'Skenario A B C'!$K$31)) | J75: =IF(7<'Skenario A B C'!$E$31,0,MAX(0,'Skenario A B C'!$I$31-'Skenario A B C'!$K$31)) | K75: =IF(8<'Skenario A B C'!$E$31,0,MAX(0,'Skenario A B C'!$I$31-'Skenario A B C'!$K$31)) | L75: =IF(9<'Skenario A B C'!$E$31,0,MAX(0,'Skenario A B C'!$I$31-'Skenario A B C'!$K$31)) | M75: =IF(10<'Skenario A B C'!$E$31,0,MAX(0,'Skenario A B C'!$I$31-'Skenario A B C'!$K$31)) | N75: =IF(11<'Skenario A B C'!$E$31,0,MAX(0,'Skenario A B C'!$I$31-'Skenario A B C'!$K$31)) | O75: =IF(12<'Skenario A B C'!$E$31,0,MAX(0,'Skenario A B C'!$I$31-'Skenario A B C'!$K$31)) | P75: =IF(13<'Skenario A B C'!$E$31,0,MAX(0,'Skenario A B C'!$J$31-'Skenario A B C'!$K$31)) | Q75: =IF(14<'Skenario A B C'!$E$31,0,MAX(0,'Skenario A B C'!$J$31-'Skenario A B C'!$K$31)) | R75: =IF(15<'Skenario A B C'!$E$31,0,MAX(0,'Skenario A B C'!$J$31-'Skenario A B C'!$K$31)) | S75: =IF(16<'Skenario A B C'!$E$31,0,MAX(0,'Skenario A B C'!$J$31-'Skenario A B C'!$K$31)) | T75: =IF(17<'Skenario A B C'!$E$31,0,MAX(0,'Skenario A B C'!$J$31-'Skenario A B C'!$K$31)) | U75: =IF(18<'Skenario A B C'!$E$31,0,MAX(0,'Skenario A B C'!$J$31-'Skenario A B C'!$K$31)) | V75: =IF(19<'Skenario A B C'!$E$31,0,MAX(0,'Skenario A B C'!$J$31-'Skenario A B C'!$K$31)) | W75: =IF(20<'Skenario A B C'!$E$31,0,MAX(0,'Skenario A B C'!$J$31-'Skenario A B C'!$K$31)) | X75: =IF(21<'Skenario A B C'!$E$31,0,MAX(0,'Skenario A B C'!$J$31-'Skenario A B C'!$K$31)) | Y75: =IF(22<'Skenario A B C'!$E$31,0,MAX(0,'Skenario A B C'!$J$31-'Skenario A B C'!$K$31)) | Z75: =IF(23<'Skenario A B C'!$E$31,0,MAX(0,'Skenario A B C'!$J$31-'Skenario A B C'!$K$31)) | AA75: =IF(24<'Skenario A B C'!$E$31,0,MAX(0,'Skenario A B C'!$J$31-'Skenario A B C'!$K$31))
A76: Partner Acquisition Padang | B76: ='Skenario A B C'!$F$32 | D76: =IF(1<'Skenario A B C'!$E$32,0,MAX(0,'Skenario A B C'!$H$32-'Skenario A B C'!$K$32)) | E76: =IF(2<'Skenario A B C'!$E$32,0,MAX(0,'Skenario A B C'!$H$32-'Skenario A B C'!$K$32)) | F76: =IF(3<'Skenario A B C'!$E$32,0,MAX(0,'Skenario A B C'!$H$32-'Skenario A B C'!$K$32)) | G76: =IF(4<'Skenario A B C'!$E$32,0,MAX(0,'Skenario A B C'!$I$32-'Skenario A B C'!$K$32)) | H76: =IF(5<'Skenario A B C'!$E$32,0,MAX(0,'Skenario A B C'!$I$32-'Skenario A B C'!$K$32)) | I76: =IF(6<'Skenario A B C'!$E$32,0,MAX(0,'Skenario A B C'!$I$32-'Skenario A B C'!$K$32)) | J76: =IF(7<'Skenario A B C'!$E$32,0,MAX(0,'Skenario A B C'!$I$32-'Skenario A B C'!$K$32)) | K76: =IF(8<'Skenario A B C'!$E$32,0,MAX(0,'Skenario A B C'!$I$32-'Skenario A B C'!$K$32)) | L76: =IF(9<'Skenario A B C'!$E$32,0,MAX(0,'Skenario A B C'!$I$32-'Skenario A B C'!$K$32)) | M76: =IF(10<'Skenario A B C'!$E$32,0,MAX(0,'Skenario A B C'!$I$32-'Skenario A B C'!$K$32)) | N76: =IF(11<'Skenario A B C'!$E$32,0,MAX(0,'Skenario A B C'!$I$32-'Skenario A B C'!$K$32)) | O76: =IF(12<'Skenario A B C'!$E$32,0,MAX(0,'Skenario A B C'!$I$32-'Skenario A B C'!$K$32)) | P76: =IF(13<'Skenario A B C'!$E$32,0,MAX(0,'Skenario A B C'!$J$32-'Skenario A B C'!$K$32)) | Q76: =IF(14<'Skenario A B C'!$E$32,0,MAX(0,'Skenario A B C'!$J$32-'Skenario A B C'!$K$32)) | R76: =IF(15<'Skenario A B C'!$E$32,0,MAX(0,'Skenario A B C'!$J$32-'Skenario A B C'!$K$32)) | S76: =IF(16<'Skenario A B C'!$E$32,0,MAX(0,'Skenario A B C'!$J$32-'Skenario A B C'!$K$32)) | T76: =IF(17<'Skenario A B C'!$E$32,0,MAX(0,'Skenario A B C'!$J$32-'Skenario A B C'!$K$32)) | U76: =IF(18<'Skenario A B C'!$E$32,0,MAX(0,'Skenario A B C'!$J$32-'Skenario A B C'!$K$32)) | V76: =IF(19<'Skenario A B C'!$E$32,0,MAX(0,'Skenario A B C'!$J$32-'Skenario A B C'!$K$32)) | W76: =IF(20<'Skenario A B C'!$E$32,0,MAX(0,'Skenario A B C'!$J$32-'Skenario A B C'!$K$32)) | X76: =IF(21<'Skenario A B C'!$E$32,0,MAX(0,'Skenario A B C'!$J$32-'Skenario A B C'!$K$32)) | Y76: =IF(22<'Skenario A B C'!$E$32,0,MAX(0,'Skenario A B C'!$J$32-'Skenario A B C'!$K$32)) | Z76: =IF(23<'Skenario A B C'!$E$32,0,MAX(0,'Skenario A B C'!$J$32-'Skenario A B C'!$K$32)) | AA76: =IF(24<'Skenario A B C'!$E$32,0,MAX(0,'Skenario A B C'!$J$32-'Skenario A B C'!$K$32))
A77: Ops Supervisor Padang | B77: ='Skenario A B C'!$F$33 | D77: =IF(1<'Skenario A B C'!$E$33,0,MAX(0,'Skenario A B C'!$H$33-'Skenario A B C'!$K$33)) | E77: =IF(2<'Skenario A B C'!$E$33,0,MAX(0,'Skenario A B C'!$H$33-'Skenario A B C'!$K$33)) | F77: =IF(3<'Skenario A B C'!$E$33,0,MAX(0,'Skenario A B C'!$H$33-'Skenario A B C'!$K$33)) | G77: =IF(4<'Skenario A B C'!$E$33,0,MAX(0,'Skenario A B C'!$I$33-'Skenario A B C'!$K$33)) | H77: =IF(5<'Skenario A B C'!$E$33,0,MAX(0,'Skenario A B C'!$I$33-'Skenario A B C'!$K$33)) | I77: =IF(6<'Skenario A B C'!$E$33,0,MAX(0,'Skenario A B C'!$I$33-'Skenario A B C'!$K$33)) | J77: =IF(7<'Skenario A B C'!$E$33,0,MAX(0,'Skenario A B C'!$I$33-'Skenario A B C'!$K$33)) | K77: =IF(8<'Skenario A B C'!$E$33,0,MAX(0,'Skenario A B C'!$I$33-'Skenario A B C'!$K$33)) | L77: =IF(9<'Skenario A B C'!$E$33,0,MAX(0,'Skenario A B C'!$I$33-'Skenario A B C'!$K$33)) | M77: =IF(10<'Skenario A B C'!$E$33,0,MAX(0,'Skenario A B C'!$I$33-'Skenario A B C'!$K$33)) | N77: =IF(11<'Skenario A B C'!$E$33,0,MAX(0,'Skenario A B C'!$I$33-'Skenario A B C'!$K$33)) | O77: =IF(12<'Skenario A B C'!$E$33,0,MAX(0,'Skenario A B C'!$I$33-'Skenario A B C'!$K$33)) | P77: =IF(13<'Skenario A B C'!$E$33,0,MAX(0,'Skenario A B C'!$J$33-'Skenario A B C'!$K$33)) | Q77: =IF(14<'Skenario A B C'!$E$33,0,MAX(0,'Skenario A B C'!$J$33-'Skenario A B C'!$K$33)) | R77: =IF(15<'Skenario A B C'!$E$33,0,MAX(0,'Skenario A B C'!$J$33-'Skenario A B C'!$K$33)) | S77: =IF(16<'Skenario A B C'!$E$33,0,MAX(0,'Skenario A B C'!$J$33-'Skenario A B C'!$K$33)) | T77: =IF(17<'Skenario A B C'!$E$33,0,MAX(0,'Skenario A B C'!$J$33-'Skenario A B C'!$K$33)) | U77: =IF(18<'Skenario A B C'!$E$33,0,MAX(0,'Skenario A B C'!$J$33-'Skenario A B C'!$K$33)) | V77: =IF(19<'Skenario A B C'!$E$33,0,MAX(0,'Skenario A B C'!$J$33-'Skenario A B C'!$K$33)) | W77: =IF(20<'Skenario A B C'!$E$33,0,MAX(0,'Skenario A B C'!$J$33-'Skenario A B C'!$K$33)) | X77: =IF(21<'Skenario A B C'!$E$33,0,MAX(0,'Skenario A B C'!$J$33-'Skenario A B C'!$K$33)) | Y77: =IF(22<'Skenario A B C'!$E$33,0,MAX(0,'Skenario A B C'!$J$33-'Skenario A B C'!$K$33)) | Z77: =IF(23<'Skenario A B C'!$E$33,0,MAX(0,'Skenario A B C'!$J$33-'Skenario A B C'!$K$33)) | AA77: =IF(24<'Skenario A B C'!$E$33,0,MAX(0,'Skenario A B C'!$J$33-'Skenario A B C'!$K$33))
