Workbook

Sheet Ringkasan
A1: AntarKita - Model Biaya SDM: Ringkasan Eksekutif
A2: Tanggal penyusunan: 7 September 2026 | Versi model 1.0 | Penyusun: Analis Keuangan SDM AntarKita
A3: PERINGATAN WAJIB DIBACA: seluruh PITA GAJI dalam model ini berlabel [ASUMSI]. Angka tersebut adalah konstruksi penyusun (tabel A.4.3 riset), BUKAN kutipan benchmark pasar, dan tidak boleh disajikan sebagai klaim faktual. Tarif iuran BPJS, plafon upah, UMK dan dasar THR BERSUMBER dan dikutip - lihat lembar 'Sumber & Catatan'.
A5: A. ANGKA KUNCI PER FASE
A6: Metrik | B6: Fase 0 (bulan 1-3) | C6: Fase 1 (bulan 4-12) | D6: Fase 2 (bulan 13-24) | E6: Sumber angka
A7: Jumlah karyawan (kumulatif) | B7: =Headcount!$H$43 -> 9 | C7: =Headcount!$I$43 -> 24 | D7: =Headcount!$J$43 -> 42 | E7: Lembar 'Headcount' - target mengikat DESAIN-ORGANISASI §3
A8: Biaya SDM per bulan (Rp) | B8: ='Biaya Bulanan'!$Y$64 -> 230332093 | C8: ='Biaya Bulanan'!$Z$64 -> 4.3555549e+08 | D8: ='Biaya Bulanan'!$AA$64 -> 6.3627206e+08 | E8: Lembar 'Biaya Bulanan' baris TOTAL (run-rate pada staf penuh fase tsb.)
A9: Biaya SDM per tahun / run-rate 12 bulan (Rp) | B9: ='Biaya Bulanan'!$Y$64*12 -> 2763985116 | C9: ='Biaya Bulanan'!$Z$64*12 -> 5226665838 | D9: ='Biaya Bulanan'!$AA$64*12 -> 7635264741 | E9: Run-rate, bukan biaya aktual fase (fase 0 & 1 lebih pendek dari 12 bulan)
A10: Rata-rata biaya SDM per orang per bulan (Rp) | B10: =IF(B7=0,0,B8/B7) -> 25592455 | C10: =IF(C7=0,0,C8/C7) -> 18148145 | D10: =IF(D7=0,0,D8/D7) -> 15149335 | E10: Turunan: biaya per bulan / jumlah karyawan
A11: Rasio total cost to company : gaji pokok (rata-rata tertimbang) | B11: =IF(SUMPRODUCT('Biaya Bulanan'!$K$26:$K$63,'Biaya Bulanan'!$V$26:$V$63)=0,0,B8/SUMPRODUCT('Biaya Bulanan'!$K$26:$K$63,'Biaya Bulanan'!$V$26:$V$63)) -> 1.2760781 | C11: =C8/SUMPRODUCT('Biaya Bulanan'!$K$26:$K$63,'Biaya Bulanan'!$W$26:$W$63) -> 1.2838776 | D11: =D8/SUMPRODUCT('Biaya Bulanan'!$K$26:$K$63,'Biaya Bulanan'!$X$26:$X$63) -> 1.2892398 | E11: Kebijakan DESAIN §4.3 memakai angka indikatif 1,19x - lihat catatan koreksi
A12: Biaya non-gaji SDM berulang per bulan (Rp) | B12: ='Biaya Non-Gaji'!$I$11 -> 19350000 | C12: ='Biaya Non-Gaji'!$J$11 -> 48000000 | D12: ='Biaya Non-Gaji'!$K$11 -> 78300000 | E12: Lembar 'Biaya Non-Gaji' Subtotal A - SELURUHNYA [ASUMSI]
A14: B. BIAYA KUMULATIF 24 BULAN & PORSI TERHADAP KEBUTUHAN PENDANAAN
A15: Pos | B15: Nilai (Rp) | E15: Sumber / status
A16: Biaya SDM (gaji + iuran + THR) kumulatif bulan 1-24 | B16: ='Proyeksi 24 Bulan'!$D$55 -> 11689208853 | E16: Lembar 'Proyeksi 24 Bulan' - mengikuti jadwal rekrutmen per posisi
A17: Biaya SDM kumulatif bulan 1-12 (tahun pertama) | B17: ='Proyeksi 24 Bulan'!$D$56 -> 4443025431 | E17: Lembar 'Proyeksi 24 Bulan'
A18: Biaya non-gaji SDM kumulatif bulan 1-24 | B18: ='Biaya Non-Gaji'!$M$19 -> 1927050000 | E18: Lembar 'Biaya Non-Gaji' - SELURUHNYA [ASUMSI]
A19: TOTAL BIAYA TERKAIT SDM 24 BULAN | B19: =B16+B18 -> 13616258853 | E19: Jumlah dua baris di atas
A20: Modal minimum sektoral KBLI 53200 Aktivitas Kurir | B20: 500000000 | E20: [S-41] Klinik Hukumonline 20 Apr 2026 - kegiatan berisiko tinggi
A21: Pos non-SDM lainnya 24 bulan (insentif mitra, pemasaran, infrastruktur, perizinan) | B21: 12000000000 | E21: [ASUMSI] INPUT PENGGUNA - WAJIB diganti dengan angka rencana bisnis. Tidak ada sumber (CAC/CAD tidak ditemukan benchmark-nya)
A22: KEBUTUHAN PENDANAAN 24 BULAN | B22: =B19+B20+B21 -> 26116258853 | E22: Total biaya terkait SDM + modal sektoral + pos non-SDM lainnya
A23: Porsi BIAYA SDM (gaji) terhadap kebutuhan pendanaan 24 bulan | B23: =B16/B22 -> 0.44758359 | E23: Sensitif terhadap 'Pos non-SDM lainnya' yang berlabel [ASUMSI]
A24: Porsi TOTAL BIAYA TERKAIT SDM (gaji + non-gaji) terhadap kebutuhan pendanaan 24 bulan | B24: =B19/B22 -> 0.52137096 | E24: Sensitif terhadap 'Pos non-SDM lainnya' yang berlabel [ASUMSI]
A26: C. SKENARIO - HEMAT / DASAR / AGRESIF
A27: Skenario | B27: Posisi pita gaji | C27: Faktor jumlah posisi | D27: Headcount Fase 2 (orang) | E27: Biaya SDM/bulan Fase 2 (Rp) | F27: Biaya SDM/tahun Fase 2 (Rp) | G27: Biaya SDM kumulatif 24 bulan (Rp) | H27: Keterangan
A28: Hemat | B28: P25 | C28: 0.85 | D28: =ROUND(Headcount!$J$43*$C28,0) -> 36 | E28: =$C28*SUMPRODUCT('Biaya Bulanan'!$AG$26:$AG$63,'Biaya Bulanan'!$X$26:$X$63) -> 4.281074e+08 | F28: =$E28*12 -> 5.1372888e+09 | G28: =$C28*SUMPRODUCT('Biaya Bulanan'!$AG$26:$AG$63,'Biaya Bulanan'!$AK$26:$AK$63) -> 8.0212246e+09 | H28: Menawar di batas bawah pita; 6 posisi ditunda ke Fase 3. Risiko: gagal merekrut Senior Engineer & Head, waktu rekrutmen memanjang.
A29: Dasar | B29: P50 | C29: 1 | D29: =ROUND(Headcount!$J$43*$C29,0) -> 42 | E29: =$C29*SUMPRODUCT('Biaya Bulanan'!$AH$26:$AH$63,'Biaya Bulanan'!$X$26:$X$63) -> 6.3627206e+08 | F29: =$E29*12 -> 7635264741 | G29: =$C29*SUMPRODUCT('Biaya Bulanan'!$AH$26:$AH$63,'Biaya Bulanan'!$AK$26:$AK$63) -> 11689208853 | H29: Kebijakan resmi DESAIN-ORGANISASI §4.2 (penawaran default P50; C-Level tetap P25 + ESOP). Ini angka yang dipakai seluruh lembar lain.
A30: Agresif | B30: P75 | C30: 1.15 | D30: =ROUND(Headcount!$J$43*$C30,0) -> 48 | E30: =$C30*SUMPRODUCT('Biaya Bulanan'!$AI$26:$AI$63,'Biaya Bulanan'!$X$26:$X$63) -> 8.8229182e+08 | F30: =$E30*12 -> 1.0587502e+10 | G30: =$C30*SUMPRODUCT('Biaya Bulanan'!$AI$26:$AI$63,'Biaya Bulanan'!$AK$26:$AK$63) -> 1.6002418e+10 | H30: Merebut talenta senior & mempercepat kota kedua; 6 posisi tambahan. Naikkan hanya bila pendanaan sudah pasti.
A31: Uji: skenario Dasar harus sama dengan lembar 'Biaya Bulanan' (selisih = 0) | E31: =E29-'Biaya Bulanan'!$AA$64 -> 0 | G31: =G29-'Proyeksi 24 Bulan'!$D$55 -> 0
A33: D. CATATAN PENTING
A34: 1. Tanggal penyusunan model: 7 September 2026. Seluruh sumber diakses pada tanggal yang sama (lihat lembar 'Sumber & Catatan').
A35: 2. SELURUH PITA GAJI BERLABEL [ASUMSI]. Diturunkan dari tabel A.4.3 riset yang sendiri merupakan konstruksi penyusun, bukan kutipan salary guide. Wajib divalidasi dengan minimal 5 penawaran gaji riil sebelum dipakai sebagai klaim.
A36: 3. Tarif JKK 0,54% (kantor) dan 0,89% (lapangan) juga [ASUMSI]: kelompok risiko ditetapkan BPJS Ketenagakerjaan berdasarkan jenis usaha, bukan deklarasi perusahaan.
A37: 4. PPh 21 (PP 58/2023, skema TER) TIDAK dimodelkan sebagai biaya perusahaan - dipotong dari upah pekerja. Tidak ada kebijakan gross-up dalam model ini.
A38: 5. Biaya mitra pengemudi (BPJS BPU, BHR 25%) BERADA DI LUAR model ini karena berstatus kemitraan, bukan hubungan kerja. Ini adalah risiko regulasi tingkat pertama - bila status berubah menjadi hubungan kerja, struktur biaya berubah fundamental.
A39: 6. Model tidak memuat kenaikan gaji tahunan, insentif variabel (maks. 20% - DESAIN §4.5), lembur, maupun beban ESOP.
A40: 7. Sel bertulisan BIRU adalah input yang boleh diubah investor; sel berlatar KUNING adalah asumsi kunci. Semua angka lain adalah rumus hidup.
A42: Sumber baris: seluruh angka pada lembar ini adalah tautan hidup ke lembar 'Headcount', 'Biaya Bulanan', 'Proyeksi 24 Bulan' dan 'Biaya Non-Gaji'. Dasar statutori: [S-07] s.d. [S-16]; UMK [S-01][S-03][S-04][S-05][S-06]; pita gaji [S-18][S-19] + [ASUMSI] A.4.3.

Sheet Headcount
A1: AntarKita - Daftar Posisi & Rencana Tenaga Kerja Bertahap
A2: Disusun 7 September 2026. Struktur mengikuti docs/organisasi/DESAIN-ORGANISASI.md §2 dan §3 (keputusan mengikat). Angka orang bersifat KUMULATIF per fase.
A4: No | B4: Direktorat | C4: Posisi | D4: Kota Kerja | E4: Kota Payroll | F4: Level | G4: Bulan Mulai | H4: Orang Fase 0 (bln 1-3) | I4: Orang Fase 1 (bln 4-12) | J4: Orang Fase 2 (bln 13-24) | K4: Catatan peran
A5: 1 | B5: Direksi & Tata Kelola | C5: Direktur Utama (CEO) | D5: Pekanbaru | E5: Pekanbaru | F5: C-Level | G5: 1 | H5: ='Biaya Bulanan'!$V$26 -> 1 | I5: ='Biaya Bulanan'!$W$26 -> 1 | J5: ='Biaya Bulanan'!$X$26 -> 1 | K5: Pemegang KPI kas & runway. Gaji tunai ditahan di P25; selisih dikompensasi ESOP (DESAIN-ORGANISASI §4.4).
A6: 2 | B6: Direksi & Tata Kelola | C6: HR & GA Generalist | D6: Pekanbaru | E6: Pekanbaru | F6: Staf Senior | G6: 3 | H6: ='Biaya Bulanan'!$V$27 -> 1 | I6: ='Biaya Bulanan'!$W$27 -> 1 | J6: ='Biaya Bulanan'!$X$27 -> 1 | K6: Garis putus ke seluruh direktorat: rekrutmen, payroll, BPJS, kantor 2 kota.
A7: 3 | B7: Teknologi | C7: Direktur Teknologi (CTO) | D7: Pekanbaru | E7: Pekanbaru | F7: C-Level | G7: 1 | H7: ='Biaya Bulanan'!$V$28 -> 1 | I7: ='Biaya Bulanan'!$W$28 -> 1 | J7: ='Biaya Bulanan'!$X$28 -> 1 | K7: KPI operasional sendiri: crash-free session & waktu balas API p95 (DESAIN §5).
A8: 4 | B8: Teknologi | C8: Engineering Manager | D8: Remote | E8: Pekanbaru | F8: Manajer | G8: 4 | H8: ='Biaya Bulanan'!$V$29 -> 0 | I8: ='Biaya Bulanan'!$W$29 -> 1 | J8: ='Biaya Bulanan'!$X$29 -> 1 | K8: Rentang kendali 3-6 engineer (DESAIN §1.4). Payroll mengikuti struktur Pekanbaru.
A9: 5 | B9: Teknologi | C9: Mobile Engineer (Senior) | D9: Pekanbaru | E9: Pekanbaru | F9: Senior | G9: 1 | H9: ='Biaya Bulanan'!$V$30 -> 1 | I9: ='Biaya Bulanan'!$W$30 -> 1 | J9: ='Biaya Bulanan'!$X$30 -> 1 | K9: Aplikasi pengguna & mitra; wajib ada sejak Fase 0 untuk uji tertutup.
A10: 6 | B10: Teknologi | C10: Mobile Engineer (Mid) | D10: Remote | E10: Pekanbaru | F10: Mid | G10: 5 | H10: ='Biaya Bulanan'!$V$31 -> 0 | I10: ='Biaya Bulanan'!$W$31 -> 1 | J10: ='Biaya Bulanan'!$X$31 -> 1
A11: 7 | B11: Teknologi | C11: Mobile Engineer (Mid) - gelombang 2 | D11: Remote | E11: Pekanbaru | F11: Mid | G11: 14 | H11: ='Biaya Bulanan'!$V$32 -> 0 | I11: ='Biaya Bulanan'!$W$32 -> 0 | J11: ='Biaya Bulanan'!$X$32 -> 1 | K11: Beban fitur dua kota + AntarFood/AntarSend.
A12: 8 | B12: Teknologi | C12: Backend Engineer (Senior) | D12: Pekanbaru | E12: Pekanbaru | F12: Senior | G12: 1 | H12: ='Biaya Bulanan'!$V$33 -> 1 | I12: ='Biaya Bulanan'!$W$33 -> 1 | J12: ='Biaya Bulanan'!$X$33 -> 1 | K12: Pemilik skema dompet & rekonsiliasi; kritikal untuk pemisahan tugas keuangan.
A13: 9 | B13: Teknologi | C13: Backend Engineer (Senior) - gelombang 2 | D13: Remote | E13: Pekanbaru | F13: Senior | G13: 19 | H13: ='Biaya Bulanan'!$V$34 -> 0 | I13: ='Biaya Bulanan'!$W$34 -> 0 | J13: ='Biaya Bulanan'!$X$34 -> 1
A14: 10 | B14: Teknologi | C14: Backend Engineer (Mid) | D14: Remote | E14: Pekanbaru | F14: Mid | G14: 4 | H14: ='Biaya Bulanan'!$V$35 -> 0 | I14: ='Biaya Bulanan'!$W$35 -> 1 | J14: ='Biaya Bulanan'!$X$35 -> 1
A15: 11 | B15: Teknologi | C15: Backend Engineer (Mid) - gelombang 2 | D15: Remote | E15: Pekanbaru | F15: Mid | G15: 13 | H15: ='Biaya Bulanan'!$V$36 -> 0 | I15: ='Biaya Bulanan'!$W$36 -> 0 | J15: ='Biaya Bulanan'!$X$36 -> 1
A16: 12 | B16: Teknologi | C16: QA Engineer | D16: Pekanbaru | E16: Pekanbaru | F16: Mid | G16: 6 | H16: ='Biaya Bulanan'!$V$37 -> 0 | I16: ='Biaya Bulanan'!$W$37 -> 1 | J16: ='Biaya Bulanan'!$X$37 -> 1 | K16: Gerbang rilis; menahan regresi pada alur pembayaran.
A17: 13 | B17: Teknologi | C17: QA Engineer - gelombang 2 | D17: Remote | E17: Pekanbaru | F17: Mid | G17: 15 | H17: ='Biaya Bulanan'!$V$38 -> 0 | I17: ='Biaya Bulanan'!$W$38 -> 0 | J17: ='Biaya Bulanan'!$X$38 -> 1
A18: 14 | B18: Teknologi | C18: Junior Software Engineer | D18: Pekanbaru | E18: Pekanbaru | F18: Junior | G18: 16 | H18: ='Biaya Bulanan'!$V$39 -> 0 | I18: ='Biaya Bulanan'!$W$39 -> 0 | J18: ='Biaya Bulanan'!$X$39 -> 1 | K18: Jalur kaderisasi lokal; menekan biaya rata-rata per engineer.
A19: 15 | B19: Teknologi | C19: Junior Software Engineer - Padang | D19: Padang | E19: Padang | F19: Junior | G19: 18 | H19: ='Biaya Bulanan'!$V$40 -> 0 | I19: ='Biaya Bulanan'!$W$40 -> 0 | J19: ='Biaya Bulanan'!$X$40 -> 1 | K19: Direkrut di Padang; struktur payroll Padang.
A20: 16 | B20: Teknologi | C20: Product Designer (UI/UX) | D20: Pekanbaru | E20: Pekanbaru | F20: Mid | G20: 2 | H20: ='Biaya Bulanan'!$V$41 -> 1 | I20: ='Biaya Bulanan'!$W$41 -> 1 | J20: ='Biaya Bulanan'!$X$41 -> 1
A21: 17 | B21: Teknologi | C21: Product Designer (UI/UX) - gelombang 2 | D21: Remote | E21: Pekanbaru | F21: Mid | G21: 17 | H21: ='Biaya Bulanan'!$V$42 -> 0 | I21: ='Biaya Bulanan'!$W$42 -> 0 | J21: ='Biaya Bulanan'!$X$42 -> 1
A22: 18 | B22: Teknologi | C22: Data Analyst | D22: Pekanbaru | E22: Pekanbaru | F22: Mid | G22: 13 | H22: ='Biaya Bulanan'!$V$43 -> 0 | I22: ='Biaya Bulanan'!$W$43 -> 0 | J22: ='Biaya Bulanan'!$X$43 -> 1 | K22: Menyusun laporan Portal Eksekutif & audit KPI dari tabel orders/tickets.
A23: 19 | B23: Operasi | C23: Direktur Operasi (COO) | D23: Pekanbaru | E23: Pekanbaru | F23: C-Level | G23: 1 | H23: ='Biaya Bulanan'!$V$44 -> 1 | I23: ='Biaya Bulanan'!$W$44 -> 1 | J23: ='Biaya Bulanan'!$X$44 -> 1 | K23: Gaji tunai ditahan di P25 (DESAIN §4.4).
A24: 20 | B24: Operasi | C24: City Manager Pekanbaru | D24: Pekanbaru | E24: Pekanbaru | F24: Manajer | G24: 2 | H24: ='Biaya Bulanan'!$V$45 -> 1 | I24: ='Biaya Bulanan'!$W$45 -> 1 | J24: ='Biaya Bulanan'!$X$45 -> 1 | K24: P&L tingkat kota; target likuiditas pasar Fase 1.
A25: 21 | B25: Operasi | C25: Ops Supervisor Pekanbaru | D25: Pekanbaru | E25: Pekanbaru | F25: Supervisor | G25: 4 | H25: ='Biaya Bulanan'!$V$46 -> 0 | I25: ='Biaya Bulanan'!$W$46 -> 1 | J25: ='Biaya Bulanan'!$X$46 -> 1
A26: 22 | B26: Operasi | C26: Partner Acquisition Pekanbaru | D26: Pekanbaru | E26: Pekanbaru | F26: Staf | G26: 4 | H26: ='Biaya Bulanan'!$V$47 -> 0 | I26: ='Biaya Bulanan'!$W$47 -> 2 | J26: ='Biaya Bulanan'!$X$47 -> 2 | K26: 2 orang. Target dihitung dari mitra AKTIF (hanya +-20% mitra terdaftar aktif, [S-58]). Insentif variabel maks. 20% (DESAIN §4.5) TIDAK dimodelkan di sini.
A27: 23 | B27: Operasi | C27: Head of Customer Experience | D27: Pekanbaru | E27: Pekanbaru | F27: Head | G27: 4 | H27: ='Biaya Bulanan'!$V$48 -> 0 | I27: ='Biaya Bulanan'!$W$48 -> 1 | J27: ='Biaya Bulanan'!$X$48 -> 1 | K27: Merangkap CS Lead pada Fase 1 (tidak ada peran yang hanya mengawasi, DESAIN §1.5).
A28: 24 | B28: Operasi | C28: CS Agent Pekanbaru (shift) | D28: Pekanbaru | E28: Pekanbaru | F28: Staf | G28: 5 | H28: ='Biaya Bulanan'!$V$49 -> 0 | I28: ='Biaya Bulanan'!$W$49 -> 3 | J28: ='Biaya Bulanan'!$X$49 -> 3 | K28: 3 orang untuk 3 shift. Gaji pokok P25 = lantai UMK Pekanbaru.
A29: 25 | B29: Operasi | C29: Trust & Safety Officer | D29: Pekanbaru | E29: Pekanbaru | F29: Staf Senior | G29: 6 | H29: ='Biaya Bulanan'!$V$50 -> 0 | I29: ='Biaya Bulanan'!$W$50 -> 1 | J29: ='Biaya Bulanan'!$X$50 -> 1 | K29: Anti-fraud, penanganan insiden, tombol SOS. Wajib ada sebelum volume order naik.
A30: 26 | B30: Operasi | C30: City Manager Padang | D30: Padang | E30: Padang | F30: Manajer | G30: 13 | H30: ='Biaya Bulanan'!$V$51 -> 0 | I30: ='Biaya Bulanan'!$W$51 -> 0 | J30: ='Biaya Bulanan'!$X$51 -> 1 | K30: Pembuka kota kedua; pola +1 City Manager + 2 Ops per kota baru (DESAIN §1.1).
A31: 27 | B31: Operasi | C31: Partner Acquisition Padang | D31: Padang | E31: Padang | F31: Staf | G31: 13 | H31: ='Biaya Bulanan'!$V$52 -> 0 | I31: ='Biaya Bulanan'!$W$52 -> 0 | J31: ='Biaya Bulanan'!$X$52 -> 1
A32: 28 | B32: Operasi | C32: Ops Supervisor Padang | D32: Padang | E32: Padang | F32: Supervisor | G32: 14 | H32: ='Biaya Bulanan'!$V$53 -> 0 | I32: ='Biaya Bulanan'!$W$53 -> 0 | J32: ='Biaya Bulanan'!$X$53 -> 1
A33: 29 | B33: Operasi | C33: CS Agent Padang (shift) | D33: Padang | E33: Padang | F33: Staf | G33: 14 | H33: ='Biaya Bulanan'!$V$54 -> 0 | I33: ='Biaya Bulanan'!$W$54 -> 0 | J33: ='Biaya Bulanan'!$X$54 -> 2 | K33: 2 orang. CS Pekanbaru menutup shift ketiga lintas kota.
A34: 30 | B34: Operasi | C34: Partner Acquisition Padang - gelombang 2 | D34: Padang | E34: Padang | F34: Staf | G34: 15 | H34: ='Biaya Bulanan'!$V$55 -> 0 | I34: ='Biaya Bulanan'!$W$55 -> 0 | J34: ='Biaya Bulanan'!$X$55 -> 1
A35: 31 | B35: Growth & Partnership | C35: Head of Growth & Partnership | D35: Pekanbaru | E35: Pekanbaru | F35: Head | G35: 4 | H35: ='Biaya Bulanan'!$V$56 -> 0 | I35: ='Biaya Bulanan'!$W$56 -> 1 | J35: ='Biaya Bulanan'!$X$56 -> 1 | K35: Memikul target pendapatan non-komisi - penting karena batas potongan ojek roda dua maks. 8% (Perpres 27/2026, [S-25]).
A36: 32 | B36: Growth & Partnership | C36: Digital Marketing Staff | D36: Pekanbaru | E36: Pekanbaru | F36: Staf | G36: 13 | H36: ='Biaya Bulanan'!$V$57 -> 0 | I36: ='Biaya Bulanan'!$W$57 -> 0 | J36: ='Biaya Bulanan'!$X$57 -> 1
A37: 33 | B37: Growth & Partnership | C37: Merchant Acquisition Officer | D37: Pekanbaru | E37: Pekanbaru | F37: Staf | G37: 13 | H37: ='Biaya Bulanan'!$V$58 -> 0 | I37: ='Biaya Bulanan'!$W$58 -> 0 | J37: ='Biaya Bulanan'!$X$58 -> 1 | K37: Akuisisi merchant AntarFood/AntarShop; pita disamakan dengan Field/Driver Acquisition officer.
A38: 34 | B38: Keuangan | C38: Head of Finance | D38: Pekanbaru | E38: Pekanbaru | F38: C-Level | G38: 2 | H38: ='Biaya Bulanan'!$V$59 -> 1 | I38: ='Biaya Bulanan'!$W$59 -> 1 | J38: ='Biaya Bulanan'!$X$59 -> 1 | K38: Merangkap Direktur Keuangan pada Fase 1-2 (DESAIN §2). Gaji tunai ditahan di P25.
A39: 35 | B39: Keuangan | C39: Finance & Accounting Staff | D39: Pekanbaru | E39: Pekanbaru | F39: Staf | G39: 4 | H39: ='Biaya Bulanan'!$V$60 -> 0 | I39: ='Biaya Bulanan'!$W$60 -> 1 | J39: ='Biaya Bulanan'!$X$60 -> 1 | K39: Pelaksana pencairan - terpisah dari penyetuju dan perekonsiliasi (DESAIN §6).
A40: 36 | B40: Keuangan | C40: Treasury/Settlement Officer | D40: Pekanbaru | E40: Pekanbaru | F40: Staf Senior | G40: 13 | H40: ='Biaya Bulanan'!$V$61 -> 0 | I40: ='Biaya Bulanan'!$W$61 -> 0 | J40: ='Biaya Bulanan'!$X$61 -> 1 | K40: Rekonsiliasi dompet & payout mitra; pemisah tugas ketiga. Relevan dengan ambang dana float Rp1 miliar ([S-31]).
A41: 37 | B41: Keuangan | C41: Finance & Accounting Staff - Padang | D41: Padang | E41: Padang | F41: Staf | G41: 16 | H41: ='Biaya Bulanan'!$V$62 -> 0 | I41: ='Biaya Bulanan'!$W$62 -> 0 | J41: ='Biaya Bulanan'!$X$62 -> 1
A42: 38 | B42: Legal & Kepatuhan | C42: Head of Legal & Compliance (merangkap DPO) | D42: Pekanbaru | E42: Pekanbaru | F42: Head | G42: 4 | H42: ='Biaya Bulanan'!$V$63 -> 0 | I42: ='Biaya Bulanan'!$W$63 -> 1 | J42: ='Biaya Bulanan'!$X$63 -> 1 | K42: Wajib sejak Fase 1: UU 27/2022 Ps.53 + Putusan MK 151/PUU-XXII/2024 ([S-37],[S-39]); juga menangani PSE/TDPSE dan KBLI.
C43: TOTAL HEADCOUNT (kumulatif) | H43: =SUM(H5:H42) -> 9 | I43: =SUM(I5:I42) -> 24 | J43: =SUM(J5:J42) -> 42
C44: Target DESAIN-ORGANISASI §3 (mengikat) | H44: 9 | I44: 24 | J44: 42
C45: UJI KECOCOKAN (harus 0) | H45: =H43-H44 -> 0 | I45: =I43-I44 -> 0 | J45: =J43-J44 -> 0
A47: REKAP HEADCOUNT PER DIREKTORAT
A48: Direktorat | H48: Fase 0 | I48: Fase 1 | J48: Fase 2
A49: Direksi & Tata Kelola | H49: =SUMIF($B$5:$B$42,$A49,$H$5:$H$42) -> 2 | I49: =SUMIF($B$5:$B$42,$A49,$I$5:$I$42) -> 2 | J49: =SUMIF($B$5:$B$42,$A49,$J$5:$J$42) -> 2
A50: Teknologi | H50: =SUMIF($B$5:$B$42,$A50,$H$5:$H$42) -> 4 | I50: =SUMIF($B$5:$B$42,$A50,$I$5:$I$42) -> 8 | J50: =SUMIF($B$5:$B$42,$A50,$J$5:$J$42) -> 16
A51: Operasi | H51: =SUMIF($B$5:$B$42,$A51,$H$5:$H$42) -> 2 | I51: =SUMIF($B$5:$B$42,$A51,$I$5:$I$42) -> 10 | J51: =SUMIF($B$5:$B$42,$A51,$J$5:$J$42) -> 16
A52: Growth & Partnership | H52: =SUMIF($B$5:$B$42,$A52,$H$5:$H$42) -> 0 | I52: =SUMIF($B$5:$B$42,$A52,$I$5:$I$42) -> 1 | J52: =SUMIF($B$5:$B$42,$A52,$J$5:$J$42) -> 3
A53: Keuangan | H53: =SUMIF($B$5:$B$42,$A53,$H$5:$H$42) -> 1 | I53: =SUMIF($B$5:$B$42,$A53,$I$5:$I$42) -> 2 | J53: =SUMIF($B$5:$B$42,$A53,$J$5:$J$42) -> 4
A54: Legal & Kepatuhan | H54: =SUMIF($B$5:$B$42,$A54,$H$5:$H$42) -> 0 | I54: =SUMIF($B$5:$B$42,$A54,$I$5:$I$42) -> 1 | J54: =SUMIF($B$5:$B$42,$A54,$J$5:$J$42) -> 1
A55: TOTAL | H55: =SUM(H49:H54) -> 9 | I55: =SUM(I49:I54) -> 24 | J55: =SUM(J49:J54) -> 42
A57: UJI RASIO PRODUK : OPERASI & KOMERSIAL : DUKUNGAN (target DESAIN §1.2 = 40 : 45 : 15)
A58: Kelompok | H58: Fase 0 | I58: Fase 1 | J58: Fase 2
A59: Produk & Teknologi (Direktorat Teknologi) | H59: =(SUMIF($B$5:$B$42,"Teknologi",$H$5:$H$42))/H$43 -> 0.44444444 | I59: =(SUMIF($B$5:$B$42,"Teknologi",$I$5:$I$42))/I$43 -> 0.33333333 | J59: =(SUMIF($B$5:$B$42,"Teknologi",$J$5:$J$42))/J$43 -> 0.38095238
A60: Operasi & Komersial (Operasi + Growth & Partnership) | H60: =(SUMIF($B$5:$B$42,"Operasi",$H$5:$H$42)+SUMIF($B$5:$B$42,"Growth & Partnership",$H$5:$H$42))/H$43 -> 0.22222222 | I60: =(SUMIF($B$5:$B$42,"Operasi",$I$5:$I$42)+SUMIF($B$5:$B$42,"Growth & Partnership",$I$5:$I$42))/I$43 -> 0.45833333 | J60: =(SUMIF($B$5:$B$42,"Operasi",$J$5:$J$42)+SUMIF($B$5:$B$42,"Growth & Partnership",$J$5:$J$42))/J$43 -> 0.45238095
A61: Dukungan & Tata Kelola (Direksi + Keuangan + Legal) | H61: =(SUMIF($B$5:$B$42,"Direksi & Tata Kelola",$H$5:$H$42)+SUMIF($B$5:$B$42,"Keuangan",$H$5:$H$42)+SUMIF($B$5:$B$42,"Legal & Kepatuhan",$H$5:$H$42))/H$43 -> 0.33333333 | I61: =(SUMIF($B$5:$B$42,"Direksi & Tata Kelola",$I$5:$I$42)+SUMIF($B$5:$B$42,"Keuangan",$I$5:$I$42)+SUMIF($B$5:$B$42,"Legal & Kepatuhan",$I$5:$I$42))/I$43 -> 0.20833333 | J61: =(SUMIF($B$5:$B$42,"Direksi & Tata Kelola",$J$5:$J$42)+SUMIF($B$5:$B$42,"Keuangan",$J$5:$J$42)+SUMIF($B$5:$B$42,"Legal & Kepatuhan",$J$5:$J$42))/J$43 -> 0.16666667
A63: Sumber baris: struktur & total per fase dari docs/organisasi/DESAIN-ORGANISASI.md §2-§3 (9 / 24 / 42 orang, mengikat). Kolom Orang Fase 0/1/2 adalah TAUTAN HIDUP ke lembar 'Biaya Bulanan' agar tidak ada dua sumber angka.
A64: Dewan Komisaris TIDAK dihitung sebagai karyawan (honorarium diperlakukan sebagai biaya tata kelola, di luar cakupan model ini). Mitra pengemudi berstatus KEMITRAAN, bukan hubungan kerja - lihat lembar 'Sumber & Catatan'.
A65: Deviasi rasio terhadap target 40:45:15 dijelaskan di lembar 'Sumber & Catatan' (Catatan koreksi penyusun).

Sheet Pita Gaji
A1: AntarKita - Pita Gaji per Posisi, Pekanbaru & Padang
A2: Disusun 7 September 2026. SELURUH ANGKA PADA LEMBAR INI ADALAH [ASUMSI] - diturunkan dari tabel A.4.3 docs/riset/RISET-KOMPENSASI-REGULASI.md. Bukan kutipan benchmark pasar. Wajib divalidasi dengan minimal 5 penawaran gaji riil.
C4: PEKANBARU - [ASUMSI] | F4: PADANG - [ASUMSI]
A5: Kunci Pita (posisi rujukan) | B5: Status data | C5: P25 [ASUMSI] (Rp) | D5: P50 [ASUMSI] (Rp) | E5: P75 [ASUMSI] (Rp) | F5: P25 [ASUMSI] (Rp) | G5: P50 [ASUMSI] (Rp) | H5: P75 [ASUMSI] (Rp) | I5: Rasio P50 : UMK Pekanbaru | J5: Rasio P50 : UMP Padang | K5: Uji kewajaran: P25 >= UMK kota? | L5: Basis penurunan / sumber
A6: CEO / Direktur Utama | B6: A.4.3 riset | C6: 35000000 | D6: =(C6+E6)/2 -> 47500000 | E6: 60000000 | F6: 35000000 | G6: =(F6+H6)/2 -> 47500000 | H6: 60000000 | I6: =D6/UMK_Pekanbaru -> 11.880407 | J6: =G6/UMP_Padang -> 14.92324 | K6: =IF(AND(C6>=UMK_Pekanbaru,F6>=UMP_Padang),"OK","PERIKSA") -> OK | L6: A.4.3: tidak ditemukan sumber kredibel; asumsi murni, C-level dikompensasi ekuitas pra-pendanaan
A7: CTO | B7: A.4.3 riset | C7: 30000000 | D7: =(C7+E7)/2 -> 42500000 | E7: 55000000 | F7: 30000000 | G7: =(F7+H7)/2 -> 42500000 | H7: 55000000 | I7: =D7/UMK_Pekanbaru -> 10.629838 | J7: =G7/UMP_Padang -> 13.352372 | K7: =IF(AND(C7>=UMK_Pekanbaru,F7>=UMP_Padang),"OK","PERIKSA") -> OK | L7: A.4.3: ~0,55 x Head of Engineering Jakarta 2025 (Rp81 jt) [S-19]
A8: Engineering Manager | B8: A.4.3 riset | C8: 20000000 | D8: =(C8+E8)/2 -> 27500000 | E8: 35000000 | F8: 20000000 | G8: =(F8+H8)/2 -> 27500000 | H8: 35000000 | I8: =D8/UMK_Pekanbaru -> 6.8781305 | J8: =G8/UMP_Padang -> 8.6397703 | K8: =IF(AND(C8>=UMK_Pekanbaru,F8>=UMP_Padang),"OK","PERIKSA") -> OK | L8: A.4.3: ~0,40 x Engineering Manager Jakarta 2025 (Rp67 jt) [S-19]
A9: Senior Software Engineer | B9: A.4.3 riset | C9: 15000000 | D9: =(C9+E9)/2 -> 20000000 | E9: 25000000 | F9: 15000000 | G9: =(F9+H9)/2 -> 20000000 | H9: 25000000 | I9: =D9/UMK_Pekanbaru -> 5.0022767 | J9: =G9/UMP_Padang -> 6.2834693 | K9: =IF(AND(C9>=UMK_Pekanbaru,F9>=UMP_Padang),"OK","PERIKSA") -> OK | L9: A.4.3: ~0,55 x Senior SWE Jakarta 2023 (Rp35 jt) [S-18] + inflasi upah
A10: Mid Software Engineer | B10: A.4.3 riset | C10: 9000000 | D10: =(C10+E10)/2 -> 12000000 | E10: 15000000 | F10: 9000000 | G10: =(F10+H10)/2 -> 12000000 | H10: 15000000 | I10: =D10/UMK_Pekanbaru -> 3.001366 | J10: =G10/UMP_Padang -> 3.7700816 | K10: =IF(AND(C10>=UMK_Pekanbaru,F10>=UMP_Padang),"OK","PERIKSA") -> OK | L10: A.4.3: ~0,55 x Back-end Developer Jakarta 2025 (Rp25 jt) [S-19]
A11: Junior Software Engineer | B11: A.4.3 riset | C11: 6000000 | D11: =(C11+E11)/2 -> 7500000 | E11: 9000000 | F11: 5500000 | G11: =(F11+H11)/2 -> 7000000 | H11: 8500000 | I11: =D11/UMK_Pekanbaru -> 1.8758538 | J11: =G11/UMP_Padang -> 2.1992143 | K11: =IF(AND(C11>=UMK_Pekanbaru,F11>=UMP_Padang),"OK","PERIKSA") -> OK | L11: A.4.3: 1,5-2,3 x UMK kota [S-05]/[S-03]
A12: Product Designer / UI-UX | B12: A.4.3 riset | C12: 8000000 | D12: =(C12+E12)/2 -> 13000000 | E12: 18000000 | F12: 8000000 | G12: =(F12+H12)/2 -> 13000000 | H12: 18000000 | I12: =D12/UMK_Pekanbaru -> 3.2514799 | J12: =G12/UMP_Padang -> 4.084255 | K12: =IF(AND(C12>=UMK_Pekanbaru,F12>=UMP_Padang),"OK","PERIKSA") -> OK | L12: A.4.3: ~0,25-0,45 x UX/UI Designer Jakarta 2025 (Rp43 jt) [S-19]
A13: QA Engineer | B13: A.4.3 riset | C13: 7000000 | D13: =(C13+E13)/2 -> 10000000 | E13: 13000000 | F13: 6500000 | G13: =(F13+H13)/2 -> 9250000 | H13: 12000000 | I13: =D13/UMK_Pekanbaru -> 2.5011384 | J13: =G13/UMP_Padang -> 2.9061045 | K13: =IF(AND(C13>=UMK_Pekanbaru,F13>=UMP_Padang),"OK","PERIKSA") -> OK | L13: A.4.3: ~0,30-0,50 x QA Engineer Jakarta 2023 (Rp25 jt) [S-18]
A14: Data Analyst | B14: A.4.3 riset | C14: 8000000 | D14: =(C14+E14)/2 -> 11500000 | E14: 15000000 | F14: 8000000 | G14: =(F14+H14)/2 -> 11500000 | H14: 15000000 | I14: =D14/UMK_Pekanbaru -> 2.8763091 | J14: =G14/UMP_Padang -> 3.6129948 | K14: =IF(AND(C14>=UMK_Pekanbaru,F14>=UMP_Padang),"OK","PERIKSA") -> OK | L14: A.4.3: di bawah Lead Data Scientist [S-19]; level analyst tidak tersedia di sumber
A15: Head of Operations | B15: A.4.3 riset | C15: 20000000 | D15: =(C15+E15)/2 -> 27500000 | E15: 35000000 | F15: 20000000 | G15: =(F15+H15)/2 -> 27500000 | H15: 35000000 | I15: =D15/UMK_Pekanbaru -> 6.8781305 | J15: =G15/UMP_Padang -> 8.6397703 | K15: =IF(AND(C15>=UMK_Pekanbaru,F15>=UMP_Padang),"OK","PERIKSA") -> OK | L15: A.4.3: tidak ditemukan sumber kredibel; anchor setara Engineering Manager lokal
A16: City / Area Manager | B16: A.4.3 riset | C16: 10000000 | D16: =(C16+E16)/2 -> 14000000 | E16: 18000000 | F16: 9000000 | G16: =(F16+H16)/2 -> 12500000 | H16: 16000000 | I16: =D16/UMK_Pekanbaru -> 3.5015937 | J16: =G16/UMP_Padang -> 3.9271683 | K16: =IF(AND(C16>=UMK_Pekanbaru,F16>=UMP_Padang),"OK","PERIKSA") -> OK | L16: A.4.3: 2,5-4,5 x UMK kota [S-05]/[S-03]
A17: Ops Supervisor | B17: A.4.3 riset | C17: 6000000 | D17: =(C17+E17)/2 -> 7500000 | E17: 9000000 | F17: 5000000 | G17: =(F17+H17)/2 -> 6500000 | H17: 8000000 | I17: =D17/UMK_Pekanbaru -> 1.8758538 | J17: =G17/UMP_Padang -> 2.0421275 | K17: =IF(AND(C17>=UMK_Pekanbaru,F17>=UMP_Padang),"OK","PERIKSA") -> OK | L17: A.4.3: 1,5-2,3 x UMK kota [S-05]/[S-03]
... A28: Treasury / Settlement Officer | B28: TURUNAN penyusun model | C28: 6250000 | D28: =(C28+E28)/2 -> 8125000 | E28: 10000000 | F28: 5000000 | G28: =(F28+H28)/2 -> 6875000 | H28: 8750000 | I28: =D28/UMK_Pekanbaru -> 2.0321749 | J28: =G28/UMP_Padang -> 2.1599426 | K28: =IF(AND(C28>=UMK_Pekanbaru,F28>=UMP_Padang),"OK","PERIKSA") -> OK | L28: TIDAK ADA baris di A.4.3. [ASUMSI] 1,25 x pita Finance & Accounting staff A.4.3
A30: Metode P50: titik tengah aritmetik antara P25 dan P75 (bukan median pasar - tidak ada data pasar yang dapat dikutip).
A31: Jumlah baris dengan status 'PERIKSA' (harus 0): | D31: =COUNTIF(K6:K28,"PERIKSA") -> 0
A33: Sumber baris: tabel A.4.3 docs/riset/RISET-KOMPENSASI-REGULASI.md - seluruhnya konstruksi penyusun riset, diturunkan dari [S-18] (Michael Page 2023), [S-19] (Michael Page 2025) dan UMK kota [S-01][S-03][S-04][S-05][S-06]. Faktor geografis Jakarta -> Pekanbaru/Padang (0,45-0,70) adalah [ASUMSI] tanpa dasar empiris.
A34: Tiga baris berstatus 'TURUNAN penyusun model' (Head of Customer Experience, Trust & Safety Officer, Treasury / Settlement Officer) TIDAK ADA di A.4.3 dan merupakan asumsi tambahan penyusun model biaya - dasar penurunannya ditulis di kolom terakhir.
A35: Posisi berstatus Remote memakai struktur payroll Pekanbaru (kota induk). UMK Pekanbaru 2026 Rp3.998.179; UMK/UMP Padang 2026 Rp3.182.955 - selisih 25,6%.

Sheet Biaya Bulanan
A1: AntarKita - Biaya SDM Bulanan per Posisi (total cost to company)
A2: Disusun 7 September 2026. Seluruh pita gaji berlabel [ASUMSI] (lihat lembar 'Pita Gaji'). Tulisan BIRU = input yang boleh diubah investor; tulisan hitam = rumus hidup.
A4: BLOK ASUMSI (bernama) - seluruh rumus di berkas ini merujuk ke sel-sel di bawah
A5: Parameter | D5: Nilai | E5: Dasar hukum / sumber / status data
A6: UMK Kota Pekanbaru 2026 (Rp/bulan) | D6: 3998179.5 | E6: [S-01] [S-05] [S-06] - berlaku 1 Januari 2026
A7: UMK/UMP Kota Padang 2026 (Rp/bulan) | D7: 3182955 | E7: [S-03] [S-04] - Sumbar tidak menetapkan UMK tersendiri
A8: Tunjangan tetap (% gaji pokok) | D8: 0.1 | E8: [ASUMSI] penyusun model - transport & komunikasi. Tidak ada sumber. Gaji pokok tetap 90,9% dari upah, memenuhi batas min. 75% PP 36/2021 [S-14]
A9: JKK pemberi kerja - karyawan kantor | D9: 0.0054 | E9: [ASUMSI] kelompok risiko RENDAH, PP 44/2015 [S-08]. Penetapan final oleh BPJS Ketenagakerjaan
A10: JKK pemberi kerja - staf lapangan | D10: 0.0089 | E10: [ASUMSI] kelompok risiko SEDANG, PP 44/2015 [S-08]. Penetapan final oleh BPJS Ketenagakerjaan
A11: JKM pemberi kerja | D11: 0.003 | E11: PP 44/2015 [S-07] [S-08] - tanpa batas upah
A12: JHT pemberi kerja | D12: 0.037 | E12: PP 46/2015 [S-07] - tanpa batas upah
A13: JP pemberi kerja | D13: 0.02 | E13: PP 45/2015 [S-07]
A14: Plafon upah dasar JP (Rp/bulan) | D14: 11086300 | E14: [S-09] [S-10] - berlaku sejak Maret 2026
A15: BPJS Kesehatan pemberi kerja | D15: 0.04 | E15: Perpres 64/2020 Pasal 30 [S-12] (total 5%: 4% pemberi kerja + 1% pekerja)
A16: Plafon upah dasar BPJS Kesehatan (Rp/bulan) | D16: 12000000 | E16: Perpres 64/2020 Pasal 30 & 32 [S-12] [S-13]. Batas bawah = UMK/UMP kota
A17: Akrual THR per bulan (% upah) | D17: 0.0833 | E17: Setara 1/12 upah sebulan. PP 36/2021 [S-14], Permenaker 6/2016 [S-15], SE Menaker M/3/HK.04.00/III/2026 [S-16]
A18: Pita gaji aktif untuk seluruh posisi non-C-Level | D18: P50 | E18: Kebijakan penawaran default (DESAIN-ORGANISASI §4.2). Ubah ke P25 / P75 untuk skenario Hemat / Agresif
A19: Pita gaji untuk posisi C-Level | D19: P25 | E19: DESAIN-ORGANISASI §4.4 - gaji tunai C-level ditahan di P25, selisih dikompensasi ESOP
A21: PPh 21 (skema TER, PP 58/2023 [S-17]) TIDAK dimodelkan sebagai biaya perusahaan - dipotong dari upah pekerja. Tidak ada kebijakan gross-up dalam model ini; bila kelak diterapkan, biaya perusahaan naik di atas angka lembar ini.
A22: Iuran pekerja (JHT 2% + JP 1% + JKN 1%) juga TIDAK termasuk - itu potongan upah, bukan beban pemberi kerja. Mitra pengemudi (BPU/BHR) berada DI LUAR cakupan model ini karena berstatus kemitraan, bukan hubungan kerja.
AC24: BLOK BANTU SKENARIO & SENSITIVITAS (dipakai lembar Ringkasan dan Sensitivitas)
A25: No | B25: Direktorat | C25: Posisi | D25: Kota Kerja | E25: Kota Payroll | F25: Level | G25: Kunci Pita Gaji | H25: Kelompok Risiko JKK | I25: Bulan Mulai | J25: Pita Dipakai | K25: Gaji Pokok /orang (Rp) | L25: Tunjangan Tetap /orang (Rp) | M25: Upah Dasar Perhitungan (Rp) | N25: JKK Pemberi Kerja (Rp) | O25: JKM Pemberi Kerja (Rp) | P25: JHT Pemberi Kerja (Rp) | Q25: JP Pemberi Kerja (Rp) | R25: BPJS Kesehatan Pemberi Kerja (Rp) | S25: Akrual THR (Rp) | T25: TOTAL COST TO COMPANY /orang (Rp) | U25: Rasio CTC : Gaji Pokok | V25: Orang Fase 0 | W25: Orang Fase 1 | X25: Orang Fase 2 | Y25: Biaya/bulan Fase 0 (Rp) | Z25: Biaya/bulan Fase 1 (Rp) | AA25: Biaya/bulan Fase 2 (Rp) | AC25: Gaji P25 (Rp) | AD25: Gaji P50 (Rp) | AE25: Gaji P75 (Rp) | AF25: Gaji pita C-Level (Rp) | AG25: CTC skenario P25 (Rp) | AH25: CTC skenario P50 (Rp) | AI25: CTC skenario P75 (Rp) | AJ25: Bulan-orang bln 1-12 | AK25: Bulan-orang bln 1-24 | AL25: Uji upah vs UMK
A26: 1 | B26: Direksi & Tata Kelola | C26: Direktur Utama (CEO) | D26: Pekanbaru | E26: Pekanbaru | F26: C-Level | G26: CEO / Direktur Utama | H26: Kantor | I26: 1 | J26: =IF($F26="C-Level",Pita_CLevel,Pita_Aktif) -> P25 | K26: =IF($J26="P25",$AC26,IF($J26="P50",$AD26,$AE26)) -> 35000000 | L26: =$K26*Tunjangan_Pct -> 3500000 | M26: =$K26+$L26 -> 38500000 | N26: =$M26*IF($H26="Lapangan",Tarif_JKK_Lapangan,Tarif_JKK_Kantor) -> 207900 | O26: =$M26*Tarif_JKM -> 115500 | P26: =$M26*Tarif_JHT -> 1424500 | Q26: =MIN($M26,Plafon_JP)*Tarif_JP -> 221726 | R26: =MIN(MAX($M26,IF($E26="Padang",UMP_Padang,UMK_Pekanbaru)),Plafon_JKN)*Tarif_JKN -> 480000 | S26: =$M26*Tarif_THR -> 3207050 | T26: =SUM($M26:$S26) -> 44156676 | U26: =$T26/$K26 -> 1.2616193 | V26: 1 | W26: 1 | X26: 1 | Y26: =$T26*$V26 -> 44156676 | Z26: =$T26*$W26 -> 44156676 | AA26: =$T26*$X26 -> 44156676 | AC26: =IF($E26="Padang",INDEX('Pita Gaji'!$F$6:$F$28,MATCH($G26,'Pita Gaji'!$A$6:$A$28,0)),INDEX('Pita Gaji'!$C$6:$C$28,MATCH($G26,'Pita Gaji'!$A$6:$A$28,0))) -> 35000000 | AD26: =IF($E26="Padang",INDEX('Pita Gaji'!$G$6:$G$28,MATCH($G26,'Pita Gaji'!$A$6:$A$28,0)),INDEX('Pita Gaji'!$D$6:$D$28,MATCH($G26,'Pita Gaji'!$A$6:$A$28,0))) -> 47500000 | AE26: =IF($E26="Padang",INDEX('Pita Gaji'!$H$6:$H$28,MATCH($G26,'Pita Gaji'!$A$6:$A$28,0)),INDEX('Pita Gaji'!$E$6:$E$28,MATCH($G26,'Pita Gaji'!$A$6:$A$28,0))) -> 60000000 | AF26: =IF(Pita_CLevel="P25",$AC26,IF(Pita_CLevel="P50",$AD26,$AE26)) -> 35000000 | AG26: =(IF($F26="C-Level",$AF26,$AC26)*(1+Tunjangan_Pct))*(1+IF($H26="Lapangan",Tarif_JKK_Lapangan,Tarif_JKK_Kantor)+Tarif_JKM+Tarif_JHT+Tarif_THR)+MIN((IF($F26="C-Level",$AF26,$AC26)*(1+Tunjangan_Pct)),Plafon_JP)*Tarif_JP+MIN(MAX((IF($F26="C-Level",$AF26,$AC26)*(1+Tunjangan_Pct)),IF($E26="Padang",UMP_Padang,UMK_Pekanbaru)),Plafon_JKN)*Tarif_JKN -> 44156676 | AH26: =(IF($F26="C-Level",$AF26,$AD26)*(1+Tunjangan_Pct))*(1+IF($H26="Lapangan",Tarif_JKK_Lapangan,Tarif_JKK_Kantor)+Tarif_JKM+Tarif_JHT+Tarif_THR)+MIN((IF($F26="C-Level",$AF26,$AD26)*(1+Tunjangan_Pct)),Plafon_JP)*Tarif_JP+MIN(MAX((IF($F26="C-Level",$AF26,$AD26)*(1+Tunjangan_Pct)),IF($E26="Padang",UMP_Padang,UMK_Pekanbaru)),Plafon_JKN)*Tarif_JKN -> 44156676 | AI26: =(IF($F26="C-Level",$AF26,$AE26)*(1+Tunjangan_Pct))*(1+IF($H26="Lapangan",Tarif_JKK_Lapangan,Tarif_JKK_Kantor)+Tarif_JKM+Tarif_JHT+Tarif_THR)+MIN((IF($F26="C-Level",$AF26,$AE26)*(1+Tunjangan_Pct)),Plafon_JP)*Tarif_JP+MIN(MAX((IF($F26="C-Level",$AF26,$AE26)*(1+Tunjangan_Pct)),IF($E26="Padang",UMP_Padang,UMK_Pekanbaru)),Plafon_JKN)*Tarif_JKN -> 44156676 | AJ26: =$V26*MAX(0,MIN(3,4-$I26))+$W26*MAX(0,MIN(9,13-MAX($I26,4))) -> 12 | AK26: =$AJ26+$X26*MAX(0,MIN(12,25-MAX($I26,13))) -> 24 | AL26: =IF($M26>=IF($E26="Padang",UMP_Padang,UMK_Pekanbaru),"OK","DI BAWAH UMK") -> OK
A27: 2 | B27: Direksi & Tata Kelola | C27: HR & GA Generalist | D27: Pekanbaru | E27: Pekanbaru | F27: Staf Senior | G27: HR generalist | H27: Kantor | I27: 3 | J27: =IF($F27="C-Level",Pita_CLevel,Pita_Aktif) -> P50 | K27: =IF($J27="P25",$AC27,IF($J27="P50",$AD27,$AE27)) -> 8500000 | L27: =$K27*Tunjangan_Pct -> 850000 | M27: =$K27+$L27 -> 9350000 | N27: =$M27*IF($H27="Lapangan",Tarif_JKK_Lapangan,Tarif_JKK_Kantor) -> 50490 | O27: =$M27*Tarif_JKM -> 28050 | P27: =$M27*Tarif_JHT -> 345950 | Q27: =MIN($M27,Plafon_JP)*Tarif_JP -> 187000 | R27: =MIN(MAX($M27,IF($E27="Padang",UMP_Padang,UMK_Pekanbaru)),Plafon_JKN)*Tarif_JKN -> 374000 | S27: =$M27*Tarif_THR -> 778855 | T27: =SUM($M27:$S27) -> 11114345 | U27: =$T27/$K27 -> 1.30757 | V27: 1 | W27: 1 | X27: 1 | Y27: =$T27*$V27 -> 11114345 | Z27: =$T27*$W27 -> 11114345 | AA27: =$T27*$X27 -> 11114345 | AC27: =IF($E27="Padang",INDEX('Pita Gaji'!$F$6:$F$28,MATCH($G27,'Pita Gaji'!$A$6:$A$28,0)),INDEX('Pita Gaji'!$C$6:$C$28,MATCH($G27,'Pita Gaji'!$A$6:$A$28,0))) -> 6000000 | AD27: =IF($E27="Padang",INDEX('Pita Gaji'!$G$6:$G$28,MATCH($G27,'Pita Gaji'!$A$6:$A$28,0)),INDEX('Pita Gaji'!$D$6:$D$28,MATCH($G27,'Pita Gaji'!$A$6:$A$28,0))) -> 8500000 | AE27: =IF($E27="Padang",INDEX('Pita Gaji'!$H$6:$H$28,MATCH($G27,'Pita Gaji'!$A$6:$A$28,0)),INDEX('Pita Gaji'!$E$6:$E$28,MATCH($G27,'Pita Gaji'!$A$6:$A$28,0))) -> 11000000 | AF27: =IF(Pita_CLevel="P25",$AC27,IF(Pita_CLevel="P50",$AD27,$AE27)) -> 6000000 | AG27: =(IF($F27="C-Level",$AF27,$AC27)*(1+Tunjangan_Pct))*(1+IF($H27="Lapangan",Tarif_JKK_Lapangan,Tarif_JKK_Kantor)+Tarif_JKM+Tarif_JHT+Tarif_THR)+MIN((IF($F27="C-Level",$AF27,$AC27)*(1+Tunjangan_Pct)),Plafon_JP)*Tarif_JP+MIN(MAX((IF($F27="C-Level",$AF27,$AC27)*(1+Tunjangan_Pct)),IF($E27="Padang",UMP_Padang,UMK_Pekanbaru)),Plafon_JKN)*Tarif_JKN -> 7845420 | AH27: =(IF($F27="C-Level",$AF27,$AD27)*(1+Tunjangan_Pct))*(1+IF($H27="Lapangan",Tarif_JKK_Lapangan,Tarif_JKK_Kantor)+Tarif_JKM+Tarif_JHT+Tarif_THR)+MIN((IF($F27="C-Level",$AF27,$AD27)*(1+Tunjangan_Pct)),Plafon_JP)*Tarif_JP+MIN(MAX((IF($F27="C-Level",$AF27,$AD27)*(1+Tunjangan_Pct)),IF($E27="Padang",UMP_Padang,UMK_Pekanbaru)),Plafon_JKN)*Tarif_JKN -> 11114345 | AI27: =(IF($F27="C-Level",$AF27,$AE27)*(1+Tunjangan_Pct))*(1+IF($H27="Lapangan",Tarif_JKK_Lapangan,Tarif_JKK_Kantor)+Tarif_JKM+Tarif_JHT+Tarif_THR)+MIN((IF($F27="C-Level",$AF27,$AE27)*(1+Tunjangan_Pct)),Plafon_JP)*Tarif_JP+MIN(MAX((IF($F27="C-Level",$AF27,$AE27)*(1+Tunjangan_Pct)),IF($E27="Padang",UMP_Padang,UMK_Pekanbaru)),Plafon_JKN)*Tarif_JKN -> 14358996 | AJ27: =$V27*MAX(0,MIN(3,4-$I27))+$W27*MAX(0,MIN(9,13-MAX($I27,4))) -> 10 | AK27: =$AJ27+$X27*MAX(0,MIN(12,25-MAX($I27,13))) -> 22 | AL27: =IF($M27>=IF($E27="Padang",UMP_Padang,UMK_Pekanbaru),"OK","DI BAWAH UMK") -> OK
A28: 3 | B28: Teknologi | C28: Direktur Teknologi (CTO) | D28: Pekanbaru | E28: Pekanbaru | F28: C-Level | G28: CTO | H28: Kantor | I28: 1 | J28: =IF($F28="C-Level",Pita_CLevel,Pita_Aktif) -> P25 | K28: =IF($J28="P25",$AC28,IF($J28="P50",$AD28,$AE28)) -> 30000000 | L28: =$K28*Tunjangan_Pct -> 3000000 | M28: =$K28+$L28 -> 33000000 | N28: =$M28*IF($H28="Lapangan",Tarif_JKK_Lapangan,Tarif_JKK_Kantor) -> 178200 | O28: =$M28*Tarif_JKM -> 99000 | P28: =$M28*Tarif_JHT -> 1221000 | Q28: =MIN($M28,Plafon_JP)*Tarif_JP -> 221726 | R28: =MIN(MAX($M28,IF($E28="Padang",UMP_Padang,UMK_Pekanbaru)),Plafon_JKN)*Tarif_JKN -> 480000 | S28: =$M28*Tarif_THR -> 2748900 | T28: =SUM($M28:$S28) -> 37948826 | U28: =$T28/$K28 -> 1.2649609 | V28: 1 | W28: 1 | X28: 1 | Y28: =$T28*$V28 -> 37948826 | Z28: =$T28*$W28 -> 37948826 | AA28: =$T28*$X28 -> 37948826 | AC28: =IF($E28="Padang",INDEX('Pita Gaji'!$F$6:$F$28,MATCH($G28,'Pita Gaji'!$A$6:$A$28,0)),INDEX('Pita Gaji'!$C$6:$C$28,MATCH($G28,'Pita Gaji'!$A$6:$A$28,0))) -> 30000000 | AD28: =IF($E28="Padang",INDEX('Pita Gaji'!$G$6:$G$28,MATCH($G28,'Pita Gaji'!$A$6:$A$28,0)),INDEX('Pita Gaji'!$D$6:$D$28,MATCH($G28,'Pita Gaji'!$A$6:$A$28,0))) -> 42500000 | AE28: =IF($E28="Padang",INDEX('Pita Gaji'!$H$6:$H$28,MATCH($G28,'Pita Gaji'!$A$6:$A$28,0)),INDEX('Pita Gaji'!$E$6:$E$28,MATCH($G28,'Pita Gaji'!$A$6:$A$28,0))) -> 55000000 | AF28: =IF(Pita_CLevel="P25",$AC28,IF(Pita_CLevel="P50",$AD28,$AE28)) -> 30000000 | AG28: =(IF($F28="C-Level",$AF28,$AC28)*(1+Tunjangan_Pct))*(1+IF($H28="Lapangan",Tarif_JKK_Lapangan,Tarif_JKK_Kantor)+Tarif_JKM+Tarif_JHT+Tarif_THR)+MIN((IF($F28="C-Level",$AF28,$AC28)*(1+Tunjangan_Pct)),Plafon_JP)*Tarif_JP+MIN(MAX((IF($F28="C-Level",$AF28,$AC28)*(1+Tunjangan_Pct)),IF($E28="Padang",UMP_Padang,UMK_Pekanbaru)),Plafon_JKN)*Tarif_JKN -> 37948826 | AH28: =(IF($F28="C-Level",$AF28,$AD28)*(1+Tunjangan_Pct))*(1+IF($H28="Lapangan",Tarif_JKK_Lapangan,Tarif_JKK_Kantor)+Tarif_JKM+Tarif_JHT+Tarif_THR)+MIN((IF($F28="C-Level",$AF28,$AD28)*(1+Tunjangan_Pct)),Plafon_JP)*Tarif_JP+MIN(MAX((IF($F28="C-Level",$AF28,$AD28)*(1+Tunjangan_Pct)),IF($E28="Padang",UMP_Padang,UMK_Pekanbaru)),Plafon_JKN)*Tarif_JKN -> 37948826 | AI28: =(IF($F28="C-Level",$AF28,$AE28)*(1+Tunjangan_Pct))*(1+IF($H28="Lapangan",Tarif_JKK_Lapangan,Tarif_JKK_Kantor)+Tarif_JKM+Tarif_JHT+Tarif_THR)+MIN((IF($F28="C-Level",$AF28,$AE28)*(1+Tunjangan_Pct)),Plafon_JP)*Tarif_JP+MIN(MAX((IF($F28="C-Level",$AF28,$AE28)*(1+Tunjangan_Pct)),IF($E28="Padang",UMP_Padang,UMK_Pekanbaru)),Plafon_JKN)*Tarif_JKN -> 37948826 | AJ28: =$V28*MAX(0,MIN(3,4-$I28))+$W28*MAX(0,MIN(9,13-MAX($I28,4))) -> 12 | AK28: =$AJ28+$X28*MAX(0,MIN(12,25-MAX($I28,13))) -> 24 | AL28: =IF($M28>=IF($E28="Padang",UMP_Padang,UMK_Pekanbaru),"OK","DI BAWAH UMK") -> OK
A29: 4 | B29: Teknologi | C29: Engineering Manager | D29: Remote | E29: Pekanbaru | F29: Manajer | G29: Engineering Manager | H29: Kantor | I29: 4 | J29: =IF($F29="C-Level",Pita_CLevel,Pita_Aktif) -> P50 | K29: =IF($J29="P25",$AC29,IF($J29="P50",$AD29,$AE29)) -> 27500000 | L29: =$K29*Tunjangan_Pct -> 2750000 | M29: =$K29+$L29 -> 30250000 | N29: =$M29*IF($H29="Lapangan",Tarif_JKK_Lapangan,Tarif_JKK_Kantor) -> 163350 | O29: =$M29*Tarif_JKM -> 90750 | P29: =$M29*Tarif_JHT -> 1119250 | Q29: =MIN($M29,Plafon_JP)*Tarif_JP -> 221726 | R29: =MIN(MAX($M29,IF($E29="Padang",UMP_Padang,UMK_Pekanbaru)),Plafon_JKN)*Tarif_JKN -> 480000 | S29: =$M29*Tarif_THR -> 2519825 | T29: =SUM($M29:$S29) -> 34844901 | U29: =$T29/$K29 -> 1.2670873 | V29: 0 | W29: 1 | X29: 1 | Y29: =$T29*$V29 -> 0 | Z29: =$T29*$W29 -> 34844901 | AA29: =$T29*$X29 -> 34844901 | AC29: =IF($E29="Padang",INDEX('Pita Gaji'!$F$6:$F$28,MATCH($G29,'Pita Gaji'!$A$6:$A$28,0)),INDEX('Pita Gaji'!$C$6:$C$28,MATCH($G29,'Pita Gaji'!$A$6:$A$28,0))) -> 20000000 | AD29: =IF($E29="Padang",INDEX('Pita Gaji'!$G$6:$G$28,MATCH($G29,'Pita Gaji'!$A$6:$A$28,0)),INDEX('Pita Gaji'!$D$6:$D$28,MATCH($G29,'Pita Gaji'!$A$6:$A$28,0))) -> 27500000 | AE29: =IF($E29="Padang",INDEX('Pita Gaji'!$H$6:$H$28,MATCH($G29,'Pita Gaji'!$A$6:$A$28,0)),INDEX('Pita Gaji'!$E$6:$E$28,MATCH($G29,'Pita Gaji'!$A$6:$A$28,0))) -> 35000000 | AF29: =IF(Pita_CLevel="P25",$AC29,IF(Pita_CLevel="P50",$AD29,$AE29)) -> 20000000 | AG29: =(IF($F29="C-Level",$AF29,$AC29)*(1+Tunjangan_Pct))*(1+IF($H29="Lapangan",Tarif_JKK_Lapangan,Tarif_JKK_Kantor)+Tarif_JKM+Tarif_JHT+Tarif_THR)+MIN((IF($F29="C-Level",$AF29,$AC29)*(1+Tunjangan_Pct)),Plafon_JP)*Tarif_JP+MIN(MAX((IF($F29="C-Level",$AF29,$AC29)*(1+Tunjangan_Pct)),IF($E29="Padang",UMP_Padang,UMK_Pekanbaru)),Plafon_JKN)*Tarif_JKN -> 25533126 | AH29: =(IF($F29="C-Level",$AF29,$AD29)*(1+Tunjangan_Pct))*(1+IF($H29="Lapangan",Tarif_JKK_Lapangan,Tarif_JKK_Kantor)+Tarif_JKM+Tarif_JHT+Tarif_THR)+MIN((IF($F29="C-Level",$AF29,$AD29)*(1+Tunjangan_Pct)),Plafon_JP)*Tarif_JP+MIN(MAX((IF($F29="C-Level",$AF29,$AD29)*(1+Tunjangan_Pct)),IF($E29="Padang",UMP_Padang,UMK_Pekanbaru)),Plafon_JKN)*Tarif_JKN -> 34844901 | AI29: =(IF($F29="C-Level",$AF29,$AE29)*(1+Tunjangan_Pct))*(1+IF($H29="Lapangan",Tarif_JKK_Lapangan,Tarif_JKK_Kantor)+Tarif_JKM+Tarif_JHT+Tarif_THR)+MIN((IF($F29="C-Level",$AF29,$AE29)*(1+Tunjangan_Pct)),Plafon_JP)*Tarif_JP+MIN(MAX((IF($F29="C-Level",$AF29,$AE29)*(1+Tunjangan_Pct)),IF($E29="Padang",UMP_Padang,UMK_Pekanbaru)),Plafon_JKN)*Tarif_JKN -> 44156676 | AJ29: =$V29*MAX(0,MIN(3,4-$I29))+$W29*MAX(0,MIN(9,13-MAX($I29,4))) -> 9 | AK29: =$AJ29+$X29*MAX(0,MIN(12,25-MAX($I29,13))) -> 21 | AL29: =IF($M29>=IF($E29="Padang",UMP_Padang,UMK_Pekanbaru),"OK","DI BAWAH UMK") -> OK
A30: 5 | B30: Teknologi | C30: Mobile Engineer (Senior) | D30: Pekanbaru | E30: Pekanbaru | F30: Senior | G30: Senior Software Engineer | H30: Kantor | I30: 1 | J30: =IF($F30="C-Level",Pita_CLevel,Pita_Aktif) -> P50 | K30: =IF($J30="P25",$AC30,IF($J30="P50",$AD30,$AE30)) -> 20000000 | L30: =$K30*Tunjangan_Pct -> 2000000 | M30: =$K30+$L30 -> 22000000 | N30: =$M30*IF($H30="Lapangan",Tarif_JKK_Lapangan,Tarif_JKK_Kantor) -> 118800 | O30: =$M30*Tarif_JKM -> 66000 | P30: =$M30*Tarif_JHT -> 814000 | Q30: =MIN($M30,Plafon_JP)*Tarif_JP -> 221726 | R30: =MIN(MAX($M30,IF($E30="Padang",UMP_Padang,UMK_Pekanbaru)),Plafon_JKN)*Tarif_JKN -> 480000 | S30: =$M30*Tarif_THR -> 1832600 | T30: =SUM($M30:$S30) -> 25533126 | U30: =$T30/$K30 -> 1.2766563 | V30: 1 | W30: 1 | X30: 1 | Y30: =$T30*$V30 -> 25533126 | Z30: =$T30*$W30 -> 25533126 | AA30: =$T30*$X30 -> 25533126 | AC30: =IF($E30="Padang",INDEX('Pita Gaji'!$F$6:$F$28,MATCH($G30,'Pita Gaji'!$A$6:$A$28,0)),INDEX('Pita Gaji'!$C$6:$C$28,MATCH($G30,'Pita Gaji'!$A$6:$A$28,0))) -> 15000000 | AD30: =IF($E30="Padang",INDEX('Pita Gaji'!$G$6:$G$28,MATCH($G30,'Pita Gaji'!$A$6:$A$28,0)),INDEX('Pita Gaji'!$D$6:$D$28,MATCH($G30,'Pita Gaji'!$A$6:$A$28,0))) -> 20000000 | AE30: =IF($E30="Padang",INDEX('Pita Gaji'!$H$6:$H$28,MATCH($G30,'Pita Gaji'!$A$6:$A$28,0)),INDEX('Pita Gaji'!$E$6:$E$28,MATCH($G30,'Pita Gaji'!$A$6:$A$28,0))) -> 25000000 | AF30: =IF(Pita_CLevel="P25",$AC30,IF(Pita_CLevel="P50",$AD30,$AE30)) -> 15000000 | AG30: =(IF($F30="C-Level",$AF30,$AC30)*(1+Tunjangan_Pct))*(1+IF($H30="Lapangan",Tarif_JKK_Lapangan,Tarif_JKK_Kantor)+Tarif_JKM+Tarif_JHT+Tarif_THR)+MIN((IF($F30="C-Level",$AF30,$AC30)*(1+Tunjangan_Pct)),Plafon_JP)*Tarif_JP+MIN(MAX((IF($F30="C-Level",$AF30,$AC30)*(1+Tunjangan_Pct)),IF($E30="Padang",UMP_Padang,UMK_Pekanbaru)),Plafon_JKN)*Tarif_JKN -> 19325276 | AH30: =(IF($F30="C-Level",$AF30,$AD30)*(1+Tunjangan_Pct))*(1+IF($H30="Lapangan",Tarif_JKK_Lapangan,Tarif_JKK_Kantor)+Tarif_JKM+Tarif_JHT+Tarif_THR)+MIN((IF($F30="C-Level",$AF30,$AD30)*(1+Tunjangan_Pct)),Plafon_JP)*Tarif_JP+MIN(MAX((IF($F30="C-Level",$AF30,$AD30)*(1+Tunjangan_Pct)),IF($E30="Padang",UMP_Padang,UMK_Pekanbaru)),Plafon_JKN)*Tarif_JKN -> 25533126 | AI30: =(IF($F30="C-Level",$AF30,$AE30)*(1+Tunjangan_Pct))*(1+IF($H30="Lapangan",Tarif_JKK_Lapangan,Tarif_JKK_Kantor)+Tarif_JKM+Tarif_JHT+Tarif_THR)+MIN((IF($F30="C-Level",$AF30,$AE30)*(1+Tunjangan_Pct)),Plafon_JP)*Tarif_JP+MIN(MAX((IF($F30="C-Level",$AF30,$AE30)*(1+Tunjangan_Pct)),IF($E30="Padang",UMP_Padang,UMK_Pekanbaru)),Plafon_JKN)*Tarif_JKN -> 31740976 | AJ30: =$V30*MAX(0,MIN(3,4-$I30))+$W30*MAX(0,MIN(9,13-MAX($I30,4))) -> 12 | AK30: =$AJ30+$X30*MAX(0,MIN(12,25-MAX($I30,13))) -> 24 | AL30: =IF($M30>=IF($E30="Padang",UMP_Padang,UMK_Pekanbaru),"OK","DI BAWAH UMK") -> OK
A31: 6 | B31: Teknologi | C31: Mobile Engineer (Mid) | D31: Remote | E31: Pekanbaru | F31: Mid | G31: Mid Software Engineer | H31: Kantor | I31: 5 | J31: =IF($F31="C-Level",Pita_CLevel,Pita_Aktif) -> P50 | K31: =IF($J31="P25",$AC31,IF($J31="P50",$AD31,$AE31)) -> 12000000 | L31: =$K31*Tunjangan_Pct -> 1200000 | M31: =$K31+$L31 -> 13200000 | N31: =$M31*IF($H31="Lapangan",Tarif_JKK_Lapangan,Tarif_JKK_Kantor) -> 71280 | O31: =$M31*Tarif_JKM -> 39600 | P31: =$M31*Tarif_JHT -> 488400 | Q31: =MIN($M31,Plafon_JP)*Tarif_JP -> 221726 | R31: =MIN(MAX($M31,IF($E31="Padang",UMP_Padang,UMK_Pekanbaru)),Plafon_JKN)*Tarif_JKN -> 480000 | S31: =$M31*Tarif_THR -> 1099560 | T31: =SUM($M31:$S31) -> 15600566 | U31: =$T31/$K31 -> 1.3000472 | V31: 0 | W31: 1 | X31: 1 | Y31: =$T31*$V31 -> 0 | Z31: =$T31*$W31 -> 15600566 | AA31: =$T31*$X31 -> 15600566 | AC31: =IF($E31="Padang",INDEX('Pita Gaji'!$F$6:$F$28,MATCH($G31,'Pita Gaji'!$A$6:$A$28,0)),INDEX('Pita Gaji'!$C$6:$C$28,MATCH($G31,'Pita Gaji'!$A$6:$A$28,0))) -> 9000000 | AD31: =IF($E31="Padang",INDEX('Pita Gaji'!$G$6:$G$28,MATCH($G31,'Pita Gaji'!$A$6:$A$28,0)),INDEX('Pita Gaji'!$D$6:$D$28,MATCH($G31,'Pita Gaji'!$A$6:$A$28,0))) -> 12000000 | AE31: =IF($E31="Padang",INDEX('Pita Gaji'!$H$6:$H$28,MATCH($G31,'Pita Gaji'!$A$6:$A$28,0)),INDEX('Pita Gaji'!$E$6:$E$28,MATCH($G31,'Pita Gaji'!$A$6:$A$28,0))) -> 15000000 | AF31: =IF(Pita_CLevel="P25",$AC31,IF(Pita_CLevel="P50",$AD31,$AE31)) -> 9000000 | AG31: =(IF($F31="C-Level",$AF31,$AC31)*(1+Tunjangan_Pct))*(1+IF($H31="Lapangan",Tarif_JKK_Lapangan,Tarif_JKK_Kantor)+Tarif_JKM+Tarif_JHT+Tarif_THR)+MIN((IF($F31="C-Level",$AF31,$AC31)*(1+Tunjangan_Pct)),Plafon_JP)*Tarif_JP+MIN(MAX((IF($F31="C-Level",$AF31,$AC31)*(1+Tunjangan_Pct)),IF($E31="Padang",UMP_Padang,UMK_Pekanbaru)),Plafon_JKN)*Tarif_JKN -> 11768130 | AH31: =(IF($F31="C-Level",$AF31,$AD31)*(1+Tunjangan_Pct))*(1+IF($H31="Lapangan",Tarif_JKK_Lapangan,Tarif_JKK_Kantor)+Tarif_JKM+Tarif_JHT+Tarif_THR)+MIN((IF($F31="C-Level",$AF31,$AD31)*(1+Tunjangan_Pct)),Plafon_JP)*Tarif_JP+MIN(MAX((IF($F31="C-Level",$AF31,$AD31)*(1+Tunjangan_Pct)),IF($E31="Padang",UMP_Padang,UMK_Pekanbaru)),Plafon_JKN)*Tarif_JKN -> 15600566 | AI31: =(IF($F31="C-Level",$AF31,$AE31)*(1+Tunjangan_Pct))*(1+IF($H31="Lapangan",Tarif_JKK_Lapangan,Tarif_JKK_Kantor)+Tarif_JKM+Tarif_JHT+Tarif_THR)+MIN((IF($F31="C-Level",$AF31,$AE31)*(1+Tunjangan_Pct)),Plafon_JP)*Tarif_JP+MIN(MAX((IF($F31="C-Level",$AF31,$AE31)*(1+Tunjangan_Pct)),IF($E31="Padang",UMP_Padang,UMK_Pekanbaru)),Plafon_JKN)*Tarif_JKN -> 19325276 | AJ31: =$V31*MAX(0,MIN(3,4-$I31))+$W31*MAX(0,MIN(9,13-MAX($I31,4))) -> 8 | AK31: =$AJ31+$X31*MAX(0,MIN(12,25-MAX($I31,13))) -> 20 | AL31: =IF($M31>=IF($E31="Padang",UMP_Padang,UMK_Pekanbaru),"OK","DI BAWAH UMK") -> OK
A32: 7 | B32: Teknologi | C32: Mobile Engineer (Mid) - gelombang 2 | D32: Remote | E32: Pekanbaru | F32: Mid | G32: Mid Software Engineer | H32: Kantor | I32: 14 | J32: =IF($F32="C-Level",Pita_CLevel,Pita_Aktif) -> P50 | K32: =IF($J32="P25",$AC32,IF($J32="P50",$AD32,$AE32)) -> 12000000 | L32: =$K32*Tunjangan_Pct -> 1200000 | M32: =$K32+$L32 -> 13200000 | N32: =$M32*IF($H32="Lapangan",Tarif_JKK_Lapangan,Tarif_JKK_Kantor) -> 71280 | O32: =$M32*Tarif_JKM -> 39600 | P32: =$M32*Tarif_JHT -> 488400 | Q32: =MIN($M32,Plafon_JP)*Tarif_JP -> 221726 | R32: =MIN(MAX($M32,IF($E32="Padang",UMP_Padang,UMK_Pekanbaru)),Plafon_JKN)*Tarif_JKN -> 480000 | S32: =$M32*Tarif_THR -> 1099560 | T32: =SUM($M32:$S32) -> 15600566 | U32: =$T32/$K32 -> 1.3000472 | V32: 0 | W32: 0 | X32: 1 | Y32: =$T32*$V32 -> 0 | Z32: =$T32*$W32 -> 0 | AA32: =$T32*$X32 -> 15600566 | AC32: =IF($E32="Padang",INDEX('Pita Gaji'!$F$6:$F$28,MATCH($G32,'Pita Gaji'!$A$6:$A$28,0)),INDEX('Pita Gaji'!$C$6:$C$28,MATCH($G32,'Pita Gaji'!$A$6:$A$28,0))) -> 9000000 | AD32: =IF($E32="Padang",INDEX('Pita Gaji'!$G$6:$G$28,MATCH($G32,'Pita Gaji'!$A$6:$A$28,0)),INDEX('Pita Gaji'!$D$6:$D$28,MATCH($G32,'Pita Gaji'!$A$6:$A$28,0))) -> 12000000 | AE32: =IF($E32="Padang",INDEX('Pita Gaji'!$H$6:$H$28,MATCH($G32,'Pita Gaji'!$A$6:$A$28,0)),INDEX('Pita Gaji'!$E$6:$E$28,MATCH($G32,'Pita Gaji'!$A$6:$A$28,0))) -> 15000000 | AF32: =IF(Pita_CLevel="P25",$AC32,IF(Pita_CLevel="P50",$AD32,$AE32)) -> 9000000 | AG32: =(IF($F32="C-Level",$AF32,$AC32)*(1+Tunjangan_Pct))*(1+IF($H32="Lapangan",Tarif_JKK_Lapangan,Tarif_JKK_Kantor)+Tarif_JKM+Tarif_JHT+Tarif_THR)+MIN((IF($F32="C-Level",$AF32,$AC32)*(1+Tunjangan_Pct)),Plafon_JP)*Tarif_JP+MIN(MAX((IF($F32="C-Level",$AF32,$AC32)*(1+Tunjangan_Pct)),IF($E32="Padang",UMP_Padang,UMK_Pekanbaru)),Plafon_JKN)*Tarif_JKN -> 11768130 | AH32: =(IF($F32="C-Level",$AF32,$AD32)*(1+Tunjangan_Pct))*(1+IF($H32="Lapangan",Tarif_JKK_Lapangan,Tarif_JKK_Kantor)+Tarif_JKM+Tarif_JHT+Tarif_THR)+MIN((IF($F32="C-Level",$AF32,$AD32)*(1+Tunjangan_Pct)),Plafon_JP)*Tarif_JP+MIN(MAX((IF($F32="C-Level",$AF32,$AD32)*(1+Tunjangan_Pct)),IF($E32="Padang",UMP_Padang,UMK_Pekanbaru)),Plafon_JKN)*Tarif_JKN -> 15600566 | AI32: =(IF($F32="C-Level",$AF32,$AE32)*(1+Tunjangan_Pct))*(1+IF($H32="Lapangan",Tarif_JKK_Lapangan,Tarif_JKK_Kantor)+Tarif_JKM+Tarif_JHT+Tarif_THR)+MIN((IF($F32="C-Level",$AF32,$AE32)*(1+Tunjangan_Pct)),Plafon_JP)*Tarif_JP+MIN(MAX((IF($F32="C-Level",$AF32,$AE32)*(1+Tunjangan_Pct)),IF($E32="Padang",UMP_Padang,UMK_Pekanbaru)),Plafon_JKN)*Tarif_JKN -> 19325276 | AJ32: =$V32*MAX(0,MIN(3,4-$I32))+$W32*MAX(0,MIN(9,13-MAX($I32,4))) -> 0 | AK32: =$AJ32+$X32*MAX(0,MIN(12,25-MAX($I32,13))) -> 11 | AL32: =IF($M32>=IF($E32="Padang",UMP_Padang,UMK_Pekanbaru),"OK","DI BAWAH UMK") -> OK
A33: 8 | B33: Teknologi | C33: Backend Engineer (Senior) | D33: Pekanbaru | E33: Pekanbaru | F33: Senior | G33: Senior Software Engineer | H33: Kantor | I33: 1 | J33: =IF($F33="C-Level",Pita_CLevel,Pita_Aktif) -> P50 | K33: =IF($J33="P25",$AC33,IF($J33="P50",$AD33,$AE33)) -> 20000000 | L33: =$K33*Tunjangan_Pct -> 2000000 | M33: =$K33+$L33 -> 22000000 | N33: =$M33*IF($H33="Lapangan",Tarif_JKK_Lapangan,Tarif_JKK_Kantor) -> 118800 | O33: =$M33*Tarif_JKM -> 66000 | P33: =$M33*Tarif_JHT -> 814000 | Q33: =MIN($M33,Plafon_JP)*Tarif_JP -> 221726 | R33: =MIN(MAX($M33,IF($E33="Padang",UMP_Padang,UMK_Pekanbaru)),Plafon_JKN)*Tarif_JKN -> 480000 | S33: =$M33*Tarif_THR -> 1832600 | T33: =SUM($M33:$S33) -> 25533126 | U33: =$T33/$K33 -> 1.2766563 | V33: 1 | W33: 1 | X33: 1 | Y33: =$T33*$V33 -> 25533126 | Z33: =$T33*$W33 -> 25533126 | AA33: =$T33*$X33 -> 25533126 | AC33: =IF($E33="Padang",INDEX('Pita Gaji'!$F$6:$F$28,MATCH($G33,'Pita Gaji'!$A$6:$A$28,0)),INDEX('Pita Gaji'!$C$6:$C$28,MATCH($G33,'Pita Gaji'!$A$6:$A$28,0))) -> 15000000 | AD33: =IF($E33="Padang",INDEX('Pita Gaji'!$G$6:$G$28,MATCH($G33,'Pita Gaji'!$A$6:$A$28,0)),INDEX('Pita Gaji'!$D$6:$D$28,MATCH($G33,'Pita Gaji'!$A$6:$A$28,0))) -> 20000000 | AE33: =IF($E33="Padang",INDEX('Pita Gaji'!$H$6:$H$28,MATCH($G33,'Pita Gaji'!$A$6:$A$28,0)),INDEX('Pita Gaji'!$E$6:$E$28,MATCH($G33,'Pita Gaji'!$A$6:$A$28,0))) -> 25000000 | AF33: =IF(Pita_CLevel="P25",$AC33,IF(Pita_CLevel="P50",$AD33,$AE33)) -> 15000000 | AG33: =(IF($F33="C-Level",$AF33,$AC33)*(1+Tunjangan_Pct))*(1+IF($H33="Lapangan",Tarif_JKK_Lapangan,Tarif_JKK_Kantor)+Tarif_JKM+Tarif_JHT+Tarif_THR)+MIN((IF($F33="C-Level",$AF33,$AC33)*(1+Tunjangan_Pct)),Plafon_JP)*Tarif_JP+MIN(MAX((IF($F33="C-Level",$AF33,$AC33)*(1+Tunjangan_Pct)),IF($E33="Padang",UMP_Padang,UMK_Pekanbaru)),Plafon_JKN)*Tarif_JKN -> 19325276 | AH33: =(IF($F33="C-Level",$AF33,$AD33)*(1+Tunjangan_Pct))*(1+IF($H33="Lapangan",Tarif_JKK_Lapangan,Tarif_JKK_Kantor)+Tarif_JKM+Tarif_JHT+Tarif_THR)+MIN((IF($F33="C-Level",$AF33,$AD33)*(1+Tunjangan_Pct)),Plafon_JP)*Tarif_JP+MIN(MAX((IF($F33="C-Level",$AF33,$AD33)*(1+Tunjangan_Pct)),IF($E33="Padang",UMP_Padang,UMK_Pekanbaru)),Plafon_JKN)*Tarif_JKN -> 25533126 | AI33: =(IF($F33="C-Level",$AF33,$AE33)*(1+Tunjangan_Pct))*(1+IF($H33="Lapangan",Tarif_JKK_Lapangan,Tarif_JKK_Kantor)+Tarif_JKM+Tarif_JHT+Tarif_THR)+MIN((IF($F33="C-Level",$AF33,$AE33)*(1+Tunjangan_Pct)),Plafon_JP)*Tarif_JP+MIN(MAX((IF($F33="C-Level",$AF33,$AE33)*(1+Tunjangan_Pct)),IF($E33="Padang",UMP_Padang,UMK_Pekanbaru)),Plafon_JKN)*Tarif_JKN -> 31740976 | AJ33: =$V33*MAX(0,MIN(3,4-$I33))+$W33*MAX(0,MIN(9,13-MAX($I33,4))) -> 12 | AK33: =$AJ33+$X33*MAX(0,MIN(12,25-MAX($I33,13))) -> 24 | AL33: =IF($M33>=IF($E33="Padang",UMP_Padang,UMK_Pekanbaru),"OK","DI BAWAH UMK") -> OK
A34: 9 | B34: Teknologi | C34: Backend Engineer (Senior) - gelombang 2 | D34: Remote | E34: Pekanbaru | F34: Senior | G34: Senior Software Engineer | H34: Kantor | I34: 19 | J34: =IF($F34="C-Level",Pita_CLevel,Pita_Aktif) -> P50 | K34: =IF($J34="P25",$AC34,IF($J34="P50",$AD34,$AE34)) -> 20000000 | L34: =$K34*Tunjangan_Pct -> 2000000 | M34: =$K34+$L34 -> 22000000 | N34: =$M34*IF($H34="Lapangan",Tarif_JKK_Lapangan,Tarif_JKK_Kantor) -> 118800 | O34: =$M34*Tarif_JKM -> 66000 | P34: =$M34*Tarif_JHT -> 814000 | Q34: =MIN($M34,Plafon_JP)*Tarif_JP -> 221726 | R34: =MIN(MAX($M34,IF($E34="Padang",UMP_Padang,UMK_Pekanbaru)),Plafon_JKN)*Tarif_JKN -> 480000 | S34: =$M34*Tarif_THR -> 1832600 | T34: =SUM($M34:$S34) -> 25533126 | U34: =$T34/$K34 -> 1.2766563 | V34: 0 | W34: 0 | X34: 1 | Y34: =$T34*$V34 -> 0 | Z34: =$T34*$W34 -> 0 | AA34: =$T34*$X34 -> 25533126 | AC34: =IF($E34="Padang",INDEX('Pita Gaji'!$F$6:$F$28,MATCH($G34,'Pita Gaji'!$A$6:$A$28,0)),INDEX('Pita Gaji'!$C$6:$C$28,MATCH($G34,'Pita Gaji'!$A$6:$A$28,0))) -> 15000000 | AD34: =IF($E34="Padang",INDEX('Pita Gaji'!$G$6:$G$28,MATCH($G34,'Pita Gaji'!$A$6:$A$28,0)),INDEX('Pita Gaji'!$D$6:$D$28,MATCH($G34,'Pita Gaji'!$A$6:$A$28,0))) -> 20000000 | AE34: =IF($E34="Padang",INDEX('Pita Gaji'!$H$6:$H$28,MATCH($G34,'Pita Gaji'!$A$6:$A$28,0)),INDEX('Pita Gaji'!$E$6:$E$28,MATCH($G34,'Pita Gaji'!$A$6:$A$28,0))) -> 25000000 | AF34: =IF(Pita_CLevel="P25",$AC34,IF(Pita_CLevel="P50",$AD34,$AE34)) -> 15000000 | AG34: =(IF($F34="C-Level",$AF34,$AC34)*(1+Tunjangan_Pct))*(1+IF($H34="Lapangan",Tarif_JKK_Lapangan,Tarif_JKK_Kantor)+Tarif_JKM+Tarif_JHT+Tarif_THR)+MIN((IF($F34="C-Level",$AF34,$AC34)*(1+Tunjangan_Pct)),Plafon_JP)*Tarif_JP+MIN(MAX((IF($F34="C-Level",$AF34,$AC34)*(1+Tunjangan_Pct)),IF($E34="Padang",UMP_Padang,UMK_Pekanbaru)),Plafon_JKN)*Tarif_JKN -> 19325276 | AH34: =(IF($F34="C-Level",$AF34,$AD34)*(1+Tunjangan_Pct))*(1+IF($H34="Lapangan",Tarif_JKK_Lapangan,Tarif_JKK_Kantor)+Tarif_JKM+Tarif_JHT+Tarif_THR)+MIN((IF($F34="C-Level",$AF34,$AD34)*(1+Tunjangan_Pct)),Plafon_JP)*Tarif_JP+MIN(MAX((IF($F34="C-Level",$AF34,$AD34)*(1+Tunjangan_Pct)),IF($E34="Padang",UMP_Padang,UMK_Pekanbaru)),Plafon_JKN)*Tarif_JKN -> 25533126 | AI34: =(IF($F34="C-Level",$AF34,$AE34)*(1+Tunjangan_Pct))*(1+IF($H34="Lapangan",Tarif_JKK_Lapangan,Tarif_JKK_Kantor)+Tarif_JKM+Tarif_JHT+Tarif_THR)+MIN((IF($F34="C-Level",$AF34,$AE34)*(1+Tunjangan_Pct)),Plafon_JP)*Tarif_JP+MIN(MAX((IF($F34="C-Level",$AF34,$AE34)*(1+Tunjangan_Pct)),IF($E34="Padang",UMP_Padang,UMK_Pekanbaru)),Plafon_JKN)*Tarif_JKN -> 31740976 | AJ34: =$V34*MAX(0,MIN(3,4-$I34))+$W34*MAX(0,MIN(9,13-MAX($I34,4))) -> 0 | AK34: =$AJ34+$X34*MAX(0,MIN(12,25-MAX($I34,13))) -> 6 | AL34: =IF($M34>=IF($E34="Padang",UMP_Padang,UMK_Pekanbaru),"OK","DI BAWAH UMK") -> OK
A35: 10 | B35: Teknologi | C35: Backend Engineer (Mid) | D35: Remote | E35: Pekanbaru | F35: Mid | G35: Mid Software Engineer | H35: Kantor | I35: 4 | J35: =IF($F35="C-Level",Pita_CLevel,Pita_Aktif) -> P50 | K35: =IF($J35="P25",$AC35,IF($J35="P50",$AD35,$AE35)) -> 12000000 | L35: =$K35*Tunjangan_Pct -> 1200000 | M35: =$K35+$L35 -> 13200000 | N35: =$M35*IF($H35="Lapangan",Tarif_JKK_Lapangan,Tarif_JKK_Kantor) -> 71280 | O35: =$M35*Tarif_JKM -> 39600 | P35: =$M35*Tarif_JHT -> 488400 | Q35: =MIN($M35,Plafon_JP)*Tarif_JP -> 221726 | R35: =MIN(MAX($M35,IF($E35="Padang",UMP_Padang,UMK_Pekanbaru)),Plafon_JKN)*Tarif_JKN -> 480000 | S35: =$M35*Tarif_THR -> 1099560 | T35: =SUM($M35:$S35) -> 15600566 | U35: =$T35/$K35 -> 1.3000472 | V35: 0 | W35: 1 | X35: 1 | Y35: =$T35*$V35 -> 0 | Z35: =$T35*$W35 -> 15600566 | AA35: =$T35*$X35 -> 15600566 | AC35: =IF($E35="Padang",INDEX('Pita Gaji'!$F$6:$F$28,MATCH($G35,'Pita Gaji'!$A$6:$A$28,0)),INDEX('Pita Gaji'!$C$6:$C$28,MATCH($G35,'Pita Gaji'!$A$6:$A$28,0))) -> 9000000 | AD35: =IF($E35="Padang",INDEX('Pita Gaji'!$G$6:$G$28,MATCH($G35,'Pita Gaji'!$A$6:$A$28,0)),INDEX('Pita Gaji'!$D$6:$D$28,MATCH($G35,'Pita Gaji'!$A$6:$A$28,0))) -> 12000000 | AE35: =IF($E35="Padang",INDEX('Pita Gaji'!$H$6:$H$28,MATCH($G35,'Pita Gaji'!$A$6:$A$28,0)),INDEX('Pita Gaji'!$E$6:$E$28,MATCH($G35,'Pita Gaji'!$A$6:$A$28,0))) -> 15000000 | AF35: =IF(Pita_CLevel="P25",$AC35,IF(Pita_CLevel="P50",$AD35,$AE35)) -> 9000000 | AG35: =(IF($F35="C-Level",$AF35,$AC35)*(1+Tunjangan_Pct))*(1+IF($H35="Lapangan",Tarif_JKK_Lapangan,Tarif_JKK_Kantor)+Tarif_JKM+Tarif_JHT+Tarif_THR)+MIN((IF($F35="C-Level",$AF35,$AC35)*(1+Tunjangan_Pct)),Plafon_JP)*Tarif_JP+MIN(MAX((IF($F35="C-Level",$AF35,$AC35)*(1+Tunjangan_Pct)),IF($E35="Padang",UMP_Padang,UMK_Pekanbaru)),Plafon_JKN)*Tarif_JKN -> 11768130 | AH35: =(IF($F35="C-Level",$AF35,$AD35)*(1+Tunjangan_Pct))*(1+IF($H35="Lapangan",Tarif_JKK_Lapangan,Tarif_JKK_Kantor)+Tarif_JKM+Tarif_JHT+Tarif_THR)+MIN((IF($F35="C-Level",$AF35,$AD35)*(1+Tunjangan_Pct)),Plafon_JP)*Tarif_JP+MIN(MAX((IF($F35="C-Level",$AF35,$AD35)*(1+Tunjangan_Pct)),IF($E35="Padang",UMP_Padang,UMK_Pekanbaru)),Plafon_JKN)*Tarif_JKN -> 15600566 | AI35: =(IF($F35="C-Level",$AF35,$AE35)*(1+Tunjangan_Pct))*(1+IF($H35="Lapangan",Tarif_JKK_Lapangan,Tarif_JKK_Kantor)+Tarif_JKM+Tarif_JHT+Tarif_THR)+MIN((IF($F35="C-Level",$AF35,$AE35)*(1+Tunjangan_Pct)),Plafon_JP)*Tarif_JP+MIN(MAX((IF($F35="C-Level",$AF35,$AE35)*(1+Tunjangan_Pct)),IF($E35="Padang",UMP_Padang,UMK_Pekanbaru)),Plafon_JKN)*Tarif_JKN -> 19325276 | AJ35: =$V35*MAX(0,MIN(3,4-$I35))+$W35*MAX(0,MIN(9,13-MAX($I35,4))) -> 9 | AK35: =$AJ35+$X35*MAX(0,MIN(12,25-MAX($I35,13))) -> 21 | AL35: =IF($M35>=IF($E35="Padang",UMP_Padang,UMK_Pekanbaru),"OK","DI BAWAH UMK") -> OK
A36: 11 | B36: Teknologi | C36: Backend Engineer (Mid) - gelombang 2 | D36: Remote | E36: Pekanbaru | F36: Mid | G36: Mid Software Engineer | H36: Kantor | I36: 13 | J36: =IF($F36="C-Level",Pita_CLevel,Pita_Aktif) -> P50 | K36: =IF($J36="P25",$AC36,IF($J36="P50",$AD36,$AE36)) -> 12000000 | L36: =$K36*Tunjangan_Pct -> 1200000 | M36: =$K36+$L36 -> 13200000 | N36: =$M36*IF($H36="Lapangan",Tarif_JKK_Lapangan,Tarif_JKK_Kantor) -> 71280 | O36: =$M36*Tarif_JKM -> 39600 | P36: =$M36*Tarif_JHT -> 488400 | Q36: =MIN($M36,Plafon_JP)*Tarif_JP -> 221726 | R36: =MIN(MAX($M36,IF($E36="Padang",UMP_Padang,UMK_Pekanbaru)),Plafon_JKN)*Tarif_JKN -> 480000 | S36: =$M36*Tarif_THR -> 1099560 | T36: =SUM($M36:$S36) -> 15600566 | U36: =$T36/$K36 -> 1.3000472 | V36: 0 | W36: 0 | X36: 1 | Y36: =$T36*$V36 -> 0 | Z36: =$T36*$W36 -> 0 | AA36: =$T36*$X36 -> 15600566 | AC36: =IF($E36="Padang",INDEX('Pita Gaji'!$F$6:$F$28,MATCH($G36,'Pita Gaji'!$A$6:$A$28,0)),INDEX('Pita Gaji'!$C$6:$C$28,MATCH($G36,'Pita Gaji'!$A$6:$A$28,0))) -> 9000000 | AD36: =IF($E36="Padang",INDEX('Pita Gaji'!$G$6:$G$28,MATCH($G36,'Pita Gaji'!$A$6:$A$28,0)),INDEX('Pita Gaji'!$D$6:$D$28,MATCH($G36,'Pita Gaji'!$A$6:$A$28,0))) -> 12000000 | AE36: =IF($E36="Padang",INDEX('Pita Gaji'!$H$6:$H$28,MATCH($G36,'Pita Gaji'!$A$6:$A$28,0)),INDEX('Pita Gaji'!$E$6:$E$28,MATCH($G36,'Pita Gaji'!$A$6:$A$28,0))) -> 15000000 | AF36: =IF(Pita_CLevel="P25",$AC36,IF(Pita_CLevel="P50",$AD36,$AE36)) -> 9000000 | AG36: =(IF($F36="C-Level",$AF36,$AC36)*(1+Tunjangan_Pct))*(1+IF($H36="Lapangan",Tarif_JKK_Lapangan,Tarif_JKK_Kantor)+Tarif_JKM+Tarif_JHT+Tarif_THR)+MIN((IF($F36="C-Level",$AF36,$AC36)*(1+Tunjangan_Pct)),Plafon_JP)*Tarif_JP+MIN(MAX((IF($F36="C-Level",$AF36,$AC36)*(1+Tunjangan_Pct)),IF($E36="Padang",UMP_Padang,UMK_Pekanbaru)),Plafon_JKN)*Tarif_JKN -> 11768130 | AH36: =(IF($F36="C-Level",$AF36,$AD36)*(1+Tunjangan_Pct))*(1+IF($H36="Lapangan",Tarif_JKK_Lapangan,Tarif_JKK_Kantor)+Tarif_JKM+Tarif_JHT+Tarif_THR)+MIN((IF($F36="C-Level",$AF36,$AD36)*(1+Tunjangan_Pct)),Plafon_JP)*Tarif_JP+MIN(MAX((IF($F36="C-Level",$AF36,$AD36)*(1+Tunjangan_Pct)),IF($E36="Padang",UMP_Padang,UMK_Pekanbaru)),Plafon_JKN)*Tarif_JKN -> 15600566 | AI36: =(IF($F36="C-Level",$AF36,$AE36)*(1+Tunjangan_Pct))*(1+IF($H36="Lapangan",Tarif_JKK_Lapangan,Tarif_JKK_Kantor)+Tarif_JKM+Tarif_JHT+Tarif_THR)+MIN((IF($F36="C-Level",$AF36,$AE36)*(1+Tunjangan_Pct)),Plafon_JP)*Tarif_JP+MIN(MAX((IF($F36="C-Level",$AF36,$AE36)*(1+Tunjangan_Pct)),IF($E36="Padang",UMP_Padang,UMK_Pekanbaru)),Plafon_JKN)*Tarif_JKN -> 19325276 | AJ36: =$V36*MAX(0,MIN(3,4-$I36))+$W36*MAX(0,MIN(9,13-MAX($I36,4))) -> 0 | AK36: =$AJ36+$X36*MAX(0,MIN(12,25-MAX($I36,13))) -> 12 | AL36: =IF($M36>=IF($E36="Padang",UMP_Padang,UMK_Pekanbaru),"OK","DI BAWAH UMK") -> OK
A37: 12 | B37: Teknologi | C37: QA Engineer | D37: Pekanbaru | E37: Pekanbaru | F37: Mid | G37: QA Engineer | H37: Kantor | I37: 6 | J37: =IF($F37="C-Level",Pita_CLevel,Pita_Aktif) -> P50 | K37: =IF($J37="P25",$AC37,IF($J37="P50",$AD37,$AE37)) -> 10000000 | L37: =$K37*Tunjangan_Pct -> 1000000 | M37: =$K37+$L37 -> 11000000 | N37: =$M37*IF($H37="Lapangan",Tarif_JKK_Lapangan,Tarif_JKK_Kantor) -> 59400 | O37: =$M37*Tarif_JKM -> 33000 | P37: =$M37*Tarif_JHT -> 407000 | Q37: =MIN($M37,Plafon_JP)*Tarif_JP -> 220000 | R37: =MIN(MAX($M37,IF($E37="Padang",UMP_Padang,UMK_Pekanbaru)),Plafon_JKN)*Tarif_JKN -> 440000 | S37: =$M37*Tarif_THR -> 916300 | T37: =SUM($M37:$S37) -> 13075700 | U37: =$T37/$K37 -> 1.30757 | V37: 0 | W37: 1 | X37: 1 | Y37: =$T37*$V37 -> 0 | Z37: =$T37*$W37 -> 13075700 | AA37: =$T37*$X37 -> 13075700 | AC37: =IF($E37="Padang",INDEX('Pita Gaji'!$F$6:$F$28,MATCH($G37,'Pita Gaji'!$A$6:$A$28,0)),INDEX('Pita Gaji'!$C$6:$C$28,MATCH($G37,'Pita Gaji'!$A$6:$A$28,0))) -> 7000000 | AD37: =IF($E37="Padang",INDEX('Pita Gaji'!$G$6:$G$28,MATCH($G37,'Pita Gaji'!$A$6:$A$28,0)),INDEX('Pita Gaji'!$D$6:$D$28,MATCH($G37,'Pita Gaji'!$A$6:$A$28,0))) -> 10000000 | AE37: =IF($E37="Padang",INDEX('Pita Gaji'!$H$6:$H$28,MATCH($G37,'Pita Gaji'!$A$6:$A$28,0)),INDEX('Pita Gaji'!$E$6:$E$28,MATCH($G37,'Pita Gaji'!$A$6:$A$28,0))) -> 13000000 | AF37: =IF(Pita_CLevel="P25",$AC37,IF(Pita_CLevel="P50",$AD37,$AE37)) -> 7000000 | AG37: =(IF($F37="C-Level",$AF37,$AC37)*(1+Tunjangan_Pct))*(1+IF($H37="Lapangan",Tarif_JKK_Lapangan,Tarif_JKK_Kantor)+Tarif_JKM+Tarif_JHT+Tarif_THR)+MIN((IF($F37="C-Level",$AF37,$AC37)*(1+Tunjangan_Pct)),Plafon_JP)*Tarif_JP+MIN(MAX((IF($F37="C-Level",$AF37,$AC37)*(1+Tunjangan_Pct)),IF($E37="Padang",UMP_Padang,UMK_Pekanbaru)),Plafon_JKN)*Tarif_JKN -> 9152990 | AH37: =(IF($F37="C-Level",$AF37,$AD37)*(1+Tunjangan_Pct))*(1+IF($H37="Lapangan",Tarif_JKK_Lapangan,Tarif_JKK_Kantor)+Tarif_JKM+Tarif_JHT+Tarif_THR)+MIN((IF($F37="C-Level",$AF37,$AD37)*(1+Tunjangan_Pct)),Plafon_JP)*Tarif_JP+MIN(MAX((IF($F37="C-Level",$AF37,$AD37)*(1+Tunjangan_Pct)),IF($E37="Padang",UMP_Padang,UMK_Pekanbaru)),Plafon_JKN)*Tarif_JKN -> 13075700 | AI37: =(IF($F37="C-Level",$AF37,$AE37)*(1+Tunjangan_Pct))*(1+IF($H37="Lapangan",Tarif_JKK_Lapangan,Tarif_JKK_Kantor)+Tarif_JKM+Tarif_JHT+Tarif_THR)+MIN((IF($F37="C-Level",$AF37,$AE37)*(1+Tunjangan_Pct)),Plafon_JP)*Tarif_JP+MIN(MAX((IF($F37="C-Level",$AF37,$AE37)*(1+Tunjangan_Pct)),IF($E37="Padang",UMP_Padang,UMK_Pekanbaru)),Plafon_JKN)*Tarif_JKN -> 16842136 | AJ37: =$V37*MAX(0,MIN(3,4-$I37))+$W37*MAX(0,MIN(9,13-MAX($I37,4))) -> 7 | AK37: =$AJ37+$X37*MAX(0,MIN(12,25-MAX($I37,13))) -> 19 | AL37: =IF($M37>=IF($E37="Padang",UMP_Padang,UMK_Pekanbaru),"OK","DI BAWAH UMK") -> OK
... A63: 38 | B63: Legal & Kepatuhan | C63: Head of Legal & Compliance (merangkap DPO) | D63: Pekanbaru | E63: Pekanbaru | F63: Head | G63: Legal & Compliance officer | H63: Kantor | I63: 4 | J63: =IF($F63="C-Level",Pita_CLevel,Pita_Aktif) -> P50 | K63: =IF($J63="P25",$AC63,IF($J63="P50",$AD63,$AE63)) -> 13500000 | L63: =$K63*Tunjangan_Pct -> 1350000 | M63: =$K63+$L63 -> 14850000 | N63: =$M63*IF($H63="Lapangan",Tarif_JKK_Lapangan,Tarif_JKK_Kantor) -> 80190 | O63: =$M63*Tarif_JKM -> 44550 | P63: =$M63*Tarif_JHT -> 549450 | Q63: =MIN($M63,Plafon_JP)*Tarif_JP -> 221726 | R63: =MIN(MAX($M63,IF($E63="Padang",UMP_Padang,UMK_Pekanbaru)),Plafon_JKN)*Tarif_JKN -> 480000 | S63: =$M63*Tarif_THR -> 1237005 | T63: =SUM($M63:$S63) -> 17462921 | U63: =$T63/$K63 -> 1.2935497 | V63: 0 | W63: 1 | X63: 1 | Y63: =$T63*$V63 -> 0 | Z63: =$T63*$W63 -> 17462921 | AA63: =$T63*$X63 -> 17462921 | AC63: =IF($E63="Padang",INDEX('Pita Gaji'!$F$6:$F$28,MATCH($G63,'Pita Gaji'!$A$6:$A$28,0)),INDEX('Pita Gaji'!$C$6:$C$28,MATCH($G63,'Pita Gaji'!$A$6:$A$28,0))) -> 9000000 | AD63: =IF($E63="Padang",INDEX('Pita Gaji'!$G$6:$G$28,MATCH($G63,'Pita Gaji'!$A$6:$A$28,0)),INDEX('Pita Gaji'!$D$6:$D$28,MATCH($G63,'Pita Gaji'!$A$6:$A$28,0))) -> 13500000 | AE63: =IF($E63="Padang",INDEX('Pita Gaji'!$H$6:$H$28,MATCH($G63,'Pita Gaji'!$A$6:$A$28,0)),INDEX('Pita Gaji'!$E$6:$E$28,MATCH($G63,'Pita Gaji'!$A$6:$A$28,0))) -> 18000000 | AF63: =IF(Pita_CLevel="P25",$AC63,IF(Pita_CLevel="P50",$AD63,$AE63)) -> 9000000 | AG63: =(IF($F63="C-Level",$AF63,$AC63)*(1+Tunjangan_Pct))*(1+IF($H63="Lapangan",Tarif_JKK_Lapangan,Tarif_JKK_Kantor)+Tarif_JKM+Tarif_JHT+Tarif_THR)+MIN((IF($F63="C-Level",$AF63,$AC63)*(1+Tunjangan_Pct)),Plafon_JP)*Tarif_JP+MIN(MAX((IF($F63="C-Level",$AF63,$AC63)*(1+Tunjangan_Pct)),IF($E63="Padang",UMP_Padang,UMK_Pekanbaru)),Plafon_JKN)*Tarif_JKN -> 11768130 | AH63: =(IF($F63="C-Level",$AF63,$AD63)*(1+Tunjangan_Pct))*(1+IF($H63="Lapangan",Tarif_JKK_Lapangan,Tarif_JKK_Kantor)+Tarif_JKM+Tarif_JHT+Tarif_THR)+MIN((IF($F63="C-Level",$AF63,$AD63)*(1+Tunjangan_Pct)),Plafon_JP)*Tarif_JP+MIN(MAX((IF($F63="C-Level",$AF63,$AD63)*(1+Tunjangan_Pct)),IF($E63="Padang",UMP_Padang,UMK_Pekanbaru)),Plafon_JKN)*Tarif_JKN -> 17462921 | AI63: =(IF($F63="C-Level",$AF63,$AE63)*(1+Tunjangan_Pct))*(1+IF($H63="Lapangan",Tarif_JKK_Lapangan,Tarif_JKK_Kantor)+Tarif_JKM+Tarif_JHT+Tarif_THR)+MIN((IF($F63="C-Level",$AF63,$AE63)*(1+Tunjangan_Pct)),Plafon_JP)*Tarif_JP+MIN(MAX((IF($F63="C-Level",$AF63,$AE63)*(1+Tunjangan_Pct)),IF($E63="Padang",UMP_Padang,UMK_Pekanbaru)),Plafon_JKN)*Tarif_JKN -> 23049986 | AJ63: =$V63*MAX(0,MIN(3,4-$I63))+$W63*MAX(0,MIN(9,13-MAX($I63,4))) -> 9 | AK63: =$AJ63+$X63*MAX(0,MIN(12,25-MAX($I63,13))) -> 21 | AL63: =IF($M63>=IF($E63="Padang",UMP_Padang,UMK_Pekanbaru),"OK","DI BAWAH UMK") -> OK
A64: TOTAL | C64: TOTAL SELURUH POSISI | U64: =SUM(Y64:AA64)/SUMPRODUCT($K26:$K63,$X26:$X63) -> 2.6384877 | V64: =SUM(V26:V63) -> 9 | W64: =SUM(W26:W63) -> 24 | X64: =SUM(X26:X63) -> 42 | Y64: =SUM(Y26:Y63) -> 230332093 | Z64: =SUM(Z26:Z63) -> 4.3555549e+08 | AA64: =SUM(AA26:AA63) -> 6.3627206e+08 | AG64: =SUM(AG26:AG63) -> 4.837653e+08 | AH64: =SUM(AH26:AH63) -> 6.1193105e+08 | AI64: =SUM(AI26:AI63) -> 738418709 | AJ64: =SUM(AJ26:AJ63) -> 230 | AK64: =SUM(AK26:AK63) -> 705
A65: REKAP BIAYA SDM PER DIREKTORAT (Rp/bulan)
A66: Direktorat | D66: Fase 0 (bln 1-3) | E66: Fase 1 (bln 4-12) | F66: Fase 2 (bln 13-24)
A67: Direksi & Tata Kelola | D67: =SUMIF($B$26:$B$63,$A67,$Y$26:$Y$63) -> 55271021 | E67: =SUMIF($B$26:$B$63,$A67,$Z$26:$Z$63) -> 55271021 | F67: =SUMIF($B$26:$B$63,$A67,$AA$26:$AA$63) -> 55271021
A68: Teknologi | D68: =SUMIF($B$26:$B$63,$A68,$Y$26:$Y$63) -> 105857214 | E68: =SUMIF($B$26:$B$63,$A68,$Z$26:$Z$63) -> 184978947 | F68: =SUMIF($B$26:$B$63,$A68,$AA$26:$AA$63) -> 305570587
A69: Operasi | D69: =SUMIF($B$26:$B$63,$A69,$Y$26:$Y$63) -> 43670732 | E69: =SUMIF($B$26:$B$63,$A69,$Z$26:$Z$63) -> 1.1641479e+08 | F69: =SUMIF($B$26:$B$63,$A69,$AA$26:$AA$63) -> 1.6268613e+08
A70: Growth & Partnership | D70: =SUMIF($B$26:$B$63,$A70,$Y$26:$Y$63) -> 0 | E70: =SUMIF($B$26:$B$63,$A70,$Z$26:$Z$63) -> 27395481 | F70: =SUMIF($B$26:$B$63,$A70,$AA$26:$AA$63) -> 43433426
A71: Keuangan | D71: =SUMIF($B$26:$B$63,$A71,$Y$26:$Y$63) -> 25533126 | E71: =SUMIF($B$26:$B$63,$A71,$Z$26:$Z$63) -> 34032331 | F71: =SUMIF($B$26:$B$63,$A71,$AA$26:$AA$63) -> 51847972
A72: Legal & Kepatuhan | D72: =SUMIF($B$26:$B$63,$A72,$Y$26:$Y$63) -> 0 | E72: =SUMIF($B$26:$B$63,$A72,$Z$26:$Z$63) -> 17462921 | F72: =SUMIF($B$26:$B$63,$A72,$AA$26:$AA$63) -> 17462921
A73: TOTAL | D73: =SUM(D67:D72) -> 230332093 | E73: =SUM(E67:E72) -> 4.3555549e+08 | F73: =SUM(F67:F72) -> 6.3627206e+08
A75: Sumber baris: iuran BPJS Ketenagakerjaan [S-07][S-08][S-09][S-10]; BPJS Kesehatan Perpres 64/2020 [S-12][S-13]; THR PP 36/2021 & SE Menaker M/3/HK.04.00/III/2026 [S-14][S-15][S-16]; UMK [S-01][S-03][S-04][S-05][S-06]. Pita gaji: lembar 'Pita Gaji' - SELURUHNYA [ASUMSI].
A76: Upah Dasar Perhitungan = gaji pokok + tunjangan tetap (definisi 'upah sebulan' untuk iuran jaminan sosial dan THR). Total cost to company TIDAK memuat insentif variabel, lembur, PPh 21, maupun biaya non-gaji (lihat lembar 'Biaya Non-Gaji').

Sheet Proyeksi 24 Bulan
A1: AntarKita - Proyeksi Biaya SDM Bulan 1-24
A2: Disusun 7 September 2026. Setiap sel = jumlah orang aktif pada bulan tersebut x total cost to company/orang dari lembar 'Biaya Bulanan'. Fase 0 = bulan 1-3, Fase 1 = bulan 4-12, Fase 2 = bulan 13-24.
D3: BULAN KE-
A4: No | B4: Direktorat | C4: Posisi | D4: 1 | E4: 2 | F4: 3 | G4: 4 | H4: 5 | I4: 6 | J4: 7 | K4: 8 | L4: 9 | M4: 10 | N4: 11 | O4: 12 | P4: 13 | Q4: 14 | R4: 15 | S4: 16 | T4: 17 | U4: 18 | V4: 19 | W4: 20 | X4: 21 | Y4: 22 | Z4: 23 | AA4: 24
A5: 1 | B5: ='Biaya Bulanan'!$B$26 -> Direksi & Tata Kelola | C5: ='Biaya Bulanan'!$C$26 -> Direktur Utama (CEO) | D5: =IF(D$4<'Biaya Bulanan'!$I$26,0,IF(D$4<=3,'Biaya Bulanan'!$V$26,IF(D$4<=12,'Biaya Bulanan'!$W$26,'Biaya Bulanan'!$X$26)))*'Biaya Bulanan'!$T$26 -> 44156676 | E5: =IF(E$4<'Biaya Bulanan'!$I$26,0,IF(E$4<=3,'Biaya Bulanan'!$V$26,IF(E$4<=12,'Biaya Bulanan'!$W$26,'Biaya Bulanan'!$X$26)))*'Biaya Bulanan'!$T$26 -> 44156676 | F5: =IF(F$4<'Biaya Bulanan'!$I$26,0,IF(F$4<=3,'Biaya Bulanan'!$V$26,IF(F$4<=12,'Biaya Bulanan'!$W$26,'Biaya Bulanan'!$X$26)))*'Biaya Bulanan'!$T$26 -> 44156676 | G5: =IF(G$4<'Biaya Bulanan'!$I$26,0,IF(G$4<=3,'Biaya Bulanan'!$V$26,IF(G$4<=12,'Biaya Bulanan'!$W$26,'Biaya Bulanan'!$X$26)))*'Biaya Bulanan'!$T$26 -> 44156676 | H5: =IF(H$4<'Biaya Bulanan'!$I$26,0,IF(H$4<=3,'Biaya Bulanan'!$V$26,IF(H$4<=12,'Biaya Bulanan'!$W$26,'Biaya Bulanan'!$X$26)))*'Biaya Bulanan'!$T$26 -> 44156676 | I5: =IF(I$4<'Biaya Bulanan'!$I$26,0,IF(I$4<=3,'Biaya Bulanan'!$V$26,IF(I$4<=12,'Biaya Bulanan'!$W$26,'Biaya Bulanan'!$X$26)))*'Biaya Bulanan'!$T$26 -> 44156676 | J5: =IF(J$4<'Biaya Bulanan'!$I$26,0,IF(J$4<=3,'Biaya Bulanan'!$V$26,IF(J$4<=12,'Biaya Bulanan'!$W$26,'Biaya Bulanan'!$X$26)))*'Biaya Bulanan'!$T$26 -> 44156676 | K5: =IF(K$4<'Biaya Bulanan'!$I$26,0,IF(K$4<=3,'Biaya Bulanan'!$V$26,IF(K$4<=12,'Biaya Bulanan'!$W$26,'Biaya Bulanan'!$X$26)))*'Biaya Bulanan'!$T$26 -> 44156676 | ... AA5: =IF(AA$4<'Biaya Bulanan'!$I$26,0,IF(AA$4<=3,'Biaya Bulanan'!$V$26,IF(AA$4<=12,'Biaya Bulanan'!$W$26,'Biaya Bulanan'!$X$26)))*'Biaya Bulanan'!$T$26 -> 44156676
A6: 2 | B6: ='Biaya Bulanan'!$B$27 -> Direksi & Tata Kelola | C6: ='Biaya Bulanan'!$C$27 -> HR & GA Generalist | D6: =IF(D$4<'Biaya Bulanan'!$I$27,0,IF(D$4<=3,'Biaya Bulanan'!$V$27,IF(D$4<=12,'Biaya Bulanan'!$W$27,'Biaya Bulanan'!$X$27)))*'Biaya Bulanan'!$T$27 -> 0 | E6: =IF(E$4<'Biaya Bulanan'!$I$27,0,IF(E$4<=3,'Biaya Bulanan'!$V$27,IF(E$4<=12,'Biaya Bulanan'!$W$27,'Biaya Bulanan'!$X$27)))*'Biaya Bulanan'!$T$27 -> 0 | F6: =IF(F$4<'Biaya Bulanan'!$I$27,0,IF(F$4<=3,'Biaya Bulanan'!$V$27,IF(F$4<=12,'Biaya Bulanan'!$W$27,'Biaya Bulanan'!$X$27)))*'Biaya Bulanan'!$T$27 -> 11114345 | G6: =IF(G$4<'Biaya Bulanan'!$I$27,0,IF(G$4<=3,'Biaya Bulanan'!$V$27,IF(G$4<=12,'Biaya Bulanan'!$W$27,'Biaya Bulanan'!$X$27)))*'Biaya Bulanan'!$T$27 -> 11114345 | H6: =IF(H$4<'Biaya Bulanan'!$I$27,0,IF(H$4<=3,'Biaya Bulanan'!$V$27,IF(H$4<=12,'Biaya Bulanan'!$W$27,'Biaya Bulanan'!$X$27)))*'Biaya Bulanan'!$T$27 -> 11114345 | I6: =IF(I$4<'Biaya Bulanan'!$I$27,0,IF(I$4<=3,'Biaya Bulanan'!$V$27,IF(I$4<=12,'Biaya Bulanan'!$W$27,'Biaya Bulanan'!$X$27)))*'Biaya Bulanan'!$T$27 -> 11114345 | J6: =IF(J$4<'Biaya Bulanan'!$I$27,0,IF(J$4<=3,'Biaya Bulanan'!$V$27,IF(J$4<=12,'Biaya Bulanan'!$W$27,'Biaya Bulanan'!$X$27)))*'Biaya Bulanan'!$T$27 -> 11114345 | K6: =IF(K$4<'Biaya Bulanan'!$I$27,0,IF(K$4<=3,'Biaya Bulanan'!$V$27,IF(K$4<=12,'Biaya Bulanan'!$W$27,'Biaya Bulanan'!$X$27)))*'Biaya Bulanan'!$T$27 -> 11114345 | ... AA6: =IF(AA$4<'Biaya Bulanan'!$I$27,0,IF(AA$4<=3,'Biaya Bulanan'!$V$27,IF(AA$4<=12,'Biaya Bulanan'!$W$27,'Biaya Bulanan'!$X$27)))*'Biaya Bulanan'!$T$27 -> 11114345
A7: 3 | B7: ='Biaya Bulanan'!$B$28 -> Teknologi | C7: ='Biaya Bulanan'!$C$28 -> Direktur Teknologi (CTO) | D7: =IF(D$4<'Biaya Bulanan'!$I$28,0,IF(D$4<=3,'Biaya Bulanan'!$V$28,IF(D$4<=12,'Biaya Bulanan'!$W$28,'Biaya Bulanan'!$X$28)))*'Biaya Bulanan'!$T$28 -> 37948826 | E7: =IF(E$4<'Biaya Bulanan'!$I$28,0,IF(E$4<=3,'Biaya Bulanan'!$V$28,IF(E$4<=12,'Biaya Bulanan'!$W$28,'Biaya Bulanan'!$X$28)))*'Biaya Bulanan'!$T$28 -> 37948826 | F7: =IF(F$4<'Biaya Bulanan'!$I$28,0,IF(F$4<=3,'Biaya Bulanan'!$V$28,IF(F$4<=12,'Biaya Bulanan'!$W$28,'Biaya Bulanan'!$X$28)))*'Biaya Bulanan'!$T$28 -> 37948826 | G7: =IF(G$4<'Biaya Bulanan'!$I$28,0,IF(G$4<=3,'Biaya Bulanan'!$V$28,IF(G$4<=12,'Biaya Bulanan'!$W$28,'Biaya Bulanan'!$X$28)))*'Biaya Bulanan'!$T$28 -> 37948826 | H7: =IF(H$4<'Biaya Bulanan'!$I$28,0,IF(H$4<=3,'Biaya Bulanan'!$V$28,IF(H$4<=12,'Biaya Bulanan'!$W$28,'Biaya Bulanan'!$X$28)))*'Biaya Bulanan'!$T$28 -> 37948826 | I7: =IF(I$4<'Biaya Bulanan'!$I$28,0,IF(I$4<=3,'Biaya Bulanan'!$V$28,IF(I$4<=12,'Biaya Bulanan'!$W$28,'Biaya Bulanan'!$X$28)))*'Biaya Bulanan'!$T$28 -> 37948826 | J7: =IF(J$4<'Biaya Bulanan'!$I$28,0,IF(J$4<=3,'Biaya Bulanan'!$V$28,IF(J$4<=12,'Biaya Bulanan'!$W$28,'Biaya Bulanan'!$X$28)))*'Biaya Bulanan'!$T$28 -> 37948826 | K7: =IF(K$4<'Biaya Bulanan'!$I$28,0,IF(K$4<=3,'Biaya Bulanan'!$V$28,IF(K$4<=12,'Biaya Bulanan'!$W$28,'Biaya Bulanan'!$X$28)))*'Biaya Bulanan'!$T$28 -> 37948826 | ... AA7: =IF(AA$4<'Biaya Bulanan'!$I$28,0,IF(AA$4<=3,'Biaya Bulanan'!$V$28,IF(AA$4<=12,'Biaya Bulanan'!$W$28,'Biaya Bulanan'!$X$28)))*'Biaya Bulanan'!$T$28 -> 37948826
A8: 4 | B8: ='Biaya Bulanan'!$B$29 -> Teknologi | C8: ='Biaya Bulanan'!$C$29 -> Engineering Manager | D8: =IF(D$4<'Biaya Bulanan'!$I$29,0,IF(D$4<=3,'Biaya Bulanan'!$V$29,IF(D$4<=12,'Biaya Bulanan'!$W$29,'Biaya Bulanan'!$X$29)))*'Biaya Bulanan'!$T$29 -> 0 | E8: =IF(E$4<'Biaya Bulanan'!$I$29,0,IF(E$4<=3,'Biaya Bulanan'!$V$29,IF(E$4<=12,'Biaya Bulanan'!$W$29,'Biaya Bulanan'!$X$29)))*'Biaya Bulanan'!$T$29 -> 0 | F8: =IF(F$4<'Biaya Bulanan'!$I$29,0,IF(F$4<=3,'Biaya Bulanan'!$V$29,IF(F$4<=12,'Biaya Bulanan'!$W$29,'Biaya Bulanan'!$X$29)))*'Biaya Bulanan'!$T$29 -> 0 | G8: =IF(G$4<'Biaya Bulanan'!$I$29,0,IF(G$4<=3,'Biaya Bulanan'!$V$29,IF(G$4<=12,'Biaya Bulanan'!$W$29,'Biaya Bulanan'!$X$29)))*'Biaya Bulanan'!$T$29 -> 34844901 | H8: =IF(H$4<'Biaya Bulanan'!$I$29,0,IF(H$4<=3,'Biaya Bulanan'!$V$29,IF(H$4<=12,'Biaya Bulanan'!$W$29,'Biaya Bulanan'!$X$29)))*'Biaya Bulanan'!$T$29 -> 34844901 | I8: =IF(I$4<'Biaya Bulanan'!$I$29,0,IF(I$4<=3,'Biaya Bulanan'!$V$29,IF(I$4<=12,'Biaya Bulanan'!$W$29,'Biaya Bulanan'!$X$29)))*'Biaya Bulanan'!$T$29 -> 34844901 | J8: =IF(J$4<'Biaya Bulanan'!$I$29,0,IF(J$4<=3,'Biaya Bulanan'!$V$29,IF(J$4<=12,'Biaya Bulanan'!$W$29,'Biaya Bulanan'!$X$29)))*'Biaya Bulanan'!$T$29 -> 34844901 | K8: =IF(K$4<'Biaya Bulanan'!$I$29,0,IF(K$4<=3,'Biaya Bulanan'!$V$29,IF(K$4<=12,'Biaya Bulanan'!$W$29,'Biaya Bulanan'!$X$29)))*'Biaya Bulanan'!$T$29 -> 34844901 | ... AA8: =IF(AA$4<'Biaya Bulanan'!$I$29,0,IF(AA$4<=3,'Biaya Bulanan'!$V$29,IF(AA$4<=12,'Biaya Bulanan'!$W$29,'Biaya Bulanan'!$X$29)))*'Biaya Bulanan'!$T$29 -> 34844901
A9: 5 | B9: ='Biaya Bulanan'!$B$30 -> Teknologi | C9: ='Biaya Bulanan'!$C$30 -> Mobile Engineer (Senior) | D9: =IF(D$4<'Biaya Bulanan'!$I$30,0,IF(D$4<=3,'Biaya Bulanan'!$V$30,IF(D$4<=12,'Biaya Bulanan'!$W$30,'Biaya Bulanan'!$X$30)))*'Biaya Bulanan'!$T$30 -> 25533126 | E9: =IF(E$4<'Biaya Bulanan'!$I$30,0,IF(E$4<=3,'Biaya Bulanan'!$V$30,IF(E$4<=12,'Biaya Bulanan'!$W$30,'Biaya Bulanan'!$X$30)))*'Biaya Bulanan'!$T$30 -> 25533126 | F9: =IF(F$4<'Biaya Bulanan'!$I$30,0,IF(F$4<=3,'Biaya Bulanan'!$V$30,IF(F$4<=12,'Biaya Bulanan'!$W$30,'Biaya Bulanan'!$X$30)))*'Biaya Bulanan'!$T$30 -> 25533126 | G9: =IF(G$4<'Biaya Bulanan'!$I$30,0,IF(G$4<=3,'Biaya Bulanan'!$V$30,IF(G$4<=12,'Biaya Bulanan'!$W$30,'Biaya Bulanan'!$X$30)))*'Biaya Bulanan'!$T$30 -> 25533126 | H9: =IF(H$4<'Biaya Bulanan'!$I$30,0,IF(H$4<=3,'Biaya Bulanan'!$V$30,IF(H$4<=12,'Biaya Bulanan'!$W$30,'Biaya Bulanan'!$X$30)))*'Biaya Bulanan'!$T$30 -> 25533126 | I9: =IF(I$4<'Biaya Bulanan'!$I$30,0,IF(I$4<=3,'Biaya Bulanan'!$V$30,IF(I$4<=12,'Biaya Bulanan'!$W$30,'Biaya Bulanan'!$X$30)))*'Biaya Bulanan'!$T$30 -> 25533126 | J9: =IF(J$4<'Biaya Bulanan'!$I$30,0,IF(J$4<=3,'Biaya Bulanan'!$V$30,IF(J$4<=12,'Biaya Bulanan'!$W$30,'Biaya Bulanan'!$X$30)))*'Biaya Bulanan'!$T$30 -> 25533126 | K9: =IF(K$4<'Biaya Bulanan'!$I$30,0,IF(K$4<=3,'Biaya Bulanan'!$V$30,IF(K$4<=12,'Biaya Bulanan'!$W$30,'Biaya Bulanan'!$X$30)))*'Biaya Bulanan'!$T$30 -> 25533126 | ... AA9: =IF(AA$4<'Biaya Bulanan'!$I$30,0,IF(AA$4<=3,'Biaya Bulanan'!$V$30,IF(AA$4<=12,'Biaya Bulanan'!$W$30,'Biaya Bulanan'!$X$30)))*'Biaya Bulanan'!$T$30 -> 25533126
A10: 6 | B10: ='Biaya Bulanan'!$B$31 -> Teknologi | C10: ='Biaya Bulanan'!$C$31 -> Mobile Engineer (Mid) | D10: =IF(D$4<'Biaya Bulanan'!$I$31,0,IF(D$4<=3,'Biaya Bulanan'!$V$31,IF(D$4<=12,'Biaya Bulanan'!$W$31,'Biaya Bulanan'!$X$31)))*'Biaya Bulanan'!$T$31 -> 0 | E10: =IF(E$4<'Biaya Bulanan'!$I$31,0,IF(E$4<=3,'Biaya Bulanan'!$V$31,IF(E$4<=12,'Biaya Bulanan'!$W$31,'Biaya Bulanan'!$X$31)))*'Biaya Bulanan'!$T$31 -> 0 | F10: =IF(F$4<'Biaya Bulanan'!$I$31,0,IF(F$4<=3,'Biaya Bulanan'!$V$31,IF(F$4<=12,'Biaya Bulanan'!$W$31,'Biaya Bulanan'!$X$31)))*'Biaya Bulanan'!$T$31 -> 0 | G10: =IF(G$4<'Biaya Bulanan'!$I$31,0,IF(G$4<=3,'Biaya Bulanan'!$V$31,IF(G$4<=12,'Biaya Bulanan'!$W$31,'Biaya Bulanan'!$X$31)))*'Biaya Bulanan'!$T$31 -> 0 | H10: =IF(H$4<'Biaya Bulanan'!$I$31,0,IF(H$4<=3,'Biaya Bulanan'!$V$31,IF(H$4<=12,'Biaya Bulanan'!$W$31,'Biaya Bulanan'!$X$31)))*'Biaya Bulanan'!$T$31 -> 15600566 | I10: =IF(I$4<'Biaya Bulanan'!$I$31,0,IF(I$4<=3,'Biaya Bulanan'!$V$31,IF(I$4<=12,'Biaya Bulanan'!$W$31,'Biaya Bulanan'!$X$31)))*'Biaya Bulanan'!$T$31 -> 15600566 | J10: =IF(J$4<'Biaya Bulanan'!$I$31,0,IF(J$4<=3,'Biaya Bulanan'!$V$31,IF(J$4<=12,'Biaya Bulanan'!$W$31,'Biaya Bulanan'!$X$31)))*'Biaya Bulanan'!$T$31 -> 15600566 | K10: =IF(K$4<'Biaya Bulanan'!$I$31,0,IF(K$4<=3,'Biaya Bulanan'!$V$31,IF(K$4<=12,'Biaya Bulanan'!$W$31,'Biaya Bulanan'!$X$31)))*'Biaya Bulanan'!$T$31 -> 15600566 | ... AA10: =IF(AA$4<'Biaya Bulanan'!$I$31,0,IF(AA$4<=3,'Biaya Bulanan'!$V$31,IF(AA$4<=12,'Biaya Bulanan'!$W$31,'Biaya Bulanan'!$X$31)))*'Biaya Bulanan'!$T$31 -> 15600566
A11: 7 | B11: ='Biaya Bulanan'!$B$32 -> Teknologi | C11: ='Biaya Bulanan'!$C$32 -> Mobile Engineer (Mid) - gelombang 2 | D11: =IF(D$4<'Biaya Bulanan'!$I$32,0,IF(D$4<=3,'Biaya Bulanan'!$V$32,IF(D$4<=12,'Biaya Bulanan'!$W$32,'Biaya Bulanan'!$X$32)))*'Biaya Bulanan'!$T$32 -> 0 | E11: =IF(E$4<'Biaya Bulanan'!$I$32,0,IF(E$4<=3,'Biaya Bulanan'!$V$32,IF(E$4<=12,'Biaya Bulanan'!$W$32,'Biaya Bulanan'!$X$32)))*'Biaya Bulanan'!$T$32 -> 0 | F11: =IF(F$4<'Biaya Bulanan'!$I$32,0,IF(F$4<=3,'Biaya Bulanan'!$V$32,IF(F$4<=12,'Biaya Bulanan'!$W$32,'Biaya Bulanan'!$X$32)))*'Biaya Bulanan'!$T$32 -> 0 | G11: =IF(G$4<'Biaya Bulanan'!$I$32,0,IF(G$4<=3,'Biaya Bulanan'!$V$32,IF(G$4<=12,'Biaya Bulanan'!$W$32,'Biaya Bulanan'!$X$32)))*'Biaya Bulanan'!$T$32 -> 0 | H11: =IF(H$4<'Biaya Bulanan'!$I$32,0,IF(H$4<=3,'Biaya Bulanan'!$V$32,IF(H$4<=12,'Biaya Bulanan'!$W$32,'Biaya Bulanan'!$X$32)))*'Biaya Bulanan'!$T$32 -> 0 | I11: =IF(I$4<'Biaya Bulanan'!$I$32,0,IF(I$4<=3,'Biaya Bulanan'!$V$32,IF(I$4<=12,'Biaya Bulanan'!$W$32,'Biaya Bulanan'!$X$32)))*'Biaya Bulanan'!$T$32 -> 0 | J11: =IF(J$4<'Biaya Bulanan'!$I$32,0,IF(J$4<=3,'Biaya Bulanan'!$V$32,IF(J$4<=12,'Biaya Bulanan'!$W$32,'Biaya Bulanan'!$X$32)))*'Biaya Bulanan'!$T$32 -> 0 | K11: =IF(K$4<'Biaya Bulanan'!$I$32,0,IF(K$4<=3,'Biaya Bulanan'!$V$32,IF(K$4<=12,'Biaya Bulanan'!$W$32,'Biaya Bulanan'!$X$32)))*'Biaya Bulanan'!$T$32 -> 0 | ... AA11: =IF(AA$4<'Biaya Bulanan'!$I$32,0,IF(AA$4<=3,'Biaya Bulanan'!$V$32,IF(AA$4<=12,'Biaya Bulanan'!$W$32,'Biaya Bulanan'!$X$32)))*'Biaya Bulanan'!$T$32 -> 15600566
A12: 8 | B12: ='Biaya Bulanan'!$B$33 -> Teknologi | C12: ='Biaya Bulanan'!$C$33 -> Backend Engineer (Senior) | D12: =IF(D$4<'Biaya Bulanan'!$I$33,0,IF(D$4<=3,'Biaya Bulanan'!$V$33,IF(D$4<=12,'Biaya Bulanan'!$W$33,'Biaya Bulanan'!$X$33)))*'Biaya Bulanan'!$T$33 -> 25533126 | E12: =IF(E$4<'Biaya Bulanan'!$I$33,0,IF(E$4<=3,'Biaya Bulanan'!$V$33,IF(E$4<=12,'Biaya Bulanan'!$W$33,'Biaya Bulanan'!$X$33)))*'Biaya Bulanan'!$T$33 -> 25533126 | F12: =IF(F$4<'Biaya Bulanan'!$I$33,0,IF(F$4<=3,'Biaya Bulanan'!$V$33,IF(F$4<=12,'Biaya Bulanan'!$W$33,'Biaya Bulanan'!$X$33)))*'Biaya Bulanan'!$T$33 -> 25533126 | G12: =IF(G$4<'Biaya Bulanan'!$I$33,0,IF(G$4<=3,'Biaya Bulanan'!$V$33,IF(G$4<=12,'Biaya Bulanan'!$W$33,'Biaya Bulanan'!$X$33)))*'Biaya Bulanan'!$T$33 -> 25533126 | H12: =IF(H$4<'Biaya Bulanan'!$I$33,0,IF(H$4<=3,'Biaya Bulanan'!$V$33,IF(H$4<=12,'Biaya Bulanan'!$W$33,'Biaya Bulanan'!$X$33)))*'Biaya Bulanan'!$T$33 -> 25533126 | I12: =IF(I$4<'Biaya Bulanan'!$I$33,0,IF(I$4<=3,'Biaya Bulanan'!$V$33,IF(I$4<=12,'Biaya Bulanan'!$W$33,'Biaya Bulanan'!$X$33)))*'Biaya Bulanan'!$T$33 -> 25533126 | J12: =IF(J$4<'Biaya Bulanan'!$I$33,0,IF(J$4<=3,'Biaya Bulanan'!$V$33,IF(J$4<=12,'Biaya Bulanan'!$W$33,'Biaya Bulanan'!$X$33)))*'Biaya Bulanan'!$T$33 -> 25533126 | K12: =IF(K$4<'Biaya Bulanan'!$I$33,0,IF(K$4<=3,'Biaya Bulanan'!$V$33,IF(K$4<=12,'Biaya Bulanan'!$W$33,'Biaya Bulanan'!$X$33)))*'Biaya Bulanan'!$T$33 -> 25533126 | ... AA12: =IF(AA$4<'Biaya Bulanan'!$I$33,0,IF(AA$4<=3,'Biaya Bulanan'!$V$33,IF(AA$4<=12,'Biaya Bulanan'!$W$33,'Biaya Bulanan'!$X$33)))*'Biaya Bulanan'!$T$33 -> 25533126
A13: 9 | B13: ='Biaya Bulanan'!$B$34 -> Teknologi | C13: ='Biaya Bulanan'!$C$34 -> Backend Engineer (Senior) - gelombang 2 | D13: =IF(D$4<'Biaya Bulanan'!$I$34,0,IF(D$4<=3,'Biaya Bulanan'!$V$34,IF(D$4<=12,'Biaya Bulanan'!$W$34,'Biaya Bulanan'!$X$34)))*'Biaya Bulanan'!$T$34 -> 0 | E13: =IF(E$4<'Biaya Bulanan'!$I$34,0,IF(E$4<=3,'Biaya Bulanan'!$V$34,IF(E$4<=12,'Biaya Bulanan'!$W$34,'Biaya Bulanan'!$X$34)))*'Biaya Bulanan'!$T$34 -> 0 | F13: =IF(F$4<'Biaya Bulanan'!$I$34,0,IF(F$4<=3,'Biaya Bulanan'!$V$34,IF(F$4<=12,'Biaya Bulanan'!$W$34,'Biaya Bulanan'!$X$34)))*'Biaya Bulanan'!$T$34 -> 0 | G13: =IF(G$4<'Biaya Bulanan'!$I$34,0,IF(G$4<=3,'Biaya Bulanan'!$V$34,IF(G$4<=12,'Biaya Bulanan'!$W$34,'Biaya Bulanan'!$X$34)))*'Biaya Bulanan'!$T$34 -> 0 | H13: =IF(H$4<'Biaya Bulanan'!$I$34,0,IF(H$4<=3,'Biaya Bulanan'!$V$34,IF(H$4<=12,'Biaya Bulanan'!$W$34,'Biaya Bulanan'!$X$34)))*'Biaya Bulanan'!$T$34 -> 0 | I13: =IF(I$4<'Biaya Bulanan'!$I$34,0,IF(I$4<=3,'Biaya Bulanan'!$V$34,IF(I$4<=12,'Biaya Bulanan'!$W$34,'Biaya Bulanan'!$X$34)))*'Biaya Bulanan'!$T$34 -> 0 | J13: =IF(J$4<'Biaya Bulanan'!$I$34,0,IF(J$4<=3,'Biaya Bulanan'!$V$34,IF(J$4<=12,'Biaya Bulanan'!$W$34,'Biaya Bulanan'!$X$34)))*'Biaya Bulanan'!$T$34 -> 0 | K13: =IF(K$4<'Biaya Bulanan'!$I$34,0,IF(K$4<=3,'Biaya Bulanan'!$V$34,IF(K$4<=12,'Biaya Bulanan'!$W$34,'Biaya Bulanan'!$X$34)))*'Biaya Bulanan'!$T$34 -> 0 | ... AA13: =IF(AA$4<'Biaya Bulanan'!$I$34,0,IF(AA$4<=3,'Biaya Bulanan'!$V$34,IF(AA$4<=12,'Biaya Bulanan'!$W$34,'Biaya Bulanan'!$X$34)))*'Biaya Bulanan'!$T$34 -> 25533126
A14: 10 | B14: ='Biaya Bulanan'!$B$35 -> Teknologi | C14: ='Biaya Bulanan'!$C$35 -> Backend Engineer (Mid) | D14: =IF(D$4<'Biaya Bulanan'!$I$35,0,IF(D$4<=3,'Biaya Bulanan'!$V$35,IF(D$4<=12,'Biaya Bulanan'!$W$35,'Biaya Bulanan'!$X$35)))*'Biaya Bulanan'!$T$35 -> 0 | E14: =IF(E$4<'Biaya Bulanan'!$I$35,0,IF(E$4<=3,'Biaya Bulanan'!$V$35,IF(E$4<=12,'Biaya Bulanan'!$W$35,'Biaya Bulanan'!$X$35)))*'Biaya Bulanan'!$T$35 -> 0 | F14: =IF(F$4<'Biaya Bulanan'!$I$35,0,IF(F$4<=3,'Biaya Bulanan'!$V$35,IF(F$4<=12,'Biaya Bulanan'!$W$35,'Biaya Bulanan'!$X$35)))*'Biaya Bulanan'!$T$35 -> 0 | G14: =IF(G$4<'Biaya Bulanan'!$I$35,0,IF(G$4<=3,'Biaya Bulanan'!$V$35,IF(G$4<=12,'Biaya Bulanan'!$W$35,'Biaya Bulanan'!$X$35)))*'Biaya Bulanan'!$T$35 -> 15600566 | H14: =IF(H$4<'Biaya Bulanan'!$I$35,0,IF(H$4<=3,'Biaya Bulanan'!$V$35,IF(H$4<=12,'Biaya Bulanan'!$W$35,'Biaya Bulanan'!$X$35)))*'Biaya Bulanan'!$T$35 -> 15600566 | I14: =IF(I$4<'Biaya Bulanan'!$I$35,0,IF(I$4<=3,'Biaya Bulanan'!$V$35,IF(I$4<=12,'Biaya Bulanan'!$W$35,'Biaya Bulanan'!$X$35)))*'Biaya Bulanan'!$T$35 -> 15600566 | J14: =IF(J$4<'Biaya Bulanan'!$I$35,0,IF(J$4<=3,'Biaya Bulanan'!$V$35,IF(J$4<=12,'Biaya Bulanan'!$W$35,'Biaya Bulanan'!$X$35)))*'Biaya Bulanan'!$T$35 -> 15600566 | K14: =IF(K$4<'Biaya Bulanan'!$I$35,0,IF(K$4<=3,'Biaya Bulanan'!$V$35,IF(K$4<=12,'Biaya Bulanan'!$W$35,'Biaya Bulanan'!$X$35)))*'Biaya Bulanan'!$T$35 -> 15600566 | ... AA14: =IF(AA$4<'Biaya Bulanan'!$I$35,0,IF(AA$4<=3,'Biaya Bulanan'!$V$35,IF(AA$4<=12,'Biaya Bulanan'!$W$35,'Biaya Bulanan'!$X$35)))*'Biaya Bulanan'!$T$35 -> 15600566
A15: 11 | B15: ='Biaya Bulanan'!$B$36 -> Teknologi | C15: ='Biaya Bulanan'!$C$36 -> Backend Engineer (Mid) - gelombang 2 | D15: =IF(D$4<'Biaya Bulanan'!$I$36,0,IF(D$4<=3,'Biaya Bulanan'!$V$36,IF(D$4<=12,'Biaya Bulanan'!$W$36,'Biaya Bulanan'!$X$36)))*'Biaya Bulanan'!$T$36 -> 0 | E15: =IF(E$4<'Biaya Bulanan'!$I$36,0,IF(E$4<=3,'Biaya Bulanan'!$V$36,IF(E$4<=12,'Biaya Bulanan'!$W$36,'Biaya Bulanan'!$X$36)))*'Biaya Bulanan'!$T$36 -> 0 | F15: =IF(F$4<'Biaya Bulanan'!$I$36,0,IF(F$4<=3,'Biaya Bulanan'!$V$36,IF(F$4<=12,'Biaya Bulanan'!$W$36,'Biaya Bulanan'!$X$36)))*'Biaya Bulanan'!$T$36 -> 0 | G15: =IF(G$4<'Biaya Bulanan'!$I$36,0,IF(G$4<=3,'Biaya Bulanan'!$V$36,IF(G$4<=12,'Biaya Bulanan'!$W$36,'Biaya Bulanan'!$X$36)))*'Biaya Bulanan'!$T$36 -> 0 | H15: =IF(H$4<'Biaya Bulanan'!$I$36,0,IF(H$4<=3,'Biaya Bulanan'!$V$36,IF(H$4<=12,'Biaya Bulanan'!$W$36,'Biaya Bulanan'!$X$36)))*'Biaya Bulanan'!$T$36 -> 0 | I15: =IF(I$4<'Biaya Bulanan'!$I$36,0,IF(I$4<=3,'Biaya Bulanan'!$V$36,IF(I$4<=12,'Biaya Bulanan'!$W$36,'Biaya Bulanan'!$X$36)))*'Biaya Bulanan'!$T$36 -> 0 | J15: =IF(J$4<'Biaya Bulanan'!$I$36,0,IF(J$4<=3,'Biaya Bulanan'!$V$36,IF(J$4<=12,'Biaya Bulanan'!$W$36,'Biaya Bulanan'!$X$36)))*'Biaya Bulanan'!$T$36 -> 0 | K15: =IF(K$4<'Biaya Bulanan'!$I$36,0,IF(K$4<=3,'Biaya Bulanan'!$V$36,IF(K$4<=12,'Biaya Bulanan'!$W$36,'Biaya Bulanan'!$X$36)))*'Biaya Bulanan'!$T$36 -> 0 | ... AA15: =IF(AA$4<'Biaya Bulanan'!$I$36,0,IF(AA$4<=3,'Biaya Bulanan'!$V$36,IF(AA$4<=12,'Biaya Bulanan'!$W$36,'Biaya Bulanan'!$X$36)))*'Biaya Bulanan'!$T$36 -> 15600566
A16: 12 | B16: ='Biaya Bulanan'!$B$37 -> Teknologi | C16: ='Biaya Bulanan'!$C$37 -> QA Engineer | D16: =IF(D$4<'Biaya Bulanan'!$I$37,0,IF(D$4<=3,'Biaya Bulanan'!$V$37,IF(D$4<=12,'Biaya Bulanan'!$W$37,'Biaya Bulanan'!$X$37)))*'Biaya Bulanan'!$T$37 -> 0 | E16: =IF(E$4<'Biaya Bulanan'!$I$37,0,IF(E$4<=3,'Biaya Bulanan'!$V$37,IF(E$4<=12,'Biaya Bulanan'!$W$37,'Biaya Bulanan'!$X$37)))*'Biaya Bulanan'!$T$37 -> 0 | F16: =IF(F$4<'Biaya Bulanan'!$I$37,0,IF(F$4<=3,'Biaya Bulanan'!$V$37,IF(F$4<=12,'Biaya Bulanan'!$W$37,'Biaya Bulanan'!$X$37)))*'Biaya Bulanan'!$T$37 -> 0 | G16: =IF(G$4<'Biaya Bulanan'!$I$37,0,IF(G$4<=3,'Biaya Bulanan'!$V$37,IF(G$4<=12,'Biaya Bulanan'!$W$37,'Biaya Bulanan'!$X$37)))*'Biaya Bulanan'!$T$37 -> 0 | H16: =IF(H$4<'Biaya Bulanan'!$I$37,0,IF(H$4<=3,'Biaya Bulanan'!$V$37,IF(H$4<=12,'Biaya Bulanan'!$W$37,'Biaya Bulanan'!$X$37)))*'Biaya Bulanan'!$T$37 -> 0 | I16: =IF(I$4<'Biaya Bulanan'!$I$37,0,IF(I$4<=3,'Biaya Bulanan'!$V$37,IF(I$4<=12,'Biaya Bulanan'!$W$37,'Biaya Bulanan'!$X$37)))*'Biaya Bulanan'!$T$37 -> 13075700 | J16: =IF(J$4<'Biaya Bulanan'!$I$37,0,IF(J$4<=3,'Biaya Bulanan'!$V$37,IF(J$4<=12,'Biaya Bulanan'!$W$37,'Biaya Bulanan'!$X$37)))*'Biaya Bulanan'!$T$37 -> 13075700 | K16: =IF(K$4<'Biaya Bulanan'!$I$37,0,IF(K$4<=3,'Biaya Bulanan'!$V$37,IF(K$4<=12,'Biaya Bulanan'!$W$37,'Biaya Bulanan'!$X$37)))*'Biaya Bulanan'!$T$37 -> 13075700 | ... AA16: =IF(AA$4<'Biaya Bulanan'!$I$37,0,IF(AA$4<=3,'Biaya Bulanan'!$V$37,IF(AA$4<=12,'Biaya Bulanan'!$W$37,'Biaya Bulanan'!$X$37)))*'Biaya Bulanan'!$T$37 -> 13075700
A17: 13 | B17: ='Biaya Bulanan'!$B$38 -> Teknologi | C17: ='Biaya Bulanan'!$C$38 -> QA Engineer - gelombang 2 | D17: =IF(D$4<'Biaya Bulanan'!$I$38,0,IF(D$4<=3,'Biaya Bulanan'!$V$38,IF(D$4<=12,'Biaya Bulanan'!$W$38,'Biaya Bulanan'!$X$38)))*'Biaya Bulanan'!$T$38 -> 0 | E17: =IF(E$4<'Biaya Bulanan'!$I$38,0,IF(E$4<=3,'Biaya Bulanan'!$V$38,IF(E$4<=12,'Biaya Bulanan'!$W$38,'Biaya Bulanan'!$X$38)))*'Biaya Bulanan'!$T$38 -> 0 | F17: =IF(F$4<'Biaya Bulanan'!$I$38,0,IF(F$4<=3,'Biaya Bulanan'!$V$38,IF(F$4<=12,'Biaya Bulanan'!$W$38,'Biaya Bulanan'!$X$38)))*'Biaya Bulanan'!$T$38 -> 0 | G17: =IF(G$4<'Biaya Bulanan'!$I$38,0,IF(G$4<=3,'Biaya Bulanan'!$V$38,IF(G$4<=12,'Biaya Bulanan'!$W$38,'Biaya Bulanan'!$X$38)))*'Biaya Bulanan'!$T$38 -> 0 | H17: =IF(H$4<'Biaya Bulanan'!$I$38,0,IF(H$4<=3,'Biaya Bulanan'!$V$38,IF(H$4<=12,'Biaya Bulanan'!$W$38,'Biaya Bulanan'!$X$38)))*'Biaya Bulanan'!$T$38 -> 0 | I17: =IF(I$4<'Biaya Bulanan'!$I$38,0,IF(I$4<=3,'Biaya Bulanan'!$V$38,IF(I$4<=12,'Biaya Bulanan'!$W$38,'Biaya Bulanan'!$X$38)))*'Biaya Bulanan'!$T$38 -> 0 | J17: =IF(J$4<'Biaya Bulanan'!$I$38,0,IF(J$4<=3,'Biaya Bulanan'!$V$38,IF(J$4<=12,'Biaya Bulanan'!$W$38,'Biaya Bulanan'!$X$38)))*'Biaya Bulanan'!$T$38 -> 0 | K17: =IF(K$4<'Biaya Bulanan'!$I$38,0,IF(K$4<=3,'Biaya Bulanan'!$V$38,IF(K$4<=12,'Biaya Bulanan'!$W$38,'Biaya Bulanan'!$X$38)))*'Biaya Bulanan'!$T$38 -> 0 | ... AA17: =IF(AA$4<'Biaya Bulanan'!$I$38,0,IF(AA$4<=3,'Biaya Bulanan'!$V$38,IF(AA$4<=12,'Biaya Bulanan'!$W$38,'Biaya Bulanan'!$X$38)))*'Biaya Bulanan'!$T$38 -> 13075700
A18: 14 | B18: ='Biaya Bulanan'!$B$39 -> Teknologi | C18: ='Biaya Bulanan'!$C$39 -> Junior Software Engineer | D18: =IF(D$4<'Biaya Bulanan'!$I$39,0,IF(D$4<=3,'Biaya Bulanan'!$V$39,IF(D$4<=12,'Biaya Bulanan'!$W$39,'Biaya Bulanan'!$X$39)))*'Biaya Bulanan'!$T$39 -> 0 | E18: =IF(E$4<'Biaya Bulanan'!$I$39,0,IF(E$4<=3,'Biaya Bulanan'!$V$39,IF(E$4<=12,'Biaya Bulanan'!$W$39,'Biaya Bulanan'!$X$39)))*'Biaya Bulanan'!$T$39 -> 0 | F18: =IF(F$4<'Biaya Bulanan'!$I$39,0,IF(F$4<=3,'Biaya Bulanan'!$V$39,IF(F$4<=12,'Biaya Bulanan'!$W$39,'Biaya Bulanan'!$X$39)))*'Biaya Bulanan'!$T$39 -> 0 | G18: =IF(G$4<'Biaya Bulanan'!$I$39,0,IF(G$4<=3,'Biaya Bulanan'!$V$39,IF(G$4<=12,'Biaya Bulanan'!$W$39,'Biaya Bulanan'!$X$39)))*'Biaya Bulanan'!$T$39 -> 0 | H18: =IF(H$4<'Biaya Bulanan'!$I$39,0,IF(H$4<=3,'Biaya Bulanan'!$V$39,IF(H$4<=12,'Biaya Bulanan'!$W$39,'Biaya Bulanan'!$X$39)))*'Biaya Bulanan'!$T$39 -> 0 | I18: =IF(I$4<'Biaya Bulanan'!$I$39,0,IF(I$4<=3,'Biaya Bulanan'!$V$39,IF(I$4<=12,'Biaya Bulanan'!$W$39,'Biaya Bulanan'!$X$39)))*'Biaya Bulanan'!$T$39 -> 0 | J18: =IF(J$4<'Biaya Bulanan'!$I$39,0,IF(J$4<=3,'Biaya Bulanan'!$V$39,IF(J$4<=12,'Biaya Bulanan'!$W$39,'Biaya Bulanan'!$X$39)))*'Biaya Bulanan'!$T$39 -> 0 | K18: =IF(K$4<'Biaya Bulanan'!$I$39,0,IF(K$4<=3,'Biaya Bulanan'!$V$39,IF(K$4<=12,'Biaya Bulanan'!$W$39,'Biaya Bulanan'!$X$39)))*'Biaya Bulanan'!$T$39 -> 0 | ... AA18: =IF(AA$4<'Biaya Bulanan'!$I$39,0,IF(AA$4<=3,'Biaya Bulanan'!$V$39,IF(AA$4<=12,'Biaya Bulanan'!$W$39,'Biaya Bulanan'!$X$39)))*'Biaya Bulanan'!$T$39 -> 9806775
A19: 15 | B19: ='Biaya Bulanan'!$B$40 -> Teknologi | C19: ='Biaya Bulanan'!$C$40 -> Junior Software Engineer - Padang | D19: =IF(D$4<'Biaya Bulanan'!$I$40,0,IF(D$4<=3,'Biaya Bulanan'!$V$40,IF(D$4<=12,'Biaya Bulanan'!$W$40,'Biaya Bulanan'!$X$40)))*'Biaya Bulanan'!$T$40 -> 0 | E19: =IF(E$4<'Biaya Bulanan'!$I$40,0,IF(E$4<=3,'Biaya Bulanan'!$V$40,IF(E$4<=12,'Biaya Bulanan'!$W$40,'Biaya Bulanan'!$X$40)))*'Biaya Bulanan'!$T$40 -> 0 | F19: =IF(F$4<'Biaya Bulanan'!$I$40,0,IF(F$4<=3,'Biaya Bulanan'!$V$40,IF(F$4<=12,'Biaya Bulanan'!$W$40,'Biaya Bulanan'!$X$40)))*'Biaya Bulanan'!$T$40 -> 0 | G19: =IF(G$4<'Biaya Bulanan'!$I$40,0,IF(G$4<=3,'Biaya Bulanan'!$V$40,IF(G$4<=12,'Biaya Bulanan'!$W$40,'Biaya Bulanan'!$X$40)))*'Biaya Bulanan'!$T$40 -> 0 | H19: =IF(H$4<'Biaya Bulanan'!$I$40,0,IF(H$4<=3,'Biaya Bulanan'!$V$40,IF(H$4<=12,'Biaya Bulanan'!$W$40,'Biaya Bulanan'!$X$40)))*'Biaya Bulanan'!$T$40 -> 0 | I19: =IF(I$4<'Biaya Bulanan'!$I$40,0,IF(I$4<=3,'Biaya Bulanan'!$V$40,IF(I$4<=12,'Biaya Bulanan'!$W$40,'Biaya Bulanan'!$X$40)))*'Biaya Bulanan'!$T$40 -> 0 | J19: =IF(J$4<'Biaya Bulanan'!$I$40,0,IF(J$4<=3,'Biaya Bulanan'!$V$40,IF(J$4<=12,'Biaya Bulanan'!$W$40,'Biaya Bulanan'!$X$40)))*'Biaya Bulanan'!$T$40 -> 0 | K19: =IF(K$4<'Biaya Bulanan'!$I$40,0,IF(K$4<=3,'Biaya Bulanan'!$V$40,IF(K$4<=12,'Biaya Bulanan'!$W$40,'Biaya Bulanan'!$X$40)))*'Biaya Bulanan'!$T$40 -> 0 | ... AA19: =IF(AA$4<'Biaya Bulanan'!$I$40,0,IF(AA$4<=3,'Biaya Bulanan'!$V$40,IF(AA$4<=12,'Biaya Bulanan'!$W$40,'Biaya Bulanan'!$X$40)))*'Biaya Bulanan'!$T$40 -> 9152990
A20: 16 | B20: ='Biaya Bulanan'!$B$41 -> Teknologi | C20: ='Biaya Bulanan'!$C$41 -> Product Designer (UI/UX) | D20: =IF(D$4<'Biaya Bulanan'!$I$41,0,IF(D$4<=3,'Biaya Bulanan'!$V$41,IF(D$4<=12,'Biaya Bulanan'!$W$41,'Biaya Bulanan'!$X$41)))*'Biaya Bulanan'!$T$41 -> 0 | E20: =IF(E$4<'Biaya Bulanan'!$I$41,0,IF(E$4<=3,'Biaya Bulanan'!$V$41,IF(E$4<=12,'Biaya Bulanan'!$W$41,'Biaya Bulanan'!$X$41)))*'Biaya Bulanan'!$T$41 -> 16842136 | F20: =IF(F$4<'Biaya Bulanan'!$I$41,0,IF(F$4<=3,'Biaya Bulanan'!$V$41,IF(F$4<=12,'Biaya Bulanan'!$W$41,'Biaya Bulanan'!$X$41)))*'Biaya Bulanan'!$T$41 -> 16842136 | G20: =IF(G$4<'Biaya Bulanan'!$I$41,0,IF(G$4<=3,'Biaya Bulanan'!$V$41,IF(G$4<=12,'Biaya Bulanan'!$W$41,'Biaya Bulanan'!$X$41)))*'Biaya Bulanan'!$T$41 -> 16842136 | H20: =IF(H$4<'Biaya Bulanan'!$I$41,0,IF(H$4<=3,'Biaya Bulanan'!$V$41,IF(H$4<=12,'Biaya Bulanan'!$W$41,'Biaya Bulanan'!$X$41)))*'Biaya Bulanan'!$T$41 -> 16842136 | I20: =IF(I$4<'Biaya Bulanan'!$I$41,0,IF(I$4<=3,'Biaya Bulanan'!$V$41,IF(I$4<=12,'Biaya Bulanan'!$W$41,'Biaya Bulanan'!$X$41)))*'Biaya Bulanan'!$T$41 -> 16842136 | J20: =IF(J$4<'Biaya Bulanan'!$I$41,0,IF(J$4<=3,'Biaya Bulanan'!$V$41,IF(J$4<=12,'Biaya Bulanan'!$W$41,'Biaya Bulanan'!$X$41)))*'Biaya Bulanan'!$T$41 -> 16842136 | K20: =IF(K$4<'Biaya Bulanan'!$I$41,0,IF(K$4<=3,'Biaya Bulanan'!$V$41,IF(K$4<=12,'Biaya Bulanan'!$W$41,'Biaya Bulanan'!$X$41)))*'Biaya Bulanan'!$T$41 -> 16842136 | ... AA20: =IF(AA$4<'Biaya Bulanan'!$I$41,0,IF(AA$4<=3,'Biaya Bulanan'!$V$41,IF(AA$4<=12,'Biaya Bulanan'!$W$41,'Biaya Bulanan'!$X$41)))*'Biaya Bulanan'!$T$41 -> 16842136
A21: 17 | B21: ='Biaya Bulanan'!$B$42 -> Teknologi | C21: ='Biaya Bulanan'!$C$42 -> Product Designer (UI/UX) - gelombang 2 | D21: =IF(D$4<'Biaya Bulanan'!$I$42,0,IF(D$4<=3,'Biaya Bulanan'!$V$42,IF(D$4<=12,'Biaya Bulanan'!$W$42,'Biaya Bulanan'!$X$42)))*'Biaya Bulanan'!$T$42 -> 0 | E21: =IF(E$4<'Biaya Bulanan'!$I$42,0,IF(E$4<=3,'Biaya Bulanan'!$V$42,IF(E$4<=12,'Biaya Bulanan'!$W$42,'Biaya Bulanan'!$X$42)))*'Biaya Bulanan'!$T$42 -> 0 | F21: =IF(F$4<'Biaya Bulanan'!$I$42,0,IF(F$4<=3,'Biaya Bulanan'!$V$42,IF(F$4<=12,'Biaya Bulanan'!$W$42,'Biaya Bulanan'!$X$42)))*'Biaya Bulanan'!$T$42 -> 0 | G21: =IF(G$4<'Biaya Bulanan'!$I$42,0,IF(G$4<=3,'Biaya Bulanan'!$V$42,IF(G$4<=12,'Biaya Bulanan'!$W$42,'Biaya Bulanan'!$X$42)))*'Biaya Bulanan'!$T$42 -> 0 | H21: =IF(H$4<'Biaya Bulanan'!$I$42,0,IF(H$4<=3,'Biaya Bulanan'!$V$42,IF(H$4<=12,'Biaya Bulanan'!$W$42,'Biaya Bulanan'!$X$42)))*'Biaya Bulanan'!$T$42 -> 0 | I21: =IF(I$4<'Biaya Bulanan'!$I$42,0,IF(I$4<=3,'Biaya Bulanan'!$V$42,IF(I$4<=12,'Biaya Bulanan'!$W$42,'Biaya Bulanan'!$X$42)))*'Biaya Bulanan'!$T$42 -> 0 | J21: =IF(J$4<'Biaya Bulanan'!$I$42,0,IF(J$4<=3,'Biaya Bulanan'!$V$42,IF(J$4<=12,'Biaya Bulanan'!$W$42,'Biaya Bulanan'!$X$42)))*'Biaya Bulanan'!$T$42 -> 0 | K21: =IF(K$4<'Biaya Bulanan'!$I$42,0,IF(K$4<=3,'Biaya Bulanan'!$V$42,IF(K$4<=12,'Biaya Bulanan'!$W$42,'Biaya Bulanan'!$X$42)))*'Biaya Bulanan'!$T$42 -> 0 | ... AA21: =IF(AA$4<'Biaya Bulanan'!$I$42,0,IF(AA$4<=3,'Biaya Bulanan'!$V$42,IF(AA$4<=12,'Biaya Bulanan'!$W$42,'Biaya Bulanan'!$X$42)))*'Biaya Bulanan'!$T$42 -> 16842136
A22: 18 | B22: ='Biaya Bulanan'!$B$43 -> Teknologi | C22: ='Biaya Bulanan'!$C$43 -> Data Analyst | D22: =IF(D$4<'Biaya Bulanan'!$I$43,0,IF(D$4<=3,'Biaya Bulanan'!$V$43,IF(D$4<=12,'Biaya Bulanan'!$W$43,'Biaya Bulanan'!$X$43)))*'Biaya Bulanan'!$T$43 -> 0 | E22: =IF(E$4<'Biaya Bulanan'!$I$43,0,IF(E$4<=3,'Biaya Bulanan'!$V$43,IF(E$4<=12,'Biaya Bulanan'!$W$43,'Biaya Bulanan'!$X$43)))*'Biaya Bulanan'!$T$43 -> 0 | F22: =IF(F$4<'Biaya Bulanan'!$I$43,0,IF(F$4<=3,'Biaya Bulanan'!$V$43,IF(F$4<=12,'Biaya Bulanan'!$W$43,'Biaya Bulanan'!$X$43)))*'Biaya Bulanan'!$T$43 -> 0 | G22: =IF(G$4<'Biaya Bulanan'!$I$43,0,IF(G$4<=3,'Biaya Bulanan'!$V$43,IF(G$4<=12,'Biaya Bulanan'!$W$43,'Biaya Bulanan'!$X$43)))*'Biaya Bulanan'!$T$43 -> 0 | H22: =IF(H$4<'Biaya Bulanan'!$I$43,0,IF(H$4<=3,'Biaya Bulanan'!$V$43,IF(H$4<=12,'Biaya Bulanan'!$W$43,'Biaya Bulanan'!$X$43)))*'Biaya Bulanan'!$T$43 -> 0 | I22: =IF(I$4<'Biaya Bulanan'!$I$43,0,IF(I$4<=3,'Biaya Bulanan'!$V$43,IF(I$4<=12,'Biaya Bulanan'!$W$43,'Biaya Bulanan'!$X$43)))*'Biaya Bulanan'!$T$43 -> 0 | J22: =IF(J$4<'Biaya Bulanan'!$I$43,0,IF(J$4<=3,'Biaya Bulanan'!$V$43,IF(J$4<=12,'Biaya Bulanan'!$W$43,'Biaya Bulanan'!$X$43)))*'Biaya Bulanan'!$T$43 -> 0 | K22: =IF(K$4<'Biaya Bulanan'!$I$43,0,IF(K$4<=3,'Biaya Bulanan'!$V$43,IF(K$4<=12,'Biaya Bulanan'!$W$43,'Biaya Bulanan'!$X$43)))*'Biaya Bulanan'!$T$43 -> 0 | ... AA22: =IF(AA$4<'Biaya Bulanan'!$I$43,0,IF(AA$4<=3,'Biaya Bulanan'!$V$43,IF(AA$4<=12,'Biaya Bulanan'!$W$43,'Biaya Bulanan'!$X$43)))*'Biaya Bulanan'!$T$43 -> 14979781
A23: 19 | B23: ='Biaya Bulanan'!$B$44 -> Operasi | C23: ='Biaya Bulanan'!$C$44 -> Direktur Operasi (COO) | D23: =IF(D$4<'Biaya Bulanan'!$I$44,0,IF(D$4<=3,'Biaya Bulanan'!$V$44,IF(D$4<=12,'Biaya Bulanan'!$W$44,'Biaya Bulanan'!$X$44)))*'Biaya Bulanan'!$T$44 -> 25533126 | E23: =IF(E$4<'Biaya Bulanan'!$I$44,0,IF(E$4<=3,'Biaya Bulanan'!$V$44,IF(E$4<=12,'Biaya Bulanan'!$W$44,'Biaya Bulanan'!$X$44)))*'Biaya Bulanan'!$T$44 -> 25533126 | F23: =IF(F$4<'Biaya Bulanan'!$I$44,0,IF(F$4<=3,'Biaya Bulanan'!$V$44,IF(F$4<=12,'Biaya Bulanan'!$W$44,'Biaya Bulanan'!$X$44)))*'Biaya Bulanan'!$T$44 -> 25533126 | G23: =IF(G$4<'Biaya Bulanan'!$I$44,0,IF(G$4<=3,'Biaya Bulanan'!$V$44,IF(G$4<=12,'Biaya Bulanan'!$W$44,'Biaya Bulanan'!$X$44)))*'Biaya Bulanan'!$T$44 -> 25533126 | H23: =IF(H$4<'Biaya Bulanan'!$I$44,0,IF(H$4<=3,'Biaya Bulanan'!$V$44,IF(H$4<=12,'Biaya Bulanan'!$W$44,'Biaya Bulanan'!$X$44)))*'Biaya Bulanan'!$T$44 -> 25533126 | I23: =IF(I$4<'Biaya Bulanan'!$I$44,0,IF(I$4<=3,'Biaya Bulanan'!$V$44,IF(I$4<=12,'Biaya Bulanan'!$W$44,'Biaya Bulanan'!$X$44)))*'Biaya Bulanan'!$T$44 -> 25533126 | J23: =IF(J$4<'Biaya Bulanan'!$I$44,0,IF(J$4<=3,'Biaya Bulanan'!$V$44,IF(J$4<=12,'Biaya Bulanan'!$W$44,'Biaya Bulanan'!$X$44)))*'Biaya Bulanan'!$T$44 -> 25533126 | K23: =IF(K$4<'Biaya Bulanan'!$I$44,0,IF(K$4<=3,'Biaya Bulanan'!$V$44,IF(K$4<=12,'Biaya Bulanan'!$W$44,'Biaya Bulanan'!$X$44)))*'Biaya Bulanan'!$T$44 -> 25533126 | ... AA23: =IF(AA$4<'Biaya Bulanan'!$I$44,0,IF(AA$4<=3,'Biaya Bulanan'!$V$44,IF(AA$4<=12,'Biaya Bulanan'!$W$44,'Biaya Bulanan'!$X$44)))*'Biaya Bulanan'!$T$44 -> 25533126
A24: 20 | B24: ='Biaya Bulanan'!$B$45 -> Operasi | C24: ='Biaya Bulanan'!$C$45 -> City Manager Pekanbaru | D24: =IF(D$4<'Biaya Bulanan'!$I$45,0,IF(D$4<=3,'Biaya Bulanan'!$V$45,IF(D$4<=12,'Biaya Bulanan'!$W$45,'Biaya Bulanan'!$X$45)))*'Biaya Bulanan'!$T$45 -> 0 | E24: =IF(E$4<'Biaya Bulanan'!$I$45,0,IF(E$4<=3,'Biaya Bulanan'!$V$45,IF(E$4<=12,'Biaya Bulanan'!$W$45,'Biaya Bulanan'!$X$45)))*'Biaya Bulanan'!$T$45 -> 18137606 | F24: =IF(F$4<'Biaya Bulanan'!$I$45,0,IF(F$4<=3,'Biaya Bulanan'!$V$45,IF(F$4<=12,'Biaya Bulanan'!$W$45,'Biaya Bulanan'!$X$45)))*'Biaya Bulanan'!$T$45 -> 18137606 | G24: =IF(G$4<'Biaya Bulanan'!$I$45,0,IF(G$4<=3,'Biaya Bulanan'!$V$45,IF(G$4<=12,'Biaya Bulanan'!$W$45,'Biaya Bulanan'!$X$45)))*'Biaya Bulanan'!$T$45 -> 18137606 | H24: =IF(H$4<'Biaya Bulanan'!$I$45,0,IF(H$4<=3,'Biaya Bulanan'!$V$45,IF(H$4<=12,'Biaya Bulanan'!$W$45,'Biaya Bulanan'!$X$45)))*'Biaya Bulanan'!$T$45 -> 18137606 | I24: =IF(I$4<'Biaya Bulanan'!$I$45,0,IF(I$4<=3,'Biaya Bulanan'!$V$45,IF(I$4<=12,'Biaya Bulanan'!$W$45,'Biaya Bulanan'!$X$45)))*'Biaya Bulanan'!$T$45 -> 18137606 | J24: =IF(J$4<'Biaya Bulanan'!$I$45,0,IF(J$4<=3,'Biaya Bulanan'!$V$45,IF(J$4<=12,'Biaya Bulanan'!$W$45,'Biaya Bulanan'!$X$45)))*'Biaya Bulanan'!$T$45 -> 18137606 | K24: =IF(K$4<'Biaya Bulanan'!$I$45,0,IF(K$4<=3,'Biaya Bulanan'!$V$45,IF(K$4<=12,'Biaya Bulanan'!$W$45,'Biaya Bulanan'!$X$45)))*'Biaya Bulanan'!$T$45 -> 18137606 | ... AA24: =IF(AA$4<'Biaya Bulanan'!$I$45,0,IF(AA$4<=3,'Biaya Bulanan'!$V$45,IF(AA$4<=12,'Biaya Bulanan'!$W$45,'Biaya Bulanan'!$X$45)))*'Biaya Bulanan'!$T$45 -> 18137606
A25: 21 | B25: ='Biaya Bulanan'!$B$46 -> Operasi | C25: ='Biaya Bulanan'!$C$46 -> Ops Supervisor Pekanbaru | D25: =IF(D$4<'Biaya Bulanan'!$I$46,0,IF(D$4<=3,'Biaya Bulanan'!$V$46,IF(D$4<=12,'Biaya Bulanan'!$W$46,'Biaya Bulanan'!$X$46)))*'Biaya Bulanan'!$T$46 -> 0 | E25: =IF(E$4<'Biaya Bulanan'!$I$46,0,IF(E$4<=3,'Biaya Bulanan'!$V$46,IF(E$4<=12,'Biaya Bulanan'!$W$46,'Biaya Bulanan'!$X$46)))*'Biaya Bulanan'!$T$46 -> 0 | F25: =IF(F$4<'Biaya Bulanan'!$I$46,0,IF(F$4<=3,'Biaya Bulanan'!$V$46,IF(F$4<=12,'Biaya Bulanan'!$W$46,'Biaya Bulanan'!$X$46)))*'Biaya Bulanan'!$T$46 -> 0 | G25: =IF(G$4<'Biaya Bulanan'!$I$46,0,IF(G$4<=3,'Biaya Bulanan'!$V$46,IF(G$4<=12,'Biaya Bulanan'!$W$46,'Biaya Bulanan'!$X$46)))*'Biaya Bulanan'!$T$46 -> 9835650 | H25: =IF(H$4<'Biaya Bulanan'!$I$46,0,IF(H$4<=3,'Biaya Bulanan'!$V$46,IF(H$4<=12,'Biaya Bulanan'!$W$46,'Biaya Bulanan'!$X$46)))*'Biaya Bulanan'!$T$46 -> 9835650 | I25: =IF(I$4<'Biaya Bulanan'!$I$46,0,IF(I$4<=3,'Biaya Bulanan'!$V$46,IF(I$4<=12,'Biaya Bulanan'!$W$46,'Biaya Bulanan'!$X$46)))*'Biaya Bulanan'!$T$46 -> 9835650 | J25: =IF(J$4<'Biaya Bulanan'!$I$46,0,IF(J$4<=3,'Biaya Bulanan'!$V$46,IF(J$4<=12,'Biaya Bulanan'!$W$46,'Biaya Bulanan'!$X$46)))*'Biaya Bulanan'!$T$46 -> 9835650 | K25: =IF(K$4<'Biaya Bulanan'!$I$46,0,IF(K$4<=3,'Biaya Bulanan'!$V$46,IF(K$4<=12,'Biaya Bulanan'!$W$46,'Biaya Bulanan'!$X$46)))*'Biaya Bulanan'!$T$46 -> 9835650 | ... AA25: =IF(AA$4<'Biaya Bulanan'!$I$46,0,IF(AA$4<=3,'Biaya Bulanan'!$V$46,IF(AA$4<=12,'Biaya Bulanan'!$W$46,'Biaya Bulanan'!$X$46)))*'Biaya Bulanan'!$T$46 -> 9835650
A26: 22 | B26: ='Biaya Bulanan'!$B$47 -> Operasi | C26: ='Biaya Bulanan'!$C$47 -> Partner Acquisition Pekanbaru | D26: =IF(D$4<'Biaya Bulanan'!$I$47,0,IF(D$4<=3,'Biaya Bulanan'!$V$47,IF(D$4<=12,'Biaya Bulanan'!$W$47,'Biaya Bulanan'!$X$47)))*'Biaya Bulanan'!$T$47 -> 0 | E26: =IF(E$4<'Biaya Bulanan'!$I$47,0,IF(E$4<=3,'Biaya Bulanan'!$V$47,IF(E$4<=12,'Biaya Bulanan'!$W$47,'Biaya Bulanan'!$X$47)))*'Biaya Bulanan'!$T$47 -> 0 | F26: =IF(F$4<'Biaya Bulanan'!$I$47,0,IF(F$4<=3,'Biaya Bulanan'!$V$47,IF(F$4<=12,'Biaya Bulanan'!$W$47,'Biaya Bulanan'!$X$47)))*'Biaya Bulanan'!$T$47 -> 0 | G26: =IF(G$4<'Biaya Bulanan'!$I$47,0,IF(G$4<=3,'Biaya Bulanan'!$V$47,IF(G$4<=12,'Biaya Bulanan'!$W$47,'Biaya Bulanan'!$X$47)))*'Biaya Bulanan'!$T$47 -> 13769910 | H26: =IF(H$4<'Biaya Bulanan'!$I$47,0,IF(H$4<=3,'Biaya Bulanan'!$V$47,IF(H$4<=12,'Biaya Bulanan'!$W$47,'Biaya Bulanan'!$X$47)))*'Biaya Bulanan'!$T$47 -> 13769910 | I26: =IF(I$4<'Biaya Bulanan'!$I$47,0,IF(I$4<=3,'Biaya Bulanan'!$V$47,IF(I$4<=12,'Biaya Bulanan'!$W$47,'Biaya Bulanan'!$X$47)))*'Biaya Bulanan'!$T$47 -> 13769910 | J26: =IF(J$4<'Biaya Bulanan'!$I$47,0,IF(J$4<=3,'Biaya Bulanan'!$V$47,IF(J$4<=12,'Biaya Bulanan'!$W$47,'Biaya Bulanan'!$X$47)))*'Biaya Bulanan'!$T$47 -> 13769910 | K26: =IF(K$4<'Biaya Bulanan'!$I$47,0,IF(K$4<=3,'Biaya Bulanan'!$V$47,IF(K$4<=12,'Biaya Bulanan'!$W$47,'Biaya Bulanan'!$X$47)))*'Biaya Bulanan'!$T$47 -> 13769910 | ... AA26: =IF(AA$4<'Biaya Bulanan'!$I$47,0,IF(AA$4<=3,'Biaya Bulanan'!$V$47,IF(AA$4<=12,'Biaya Bulanan'!$W$47,'Biaya Bulanan'!$X$47)))*'Biaya Bulanan'!$T$47 -> 13769910
A27: 23 | B27: ='Biaya Bulanan'!$B$48 -> Operasi | C27: ='Biaya Bulanan'!$C$48 -> Head of Customer Experience | D27: =IF(D$4<'Biaya Bulanan'!$I$48,0,IF(D$4<=3,'Biaya Bulanan'!$V$48,IF(D$4<=12,'Biaya Bulanan'!$W$48,'Biaya Bulanan'!$X$48)))*'Biaya Bulanan'!$T$48 -> 0 | E27: =IF(E$4<'Biaya Bulanan'!$I$48,0,IF(E$4<=3,'Biaya Bulanan'!$V$48,IF(E$4<=12,'Biaya Bulanan'!$W$48,'Biaya Bulanan'!$X$48)))*'Biaya Bulanan'!$T$48 -> 0 | F27: =IF(F$4<'Biaya Bulanan'!$I$48,0,IF(F$4<=3,'Biaya Bulanan'!$V$48,IF(F$4<=12,'Biaya Bulanan'!$W$48,'Biaya Bulanan'!$X$48)))*'Biaya Bulanan'!$T$48 -> 0 | G27: =IF(G$4<'Biaya Bulanan'!$I$48,0,IF(G$4<=3,'Biaya Bulanan'!$V$48,IF(G$4<=12,'Biaya Bulanan'!$W$48,'Biaya Bulanan'!$X$48)))*'Biaya Bulanan'!$T$48 -> 18083706 | H27: =IF(H$4<'Biaya Bulanan'!$I$48,0,IF(H$4<=3,'Biaya Bulanan'!$V$48,IF(H$4<=12,'Biaya Bulanan'!$W$48,'Biaya Bulanan'!$X$48)))*'Biaya Bulanan'!$T$48 -> 18083706 | I27: =IF(I$4<'Biaya Bulanan'!$I$48,0,IF(I$4<=3,'Biaya Bulanan'!$V$48,IF(I$4<=12,'Biaya Bulanan'!$W$48,'Biaya Bulanan'!$X$48)))*'Biaya Bulanan'!$T$48 -> 18083706 | J27: =IF(J$4<'Biaya Bulanan'!$I$48,0,IF(J$4<=3,'Biaya Bulanan'!$V$48,IF(J$4<=12,'Biaya Bulanan'!$W$48,'Biaya Bulanan'!$X$48)))*'Biaya Bulanan'!$T$48 -> 18083706 | K27: =IF(K$4<'Biaya Bulanan'!$I$48,0,IF(K$4<=3,'Biaya Bulanan'!$V$48,IF(K$4<=12,'Biaya Bulanan'!$W$48,'Biaya Bulanan'!$X$48)))*'Biaya Bulanan'!$T$48 -> 18083706 | ... AA27: =IF(AA$4<'Biaya Bulanan'!$I$48,0,IF(AA$4<=3,'Biaya Bulanan'!$V$48,IF(AA$4<=12,'Biaya Bulanan'!$W$48,'Biaya Bulanan'!$X$48)))*'Biaya Bulanan'!$T$48 -> 18083706
A28: 24 | B28: ='Biaya Bulanan'!$B$49 -> Operasi | C28: ='Biaya Bulanan'!$C$49 -> CS Agent Pekanbaru (shift) | D28: =IF(D$4<'Biaya Bulanan'!$I$49,0,IF(D$4<=3,'Biaya Bulanan'!$V$49,IF(D$4<=12,'Biaya Bulanan'!$W$49,'Biaya Bulanan'!$X$49)))*'Biaya Bulanan'!$T$49 -> 0 | E28: =IF(E$4<'Biaya Bulanan'!$I$49,0,IF(E$4<=3,'Biaya Bulanan'!$V$49,IF(E$4<=12,'Biaya Bulanan'!$W$49,'Biaya Bulanan'!$X$49)))*'Biaya Bulanan'!$T$49 -> 0 | F28: =IF(F$4<'Biaya Bulanan'!$I$49,0,IF(F$4<=3,'Biaya Bulanan'!$V$49,IF(F$4<=12,'Biaya Bulanan'!$W$49,'Biaya Bulanan'!$X$49)))*'Biaya Bulanan'!$T$49 -> 0 | G28: =IF(G$4<'Biaya Bulanan'!$I$49,0,IF(G$4<=3,'Biaya Bulanan'!$V$49,IF(G$4<=12,'Biaya Bulanan'!$W$49,'Biaya Bulanan'!$X$49)))*'Biaya Bulanan'!$T$49 -> 0 | H28: =IF(H$4<'Biaya Bulanan'!$I$49,0,IF(H$4<=3,'Biaya Bulanan'!$V$49,IF(H$4<=12,'Biaya Bulanan'!$W$49,'Biaya Bulanan'!$X$49)))*'Biaya Bulanan'!$T$49 -> 18632872 | I28: =IF(I$4<'Biaya Bulanan'!$I$49,0,IF(I$4<=3,'Biaya Bulanan'!$V$49,IF(I$4<=12,'Biaya Bulanan'!$W$49,'Biaya Bulanan'!$X$49)))*'Biaya Bulanan'!$T$49 -> 18632872 | J28: =IF(J$4<'Biaya Bulanan'!$I$49,0,IF(J$4<=3,'Biaya Bulanan'!$V$49,IF(J$4<=12,'Biaya Bulanan'!$W$49,'Biaya Bulanan'!$X$49)))*'Biaya Bulanan'!$T$49 -> 18632872 | K28: =IF(K$4<'Biaya Bulanan'!$I$49,0,IF(K$4<=3,'Biaya Bulanan'!$V$49,IF(K$4<=12,'Biaya Bulanan'!$W$49,'Biaya Bulanan'!$X$49)))*'Biaya Bulanan'!$T$49 -> 18632872 | ... AA28: =IF(AA$4<'Biaya Bulanan'!$I$49,0,IF(AA$4<=3,'Biaya Bulanan'!$V$49,IF(AA$4<=12,'Biaya Bulanan'!$W$49,'Biaya Bulanan'!$X$49)))*'Biaya Bulanan'!$T$49 -> 18632872
A29: 25 | B29: ='Biaya Bulanan'!$B$50 -> Operasi | C29: ='Biaya Bulanan'!$C$50 -> Trust & Safety Officer | D29: =IF(D$4<'Biaya Bulanan'!$I$50,0,IF(D$4<=3,'Biaya Bulanan'!$V$50,IF(D$4<=12,'Biaya Bulanan'!$W$50,'Biaya Bulanan'!$X$50)))*'Biaya Bulanan'!$T$50 -> 0 | E29: =IF(E$4<'Biaya Bulanan'!$I$50,0,IF(E$4<=3,'Biaya Bulanan'!$V$50,IF(E$4<=12,'Biaya Bulanan'!$W$50,'Biaya Bulanan'!$X$50)))*'Biaya Bulanan'!$T$50 -> 0 | F29: =IF(F$4<'Biaya Bulanan'!$I$50,0,IF(F$4<=3,'Biaya Bulanan'!$V$50,IF(F$4<=12,'Biaya Bulanan'!$W$50,'Biaya Bulanan'!$X$50)))*'Biaya Bulanan'!$T$50 -> 0 | G29: =IF(G$4<'Biaya Bulanan'!$I$50,0,IF(G$4<=3,'Biaya Bulanan'!$V$50,IF(G$4<=12,'Biaya Bulanan'!$W$50,'Biaya Bulanan'!$X$50)))*'Biaya Bulanan'!$T$50 -> 0 | H29: =IF(H$4<'Biaya Bulanan'!$I$50,0,IF(H$4<=3,'Biaya Bulanan'!$V$50,IF(H$4<=12,'Biaya Bulanan'!$W$50,'Biaya Bulanan'!$X$50)))*'Biaya Bulanan'!$T$50 -> 0 | I29: =IF(I$4<'Biaya Bulanan'!$I$50,0,IF(I$4<=3,'Biaya Bulanan'!$V$50,IF(I$4<=12,'Biaya Bulanan'!$W$50,'Biaya Bulanan'!$X$50)))*'Biaya Bulanan'!$T$50 -> 12421915 | J29: =IF(J$4<'Biaya Bulanan'!$I$50,0,IF(J$4<=3,'Biaya Bulanan'!$V$50,IF(J$4<=12,'Biaya Bulanan'!$W$50,'Biaya Bulanan'!$X$50)))*'Biaya Bulanan'!$T$50 -> 12421915 | K29: =IF(K$4<'Biaya Bulanan'!$I$50,0,IF(K$4<=3,'Biaya Bulanan'!$V$50,IF(K$4<=12,'Biaya Bulanan'!$W$50,'Biaya Bulanan'!$X$50)))*'Biaya Bulanan'!$T$50 -> 12421915 | ... AA29: =IF(AA$4<'Biaya Bulanan'!$I$50,0,IF(AA$4<=3,'Biaya Bulanan'!$V$50,IF(AA$4<=12,'Biaya Bulanan'!$W$50,'Biaya Bulanan'!$X$50)))*'Biaya Bulanan'!$T$50 -> 12421915
A30: 26 | B30: ='Biaya Bulanan'!$B$51 -> Operasi | C30: ='Biaya Bulanan'!$C$51 -> City Manager Padang | D30: =IF(D$4<'Biaya Bulanan'!$I$51,0,IF(D$4<=3,'Biaya Bulanan'!$V$51,IF(D$4<=12,'Biaya Bulanan'!$W$51,'Biaya Bulanan'!$X$51)))*'Biaya Bulanan'!$T$51 -> 0 | E30: =IF(E$4<'Biaya Bulanan'!$I$51,0,IF(E$4<=3,'Biaya Bulanan'!$V$51,IF(E$4<=12,'Biaya Bulanan'!$W$51,'Biaya Bulanan'!$X$51)))*'Biaya Bulanan'!$T$51 -> 0 | F30: =IF(F$4<'Biaya Bulanan'!$I$51,0,IF(F$4<=3,'Biaya Bulanan'!$V$51,IF(F$4<=12,'Biaya Bulanan'!$W$51,'Biaya Bulanan'!$X$51)))*'Biaya Bulanan'!$T$51 -> 0 | G30: =IF(G$4<'Biaya Bulanan'!$I$51,0,IF(G$4<=3,'Biaya Bulanan'!$V$51,IF(G$4<=12,'Biaya Bulanan'!$W$51,'Biaya Bulanan'!$X$51)))*'Biaya Bulanan'!$T$51 -> 0 | H30: =IF(H$4<'Biaya Bulanan'!$I$51,0,IF(H$4<=3,'Biaya Bulanan'!$V$51,IF(H$4<=12,'Biaya Bulanan'!$W$51,'Biaya Bulanan'!$X$51)))*'Biaya Bulanan'!$T$51 -> 0 | I30: =IF(I$4<'Biaya Bulanan'!$I$51,0,IF(I$4<=3,'Biaya Bulanan'!$V$51,IF(I$4<=12,'Biaya Bulanan'!$W$51,'Biaya Bulanan'!$X$51)))*'Biaya Bulanan'!$T$51 -> 0 | J30: =IF(J$4<'Biaya Bulanan'!$I$51,0,IF(J$4<=3,'Biaya Bulanan'!$V$51,IF(J$4<=12,'Biaya Bulanan'!$W$51,'Biaya Bulanan'!$X$51)))*'Biaya Bulanan'!$T$51 -> 0 | K30: =IF(K$4<'Biaya Bulanan'!$I$51,0,IF(K$4<=3,'Biaya Bulanan'!$V$51,IF(K$4<=12,'Biaya Bulanan'!$W$51,'Biaya Bulanan'!$X$51)))*'Biaya Bulanan'!$T$51 -> 0 | ... AA30: =IF(AA$4<'Biaya Bulanan'!$I$51,0,IF(AA$4<=3,'Biaya Bulanan'!$V$51,IF(AA$4<=12,'Biaya Bulanan'!$W$51,'Biaya Bulanan'!$X$51)))*'Biaya Bulanan'!$T$51 -> 16269476
A31: 27 | B31: ='Biaya Bulanan'!$B$52 -> Operasi | C31: ='Biaya Bulanan'!$C$52 -> Partner Acquisition Padang | D31: =IF(D$4<'Biaya Bulanan'!$I$52,0,IF(D$4<=3,'Biaya Bulanan'!$V$52,IF(D$4<=12,'Biaya Bulanan'!$W$52,'Biaya Bulanan'!$X$52)))*'Biaya Bulanan'!$T$52 -> 0 | E31: =IF(E$4<'Biaya Bulanan'!$I$52,0,IF(E$4<=3,'Biaya Bulanan'!$V$52,IF(E$4<=12,'Biaya Bulanan'!$W$52,'Biaya Bulanan'!$X$52)))*'Biaya Bulanan'!$T$52 -> 0 | F31: =IF(F$4<'Biaya Bulanan'!$I$52,0,IF(F$4<=3,'Biaya Bulanan'!$V$52,IF(F$4<=12,'Biaya Bulanan'!$W$52,'Biaya Bulanan'!$X$52)))*'Biaya Bulanan'!$T$52 -> 0 | G31: =IF(G$4<'Biaya Bulanan'!$I$52,0,IF(G$4<=3,'Biaya Bulanan'!$V$52,IF(G$4<=12,'Biaya Bulanan'!$W$52,'Biaya Bulanan'!$X$52)))*'Biaya Bulanan'!$T$52 -> 0 | H31: =IF(H$4<'Biaya Bulanan'!$I$52,0,IF(H$4<=3,'Biaya Bulanan'!$V$52,IF(H$4<=12,'Biaya Bulanan'!$W$52,'Biaya Bulanan'!$X$52)))*'Biaya Bulanan'!$T$52 -> 0 | I31: =IF(I$4<'Biaya Bulanan'!$I$52,0,IF(I$4<=3,'Biaya Bulanan'!$V$52,IF(I$4<=12,'Biaya Bulanan'!$W$52,'Biaya Bulanan'!$X$52)))*'Biaya Bulanan'!$T$52 -> 0 | J31: =IF(J$4<'Biaya Bulanan'!$I$52,0,IF(J$4<=3,'Biaya Bulanan'!$V$52,IF(J$4<=12,'Biaya Bulanan'!$W$52,'Biaya Bulanan'!$X$52)))*'Biaya Bulanan'!$T$52 -> 0 | K31: =IF(K$4<'Biaya Bulanan'!$I$52,0,IF(K$4<=3,'Biaya Bulanan'!$V$52,IF(K$4<=12,'Biaya Bulanan'!$W$52,'Biaya Bulanan'!$X$52)))*'Biaya Bulanan'!$T$52 -> 0 | ... AA31: =IF(AA$4<'Biaya Bulanan'!$I$52,0,IF(AA$4<=3,'Biaya Bulanan'!$V$52,IF(AA$4<=12,'Biaya Bulanan'!$W$52,'Biaya Bulanan'!$X$52)))*'Biaya Bulanan'!$T$52 -> 5704677
A32: 28 | B32: ='Biaya Bulanan'!$B$53 -> Operasi | C32: ='Biaya Bulanan'!$C$53 -> Ops Supervisor Padang | D32: =IF(D$4<'Biaya Bulanan'!$I$53,0,IF(D$4<=3,'Biaya Bulanan'!$V$53,IF(D$4<=12,'Biaya Bulanan'!$W$53,'Biaya Bulanan'!$X$53)))*'Biaya Bulanan'!$T$53 -> 0 | E32: =IF(E$4<'Biaya Bulanan'!$I$53,0,IF(E$4<=3,'Biaya Bulanan'!$V$53,IF(E$4<=12,'Biaya Bulanan'!$W$53,'Biaya Bulanan'!$X$53)))*'Biaya Bulanan'!$T$53 -> 0 | F32: =IF(F$4<'Biaya Bulanan'!$I$53,0,IF(F$4<=3,'Biaya Bulanan'!$V$53,IF(F$4<=12,'Biaya Bulanan'!$W$53,'Biaya Bulanan'!$X$53)))*'Biaya Bulanan'!$T$53 -> 0 | G32: =IF(G$4<'Biaya Bulanan'!$I$53,0,IF(G$4<=3,'Biaya Bulanan'!$V$53,IF(G$4<=12,'Biaya Bulanan'!$W$53,'Biaya Bulanan'!$X$53)))*'Biaya Bulanan'!$T$53 -> 0 | H32: =IF(H$4<'Biaya Bulanan'!$I$53,0,IF(H$4<=3,'Biaya Bulanan'!$V$53,IF(H$4<=12,'Biaya Bulanan'!$W$53,'Biaya Bulanan'!$X$53)))*'Biaya Bulanan'!$T$53 -> 0 | I32: =IF(I$4<'Biaya Bulanan'!$I$53,0,IF(I$4<=3,'Biaya Bulanan'!$V$53,IF(I$4<=12,'Biaya Bulanan'!$W$53,'Biaya Bulanan'!$X$53)))*'Biaya Bulanan'!$T$53 -> 0 | J32: =IF(J$4<'Biaya Bulanan'!$I$53,0,IF(J$4<=3,'Biaya Bulanan'!$V$53,IF(J$4<=12,'Biaya Bulanan'!$W$53,'Biaya Bulanan'!$X$53)))*'Biaya Bulanan'!$T$53 -> 0 | K32: =IF(K$4<'Biaya Bulanan'!$I$53,0,IF(K$4<=3,'Biaya Bulanan'!$V$53,IF(K$4<=12,'Biaya Bulanan'!$W$53,'Biaya Bulanan'!$X$53)))*'Biaya Bulanan'!$T$53 -> 0 | ... AA32: =IF(AA$4<'Biaya Bulanan'!$I$53,0,IF(AA$4<=3,'Biaya Bulanan'!$V$53,IF(AA$4<=12,'Biaya Bulanan'!$W$53,'Biaya Bulanan'!$X$53)))*'Biaya Bulanan'!$T$53 -> 8524230
A33: 29 | B33: ='Biaya Bulanan'!$B$54 -> Operasi | C33: ='Biaya Bulanan'!$C$54 -> CS Agent Padang (shift) | D33: =IF(D$4<'Biaya Bulanan'!$I$54,0,IF(D$4<=3,'Biaya Bulanan'!$V$54,IF(D$4<=12,'Biaya Bulanan'!$W$54,'Biaya Bulanan'!$X$54)))*'Biaya Bulanan'!$T$54 -> 0 | E33: =IF(E$4<'Biaya Bulanan'!$I$54,0,IF(E$4<=3,'Biaya Bulanan'!$V$54,IF(E$4<=12,'Biaya Bulanan'!$W$54,'Biaya Bulanan'!$X$54)))*'Biaya Bulanan'!$T$54 -> 0 | F33: =IF(F$4<'Biaya Bulanan'!$I$54,0,IF(F$4<=3,'Biaya Bulanan'!$V$54,IF(F$4<=12,'Biaya Bulanan'!$W$54,'Biaya Bulanan'!$X$54)))*'Biaya Bulanan'!$T$54 -> 0 | G33: =IF(G$4<'Biaya Bulanan'!$I$54,0,IF(G$4<=3,'Biaya Bulanan'!$V$54,IF(G$4<=12,'Biaya Bulanan'!$W$54,'Biaya Bulanan'!$X$54)))*'Biaya Bulanan'!$T$54 -> 0 | H33: =IF(H$4<'Biaya Bulanan'!$I$54,0,IF(H$4<=3,'Biaya Bulanan'!$V$54,IF(H$4<=12,'Biaya Bulanan'!$W$54,'Biaya Bulanan'!$X$54)))*'Biaya Bulanan'!$T$54 -> 0 | I33: =IF(I$4<'Biaya Bulanan'!$I$54,0,IF(I$4<=3,'Biaya Bulanan'!$V$54,IF(I$4<=12,'Biaya Bulanan'!$W$54,'Biaya Bulanan'!$X$54)))*'Biaya Bulanan'!$T$54 -> 0 | J33: =IF(J$4<'Biaya Bulanan'!$I$54,0,IF(J$4<=3,'Biaya Bulanan'!$V$54,IF(J$4<=12,'Biaya Bulanan'!$W$54,'Biaya Bulanan'!$X$54)))*'Biaya Bulanan'!$T$54 -> 0 | K33: =IF(K$4<'Biaya Bulanan'!$I$54,0,IF(K$4<=3,'Biaya Bulanan'!$V$54,IF(K$4<=12,'Biaya Bulanan'!$W$54,'Biaya Bulanan'!$X$54)))*'Biaya Bulanan'!$T$54 -> 0 | ... AA33: =IF(AA$4<'Biaya Bulanan'!$I$54,0,IF(AA$4<=3,'Biaya Bulanan'!$V$54,IF(AA$4<=12,'Biaya Bulanan'!$W$54,'Biaya Bulanan'!$X$54)))*'Biaya Bulanan'!$T$54 -> 10068289
A34: 30 | B34: ='Biaya Bulanan'!$B$55 -> Operasi | C34: ='Biaya Bulanan'!$C$55 -> Partner Acquisition Padang - gelombang 2 | D34: =IF(D$4<'Biaya Bulanan'!$I$55,0,IF(D$4<=3,'Biaya Bulanan'!$V$55,IF(D$4<=12,'Biaya Bulanan'!$W$55,'Biaya Bulanan'!$X$55)))*'Biaya Bulanan'!$T$55 -> 0 | E34: =IF(E$4<'Biaya Bulanan'!$I$55,0,IF(E$4<=3,'Biaya Bulanan'!$V$55,IF(E$4<=12,'Biaya Bulanan'!$W$55,'Biaya Bulanan'!$X$55)))*'Biaya Bulanan'!$T$55 -> 0 | F34: =IF(F$4<'Biaya Bulanan'!$I$55,0,IF(F$4<=3,'Biaya Bulanan'!$V$55,IF(F$4<=12,'Biaya Bulanan'!$W$55,'Biaya Bulanan'!$X$55)))*'Biaya Bulanan'!$T$55 -> 0 | G34: =IF(G$4<'Biaya Bulanan'!$I$55,0,IF(G$4<=3,'Biaya Bulanan'!$V$55,IF(G$4<=12,'Biaya Bulanan'!$W$55,'Biaya Bulanan'!$X$55)))*'Biaya Bulanan'!$T$55 -> 0 | H34: =IF(H$4<'Biaya Bulanan'!$I$55,0,IF(H$4<=3,'Biaya Bulanan'!$V$55,IF(H$4<=12,'Biaya Bulanan'!$W$55,'Biaya Bulanan'!$X$55)))*'Biaya Bulanan'!$T$55 -> 0 | I34: =IF(I$4<'Biaya Bulanan'!$I$55,0,IF(I$4<=3,'Biaya Bulanan'!$V$55,IF(I$4<=12,'Biaya Bulanan'!$W$55,'Biaya Bulanan'!$X$55)))*'Biaya Bulanan'!$T$55 -> 0 | J34: =IF(J$4<'Biaya Bulanan'!$I$55,0,IF(J$4<=3,'Biaya Bulanan'!$V$55,IF(J$4<=12,'Biaya Bulanan'!$W$55,'Biaya Bulanan'!$X$55)))*'Biaya Bulanan'!$T$55 -> 0 | K34: =IF(K$4<'Biaya Bulanan'!$I$55,0,IF(K$4<=3,'Biaya Bulanan'!$V$55,IF(K$4<=12,'Biaya Bulanan'!$W$55,'Biaya Bulanan'!$X$55)))*'Biaya Bulanan'!$T$55 -> 0 | ... AA34: =IF(AA$4<'Biaya Bulanan'!$I$55,0,IF(AA$4<=3,'Biaya Bulanan'!$V$55,IF(AA$4<=12,'Biaya Bulanan'!$W$55,'Biaya Bulanan'!$X$55)))*'Biaya Bulanan'!$T$55 -> 5704677
A35: 31 | B35: ='Biaya Bulanan'!$B$56 -> Growth & Partnership | C35: ='Biaya Bulanan'!$C$56 -> Head of Growth & Partnership | D35: =IF(D$4<'Biaya Bulanan'!$I$56,0,IF(D$4<=3,'Biaya Bulanan'!$V$56,IF(D$4<=12,'Biaya Bulanan'!$W$56,'Biaya Bulanan'!$X$56)))*'Biaya Bulanan'!$T$56 -> 0 | E35: =IF(E$4<'Biaya Bulanan'!$I$56,0,IF(E$4<=3,'Biaya Bulanan'!$V$56,IF(E$4<=12,'Biaya Bulanan'!$W$56,'Biaya Bulanan'!$X$56)))*'Biaya Bulanan'!$T$56 -> 0 | F35: =IF(F$4<'Biaya Bulanan'!$I$56,0,IF(F$4<=3,'Biaya Bulanan'!$V$56,IF(F$4<=12,'Biaya Bulanan'!$W$56,'Biaya Bulanan'!$X$56)))*'Biaya Bulanan'!$T$56 -> 0 | G35: =IF(G$4<'Biaya Bulanan'!$I$56,0,IF(G$4<=3,'Biaya Bulanan'!$V$56,IF(G$4<=12,'Biaya Bulanan'!$W$56,'Biaya Bulanan'!$X$56)))*'Biaya Bulanan'!$T$56 -> 27395481 | H35: =IF(H$4<'Biaya Bulanan'!$I$56,0,IF(H$4<=3,'Biaya Bulanan'!$V$56,IF(H$4<=12,'Biaya Bulanan'!$W$56,'Biaya Bulanan'!$X$56)))*'Biaya Bulanan'!$T$56 -> 27395481 | I35: =IF(I$4<'Biaya Bulanan'!$I$56,0,IF(I$4<=3,'Biaya Bulanan'!$V$56,IF(I$4<=12,'Biaya Bulanan'!$W$56,'Biaya Bulanan'!$X$56)))*'Biaya Bulanan'!$T$56 -> 27395481 | J35: =IF(J$4<'Biaya Bulanan'!$I$56,0,IF(J$4<=3,'Biaya Bulanan'!$V$56,IF(J$4<=12,'Biaya Bulanan'!$W$56,'Biaya Bulanan'!$X$56)))*'Biaya Bulanan'!$T$56 -> 27395481 | K35: =IF(K$4<'Biaya Bulanan'!$I$56,0,IF(K$4<=3,'Biaya Bulanan'!$V$56,IF(K$4<=12,'Biaya Bulanan'!$W$56,'Biaya Bulanan'!$X$56)))*'Biaya Bulanan'!$T$56 -> 27395481 | ... AA35: =IF(AA$4<'Biaya Bulanan'!$I$56,0,IF(AA$4<=3,'Biaya Bulanan'!$V$56,IF(AA$4<=12,'Biaya Bulanan'!$W$56,'Biaya Bulanan'!$X$56)))*'Biaya Bulanan'!$T$56 -> 27395481
A36: 32 | B36: ='Biaya Bulanan'!$B$57 -> Growth & Partnership | C36: ='Biaya Bulanan'!$C$57 -> Digital Marketing Staff | D36: =IF(D$4<'Biaya Bulanan'!$I$57,0,IF(D$4<=3,'Biaya Bulanan'!$V$57,IF(D$4<=12,'Biaya Bulanan'!$W$57,'Biaya Bulanan'!$X$57)))*'Biaya Bulanan'!$T$57 -> 0 | E36: =IF(E$4<'Biaya Bulanan'!$I$57,0,IF(E$4<=3,'Biaya Bulanan'!$V$57,IF(E$4<=12,'Biaya Bulanan'!$W$57,'Biaya Bulanan'!$X$57)))*'Biaya Bulanan'!$T$57 -> 0 | F36: =IF(F$4<'Biaya Bulanan'!$I$57,0,IF(F$4<=3,'Biaya Bulanan'!$V$57,IF(F$4<=12,'Biaya Bulanan'!$W$57,'Biaya Bulanan'!$X$57)))*'Biaya Bulanan'!$T$57 -> 0 | G36: =IF(G$4<'Biaya Bulanan'!$I$57,0,IF(G$4<=3,'Biaya Bulanan'!$V$57,IF(G$4<=12,'Biaya Bulanan'!$W$57,'Biaya Bulanan'!$X$57)))*'Biaya Bulanan'!$T$57 -> 0 | H36: =IF(H$4<'Biaya Bulanan'!$I$57,0,IF(H$4<=3,'Biaya Bulanan'!$V$57,IF(H$4<=12,'Biaya Bulanan'!$W$57,'Biaya Bulanan'!$X$57)))*'Biaya Bulanan'!$T$57 -> 0 | I36: =IF(I$4<'Biaya Bulanan'!$I$57,0,IF(I$4<=3,'Biaya Bulanan'!$V$57,IF(I$4<=12,'Biaya Bulanan'!$W$57,'Biaya Bulanan'!$X$57)))*'Biaya Bulanan'!$T$57 -> 0 | J36: =IF(J$4<'Biaya Bulanan'!$I$57,0,IF(J$4<=3,'Biaya Bulanan'!$V$57,IF(J$4<=12,'Biaya Bulanan'!$W$57,'Biaya Bulanan'!$X$57)))*'Biaya Bulanan'!$T$57 -> 0 | K36: =IF(K$4<'Biaya Bulanan'!$I$57,0,IF(K$4<=3,'Biaya Bulanan'!$V$57,IF(K$4<=12,'Biaya Bulanan'!$W$57,'Biaya Bulanan'!$X$57)))*'Biaya Bulanan'!$T$57 -> 0 | ... AA36: =IF(AA$4<'Biaya Bulanan'!$I$57,0,IF(AA$4<=3,'Biaya Bulanan'!$V$57,IF(AA$4<=12,'Biaya Bulanan'!$W$57,'Biaya Bulanan'!$X$57)))*'Biaya Bulanan'!$T$57 -> 9152990
A37: 33 | B37: ='Biaya Bulanan'!$B$58 -> Growth & Partnership | C37: ='Biaya Bulanan'!$C$58 -> Merchant Acquisition Officer | D37: =IF(D$4<'Biaya Bulanan'!$I$58,0,IF(D$4<=3,'Biaya Bulanan'!$V$58,IF(D$4<=12,'Biaya Bulanan'!$W$58,'Biaya Bulanan'!$X$58)))*'Biaya Bulanan'!$T$58 -> 0 | E37: =IF(E$4<'Biaya Bulanan'!$I$58,0,IF(E$4<=3,'Biaya Bulanan'!$V$58,IF(E$4<=12,'Biaya Bulanan'!$W$58,'Biaya Bulanan'!$X$58)))*'Biaya Bulanan'!$T$58 -> 0 | F37: =IF(F$4<'Biaya Bulanan'!$I$58,0,IF(F$4<=3,'Biaya Bulanan'!$V$58,IF(F$4<=12,'Biaya Bulanan'!$W$58,'Biaya Bulanan'!$X$58)))*'Biaya Bulanan'!$T$58 -> 0 | G37: =IF(G$4<'Biaya Bulanan'!$I$58,0,IF(G$4<=3,'Biaya Bulanan'!$V$58,IF(G$4<=12,'Biaya Bulanan'!$W$58,'Biaya Bulanan'!$X$58)))*'Biaya Bulanan'!$T$58 -> 0 | H37: =IF(H$4<'Biaya Bulanan'!$I$58,0,IF(H$4<=3,'Biaya Bulanan'!$V$58,IF(H$4<=12,'Biaya Bulanan'!$W$58,'Biaya Bulanan'!$X$58)))*'Biaya Bulanan'!$T$58 -> 0 | I37: =IF(I$4<'Biaya Bulanan'!$I$58,0,IF(I$4<=3,'Biaya Bulanan'!$V$58,IF(I$4<=12,'Biaya Bulanan'!$W$58,'Biaya Bulanan'!$X$58)))*'Biaya Bulanan'!$T$58 -> 0 | J37: =IF(J$4<'Biaya Bulanan'!$I$58,0,IF(J$4<=3,'Biaya Bulanan'!$V$58,IF(J$4<=12,'Biaya Bulanan'!$W$58,'Biaya Bulanan'!$X$58)))*'Biaya Bulanan'!$T$58 -> 0 | K37: =IF(K$4<'Biaya Bulanan'!$I$58,0,IF(K$4<=3,'Biaya Bulanan'!$V$58,IF(K$4<=12,'Biaya Bulanan'!$W$58,'Biaya Bulanan'!$X$58)))*'Biaya Bulanan'!$T$58 -> 0 | ... AA37: =IF(AA$4<'Biaya Bulanan'!$I$58,0,IF(AA$4<=3,'Biaya Bulanan'!$V$58,IF(AA$4<=12,'Biaya Bulanan'!$W$58,'Biaya Bulanan'!$X$58)))*'Biaya Bulanan'!$T$58 -> 6884955
A38: 34 | B38: ='Biaya Bulanan'!$B$59 -> Keuangan | C38: ='Biaya Bulanan'!$C$59 -> Head of Finance | D38: =IF(D$4<'Biaya Bulanan'!$I$59,0,IF(D$4<=3,'Biaya Bulanan'!$V$59,IF(D$4<=12,'Biaya Bulanan'!$W$59,'Biaya Bulanan'!$X$59)))*'Biaya Bulanan'!$T$59 -> 0 | E38: =IF(E$4<'Biaya Bulanan'!$I$59,0,IF(E$4<=3,'Biaya Bulanan'!$V$59,IF(E$4<=12,'Biaya Bulanan'!$W$59,'Biaya Bulanan'!$X$59)))*'Biaya Bulanan'!$T$59 -> 25533126 | F38: =IF(F$4<'Biaya Bulanan'!$I$59,0,IF(F$4<=3,'Biaya Bulanan'!$V$59,IF(F$4<=12,'Biaya Bulanan'!$W$59,'Biaya Bulanan'!$X$59)))*'Biaya Bulanan'!$T$59 -> 25533126 | G38: =IF(G$4<'Biaya Bulanan'!$I$59,0,IF(G$4<=3,'Biaya Bulanan'!$V$59,IF(G$4<=12,'Biaya Bulanan'!$W$59,'Biaya Bulanan'!$X$59)))*'Biaya Bulanan'!$T$59 -> 25533126 | H38: =IF(H$4<'Biaya Bulanan'!$I$59,0,IF(H$4<=3,'Biaya Bulanan'!$V$59,IF(H$4<=12,'Biaya Bulanan'!$W$59,'Biaya Bulanan'!$X$59)))*'Biaya Bulanan'!$T$59 -> 25533126 | I38: =IF(I$4<'Biaya Bulanan'!$I$59,0,IF(I$4<=3,'Biaya Bulanan'!$V$59,IF(I$4<=12,'Biaya Bulanan'!$W$59,'Biaya Bulanan'!$X$59)))*'Biaya Bulanan'!$T$59 -> 25533126 | J38: =IF(J$4<'Biaya Bulanan'!$I$59,0,IF(J$4<=3,'Biaya Bulanan'!$V$59,IF(J$4<=12,'Biaya Bulanan'!$W$59,'Biaya Bulanan'!$X$59)))*'Biaya Bulanan'!$T$59 -> 25533126 | K38: =IF(K$4<'Biaya Bulanan'!$I$59,0,IF(K$4<=3,'Biaya Bulanan'!$V$59,IF(K$4<=12,'Biaya Bulanan'!$W$59,'Biaya Bulanan'!$X$59)))*'Biaya Bulanan'!$T$59 -> 25533126 | ... AA38: =IF(AA$4<'Biaya Bulanan'!$I$59,0,IF(AA$4<=3,'Biaya Bulanan'!$V$59,IF(AA$4<=12,'Biaya Bulanan'!$W$59,'Biaya Bulanan'!$X$59)))*'Biaya Bulanan'!$T$59 -> 25533126
A39: 35 | B39: ='Biaya Bulanan'!$B$60 -> Keuangan | C39: ='Biaya Bulanan'!$C$60 -> Finance & Accounting Staff | D39: =IF(D$4<'Biaya Bulanan'!$I$60,0,IF(D$4<=3,'Biaya Bulanan'!$V$60,IF(D$4<=12,'Biaya Bulanan'!$W$60,'Biaya Bulanan'!$X$60)))*'Biaya Bulanan'!$T$60 -> 0 | E39: =IF(E$4<'Biaya Bulanan'!$I$60,0,IF(E$4<=3,'Biaya Bulanan'!$V$60,IF(E$4<=12,'Biaya Bulanan'!$W$60,'Biaya Bulanan'!$X$60)))*'Biaya Bulanan'!$T$60 -> 0 | F39: =IF(F$4<'Biaya Bulanan'!$I$60,0,IF(F$4<=3,'Biaya Bulanan'!$V$60,IF(F$4<=12,'Biaya Bulanan'!$W$60,'Biaya Bulanan'!$X$60)))*'Biaya Bulanan'!$T$60 -> 0 | G39: =IF(G$4<'Biaya Bulanan'!$I$60,0,IF(G$4<=3,'Biaya Bulanan'!$V$60,IF(G$4<=12,'Biaya Bulanan'!$W$60,'Biaya Bulanan'!$X$60)))*'Biaya Bulanan'!$T$60 -> 8499205 | H39: =IF(H$4<'Biaya Bulanan'!$I$60,0,IF(H$4<=3,'Biaya Bulanan'!$V$60,IF(H$4<=12,'Biaya Bulanan'!$W$60,'Biaya Bulanan'!$X$60)))*'Biaya Bulanan'!$T$60 -> 8499205 | I39: =IF(I$4<'Biaya Bulanan'!$I$60,0,IF(I$4<=3,'Biaya Bulanan'!$V$60,IF(I$4<=12,'Biaya Bulanan'!$W$60,'Biaya Bulanan'!$X$60)))*'Biaya Bulanan'!$T$60 -> 8499205 | J39: =IF(J$4<'Biaya Bulanan'!$I$60,0,IF(J$4<=3,'Biaya Bulanan'!$V$60,IF(J$4<=12,'Biaya Bulanan'!$W$60,'Biaya Bulanan'!$X$60)))*'Biaya Bulanan'!$T$60 -> 8499205 | K39: =IF(K$4<'Biaya Bulanan'!$I$60,0,IF(K$4<=3,'Biaya Bulanan'!$V$60,IF(K$4<=12,'Biaya Bulanan'!$W$60,'Biaya Bulanan'!$X$60)))*'Biaya Bulanan'!$T$60 -> 8499205 | ... AA39: =IF(AA$4<'Biaya Bulanan'!$I$60,0,IF(AA$4<=3,'Biaya Bulanan'!$V$60,IF(AA$4<=12,'Biaya Bulanan'!$W$60,'Biaya Bulanan'!$X$60)))*'Biaya Bulanan'!$T$60 -> 8499205
A40: 36 | B40: ='Biaya Bulanan'!$B$61 -> Keuangan | C40: ='Biaya Bulanan'!$C$61 -> Treasury/Settlement Officer | D40: =IF(D$4<'Biaya Bulanan'!$I$61,0,IF(D$4<=3,'Biaya Bulanan'!$V$61,IF(D$4<=12,'Biaya Bulanan'!$W$61,'Biaya Bulanan'!$X$61)))*'Biaya Bulanan'!$T$61 -> 0 | E40: =IF(E$4<'Biaya Bulanan'!$I$61,0,IF(E$4<=3,'Biaya Bulanan'!$V$61,IF(E$4<=12,'Biaya Bulanan'!$W$61,'Biaya Bulanan'!$X$61)))*'Biaya Bulanan'!$T$61 -> 0 | F40: =IF(F$4<'Biaya Bulanan'!$I$61,0,IF(F$4<=3,'Biaya Bulanan'!$V$61,IF(F$4<=12,'Biaya Bulanan'!$W$61,'Biaya Bulanan'!$X$61)))*'Biaya Bulanan'!$T$61 -> 0 | G40: =IF(G$4<'Biaya Bulanan'!$I$61,0,IF(G$4<=3,'Biaya Bulanan'!$V$61,IF(G$4<=12,'Biaya Bulanan'!$W$61,'Biaya Bulanan'!$X$61)))*'Biaya Bulanan'!$T$61 -> 0 | H40: =IF(H$4<'Biaya Bulanan'!$I$61,0,IF(H$4<=3,'Biaya Bulanan'!$V$61,IF(H$4<=12,'Biaya Bulanan'!$W$61,'Biaya Bulanan'!$X$61)))*'Biaya Bulanan'!$T$61 -> 0 | I40: =IF(I$4<'Biaya Bulanan'!$I$61,0,IF(I$4<=3,'Biaya Bulanan'!$V$61,IF(I$4<=12,'Biaya Bulanan'!$W$61,'Biaya Bulanan'!$X$61)))*'Biaya Bulanan'!$T$61 -> 0 | J40: =IF(J$4<'Biaya Bulanan'!$I$61,0,IF(J$4<=3,'Biaya Bulanan'!$V$61,IF(J$4<=12,'Biaya Bulanan'!$W$61,'Biaya Bulanan'!$X$61)))*'Biaya Bulanan'!$T$61 -> 0 | K40: =IF(K$4<'Biaya Bulanan'!$I$61,0,IF(K$4<=3,'Biaya Bulanan'!$V$61,IF(K$4<=12,'Biaya Bulanan'!$W$61,'Biaya Bulanan'!$X$61)))*'Biaya Bulanan'!$T$61 -> 0 | ... AA40: =IF(AA$4<'Biaya Bulanan'!$I$61,0,IF(AA$4<=3,'Biaya Bulanan'!$V$61,IF(AA$4<=12,'Biaya Bulanan'!$W$61,'Biaya Bulanan'!$X$61)))*'Biaya Bulanan'!$T$61 -> 10624006
A41: 37 | B41: ='Biaya Bulanan'!$B$62 -> Keuangan | C41: ='Biaya Bulanan'!$C$62 -> Finance & Accounting Staff - Padang | D41: =IF(D$4<'Biaya Bulanan'!$I$62,0,IF(D$4<=3,'Biaya Bulanan'!$V$62,IF(D$4<=12,'Biaya Bulanan'!$W$62,'Biaya Bulanan'!$X$62)))*'Biaya Bulanan'!$T$62 -> 0 | E41: =IF(E$4<'Biaya Bulanan'!$I$62,0,IF(E$4<=3,'Biaya Bulanan'!$V$62,IF(E$4<=12,'Biaya Bulanan'!$W$62,'Biaya Bulanan'!$X$62)))*'Biaya Bulanan'!$T$62 -> 0 | F41: =IF(F$4<'Biaya Bulanan'!$I$62,0,IF(F$4<=3,'Biaya Bulanan'!$V$62,IF(F$4<=12,'Biaya Bulanan'!$W$62,'Biaya Bulanan'!$X$62)))*'Biaya Bulanan'!$T$62 -> 0 | G41: =IF(G$4<'Biaya Bulanan'!$I$62,0,IF(G$4<=3,'Biaya Bulanan'!$V$62,IF(G$4<=12,'Biaya Bulanan'!$W$62,'Biaya Bulanan'!$X$62)))*'Biaya Bulanan'!$T$62 -> 0 | H41: =IF(H$4<'Biaya Bulanan'!$I$62,0,IF(H$4<=3,'Biaya Bulanan'!$V$62,IF(H$4<=12,'Biaya Bulanan'!$W$62,'Biaya Bulanan'!$X$62)))*'Biaya Bulanan'!$T$62 -> 0 | I41: =IF(I$4<'Biaya Bulanan'!$I$62,0,IF(I$4<=3,'Biaya Bulanan'!$V$62,IF(I$4<=12,'Biaya Bulanan'!$W$62,'Biaya Bulanan'!$X$62)))*'Biaya Bulanan'!$T$62 -> 0 | J41: =IF(J$4<'Biaya Bulanan'!$I$62,0,IF(J$4<=3,'Biaya Bulanan'!$V$62,IF(J$4<=12,'Biaya Bulanan'!$W$62,'Biaya Bulanan'!$X$62)))*'Biaya Bulanan'!$T$62 -> 0 | K41: =IF(K$4<'Biaya Bulanan'!$I$62,0,IF(K$4<=3,'Biaya Bulanan'!$V$62,IF(K$4<=12,'Biaya Bulanan'!$W$62,'Biaya Bulanan'!$X$62)))*'Biaya Bulanan'!$T$62 -> 0 | ... AA41: =IF(AA$4<'Biaya Bulanan'!$I$62,0,IF(AA$4<=3,'Biaya Bulanan'!$V$62,IF(AA$4<=12,'Biaya Bulanan'!$W$62,'Biaya Bulanan'!$X$62)))*'Biaya Bulanan'!$T$62 -> 7191635
A42: 38 | B42: ='Biaya Bulanan'!$B$63 -> Legal & Kepatuhan | C42: ='Biaya Bulanan'!$C$63 -> Head of Legal & Compliance (merangkap DPO) | D42: =IF(D$4<'Biaya Bulanan'!$I$63,0,IF(D$4<=3,'Biaya Bulanan'!$V$63,IF(D$4<=12,'Biaya Bulanan'!$W$63,'Biaya Bulanan'!$X$63)))*'Biaya Bulanan'!$T$63 -> 0 | E42: =IF(E$4<'Biaya Bulanan'!$I$63,0,IF(E$4<=3,'Biaya Bulanan'!$V$63,IF(E$4<=12,'Biaya Bulanan'!$W$63,'Biaya Bulanan'!$X$63)))*'Biaya Bulanan'!$T$63 -> 0 | F42: =IF(F$4<'Biaya Bulanan'!$I$63,0,IF(F$4<=3,'Biaya Bulanan'!$V$63,IF(F$4<=12,'Biaya Bulanan'!$W$63,'Biaya Bulanan'!$X$63)))*'Biaya Bulanan'!$T$63 -> 0 | G42: =IF(G$4<'Biaya Bulanan'!$I$63,0,IF(G$4<=3,'Biaya Bulanan'!$V$63,IF(G$4<=12,'Biaya Bulanan'!$W$63,'Biaya Bulanan'!$X$63)))*'Biaya Bulanan'!$T$63 -> 17462921 | H42: =IF(H$4<'Biaya Bulanan'!$I$63,0,IF(H$4<=3,'Biaya Bulanan'!$V$63,IF(H$4<=12,'Biaya Bulanan'!$W$63,'Biaya Bulanan'!$X$63)))*'Biaya Bulanan'!$T$63 -> 17462921 | I42: =IF(I$4<'Biaya Bulanan'!$I$63,0,IF(I$4<=3,'Biaya Bulanan'!$V$63,IF(I$4<=12,'Biaya Bulanan'!$W$63,'Biaya Bulanan'!$X$63)))*'Biaya Bulanan'!$T$63 -> 17462921 | J42: =IF(J$4<'Biaya Bulanan'!$I$63,0,IF(J$4<=3,'Biaya Bulanan'!$V$63,IF(J$4<=12,'Biaya Bulanan'!$W$63,'Biaya Bulanan'!$X$63)))*'Biaya Bulanan'!$T$63 -> 17462921 | K42: =IF(K$4<'Biaya Bulanan'!$I$63,0,IF(K$4<=3,'Biaya Bulanan'!$V$63,IF(K$4<=12,'Biaya Bulanan'!$W$63,'Biaya Bulanan'!$X$63)))*'Biaya Bulanan'!$T$63 -> 17462921 | ... AA42: =IF(AA$4<'Biaya Bulanan'!$I$63,0,IF(AA$4<=3,'Biaya Bulanan'!$V$63,IF(AA$4<=12,'Biaya Bulanan'!$W$63,'Biaya Bulanan'!$X$63)))*'Biaya Bulanan'!$T$63 -> 17462921
C43: TOTAL BIAYA SDM / BULAN | D43: =SUM(D5:D42) -> 158704880 | E43: =SUM(E5:E42) -> 219217748 | F43: =SUM(F5:F42) -> 230332093 | G43: =SUM(G5:G42) -> 375824433 | H43: =SUM(H5:H42) -> 4.1005787e+08 | I43: =SUM(I5:I42) -> 4.3555549e+08 | J43: =SUM(J5:J42) -> 4.3555549e+08 | K43: =SUM(K5:K42) -> 4.3555549e+08 | ... AA43: =SUM(AA5:AA42) -> 6.3627206e+08
A45: SUBTOTAL PER DIREKTORAT (Rp/bulan)
A46: No | B46: Direktorat | C46: Posisi | D46: 1 | E46: 2 | F46: 3 | G46: 4 | H46: 5 | I46: 6 | J46: 7 | K46: 8 | L46: 9 | M46: 10 | N46: 11 | O46: 12 | P46: 13 | Q46: 14 | R46: 15 | S46: 16 | T46: 17 | U46: 18 | V46: 19 | W46: 20 | X46: 21 | Y46: 22 | Z46: 23 | AA46: 24
A47: 1 | B47: Direksi & Tata Kelola | D47: =SUMIF($B$5:$B$42,$B47,D$5:D$42) -> 44156676 | E47: =SUMIF($B$5:$B$42,$B47,E$5:E$42) -> 44156676 | F47: =SUMIF($B$5:$B$42,$B47,F$5:F$42) -> 55271021 | G47: =SUMIF($B$5:$B$42,$B47,G$5:G$42) -> 55271021 | H47: =SUMIF($B$5:$B$42,$B47,H$5:H$42) -> 55271021 | I47: =SUMIF($B$5:$B$42,$B47,I$5:I$42) -> 55271021 | J47: =SUMIF($B$5:$B$42,$B47,J$5:J$42) -> 55271021 | K47: =SUMIF($B$5:$B$42,$B47,K$5:K$42) -> 55271021 | ... AA47: =SUMIF($B$5:$B$42,$B47,AA$5:AA$42) -> 55271021
A48: 2 | B48: Teknologi | D48: =SUMIF($B$5:$B$42,$B48,D$5:D$42) -> 89015078 | E48: =SUMIF($B$5:$B$42,$B48,E$5:E$42) -> 105857214 | F48: =SUMIF($B$5:$B$42,$B48,F$5:F$42) -> 105857214 | G48: =SUMIF($B$5:$B$42,$B48,G$5:G$42) -> 156302681 | H48: =SUMIF($B$5:$B$42,$B48,H$5:H$42) -> 171903247 | I48: =SUMIF($B$5:$B$42,$B48,I$5:I$42) -> 184978947 | J48: =SUMIF($B$5:$B$42,$B48,J$5:J$42) -> 184978947 | K48: =SUMIF($B$5:$B$42,$B48,K$5:K$42) -> 184978947 | ... AA48: =SUMIF($B$5:$B$42,$B48,AA$5:AA$42) -> 305570587
A49: 3 | B49: Operasi | D49: =SUMIF($B$5:$B$42,$B49,D$5:D$42) -> 25533126 | E49: =SUMIF($B$5:$B$42,$B49,E$5:E$42) -> 43670732 | F49: =SUMIF($B$5:$B$42,$B49,F$5:F$42) -> 43670732 | G49: =SUMIF($B$5:$B$42,$B49,G$5:G$42) -> 85359998 | H49: =SUMIF($B$5:$B$42,$B49,H$5:H$42) -> 1.0399287e+08 | I49: =SUMIF($B$5:$B$42,$B49,I$5:I$42) -> 1.1641479e+08 | J49: =SUMIF($B$5:$B$42,$B49,J$5:J$42) -> 1.1641479e+08 | K49: =SUMIF($B$5:$B$42,$B49,K$5:K$42) -> 1.1641479e+08 | ... AA49: =SUMIF($B$5:$B$42,$B49,AA$5:AA$42) -> 1.6268613e+08
A50: 4 | B50: Growth & Partnership | D50: =SUMIF($B$5:$B$42,$B50,D$5:D$42) -> 0 | E50: =SUMIF($B$5:$B$42,$B50,E$5:E$42) -> 0 | F50: =SUMIF($B$5:$B$42,$B50,F$5:F$42) -> 0 | G50: =SUMIF($B$5:$B$42,$B50,G$5:G$42) -> 27395481 | H50: =SUMIF($B$5:$B$42,$B50,H$5:H$42) -> 27395481 | I50: =SUMIF($B$5:$B$42,$B50,I$5:I$42) -> 27395481 | J50: =SUMIF($B$5:$B$42,$B50,J$5:J$42) -> 27395481 | K50: =SUMIF($B$5:$B$42,$B50,K$5:K$42) -> 27395481 | ... AA50: =SUMIF($B$5:$B$42,$B50,AA$5:AA$42) -> 43433426
A51: 5 | B51: Keuangan | D51: =SUMIF($B$5:$B$42,$B51,D$5:D$42) -> 0 | E51: =SUMIF($B$5:$B$42,$B51,E$5:E$42) -> 25533126 | F51: =SUMIF($B$5:$B$42,$B51,F$5:F$42) -> 25533126 | G51: =SUMIF($B$5:$B$42,$B51,G$5:G$42) -> 34032331 | H51: =SUMIF($B$5:$B$42,$B51,H$5:H$42) -> 34032331 | I51: =SUMIF($B$5:$B$42,$B51,I$5:I$42) -> 34032331 | J51: =SUMIF($B$5:$B$42,$B51,J$5:J$42) -> 34032331 | K51: =SUMIF($B$5:$B$42,$B51,K$5:K$42) -> 34032331 | ... AA51: =SUMIF($B$5:$B$42,$B51,AA$5:AA$42) -> 51847972
A52: 6 | B52: Legal & Kepatuhan | D52: =SUMIF($B$5:$B$42,$B52,D$5:D$42) -> 0 | E52: =SUMIF($B$5:$B$42,$B52,E$5:E$42) -> 0 | F52: =SUMIF($B$5:$B$42,$B52,F$5:F$42) -> 0 | G52: =SUMIF($B$5:$B$42,$B52,G$5:G$42) -> 17462921 | H52: =SUMIF($B$5:$B$42,$B52,H$5:H$42) -> 17462921 | I52: =SUMIF($B$5:$B$42,$B52,I$5:I$42) -> 17462921 | J52: =SUMIF($B$5:$B$42,$B52,J$5:J$42) -> 17462921 | K52: =SUMIF($B$5:$B$42,$B52,K$5:K$42) -> 17462921 | ... AA52: =SUMIF($B$5:$B$42,$B52,AA$5:AA$42) -> 17462921
B53: TOTAL (uji: harus sama dengan baris TOTAL di atas) | D53: =SUM(D47:D52) -> 158704880 | E53: =SUM(E47:E52) -> 219217748 | F53: =SUM(F47:F52) -> 230332093 | G53: =SUM(G47:G52) -> 375824433 | H53: =SUM(H47:H52) -> 4.1005787e+08 | I53: =SUM(I47:I52) -> 4.3555549e+08 | J53: =SUM(J47:J52) -> 4.3555549e+08 | K53: =SUM(K47:K52) -> 4.3555549e+08 | ... AA53: =SUM(AA47:AA52) -> 6.3627206e+08
B55: Biaya SDM kumulatif bulan 1-24 (Rp) | D55: =SUM(D43:AA43) -> 11689208853
B56: Biaya SDM kumulatif bulan 1-12 (Rp) | D56: =SUM(D43:O43) -> 4443025431
B57: Biaya SDM kumulatif bulan 13-24 (Rp) | D57: =SUM(P43:AA43) -> 7246183422
A59: BIAYA SDM PER DIREKTORAT PER KUARTAL (Rp) - dasar grafik batang bertumpuk
A60: Direktorat | B60: K1 | C60: K2 | D60: K3 | E60: K4 | F60: K5 | G60: K6 | H60: K7 | I60: K8
A61: Direksi & Tata Kelola | B61: =SUM(D47:F47) -> 143584373 | C61: =SUM(G47:I47) -> 165813063 | D61: =SUM(J47:L47) -> 165813063 | E61: =SUM(M47:O47) -> 165813063 | F61: =SUM(P47:R47) -> 165813063 | G61: =SUM(S47:U47) -> 165813063 | H61: =SUM(V47:X47) -> 165813063 | I61: =SUM(Y47:AA47) -> 165813063
A62: Teknologi | B62: =SUM(D48:F48) -> 300729506 | C62: =SUM(G48:I48) -> 513184875 | D62: =SUM(J48:L48) -> 554936841 | E62: =SUM(M48:O48) -> 554936841 | F62: =SUM(P48:R48) -> 690954714 | G62: =SUM(S48:U48) -> 804964267 | H62: =SUM(V48:X48) -> 916711761 | I62: =SUM(Y48:AA48) -> 916711761
A63: Operasi | B63: =SUM(D49:F49) -> 112874590 | C63: =SUM(G49:I49) -> 305767654 | D63: =SUM(J49:L49) -> 3.4924436e+08 | E63: =SUM(M49:O49) -> 3.4924436e+08 | F63: =SUM(P49:R49) -> 4.5805653e+08 | G63: =SUM(S49:U49) -> 4.880584e+08 | H63: =SUM(V49:X49) -> 4.880584e+08 | I63: =SUM(Y49:AA49) -> 4.880584e+08
A64: Growth & Partnership | B64: =SUM(D50:F50) -> 0 | C64: =SUM(G50:I50) -> 82186443 | D64: =SUM(J50:L50) -> 82186443 | E64: =SUM(M50:O50) -> 82186443 | F64: =SUM(P50:R50) -> 130300278 | G64: =SUM(S50:U50) -> 130300278 | H64: =SUM(V50:X50) -> 130300278 | I64: =SUM(Y50:AA50) -> 130300278
A65: Keuangan | B65: =SUM(D51:F51) -> 51066252 | C65: =SUM(G51:I51) -> 102096993 | D65: =SUM(J51:L51) -> 102096993 | E65: =SUM(M51:O51) -> 102096993 | F65: =SUM(P51:R51) -> 1.3396901e+08 | G65: =SUM(S51:U51) -> 1.5554392e+08 | H65: =SUM(V51:X51) -> 1.5554392e+08 | I65: =SUM(Y51:AA51) -> 1.5554392e+08
A66: Legal & Kepatuhan | B66: =SUM(D52:F52) -> 0 | C66: =SUM(G52:I52) -> 52388763 | D66: =SUM(J52:L52) -> 52388763 | E66: =SUM(M52:O52) -> 52388763 | F66: =SUM(P52:R52) -> 52388763 | G66: =SUM(S52:U52) -> 52388763 | H66: =SUM(V52:X52) -> 52388763 | I66: =SUM(Y52:AA52) -> 52388763
A67: TOTAL | B67: =SUM(B61:B66) -> 608254721 | C67: =SUM(C61:C66) -> 1221437791 | D67: =SUM(D61:D66) -> 1.3066665e+09 | E67: =SUM(E61:E66) -> 1.3066665e+09 | F67: =SUM(F61:F66) -> 1.6314824e+09 | G67: =SUM(G61:G66) -> 1.7970687e+09 | H67: =SUM(H61:H66) -> 1.9088162e+09 | I67: =SUM(I61:I66) -> 1.9088162e+09
A69: Sumber baris: jadwal rekrutmen (kolom Bulan Mulai) dan jumlah orang per fase dari lembar 'Headcount'/'Biaya Bulanan'; tarif iuran & THR dari blok Asumsi lembar 'Biaya Bulanan' [S-07]-[S-16]. Pita gaji [ASUMSI].
A70: Model tidak memuat kenaikan gaji tahunan. Proyeksi kenaikan gaji nasional +6,3% (2025) [S-20] TIDAK diterapkan - lihat 'Keterbatasan data' pada lembar 'Sumber & Catatan'.

Sheet Biaya Non-Gaji
A1: AntarKita - Biaya Non-Gaji yang Melekat pada SDM
A2: Disusun 7 September 2026. SELURUH BIAYA SATUAN PADA LEMBAR INI BERLABEL [ASUMSI] - tidak ditemukan sumber kredibel untuk harga sewa coworking, perangkat kerja, lisensi, maupun asuransi tambahan di Pekanbaru/Padang.
A4: A. BIAYA BERULANG BULANAN (melekat per orang)
A5: No | B5: Pos Biaya | C5: Basis perhitungan | D5: Biaya Satuan (Rp) | E5: Status data | F5: Orang Fase 0 | G5: Orang Fase 1 | H5: Orang Fase 2 | I5: Biaya/bulan Fase 0 (Rp) | J5: Biaya/bulan Fase 1 (Rp) | K5: Biaya/bulan Fase 2 (Rp) | L5: Bulan-orang bln 1-24 | M5: Total 24 bulan (Rp) | N5: Catatan
A6: 1 | B6: Kantor & coworking Pekanbaru | C6: Per kursi kerja per bulan | D6: 1200000 | E6: [ASUMSI] | F6: =SUMIF('Biaya Bulanan'!$D$26:$D$63,"Pekanbaru",'Biaya Bulanan'!$V$26:$V$63) -> 9 | G6: =SUMIF('Biaya Bulanan'!$D$26:$D$63,"Pekanbaru",'Biaya Bulanan'!$W$26:$W$63) -> 21 | H6: =SUMIF('Biaya Bulanan'!$D$26:$D$63,"Pekanbaru",'Biaya Bulanan'!$X$26:$X$63) -> 26 | I6: =$D6*$F6 -> 10800000 | J6: =$D6*$G6 -> 25200000 | K6: =$D6*$H6 -> 31200000 | L6: =SUMIF('Biaya Bulanan'!$D$26:$D$63,"Pekanbaru",'Biaya Bulanan'!$AK$26:$AK$63) -> 513 | M6: =$D6*$L6 -> 615600000 | N6: Tidak ditemukan sumber tarif coworking Pekanbaru. Karyawan Remote tidak dihitung memakai kursi.
A7: 2 | B7: Kantor & coworking Padang | C7: Per kursi kerja per bulan | D7: 900000 | E7: [ASUMSI] | F7: =SUMIF('Biaya Bulanan'!$D$26:$D$63,"Padang",'Biaya Bulanan'!$V$26:$V$63) -> 0 | G7: =SUMIF('Biaya Bulanan'!$D$26:$D$63,"Padang",'Biaya Bulanan'!$W$26:$W$63) -> 0 | H7: =SUMIF('Biaya Bulanan'!$D$26:$D$63,"Padang",'Biaya Bulanan'!$X$26:$X$63) -> 8 | I7: =$D7*$F7 -> 0 | J7: =$D7*$G7 -> 0 | K7: =$D7*$H7 -> 7200000 | L7: =SUMIF('Biaya Bulanan'!$D$26:$D$63,"Padang",'Biaya Bulanan'!$AK$26:$AK$63) -> 83 | M7: =$D7*$L7 -> 74700000 | N7: Tidak ditemukan sumber tarif coworking Padang. Diturunkan proporsional terhadap selisih UMK 25,6%.
A8: 3 | B8: Tools & lisensi kerja | C8: Per orang per bulan (seat perangkat lunak) | D8: 450000 | E8: [ASUMSI] | F8: =SUM('Biaya Bulanan'!$V$26:$V$63) -> 9 | G8: =SUM('Biaya Bulanan'!$W$26:$W$63) -> 24 | H8: =SUM('Biaya Bulanan'!$X$26:$X$63) -> 42 | I8: =$D8*$F8 -> 4050000 | J8: =$D8*$G8 -> 10800000 | K8: =$D8*$H8 -> 18900000 | L8: =SUM('Biaya Bulanan'!$AK$26:$AK$63) -> 705 | M8: =$D8*$L8 -> 317250000 | N8: Repositori kode, desain, komunikasi, basis data, pemantauan. Tidak ditemukan sumber harga agregat.
A9: 4 | B9: Asuransi kesehatan tambahan | C9: Per orang per bulan (di atas BPJS Kesehatan) | D9: 350000 | E9: [ASUMSI] | F9: =SUM('Biaya Bulanan'!$V$26:$V$63) -> 9 | G9: =SUM('Biaya Bulanan'!$W$26:$W$63) -> 24 | H9: =SUM('Biaya Bulanan'!$X$26:$X$63) -> 42 | I9: =$D9*$F9 -> 3150000 | J9: =$D9*$G9 -> 8400000 | K9: =$D9*$H9 -> 14700000 | L9: =SUM('Biaya Bulanan'!$AK$26:$AK$63) -> 705 | M9: =$D9*$L9 -> 246750000 | N9: Bukan kewajiban hukum; keputusan bisnis untuk retensi. Tidak ditemukan sumber premi.
A10: 5 | B10: Pelatihan & pengembangan | C10: Per orang per bulan (setara Rp1,8 juta/orang/tahun) | D10: 150000 | E10: [ASUMSI] | F10: =SUM('Biaya Bulanan'!$V$26:$V$63) -> 9 | G10: =SUM('Biaya Bulanan'!$W$26:$W$63) -> 24 | H10: =SUM('Biaya Bulanan'!$X$26:$X$63) -> 42 | I10: =$D10*$F10 -> 1350000 | J10: =$D10*$G10 -> 3600000 | K10: =$D10*$H10 -> 6300000 | L10: =SUM('Biaya Bulanan'!$AK$26:$AK$63) -> 705 | M10: =$D10*$L10 -> 105750000 | N10: Termasuk pelatihan kepatuhan UU PDP untuk seluruh pemroses data [S-37].
B11: SUBTOTAL A - biaya berulang | I11: =SUM(I6:I10) -> 19350000 | J11: =SUM(J6:J10) -> 48000000 | K11: =SUM(K6:K10) -> 78300000 | M11: =SUM(M6:M10) -> 1360050000
A13: B. BIAYA SATU KALI PER REKRUTMEN
A14: No | B14: Pos Biaya | C14: Basis perhitungan | D14: Biaya Satuan (Rp) | E14: Status data | F14: Rekrutmen Fase 0 | G14: Rekrutmen Fase 1 | H14: Rekrutmen Fase 2 | I14: Biaya Fase 0 (Rp) | J14: Biaya Fase 1 (Rp) | K14: Biaya Fase 2 (Rp) | L14: Total orang direkrut | M14: Total 24 bulan (Rp) | N14: Catatan
A15: 1 | B15: Biaya rekrutmen | C15: Per orang direkrut (iklan lowongan, asesmen, medical check-up) | D15: 2500000 | E15: [ASUMSI] | F15: =Headcount!$H$43 -> 9 | G15: =Headcount!$I$43-Headcount!$H$43 -> 15 | H15: =Headcount!$J$43-Headcount!$I$43 -> 18 | I15: =$D15*$F15 -> 22500000 | J15: =$D15*$G15 -> 37500000 | K15: =$D15*$H15 -> 45000000 | L15: =SUM($F15:$H15) -> 42 | M15: =SUM($I15:$K15) -> 105000000 | N15: Tidak ditemukan sumber biaya rekrutmen pasar Pekanbaru/Padang.
A16: 2 | B16: Perangkat kerja | C16: Per orang direkrut (laptop, ponsel uji, headset) | D16: 11000000 | E16: [ASUMSI] | F16: =Headcount!$H$43 -> 9 | G16: =Headcount!$I$43-Headcount!$H$43 -> 15 | H16: =Headcount!$J$43-Headcount!$I$43 -> 18 | I16: =$D16*$F16 -> 99000000 | J16: =$D16*$G16 -> 165000000 | K16: =$D16*$H16 -> 198000000 | L16: =SUM($F16:$H16) -> 42 | M16: =SUM($I16:$K16) -> 462000000 | N16: Belanja modal, bukan biaya berulang. Tidak diamortisasi dalam model ini.
B17: SUBTOTAL B - biaya satu kali | I17: =SUM(I15:I16) -> 121500000 | J17: =SUM(J15:J16) -> 202500000 | K17: =SUM(K15:K16) -> 243000000 | M17: =SUM(M15:M16) -> 567000000
B19: TOTAL BIAYA NON-GAJI 24 BULAN (A + B) | M19: =M11+M17 -> 1927050000
B20: Biaya non-gaji berulang per bulan pada Fase 2 (Rp) | M20: =K11 -> 78300000
A22: Sumber baris: TIDAK ADA sumber pihak ketiga untuk seluruh biaya satuan di lembar ini - semuanya [ASUMSI] penyusun model. Volume orang dan bulan-orang adalah tautan hidup ke lembar 'Biaya Bulanan'.
A23: Tidak termasuk: honorarium Dewan Komisaris, biaya izin & badan hukum (NIB/TDPSE/izin pos KBLI 53200 [S-41]), insentif variabel karyawan (maks. 20% - DESAIN §4.5), insentif & BHR mitra pengemudi [S-52], dan belanja pemasaran.

Sheet Sensitivitas
A1: AntarKita - Sensitivitas Biaya SDM
A2: Disusun 7 September 2026. Dua arah: (a) pita gaji naik/turun 10-20%; (b) jadwal rekrutmen dimajukan/dimundurkan sampai 3 bulan. Seluruh sel adalah rumus hidup atas lembar 'Biaya Bulanan'.
A4: BLOK BANTU (per posisi) - CTC pada 5 tingkat pita gaji, dan bulan-orang pada 7 pergeseran jadwal
A5: No | B5: Posisi | C5: Gaji Pokok aktif (Rp) | D5: Kota Payroll | E5: Risiko JKK | F5: Orang F0 | G5: Orang F1 | H5: Orang F2 | I5: Bulan Mulai | J5: CTC -20% (Rp) | K5: CTC -10% (Rp) | L5: CTC +0% (Rp) | M5: CTC +10% (Rp) | N5: CTC +20% (Rp) | O5: Bln-org 1-12, geser -3 bln | P5: Bln-org 1-12, geser -2 bln | Q5: Bln-org 1-12, geser -1 bln | R5: Bln-org 1-12, geser +0 bln | S5: Bln-org 1-12, geser +1 bln | T5: Bln-org 1-12, geser +2 bln | U5: Bln-org 1-12, geser +3 bln | V5: Bln-org 1-24, geser -3 bln | W5: Bln-org 1-24, geser -2 bln | X5: Bln-org 1-24, geser -1 bln | Y5: Bln-org 1-24, geser +0 bln | Z5: Bln-org 1-24, geser +1 bln | AA5: Bln-org 1-24, geser +2 bln | AB5: Bln-org 1-24, geser +3 bln
A6: 1 | B6: ='Biaya Bulanan'!$C$26 -> Direktur Utama (CEO) | C6: ='Biaya Bulanan'!$K$26 -> 35000000 | D6: ='Biaya Bulanan'!$E$26 -> Pekanbaru | E6: ='Biaya Bulanan'!$H$26 -> Kantor | F6: ='Biaya Bulanan'!$V$26 -> 1 | G6: ='Biaya Bulanan'!$W$26 -> 1 | H6: ='Biaya Bulanan'!$X$26 -> 1 | I6: ='Biaya Bulanan'!$I$26 -> 1 | J6: =(($C6*(1+-0.2))*(1+Tunjangan_Pct))*(1+IF($E6="Lapangan",Tarif_JKK_Lapangan,Tarif_JKK_Kantor)+Tarif_JKM+Tarif_JHT+Tarif_THR)+MIN((($C6*(1+-0.2))*(1+Tunjangan_Pct)),Plafon_JP)*Tarif_JP+MIN(MAX((($C6*(1+-0.2))*(1+Tunjangan_Pct)),IF($D6="Padang",UMP_Padang,UMK_Pekanbaru)),Plafon_JKN)*Tarif_JKN -> 35465686 | K6: =(($C6*(1+-0.1))*(1+Tunjangan_Pct))*(1+IF($E6="Lapangan",Tarif_JKK_Lapangan,Tarif_JKK_Kantor)+Tarif_JKM+Tarif_JHT+Tarif_THR)+MIN((($C6*(1+-0.1))*(1+Tunjangan_Pct)),Plafon_JP)*Tarif_JP+MIN(MAX((($C6*(1+-0.1))*(1+Tunjangan_Pct)),IF($D6="Padang",UMP_Padang,UMK_Pekanbaru)),Plafon_JKN)*Tarif_JKN -> 39811181 | L6: =(($C6*(1+0))*(1+Tunjangan_Pct))*(1+IF($E6="Lapangan",Tarif_JKK_Lapangan,Tarif_JKK_Kantor)+Tarif_JKM+Tarif_JHT+Tarif_THR)+MIN((($C6*(1+0))*(1+Tunjangan_Pct)),Plafon_JP)*Tarif_JP+MIN(MAX((($C6*(1+0))*(1+Tunjangan_Pct)),IF($D6="Padang",UMP_Padang,UMK_Pekanbaru)),Plafon_JKN)*Tarif_JKN -> 44156676 | M6: =(($C6*(1+0.1))*(1+Tunjangan_Pct))*(1+IF($E6="Lapangan",Tarif_JKK_Lapangan,Tarif_JKK_Kantor)+Tarif_JKM+Tarif_JHT+Tarif_THR)+MIN((($C6*(1+0.1))*(1+Tunjangan_Pct)),Plafon_JP)*Tarif_JP+MIN(MAX((($C6*(1+0.1))*(1+Tunjangan_Pct)),IF($D6="Padang",UMP_Padang,UMK_Pekanbaru)),Plafon_JKN)*Tarif_JKN -> 48502171 | N6: =(($C6*(1+0.2))*(1+Tunjangan_Pct))*(1+IF($E6="Lapangan",Tarif_JKK_Lapangan,Tarif_JKK_Kantor)+Tarif_JKM+Tarif_JHT+Tarif_THR)+MIN((($C6*(1+0.2))*(1+Tunjangan_Pct)),Plafon_JP)*Tarif_JP+MIN(MAX((($C6*(1+0.2))*(1+Tunjangan_Pct)),IF($D6="Padang",UMP_Padang,UMK_Pekanbaru)),Plafon_JKN)*Tarif_JKN -> 52847666 | O6: =$F6*MAX(0,MIN(3,4-MAX(1,$I6+-3)))+$G6*MAX(0,MIN(9,13-MAX(MAX(1,$I6+-3),4))) -> 12 | P6: =$F6*MAX(0,MIN(3,4-MAX(1,$I6+-2)))+$G6*MAX(0,MIN(9,13-MAX(MAX(1,$I6+-2),4))) -> 12 | Q6: =$F6*MAX(0,MIN(3,4-MAX(1,$I6+-1)))+$G6*MAX(0,MIN(9,13-MAX(MAX(1,$I6+-1),4))) -> 12 | R6: =$F6*MAX(0,MIN(3,4-MAX(1,$I6+0)))+$G6*MAX(0,MIN(9,13-MAX(MAX(1,$I6+0),4))) -> 12 | S6: =$F6*MAX(0,MIN(3,4-MAX(1,$I6+1)))+$G6*MAX(0,MIN(9,13-MAX(MAX(1,$I6+1),4))) -> 11 | T6: =$F6*MAX(0,MIN(3,4-MAX(1,$I6+2)))+$G6*MAX(0,MIN(9,13-MAX(MAX(1,$I6+2),4))) -> 10 | U6: =$F6*MAX(0,MIN(3,4-MAX(1,$I6+3)))+$G6*MAX(0,MIN(9,13-MAX(MAX(1,$I6+3),4))) -> 9 | V6: =O6+$H6*MAX(0,MIN(12,25-MAX(MAX(1,$I6+-3),13))) -> 24 | W6: =P6+$H6*MAX(0,MIN(12,25-MAX(MAX(1,$I6+-2),13))) -> 24 | X6: =Q6+$H6*MAX(0,MIN(12,25-MAX(MAX(1,$I6+-1),13))) -> 24 | Y6: =R6+$H6*MAX(0,MIN(12,25-MAX(MAX(1,$I6+0),13))) -> 24 | Z6: =S6+$H6*MAX(0,MIN(12,25-MAX(MAX(1,$I6+1),13))) -> 23 | AA6: =T6+$H6*MAX(0,MIN(12,25-MAX(MAX(1,$I6+2),13))) -> 22 | AB6: =U6+$H6*MAX(0,MIN(12,25-MAX(MAX(1,$I6+3),13))) -> 21
A7: 2 | B7: ='Biaya Bulanan'!$C$27 -> HR & GA Generalist | C7: ='Biaya Bulanan'!$K$27 -> 8500000 | D7: ='Biaya Bulanan'!$E$27 -> Pekanbaru | E7: ='Biaya Bulanan'!$H$27 -> Kantor | F7: ='Biaya Bulanan'!$V$27 -> 1 | G7: ='Biaya Bulanan'!$W$27 -> 1 | H7: ='Biaya Bulanan'!$X$27 -> 1 | I7: ='Biaya Bulanan'!$I$27 -> 3 | J7: =(($C7*(1+-0.2))*(1+Tunjangan_Pct))*(1+IF($E7="Lapangan",Tarif_JKK_Lapangan,Tarif_JKK_Kantor)+Tarif_JKM+Tarif_JHT+Tarif_THR)+MIN((($C7*(1+-0.2))*(1+Tunjangan_Pct)),Plafon_JP)*Tarif_JP+MIN(MAX((($C7*(1+-0.2))*(1+Tunjangan_Pct)),IF($D7="Padang",UMP_Padang,UMK_Pekanbaru)),Plafon_JKN)*Tarif_JKN -> 8891476 | K7: =(($C7*(1+-0.1))*(1+Tunjangan_Pct))*(1+IF($E7="Lapangan",Tarif_JKK_Lapangan,Tarif_JKK_Kantor)+Tarif_JKM+Tarif_JHT+Tarif_THR)+MIN((($C7*(1+-0.1))*(1+Tunjangan_Pct)),Plafon_JP)*Tarif_JP+MIN(MAX((($C7*(1+-0.1))*(1+Tunjangan_Pct)),IF($D7="Padang",UMP_Padang,UMK_Pekanbaru)),Plafon_JKN)*Tarif_JKN -> 10002910 | L7: =(($C7*(1+0))*(1+Tunjangan_Pct))*(1+IF($E7="Lapangan",Tarif_JKK_Lapangan,Tarif_JKK_Kantor)+Tarif_JKM+Tarif_JHT+Tarif_THR)+MIN((($C7*(1+0))*(1+Tunjangan_Pct)),Plafon_JP)*Tarif_JP+MIN(MAX((($C7*(1+0))*(1+Tunjangan_Pct)),IF($D7="Padang",UMP_Padang,UMK_Pekanbaru)),Plafon_JKN)*Tarif_JKN -> 11114345 | M7: =(($C7*(1+0.1))*(1+Tunjangan_Pct))*(1+IF($E7="Lapangan",Tarif_JKK_Lapangan,Tarif_JKK_Kantor)+Tarif_JKM+Tarif_JHT+Tarif_THR)+MIN((($C7*(1+0.1))*(1+Tunjangan_Pct)),Plafon_JP)*Tarif_JP+MIN(MAX((($C7*(1+0.1))*(1+Tunjangan_Pct)),IF($D7="Padang",UMP_Padang,UMK_Pekanbaru)),Plafon_JKN)*Tarif_JKN -> 12225780 | N7: =(($C7*(1+0.2))*(1+Tunjangan_Pct))*(1+IF($E7="Lapangan",Tarif_JKK_Lapangan,Tarif_JKK_Kantor)+Tarif_JKM+Tarif_JHT+Tarif_THR)+MIN((($C7*(1+0.2))*(1+Tunjangan_Pct)),Plafon_JP)*Tarif_JP+MIN(MAX((($C7*(1+0.2))*(1+Tunjangan_Pct)),IF($D7="Padang",UMP_Padang,UMK_Pekanbaru)),Plafon_JKN)*Tarif_JKN -> 13334540 | O7: =$F7*MAX(0,MIN(3,4-MAX(1,$I7+-3)))+$G7*MAX(0,MIN(9,13-MAX(MAX(1,$I7+-3),4))) -> 12 | P7: =$F7*MAX(0,MIN(3,4-MAX(1,$I7+-2)))+$G7*MAX(0,MIN(9,13-MAX(MAX(1,$I7+-2),4))) -> 12 | Q7: =$F7*MAX(0,MIN(3,4-MAX(1,$I7+-1)))+$G7*MAX(0,MIN(9,13-MAX(MAX(1,$I7+-1),4))) -> 11 | R7: =$F7*MAX(0,MIN(3,4-MAX(1,$I7+0)))+$G7*MAX(0,MIN(9,13-MAX(MAX(1,$I7+0),4))) -> 10 | S7: =$F7*MAX(0,MIN(3,4-MAX(1,$I7+1)))+$G7*MAX(0,MIN(9,13-MAX(MAX(1,$I7+1),4))) -> 9 | T7: =$F7*MAX(0,MIN(3,4-MAX(1,$I7+2)))+$G7*MAX(0,MIN(9,13-MAX(MAX(1,$I7+2),4))) -> 8 | U7: =$F7*MAX(0,MIN(3,4-MAX(1,$I7+3)))+$G7*MAX(0,MIN(9,13-MAX(MAX(1,$I7+3),4))) -> 7 | V7: =O7+$H7*MAX(0,MIN(12,25-MAX(MAX(1,$I7+-3),13))) -> 24 | W7: =P7+$H7*MAX(0,MIN(12,25-MAX(MAX(1,$I7+-2),13))) -> 24 | X7: =Q7+$H7*MAX(0,MIN(12,25-MAX(MAX(1,$I7+-1),13))) -> 23 | Y7: =R7+$H7*MAX(0,MIN(12,25-MAX(MAX(1,$I7+0),13))) -> 22 | Z7: =S7+$H7*MAX(0,MIN(12,25-MAX(MAX(1,$I7+1),13))) -> 21 | AA7: =T7+$H7*MAX(0,MIN(12,25-MAX(MAX(1,$I7+2),13))) -> 20 | AB7: =U7+$H7*MAX(0,MIN(12,25-MAX(MAX(1,$I7+3),13))) -> 19
A8: 3 | B8: ='Biaya Bulanan'!$C$28 -> Direktur Teknologi (CTO) | C8: ='Biaya Bulanan'!$K$28 -> 30000000 | D8: ='Biaya Bulanan'!$E$28 -> Pekanbaru | E8: ='Biaya Bulanan'!$H$28 -> Kantor | F8: ='Biaya Bulanan'!$V$28 -> 1 | G8: ='Biaya Bulanan'!$W$28 -> 1 | H8: ='Biaya Bulanan'!$X$28 -> 1 | I8: ='Biaya Bulanan'!$I$28 -> 1 | J8: =(($C8*(1+-0.2))*(1+Tunjangan_Pct))*(1+IF($E8="Lapangan",Tarif_JKK_Lapangan,Tarif_JKK_Kantor)+Tarif_JKM+Tarif_JHT+Tarif_THR)+MIN((($C8*(1+-0.2))*(1+Tunjangan_Pct)),Plafon_JP)*Tarif_JP+MIN(MAX((($C8*(1+-0.2))*(1+Tunjangan_Pct)),IF($D8="Padang",UMP_Padang,UMK_Pekanbaru)),Plafon_JKN)*Tarif_JKN -> 30499406 | K8: =(($C8*(1+-0.1))*(1+Tunjangan_Pct))*(1+IF($E8="Lapangan",Tarif_JKK_Lapangan,Tarif_JKK_Kantor)+Tarif_JKM+Tarif_JHT+Tarif_THR)+MIN((($C8*(1+-0.1))*(1+Tunjangan_Pct)),Plafon_JP)*Tarif_JP+MIN(MAX((($C8*(1+-0.1))*(1+Tunjangan_Pct)),IF($D8="Padang",UMP_Padang,UMK_Pekanbaru)),Plafon_JKN)*Tarif_JKN -> 34224116 | L8: =(($C8*(1+0))*(1+Tunjangan_Pct))*(1+IF($E8="Lapangan",Tarif_JKK_Lapangan,Tarif_JKK_Kantor)+Tarif_JKM+Tarif_JHT+Tarif_THR)+MIN((($C8*(1+0))*(1+Tunjangan_Pct)),Plafon_JP)*Tarif_JP+MIN(MAX((($C8*(1+0))*(1+Tunjangan_Pct)),IF($D8="Padang",UMP_Padang,UMK_Pekanbaru)),Plafon_JKN)*Tarif_JKN -> 37948826 | M8: =(($C8*(1+0.1))*(1+Tunjangan_Pct))*(1+IF($E8="Lapangan",Tarif_JKK_Lapangan,Tarif_JKK_Kantor)+Tarif_JKM+Tarif_JHT+Tarif_THR)+MIN((($C8*(1+0.1))*(1+Tunjangan_Pct)),Plafon_JP)*Tarif_JP+MIN(MAX((($C8*(1+0.1))*(1+Tunjangan_Pct)),IF($D8="Padang",UMP_Padang,UMK_Pekanbaru)),Plafon_JKN)*Tarif_JKN -> 41673536 | N8: =(($C8*(1+0.2))*(1+Tunjangan_Pct))*(1+IF($E8="Lapangan",Tarif_JKK_Lapangan,Tarif_JKK_Kantor)+Tarif_JKM+Tarif_JHT+Tarif_THR)+MIN((($C8*(1+0.2))*(1+Tunjangan_Pct)),Plafon_JP)*Tarif_JP+MIN(MAX((($C8*(1+0.2))*(1+Tunjangan_Pct)),IF($D8="Padang",UMP_Padang,UMK_Pekanbaru)),Plafon_JKN)*Tarif_JKN -> 45398246 | O8: =$F8*MAX(0,MIN(3,4-MAX(1,$I8+-3)))+$G8*MAX(0,MIN(9,13-MAX(MAX(1,$I8+-3),4))) -> 12 | P8: =$F8*MAX(0,MIN(3,4-MAX(1,$I8+-2)))+$G8*MAX(0,MIN(9,13-MAX(MAX(1,$I8+-2),4))) -> 12 | Q8: =$F8*MAX(0,MIN(3,4-MAX(1,$I8+-1)))+$G8*MAX(0,MIN(9,13-MAX(MAX(1,$I8+-1),4))) -> 12 | R8: =$F8*MAX(0,MIN(3,4-MAX(1,$I8+0)))+$G8*MAX(0,MIN(9,13-MAX(MAX(1,$I8+0),4))) -> 12 | S8: =$F8*MAX(0,MIN(3,4-MAX(1,$I8+1)))+$G8*MAX(0,MIN(9,13-MAX(MAX(1,$I8+1),4))) -> 11 | T8: =$F8*MAX(0,MIN(3,4-MAX(1,$I8+2)))+$G8*MAX(0,MIN(9,13-MAX(MAX(1,$I8+2),4))) -> 10 | U8: =$F8*MAX(0,MIN(3,4-MAX(1,$I8+3)))+$G8*MAX(0,MIN(9,13-MAX(MAX(1,$I8+3),4))) -> 9 | V8: =O8+$H8*MAX(0,MIN(12,25-MAX(MAX(1,$I8+-3),13))) -> 24 | W8: =P8+$H8*MAX(0,MIN(12,25-MAX(MAX(1,$I8+-2),13))) -> 24 | X8: =Q8+$H8*MAX(0,MIN(12,25-MAX(MAX(1,$I8+-1),13))) -> 24 | Y8: =R8+$H8*MAX(0,MIN(12,25-MAX(MAX(1,$I8+0),13))) -> 24 | Z8: =S8+$H8*MAX(0,MIN(12,25-MAX(MAX(1,$I8+1),13))) -> 23 | AA8: =T8+$H8*MAX(0,MIN(12,25-MAX(MAX(1,$I8+2),13))) -> 22 | AB8: =U8+$H8*MAX(0,MIN(12,25-MAX(MAX(1,$I8+3),13))) -> 21
A9: 4 | B9: ='Biaya Bulanan'!$C$29 -> Engineering Manager | C9: ='Biaya Bulanan'!$K$29 -> 27500000 | D9: ='Biaya Bulanan'!$E$29 -> Pekanbaru | E9: ='Biaya Bulanan'!$H$29 -> Kantor | F9: ='Biaya Bulanan'!$V$29 -> 0 | G9: ='Biaya Bulanan'!$W$29 -> 1 | H9: ='Biaya Bulanan'!$X$29 -> 1 | I9: ='Biaya Bulanan'!$I$29 -> 4 | J9: =(($C9*(1+-0.2))*(1+Tunjangan_Pct))*(1+IF($E9="Lapangan",Tarif_JKK_Lapangan,Tarif_JKK_Kantor)+Tarif_JKM+Tarif_JHT+Tarif_THR)+MIN((($C9*(1+-0.2))*(1+Tunjangan_Pct)),Plafon_JP)*Tarif_JP+MIN(MAX((($C9*(1+-0.2))*(1+Tunjangan_Pct)),IF($D9="Padang",UMP_Padang,UMK_Pekanbaru)),Plafon_JKN)*Tarif_JKN -> 28016266 | K9: =(($C9*(1+-0.1))*(1+Tunjangan_Pct))*(1+IF($E9="Lapangan",Tarif_JKK_Lapangan,Tarif_JKK_Kantor)+Tarif_JKM+Tarif_JHT+Tarif_THR)+MIN((($C9*(1+-0.1))*(1+Tunjangan_Pct)),Plafon_JP)*Tarif_JP+MIN(MAX((($C9*(1+-0.1))*(1+Tunjangan_Pct)),IF($D9="Padang",UMP_Padang,UMK_Pekanbaru)),Plafon_JKN)*Tarif_JKN -> 31430584 | L9: =(($C9*(1+0))*(1+Tunjangan_Pct))*(1+IF($E9="Lapangan",Tarif_JKK_Lapangan,Tarif_JKK_Kantor)+Tarif_JKM+Tarif_JHT+Tarif_THR)+MIN((($C9*(1+0))*(1+Tunjangan_Pct)),Plafon_JP)*Tarif_JP+MIN(MAX((($C9*(1+0))*(1+Tunjangan_Pct)),IF($D9="Padang",UMP_Padang,UMK_Pekanbaru)),Plafon_JKN)*Tarif_JKN -> 34844901 | M9: =(($C9*(1+0.1))*(1+Tunjangan_Pct))*(1+IF($E9="Lapangan",Tarif_JKK_Lapangan,Tarif_JKK_Kantor)+Tarif_JKM+Tarif_JHT+Tarif_THR)+MIN((($C9*(1+0.1))*(1+Tunjangan_Pct)),Plafon_JP)*Tarif_JP+MIN(MAX((($C9*(1+0.1))*(1+Tunjangan_Pct)),IF($D9="Padang",UMP_Padang,UMK_Pekanbaru)),Plafon_JKN)*Tarif_JKN -> 38259218 | N9: =(($C9*(1+0.2))*(1+Tunjangan_Pct))*(1+IF($E9="Lapangan",Tarif_JKK_Lapangan,Tarif_JKK_Kantor)+Tarif_JKM+Tarif_JHT+Tarif_THR)+MIN((($C9*(1+0.2))*(1+Tunjangan_Pct)),Plafon_JP)*Tarif_JP+MIN(MAX((($C9*(1+0.2))*(1+Tunjangan_Pct)),IF($D9="Padang",UMP_Padang,UMK_Pekanbaru)),Plafon_JKN)*Tarif_JKN -> 41673536 | O9: =$F9*MAX(0,MIN(3,4-MAX(1,$I9+-3)))+$G9*MAX(0,MIN(9,13-MAX(MAX(1,$I9+-3),4))) -> 9 | P9: =$F9*MAX(0,MIN(3,4-MAX(1,$I9+-2)))+$G9*MAX(0,MIN(9,13-MAX(MAX(1,$I9+-2),4))) -> 9 | Q9: =$F9*MAX(0,MIN(3,4-MAX(1,$I9+-1)))+$G9*MAX(0,MIN(9,13-MAX(MAX(1,$I9+-1),4))) -> 9 | R9: =$F9*MAX(0,MIN(3,4-MAX(1,$I9+0)))+$G9*MAX(0,MIN(9,13-MAX(MAX(1,$I9+0),4))) -> 9 | S9: =$F9*MAX(0,MIN(3,4-MAX(1,$I9+1)))+$G9*MAX(0,MIN(9,13-MAX(MAX(1,$I9+1),4))) -> 8 | T9: =$F9*MAX(0,MIN(3,4-MAX(1,$I9+2)))+$G9*MAX(0,MIN(9,13-MAX(MAX(1,$I9+2),4))) -> 7 | U9: =$F9*MAX(0,MIN(3,4-MAX(1,$I9+3)))+$G9*MAX(0,MIN(9,13-MAX(MAX(1,$I9+3),4))) -> 6 | V9: =O9+$H9*MAX(0,MIN(12,25-MAX(MAX(1,$I9+-3),13))) -> 21 | W9: =P9+$H9*MAX(0,MIN(12,25-MAX(MAX(1,$I9+-2),13))) -> 21 | X9: =Q9+$H9*MAX(0,MIN(12,25-MAX(MAX(1,$I9+-1),13))) -> 21 | Y9: =R9+$H9*MAX(0,MIN(12,25-MAX(MAX(1,$I9+0),13))) -> 21 | Z9: =S9+$H9*MAX(0,MIN(12,25-MAX(MAX(1,$I9+1),13))) -> 20 | AA9: =T9+$H9*MAX(0,MIN(12,25-MAX(MAX(1,$I9+2),13))) -> 19 | AB9: =U9+$H9*MAX(0,MIN(12,25-MAX(MAX(1,$I9+3),13))) -> 18
A10: 5 | B10: ='Biaya Bulanan'!$C$30 -> Mobile Engineer (Senior) | C10: ='Biaya Bulanan'!$K$30 -> 20000000 | D10: ='Biaya Bulanan'!$E$30 -> Pekanbaru | E10: ='Biaya Bulanan'!$H$30 -> Kantor | F10: ='Biaya Bulanan'!$V$30 -> 1 | G10: ='Biaya Bulanan'!$W$30 -> 1 | H10: ='Biaya Bulanan'!$X$30 -> 1 | I10: ='Biaya Bulanan'!$I$30 -> 1 | J10: =(($C10*(1+-0.2))*(1+Tunjangan_Pct))*(1+IF($E10="Lapangan",Tarif_JKK_Lapangan,Tarif_JKK_Kantor)+Tarif_JKM+Tarif_JHT+Tarif_THR)+MIN((($C10*(1+-0.2))*(1+Tunjangan_Pct)),Plafon_JP)*Tarif_JP+MIN(MAX((($C10*(1+-0.2))*(1+Tunjangan_Pct)),IF($D10="Padang",UMP_Padang,UMK_Pekanbaru)),Plafon_JKN)*Tarif_JKN -> 20566846 | K10: =(($C10*(1+-0.1))*(1+Tunjangan_Pct))*(1+IF($E10="Lapangan",Tarif_JKK_Lapangan,Tarif_JKK_Kantor)+Tarif_JKM+Tarif_JHT+Tarif_THR)+MIN((($C10*(1+-0.1))*(1+Tunjangan_Pct)),Plafon_JP)*Tarif_JP+MIN(MAX((($C10*(1+-0.1))*(1+Tunjangan_Pct)),IF($D10="Padang",UMP_Padang,UMK_Pekanbaru)),Plafon_JKN)*Tarif_JKN -> 23049986 | L10: =(($C10*(1+0))*(1+Tunjangan_Pct))*(1+IF($E10="Lapangan",Tarif_JKK_Lapangan,Tarif_JKK_Kantor)+Tarif_JKM+Tarif_JHT+Tarif_THR)+MIN((($C10*(1+0))*(1+Tunjangan_Pct)),Plafon_JP)*Tarif_JP+MIN(MAX((($C10*(1+0))*(1+Tunjangan_Pct)),IF($D10="Padang",UMP_Padang,UMK_Pekanbaru)),Plafon_JKN)*Tarif_JKN -> 25533126 | M10: =(($C10*(1+0.1))*(1+Tunjangan_Pct))*(1+IF($E10="Lapangan",Tarif_JKK_Lapangan,Tarif_JKK_Kantor)+Tarif_JKM+Tarif_JHT+Tarif_THR)+MIN((($C10*(1+0.1))*(1+Tunjangan_Pct)),Plafon_JP)*Tarif_JP+MIN(MAX((($C10*(1+0.1))*(1+Tunjangan_Pct)),IF($D10="Padang",UMP_Padang,UMK_Pekanbaru)),Plafon_JKN)*Tarif_JKN -> 28016266 | N10: =(($C10*(1+0.2))*(1+Tunjangan_Pct))*(1+IF($E10="Lapangan",Tarif_JKK_Lapangan,Tarif_JKK_Kantor)+Tarif_JKM+Tarif_JHT+Tarif_THR)+MIN((($C10*(1+0.2))*(1+Tunjangan_Pct)),Plafon_JP)*Tarif_JP+MIN(MAX((($C10*(1+0.2))*(1+Tunjangan_Pct)),IF($D10="Padang",UMP_Padang,UMK_Pekanbaru)),Plafon_JKN)*Tarif_JKN -> 30499406 | O10: =$F10*MAX(0,MIN(3,4-MAX(1,$I10+-3)))+$G10*MAX(0,MIN(9,13-MAX(MAX(1,$I10+-3),4))) -> 12 | P10: =$F10*MAX(0,MIN(3,4-MAX(1,$I10+-2)))+$G10*MAX(0,MIN(9,13-MAX(MAX(1,$I10+-2),4))) -> 12 | Q10: =$F10*MAX(0,MIN(3,4-MAX(1,$I10+-1)))+$G10*MAX(0,MIN(9,13-MAX(MAX(1,$I10+-1),4))) -> 12 | R10: =$F10*MAX(0,MIN(3,4-MAX(1,$I10+0)))+$G10*MAX(0,MIN(9,13-MAX(MAX(1,$I10+0),4))) -> 12 | S10: =$F10*MAX(0,MIN(3,4-MAX(1,$I10+1)))+$G10*MAX(0,MIN(9,13-MAX(MAX(1,$I10+1),4))) -> 11 | T10: =$F10*MAX(0,MIN(3,4-MAX(1,$I10+2)))+$G10*MAX(0,MIN(9,13-MAX(MAX(1,$I10+2),4))) -> 10 | U10: =$F10*MAX(0,MIN(3,4-MAX(1,$I10+3)))+$G10*MAX(0,MIN(9,13-MAX(MAX(1,$I10+3),4))) -> 9 | V10: =O10+$H10*MAX(0,MIN(12,25-MAX(MAX(1,$I10+-3),13))) -> 24 | W10: =P10+$H10*MAX(0,MIN(12,25-MAX(MAX(1,$I10+-2),13))) -> 24 | X10: =Q10+$H10*MAX(0,MIN(12,25-MAX(MAX(1,$I10+-1),13))) -> 24 | Y10: =R10+$H10*MAX(0,MIN(12,25-MAX(MAX(1,$I10+0),13))) -> 24 | Z10: =S10+$H10*MAX(0,MIN(12,25-MAX(MAX(1,$I10+1),13))) -> 23 | AA10: =T10+$H10*MAX(0,MIN(12,25-MAX(MAX(1,$I10+2),13))) -> 22 | AB10: =U10+$H10*MAX(0,MIN(12,25-MAX(MAX(1,$I10+3),13))) -> 21
A11: 6 | B11: ='Biaya Bulanan'!$C$31 -> Mobile Engineer (Mid) | C11: ='Biaya Bulanan'!$K$31 -> 12000000 | D11: ='Biaya Bulanan'!$E$31 -> Pekanbaru | E11: ='Biaya Bulanan'!$H$31 -> Kantor | F11: ='Biaya Bulanan'!$V$31 -> 0 | G11: ='Biaya Bulanan'!$W$31 -> 1 | H11: ='Biaya Bulanan'!$X$31 -> 1 | I11: ='Biaya Bulanan'!$I$31 -> 5 | J11: =(($C11*(1+-0.2))*(1+Tunjangan_Pct))*(1+IF($E11="Lapangan",Tarif_JKK_Lapangan,Tarif_JKK_Kantor)+Tarif_JKM+Tarif_JHT+Tarif_THR)+MIN((($C11*(1+-0.2))*(1+Tunjangan_Pct)),Plafon_JP)*Tarif_JP+MIN(MAX((($C11*(1+-0.2))*(1+Tunjangan_Pct)),IF($D11="Padang",UMP_Padang,UMK_Pekanbaru)),Plafon_JKN)*Tarif_JKN -> 12552672 | K11: =(($C11*(1+-0.1))*(1+Tunjangan_Pct))*(1+IF($E11="Lapangan",Tarif_JKK_Lapangan,Tarif_JKK_Kantor)+Tarif_JKM+Tarif_JHT+Tarif_THR)+MIN((($C11*(1+-0.1))*(1+Tunjangan_Pct)),Plafon_JP)*Tarif_JP+MIN(MAX((($C11*(1+-0.1))*(1+Tunjangan_Pct)),IF($D11="Padang",UMP_Padang,UMK_Pekanbaru)),Plafon_JKN)*Tarif_JKN -> 14105882 | L11: =(($C11*(1+0))*(1+Tunjangan_Pct))*(1+IF($E11="Lapangan",Tarif_JKK_Lapangan,Tarif_JKK_Kantor)+Tarif_JKM+Tarif_JHT+Tarif_THR)+MIN((($C11*(1+0))*(1+Tunjangan_Pct)),Plafon_JP)*Tarif_JP+MIN(MAX((($C11*(1+0))*(1+Tunjangan_Pct)),IF($D11="Padang",UMP_Padang,UMK_Pekanbaru)),Plafon_JKN)*Tarif_JKN -> 15600566 | M11: =(($C11*(1+0.1))*(1+Tunjangan_Pct))*(1+IF($E11="Lapangan",Tarif_JKK_Lapangan,Tarif_JKK_Kantor)+Tarif_JKM+Tarif_JHT+Tarif_THR)+MIN((($C11*(1+0.1))*(1+Tunjangan_Pct)),Plafon_JP)*Tarif_JP+MIN(MAX((($C11*(1+0.1))*(1+Tunjangan_Pct)),IF($D11="Padang",UMP_Padang,UMK_Pekanbaru)),Plafon_JKN)*Tarif_JKN -> 17090450 | N11: =(($C11*(1+0.2))*(1+Tunjangan_Pct))*(1+IF($E11="Lapangan",Tarif_JKK_Lapangan,Tarif_JKK_Kantor)+Tarif_JKM+Tarif_JHT+Tarif_THR)+MIN((($C11*(1+0.2))*(1+Tunjangan_Pct)),Plafon_JP)*Tarif_JP+MIN(MAX((($C11*(1+0.2))*(1+Tunjangan_Pct)),IF($D11="Padang",UMP_Padang,UMK_Pekanbaru)),Plafon_JKN)*Tarif_JKN -> 18580334 | O11: =$F11*MAX(0,MIN(3,4-MAX(1,$I11+-3)))+$G11*MAX(0,MIN(9,13-MAX(MAX(1,$I11+-3),4))) -> 9 | P11: =$F11*MAX(0,MIN(3,4-MAX(1,$I11+-2)))+$G11*MAX(0,MIN(9,13-MAX(MAX(1,$I11+-2),4))) -> 9 | Q11: =$F11*MAX(0,MIN(3,4-MAX(1,$I11+-1)))+$G11*MAX(0,MIN(9,13-MAX(MAX(1,$I11+-1),4))) -> 9 | R11: =$F11*MAX(0,MIN(3,4-MAX(1,$I11+0)))+$G11*MAX(0,MIN(9,13-MAX(MAX(1,$I11+0),4))) -> 8 | S11: =$F11*MAX(0,MIN(3,4-MAX(1,$I11+1)))+$G11*MAX(0,MIN(9,13-MAX(MAX(1,$I11+1),4))) -> 7 | T11: =$F11*MAX(0,MIN(3,4-MAX(1,$I11+2)))+$G11*MAX(0,MIN(9,13-MAX(MAX(1,$I11+2),4))) -> 6 | U11: =$F11*MAX(0,MIN(3,4-MAX(1,$I11+3)))+$G11*MAX(0,MIN(9,13-MAX(MAX(1,$I11+3),4))) -> 5 | V11: =O11+$H11*MAX(0,MIN(12,25-MAX(MAX(1,$I11+-3),13))) -> 21 | W11: =P11+$H11*MAX(0,MIN(12,25-MAX(MAX(1,$I11+-2),13))) -> 21 | X11: =Q11+$H11*MAX(0,MIN(12,25-MAX(MAX(1,$I11+-1),13))) -> 21 | Y11: =R11+$H11*MAX(0,MIN(12,25-MAX(MAX(1,$I11+0),13))) -> 20 | Z11: =S11+$H11*MAX(0,MIN(12,25-MAX(MAX(1,$I11+1),13))) -> 19 | AA11: =T11+$H11*MAX(0,MIN(12,25-MAX(MAX(1,$I11+2),13))) -> 18 | AB11: =U11+$H11*MAX(0,MIN(12,25-MAX(MAX(1,$I11+3),13))) -> 17
A12: 7 | B12: ='Biaya Bulanan'!$C$32 -> Mobile Engineer (Mid) - gelombang 2 | C12: ='Biaya Bulanan'!$K$32 -> 12000000 | D12: ='Biaya Bulanan'!$E$32 -> Pekanbaru | E12: ='Biaya Bulanan'!$H$32 -> Kantor | F12: ='Biaya Bulanan'!$V$32 -> 0 | G12: ='Biaya Bulanan'!$W$32 -> 0 | H12: ='Biaya Bulanan'!$X$32 -> 1 | I12: ='Biaya Bulanan'!$I$32 -> 14 | J12: =(($C12*(1+-0.2))*(1+Tunjangan_Pct))*(1+IF($E12="Lapangan",Tarif_JKK_Lapangan,Tarif_JKK_Kantor)+Tarif_JKM+Tarif_JHT+Tarif_THR)+MIN((($C12*(1+-0.2))*(1+Tunjangan_Pct)),Plafon_JP)*Tarif_JP+MIN(MAX((($C12*(1+-0.2))*(1+Tunjangan_Pct)),IF($D12="Padang",UMP_Padang,UMK_Pekanbaru)),Plafon_JKN)*Tarif_JKN -> 12552672 | K12: =(($C12*(1+-0.1))*(1+Tunjangan_Pct))*(1+IF($E12="Lapangan",Tarif_JKK_Lapangan,Tarif_JKK_Kantor)+Tarif_JKM+Tarif_JHT+Tarif_THR)+MIN((($C12*(1+-0.1))*(1+Tunjangan_Pct)),Plafon_JP)*Tarif_JP+MIN(MAX((($C12*(1+-0.1))*(1+Tunjangan_Pct)),IF($D12="Padang",UMP_Padang,UMK_Pekanbaru)),Plafon_JKN)*Tarif_JKN -> 14105882 | L12: =(($C12*(1+0))*(1+Tunjangan_Pct))*(1+IF($E12="Lapangan",Tarif_JKK_Lapangan,Tarif_JKK_Kantor)+Tarif_JKM+Tarif_JHT+Tarif_THR)+MIN((($C12*(1+0))*(1+Tunjangan_Pct)),Plafon_JP)*Tarif_JP+MIN(MAX((($C12*(1+0))*(1+Tunjangan_Pct)),IF($D12="Padang",UMP_Padang,UMK_Pekanbaru)),Plafon_JKN)*Tarif_JKN -> 15600566 | M12: =(($C12*(1+0.1))*(1+Tunjangan_Pct))*(1+IF($E12="Lapangan",Tarif_JKK_Lapangan,Tarif_JKK_Kantor)+Tarif_JKM+Tarif_JHT+Tarif_THR)+MIN((($C12*(1+0.1))*(1+Tunjangan_Pct)),Plafon_JP)*Tarif_JP+MIN(MAX((($C12*(1+0.1))*(1+Tunjangan_Pct)),IF($D12="Padang",UMP_Padang,UMK_Pekanbaru)),Plafon_JKN)*Tarif_JKN -> 17090450 | N12: =(($C12*(1+0.2))*(1+Tunjangan_Pct))*(1+IF($E12="Lapangan",Tarif_JKK_Lapangan,Tarif_JKK_Kantor)+Tarif_JKM+Tarif_JHT+Tarif_THR)+MIN((($C12*(1+0.2))*(1+Tunjangan_Pct)),Plafon_JP)*Tarif_JP+MIN(MAX((($C12*(1+0.2))*(1+Tunjangan_Pct)),IF($D12="Padang",UMP_Padang,UMK_Pekanbaru)),Plafon_JKN)*Tarif_JKN -> 18580334 | O12: =$F12*MAX(0,MIN(3,4-MAX(1,$I12+-3)))+$G12*MAX(0,MIN(9,13-MAX(MAX(1,$I12+-3),4))) -> 0 | P12: =$F12*MAX(0,MIN(3,4-MAX(1,$I12+-2)))+$G12*MAX(0,MIN(9,13-MAX(MAX(1,$I12+-2),4))) -> 0 | Q12: =$F12*MAX(0,MIN(3,4-MAX(1,$I12+-1)))+$G12*MAX(0,MIN(9,13-MAX(MAX(1,$I12+-1),4))) -> 0 | R12: =$F12*MAX(0,MIN(3,4-MAX(1,$I12+0)))+$G12*MAX(0,MIN(9,13-MAX(MAX(1,$I12+0),4))) -> 0 | S12: =$F12*MAX(0,MIN(3,4-MAX(1,$I12+1)))+$G12*MAX(0,MIN(9,13-MAX(MAX(1,$I12+1),4))) -> 0 | T12: =$F12*MAX(0,MIN(3,4-MAX(1,$I12+2)))+$G12*MAX(0,MIN(9,13-MAX(MAX(1,$I12+2),4))) -> 0 | U12: =$F12*MAX(0,MIN(3,4-MAX(1,$I12+3)))+$G12*MAX(0,MIN(9,13-MAX(MAX(1,$I12+3),4))) -> 0 | V12: =O12+$H12*MAX(0,MIN(12,25-MAX(MAX(1,$I12+-3),13))) -> 12 | W12: =P12+$H12*MAX(0,MIN(12,25-MAX(MAX(1,$I12+-2),13))) -> 12 | X12: =Q12+$H12*MAX(0,MIN(12,25-MAX(MAX(1,$I12+-1),13))) -> 12 | Y12: =R12+$H12*MAX(0,MIN(12,25-MAX(MAX(1,$I12+0),13))) -> 11 | Z12: =S12+$H12*MAX(0,MIN(12,25-MAX(MAX(1,$I12+1),13))) -> 10 | AA12: =T12+$H12*MAX(0,MIN(12,25-MAX(MAX(1,$I12+2),13))) -> 9 | AB12: =U12+$H12*MAX(0,MIN(12,25-MAX(MAX(1,$I12+3),13))) -> 8
A13: 8 | B13: ='Biaya Bulanan'!$C$33 -> Backend Engineer (Senior) | C13: ='Biaya Bulanan'!$K$33 -> 20000000 | D13: ='Biaya Bulanan'!$E$33 -> Pekanbaru | E13: ='Biaya Bulanan'!$H$33 -> Kantor | F13: ='Biaya Bulanan'!$V$33 -> 1 | G13: ='Biaya Bulanan'!$W$33 -> 1 | H13: ='Biaya Bulanan'!$X$33 -> 1 | I13: ='Biaya Bulanan'!$I$33 -> 1 | J13: =(($C13*(1+-0.2))*(1+Tunjangan_Pct))*(1+IF($E13="Lapangan",Tarif_JKK_Lapangan,Tarif_JKK_Kantor)+Tarif_JKM+Tarif_JHT+Tarif_THR)+MIN((($C13*(1+-0.2))*(1+Tunjangan_Pct)),Plafon_JP)*Tarif_JP+MIN(MAX((($C13*(1+-0.2))*(1+Tunjangan_Pct)),IF($D13="Padang",UMP_Padang,UMK_Pekanbaru)),Plafon_JKN)*Tarif_JKN -> 20566846 | K13: =(($C13*(1+-0.1))*(1+Tunjangan_Pct))*(1+IF($E13="Lapangan",Tarif_JKK_Lapangan,Tarif_JKK_Kantor)+Tarif_JKM+Tarif_JHT+Tarif_THR)+MIN((($C13*(1+-0.1))*(1+Tunjangan_Pct)),Plafon_JP)*Tarif_JP+MIN(MAX((($C13*(1+-0.1))*(1+Tunjangan_Pct)),IF($D13="Padang",UMP_Padang,UMK_Pekanbaru)),Plafon_JKN)*Tarif_JKN -> 23049986 | L13: =(($C13*(1+0))*(1+Tunjangan_Pct))*(1+IF($E13="Lapangan",Tarif_JKK_Lapangan,Tarif_JKK_Kantor)+Tarif_JKM+Tarif_JHT+Tarif_THR)+MIN((($C13*(1+0))*(1+Tunjangan_Pct)),Plafon_JP)*Tarif_JP+MIN(MAX((($C13*(1+0))*(1+Tunjangan_Pct)),IF($D13="Padang",UMP_Padang,UMK_Pekanbaru)),Plafon_JKN)*Tarif_JKN -> 25533126 | M13: =(($C13*(1+0.1))*(1+Tunjangan_Pct))*(1+IF($E13="Lapangan",Tarif_JKK_Lapangan,Tarif_JKK_Kantor)+Tarif_JKM+Tarif_JHT+Tarif_THR)+MIN((($C13*(1+0.1))*(1+Tunjangan_Pct)),Plafon_JP)*Tarif_JP+MIN(MAX((($C13*(1+0.1))*(1+Tunjangan_Pct)),IF($D13="Padang",UMP_Padang,UMK_Pekanbaru)),Plafon_JKN)*Tarif_JKN -> 28016266 | N13: =(($C13*(1+0.2))*(1+Tunjangan_Pct))*(1+IF($E13="Lapangan",Tarif_JKK_Lapangan,Tarif_JKK_Kantor)+Tarif_JKM+Tarif_JHT+Tarif_THR)+MIN((($C13*(1+0.2))*(1+Tunjangan_Pct)),Plafon_JP)*Tarif_JP+MIN(MAX((($C13*(1+0.2))*(1+Tunjangan_Pct)),IF($D13="Padang",UMP_Padang,UMK_Pekanbaru)),Plafon_JKN)*Tarif_JKN -> 30499406 | O13: =$F13*MAX(0,MIN(3,4-MAX(1,$I13+-3)))+$G13*MAX(0,MIN(9,13-MAX(MAX(1,$I13+-3),4))) -> 12 | P13: =$F13*MAX(0,MIN(3,4-MAX(1,$I13+-2)))+$G13*MAX(0,MIN(9,13-MAX(MAX(1,$I13+-2),4))) -> 12 | Q13: =$F13*MAX(0,MIN(3,4-MAX(1,$I13+-1)))+$G13*MAX(0,MIN(9,13-MAX(MAX(1,$I13+-1),4))) -> 12 | R13: =$F13*MAX(0,MIN(3,4-MAX(1,$I13+0)))+$G13*MAX(0,MIN(9,13-MAX(MAX(1,$I13+0),4))) -> 12 | S13: =$F13*MAX(0,MIN(3,4-MAX(1,$I13+1)))+$G13*MAX(0,MIN(9,13-MAX(MAX(1,$I13+1),4))) -> 11 | T13: =$F13*MAX(0,MIN(3,4-MAX(1,$I13+2)))+$G13*MAX(0,MIN(9,13-MAX(MAX(1,$I13+2),4))) -> 10 | U13: =$F13*MAX(0,MIN(3,4-MAX(1,$I13+3)))+$G13*MAX(0,MIN(9,13-MAX(MAX(1,$I13+3),4))) -> 9 | V13: =O13+$H13*MAX(0,MIN(12,25-MAX(MAX(1,$I13+-3),13))) -> 24 | W13: =P13+$H13*MAX(0,MIN(12,25-MAX(MAX(1,$I13+-2),13))) -> 24 | X13: =Q13+$H13*MAX(0,MIN(12,25-MAX(MAX(1,$I13+-1),13))) -> 24 | Y13: =R13+$H13*MAX(0,MIN(12,25-MAX(MAX(1,$I13+0),13))) -> 24 | Z13: =S13+$H13*MAX(0,MIN(12,25-MAX(MAX(1,$I13+1),13))) -> 23 | AA13: =T13+$H13*MAX(0,MIN(12,25-MAX(MAX(1,$I13+2),13))) -> 22 | AB13: =U13+$H13*MAX(0,MIN(12,25-MAX(MAX(1,$I13+3),13))) -> 21
A14: 9 | B14: ='Biaya Bulanan'!$C$34 -> Backend Engineer (Senior) - gelombang 2 | C14: ='Biaya Bulanan'!$K$34 -> 20000000 | D14: ='Biaya Bulanan'!$E$34 -> Pekanbaru | E14: ='Biaya Bulanan'!$H$34 -> Kantor | F14: ='Biaya Bulanan'!$V$34 -> 0 | G14: ='Biaya Bulanan'!$W$34 -> 0 | H14: ='Biaya Bulanan'!$X$34 -> 1 | I14: ='Biaya Bulanan'!$I$34 -> 19 | J14: =(($C14*(1+-0.2))*(1+Tunjangan_Pct))*(1+IF($E14="Lapangan",Tarif_JKK_Lapangan,Tarif_JKK_Kantor)+Tarif_JKM+Tarif_JHT+Tarif_THR)+MIN((($C14*(1+-0.2))*(1+Tunjangan_Pct)),Plafon_JP)*Tarif_JP+MIN(MAX((($C14*(1+-0.2))*(1+Tunjangan_Pct)),IF($D14="Padang",UMP_Padang,UMK_Pekanbaru)),Plafon_JKN)*Tarif_JKN -> 20566846 | K14: =(($C14*(1+-0.1))*(1+Tunjangan_Pct))*(1+IF($E14="Lapangan",Tarif_JKK_Lapangan,Tarif_JKK_Kantor)+Tarif_JKM+Tarif_JHT+Tarif_THR)+MIN((($C14*(1+-0.1))*(1+Tunjangan_Pct)),Plafon_JP)*Tarif_JP+MIN(MAX((($C14*(1+-0.1))*(1+Tunjangan_Pct)),IF($D14="Padang",UMP_Padang,UMK_Pekanbaru)),Plafon_JKN)*Tarif_JKN -> 23049986 | L14: =(($C14*(1+0))*(1+Tunjangan_Pct))*(1+IF($E14="Lapangan",Tarif_JKK_Lapangan,Tarif_JKK_Kantor)+Tarif_JKM+Tarif_JHT+Tarif_THR)+MIN((($C14*(1+0))*(1+Tunjangan_Pct)),Plafon_JP)*Tarif_JP+MIN(MAX((($C14*(1+0))*(1+Tunjangan_Pct)),IF($D14="Padang",UMP_Padang,UMK_Pekanbaru)),Plafon_JKN)*Tarif_JKN -> 25533126 | M14: =(($C14*(1+0.1))*(1+Tunjangan_Pct))*(1+IF($E14="Lapangan",Tarif_JKK_Lapangan,Tarif_JKK_Kantor)+Tarif_JKM+Tarif_JHT+Tarif_THR)+MIN((($C14*(1+0.1))*(1+Tunjangan_Pct)),Plafon_JP)*Tarif_JP+MIN(MAX((($C14*(1+0.1))*(1+Tunjangan_Pct)),IF($D14="Padang",UMP_Padang,UMK_Pekanbaru)),Plafon_JKN)*Tarif_JKN -> 28016266 | N14: =(($C14*(1+0.2))*(1+Tunjangan_Pct))*(1+IF($E14="Lapangan",Tarif_JKK_Lapangan,Tarif_JKK_Kantor)+Tarif_JKM+Tarif_JHT+Tarif_THR)+MIN((($C14*(1+0.2))*(1+Tunjangan_Pct)),Plafon_JP)*Tarif_JP+MIN(MAX((($C14*(1+0.2))*(1+Tunjangan_Pct)),IF($D14="Padang",UMP_Padang,UMK_Pekanbaru)),Plafon_JKN)*Tarif_JKN -> 30499406 | O14: =$F14*MAX(0,MIN(3,4-MAX(1,$I14+-3)))+$G14*MAX(0,MIN(9,13-MAX(MAX(1,$I14+-3),4))) -> 0 | P14: =$F14*MAX(0,MIN(3,4-MAX(1,$I14+-2)))+$G14*MAX(0,MIN(9,13-MAX(MAX(1,$I14+-2),4))) -> 0 | Q14: =$F14*MAX(0,MIN(3,4-MAX(1,$I14+-1)))+$G14*MAX(0,MIN(9,13-MAX(MAX(1,$I14+-1),4))) -> 0 | R14: =$F14*MAX(0,MIN(3,4-MAX(1,$I14+0)))+$G14*MAX(0,MIN(9,13-MAX(MAX(1,$I14+0),4))) -> 0 | S14: =$F14*MAX(0,MIN(3,4-MAX(1,$I14+1)))+$G14*MAX(0,MIN(9,13-MAX(MAX(1,$I14+1),4))) -> 0 | T14: =$F14*MAX(0,MIN(3,4-MAX(1,$I14+2)))+$G14*MAX(0,MIN(9,13-MAX(MAX(1,$I14+2),4))) -> 0 | U14: =$F14*MAX(0,MIN(3,4-MAX(1,$I14+3)))+$G14*MAX(0,MIN(9,13-MAX(MAX(1,$I14+3),4))) -> 0 | V14: =O14+$H14*MAX(0,MIN(12,25-MAX(MAX(1,$I14+-3),13))) -> 9 | W14: =P14+$H14*MAX(0,MIN(12,25-MAX(MAX(1,$I14+-2),13))) -> 8 | X14: =Q14+$H14*MAX(0,MIN(12,25-MAX(MAX(1,$I14+-1),13))) -> 7 | Y14: =R14+$H14*MAX(0,MIN(12,25-MAX(MAX(1,$I14+0),13))) -> 6 | Z14: =S14+$H14*MAX(0,MIN(12,25-MAX(MAX(1,$I14+1),13))) -> 5 | AA14: =T14+$H14*MAX(0,MIN(12,25-MAX(MAX(1,$I14+2),13))) -> 4 | AB14: =U14+$H14*MAX(0,MIN(12,25-MAX(MAX(1,$I14+3),13))) -> 3
A15: 10 | B15: ='Biaya Bulanan'!$C$35 -> Backend Engineer (Mid) | C15: ='Biaya Bulanan'!$K$35 -> 12000000 | D15: ='Biaya Bulanan'!$E$35 -> Pekanbaru | E15: ='Biaya Bulanan'!$H$35 -> Kantor | F15: ='Biaya Bulanan'!$V$35 -> 0 | G15: ='Biaya Bulanan'!$W$35 -> 1 | H15: ='Biaya Bulanan'!$X$35 -> 1 | I15: ='Biaya Bulanan'!$I$35 -> 4 | J15: =(($C15*(1+-0.2))*(1+Tunjangan_Pct))*(1+IF($E15="Lapangan",Tarif_JKK_Lapangan,Tarif_JKK_Kantor)+Tarif_JKM+Tarif_JHT+Tarif_THR)+MIN((($C15*(1+-0.2))*(1+Tunjangan_Pct)),Plafon_JP)*Tarif_JP+MIN(MAX((($C15*(1+-0.2))*(1+Tunjangan_Pct)),IF($D15="Padang",UMP_Padang,UMK_Pekanbaru)),Plafon_JKN)*Tarif_JKN -> 12552672 | K15: =(($C15*(1+-0.1))*(1+Tunjangan_Pct))*(1+IF($E15="Lapangan",Tarif_JKK_Lapangan,Tarif_JKK_Kantor)+Tarif_JKM+Tarif_JHT+Tarif_THR)+MIN((($C15*(1+-0.1))*(1+Tunjangan_Pct)),Plafon_JP)*Tarif_JP+MIN(MAX((($C15*(1+-0.1))*(1+Tunjangan_Pct)),IF($D15="Padang",UMP_Padang,UMK_Pekanbaru)),Plafon_JKN)*Tarif_JKN -> 14105882 | L15: =(($C15*(1+0))*(1+Tunjangan_Pct))*(1+IF($E15="Lapangan",Tarif_JKK_Lapangan,Tarif_JKK_Kantor)+Tarif_JKM+Tarif_JHT+Tarif_THR)+MIN((($C15*(1+0))*(1+Tunjangan_Pct)),Plafon_JP)*Tarif_JP+MIN(MAX((($C15*(1+0))*(1+Tunjangan_Pct)),IF($D15="Padang",UMP_Padang,UMK_Pekanbaru)),Plafon_JKN)*Tarif_JKN -> 15600566 | M15: =(($C15*(1+0.1))*(1+Tunjangan_Pct))*(1+IF($E15="Lapangan",Tarif_JKK_Lapangan,Tarif_JKK_Kantor)+Tarif_JKM+Tarif_JHT+Tarif_THR)+MIN((($C15*(1+0.1))*(1+Tunjangan_Pct)),Plafon_JP)*Tarif_JP+MIN(MAX((($C15*(1+0.1))*(1+Tunjangan_Pct)),IF($D15="Padang",UMP_Padang,UMK_Pekanbaru)),Plafon_JKN)*Tarif_JKN -> 17090450 | N15: =(($C15*(1+0.2))*(1+Tunjangan_Pct))*(1+IF($E15="Lapangan",Tarif_JKK_Lapangan,Tarif_JKK_Kantor)+Tarif_JKM+Tarif_JHT+Tarif_THR)+MIN((($C15*(1+0.2))*(1+Tunjangan_Pct)),Plafon_JP)*Tarif_JP+MIN(MAX((($C15*(1+0.2))*(1+Tunjangan_Pct)),IF($D15="Padang",UMP_Padang,UMK_Pekanbaru)),Plafon_JKN)*Tarif_JKN -> 18580334 | O15: =$F15*MAX(0,MIN(3,4-MAX(1,$I15+-3)))+$G15*MAX(0,MIN(9,13-MAX(MAX(1,$I15+-3),4))) -> 9 | P15: =$F15*MAX(0,MIN(3,4-MAX(1,$I15+-2)))+$G15*MAX(0,MIN(9,13-MAX(MAX(1,$I15+-2),4))) -> 9 | Q15: =$F15*MAX(0,MIN(3,4-MAX(1,$I15+-1)))+$G15*MAX(0,MIN(9,13-MAX(MAX(1,$I15+-1),4))) -> 9 | R15: =$F15*MAX(0,MIN(3,4-MAX(1,$I15+0)))+$G15*MAX(0,MIN(9,13-MAX(MAX(1,$I15+0),4))) -> 9 | S15: =$F15*MAX(0,MIN(3,4-MAX(1,$I15+1)))+$G15*MAX(0,MIN(9,13-MAX(MAX(1,$I15+1),4))) -> 8 | T15: =$F15*MAX(0,MIN(3,4-MAX(1,$I15+2)))+$G15*MAX(0,MIN(9,13-MAX(MAX(1,$I15+2),4))) -> 7 | U15: =$F15*MAX(0,MIN(3,4-MAX(1,$I15+3)))+$G15*MAX(0,MIN(9,13-MAX(MAX(1,$I15+3),4))) -> 6 | V15: =O15+$H15*MAX(0,MIN(12,25-MAX(MAX(1,$I15+-3),13))) -> 21 | W15: =P15+$H15*MAX(0,MIN(12,25-MAX(MAX(1,$I15+-2),13))) -> 21 | X15: =Q15+$H15*MAX(0,MIN(12,25-MAX(MAX(1,$I15+-1),13))) -> 21 | Y15: =R15+$H15*MAX(0,MIN(12,25-MAX(MAX(1,$I15+0),13))) -> 21 | Z15: =S15+$H15*MAX(0,MIN(12,25-MAX(MAX(1,$I15+1),13))) -> 20 | AA15: =T15+$H15*MAX(0,MIN(12,25-MAX(MAX(1,$I15+2),13))) -> 19 | AB15: =U15+$H15*MAX(0,MIN(12,25-MAX(MAX(1,$I15+3),13))) -> 18
A16: 11 | B16: ='Biaya Bulanan'!$C$36 -> Backend Engineer (Mid) - gelombang 2 | C16: ='Biaya Bulanan'!$K$36 -> 12000000 | D16: ='Biaya Bulanan'!$E$36 -> Pekanbaru | E16: ='Biaya Bulanan'!$H$36 -> Kantor | F16: ='Biaya Bulanan'!$V$36 -> 0 | G16: ='Biaya Bulanan'!$W$36 -> 0 | H16: ='Biaya Bulanan'!$X$36 -> 1 | I16: ='Biaya Bulanan'!$I$36 -> 13 | J16: =(($C16*(1+-0.2))*(1+Tunjangan_Pct))*(1+IF($E16="Lapangan",Tarif_JKK_Lapangan,Tarif_JKK_Kantor)+Tarif_JKM+Tarif_JHT+Tarif_THR)+MIN((($C16*(1+-0.2))*(1+Tunjangan_Pct)),Plafon_JP)*Tarif_JP+MIN(MAX((($C16*(1+-0.2))*(1+Tunjangan_Pct)),IF($D16="Padang",UMP_Padang,UMK_Pekanbaru)),Plafon_JKN)*Tarif_JKN -> 12552672 | K16: =(($C16*(1+-0.1))*(1+Tunjangan_Pct))*(1+IF($E16="Lapangan",Tarif_JKK_Lapangan,Tarif_JKK_Kantor)+Tarif_JKM+Tarif_JHT+Tarif_THR)+MIN((($C16*(1+-0.1))*(1+Tunjangan_Pct)),Plafon_JP)*Tarif_JP+MIN(MAX((($C16*(1+-0.1))*(1+Tunjangan_Pct)),IF($D16="Padang",UMP_Padang,UMK_Pekanbaru)),Plafon_JKN)*Tarif_JKN -> 14105882 | L16: =(($C16*(1+0))*(1+Tunjangan_Pct))*(1+IF($E16="Lapangan",Tarif_JKK_Lapangan,Tarif_JKK_Kantor)+Tarif_JKM+Tarif_JHT+Tarif_THR)+MIN((($C16*(1+0))*(1+Tunjangan_Pct)),Plafon_JP)*Tarif_JP+MIN(MAX((($C16*(1+0))*(1+Tunjangan_Pct)),IF($D16="Padang",UMP_Padang,UMK_Pekanbaru)),Plafon_JKN)*Tarif_JKN -> 15600566 | M16: =(($C16*(1+0.1))*(1+Tunjangan_Pct))*(1+IF($E16="Lapangan",Tarif_JKK_Lapangan,Tarif_JKK_Kantor)+Tarif_JKM+Tarif_JHT+Tarif_THR)+MIN((($C16*(1+0.1))*(1+Tunjangan_Pct)),Plafon_JP)*Tarif_JP+MIN(MAX((($C16*(1+0.1))*(1+Tunjangan_Pct)),IF($D16="Padang",UMP_Padang,UMK_Pekanbaru)),Plafon_JKN)*Tarif_JKN -> 17090450 | N16: =(($C16*(1+0.2))*(1+Tunjangan_Pct))*(1+IF($E16="Lapangan",Tarif_JKK_Lapangan,Tarif_JKK_Kantor)+Tarif_JKM+Tarif_JHT+Tarif_THR)+MIN((($C16*(1+0.2))*(1+Tunjangan_Pct)),Plafon_JP)*Tarif_JP+MIN(MAX((($C16*(1+0.2))*(1+Tunjangan_Pct)),IF($D16="Padang",UMP_Padang,UMK_Pekanbaru)),Plafon_JKN)*Tarif_JKN -> 18580334 | O16: =$F16*MAX(0,MIN(3,4-MAX(1,$I16+-3)))+$G16*MAX(0,MIN(9,13-MAX(MAX(1,$I16+-3),4))) -> 0 | P16: =$F16*MAX(0,MIN(3,4-MAX(1,$I16+-2)))+$G16*MAX(0,MIN(9,13-MAX(MAX(1,$I16+-2),4))) -> 0 | Q16: =$F16*MAX(0,MIN(3,4-MAX(1,$I16+-1)))+$G16*MAX(0,MIN(9,13-MAX(MAX(1,$I16+-1),4))) -> 0 | R16: =$F16*MAX(0,MIN(3,4-MAX(1,$I16+0)))+$G16*MAX(0,MIN(9,13-MAX(MAX(1,$I16+0),4))) -> 0 | S16: =$F16*MAX(0,MIN(3,4-MAX(1,$I16+1)))+$G16*MAX(0,MIN(9,13-MAX(MAX(1,$I16+1),4))) -> 0 | T16: =$F16*MAX(0,MIN(3,4-MAX(1,$I16+2)))+$G16*MAX(0,MIN(9,13-MAX(MAX(1,$I16+2),4))) -> 0 | U16: =$F16*MAX(0,MIN(3,4-MAX(1,$I16+3)))+$G16*MAX(0,MIN(9,13-MAX(MAX(1,$I16+3),4))) -> 0 | V16: =O16+$H16*MAX(0,MIN(12,25-MAX(MAX(1,$I16+-3),13))) -> 12 | W16: =P16+$H16*MAX(0,MIN(12,25-MAX(MAX(1,$I16+-2),13))) -> 12 | X16: =Q16+$H16*MAX(0,MIN(12,25-MAX(MAX(1,$I16+-1),13))) -> 12 | Y16: =R16+$H16*MAX(0,MIN(12,25-MAX(MAX(1,$I16+0),13))) -> 12 | Z16: =S16+$H16*MAX(0,MIN(12,25-MAX(MAX(1,$I16+1),13))) -> 11 | AA16: =T16+$H16*MAX(0,MIN(12,25-MAX(MAX(1,$I16+2),13))) -> 10 | AB16: =U16+$H16*MAX(0,MIN(12,25-MAX(MAX(1,$I16+3),13))) -> 9
A17: 12 | B17: ='Biaya Bulanan'!$C$37 -> QA Engineer | C17: ='Biaya Bulanan'!$K$37 -> 10000000 | D17: ='Biaya Bulanan'!$E$37 -> Pekanbaru | E17: ='Biaya Bulanan'!$H$37 -> Kantor | F17: ='Biaya Bulanan'!$V$37 -> 0 | G17: ='Biaya Bulanan'!$W$37 -> 1 | H17: ='Biaya Bulanan'!$X$37 -> 1 | I17: ='Biaya Bulanan'!$I$37 -> 6 | J17: =(($C17*(1+-0.2))*(1+Tunjangan_Pct))*(1+IF($E17="Lapangan",Tarif_JKK_Lapangan,Tarif_JKK_Kantor)+Tarif_JKM+Tarif_JHT+Tarif_THR)+MIN((($C17*(1+-0.2))*(1+Tunjangan_Pct)),Plafon_JP)*Tarif_JP+MIN(MAX((($C17*(1+-0.2))*(1+Tunjangan_Pct)),IF($D17="Padang",UMP_Padang,UMK_Pekanbaru)),Plafon_JKN)*Tarif_JKN -> 10460560 | K17: =(($C17*(1+-0.1))*(1+Tunjangan_Pct))*(1+IF($E17="Lapangan",Tarif_JKK_Lapangan,Tarif_JKK_Kantor)+Tarif_JKM+Tarif_JHT+Tarif_THR)+MIN((($C17*(1+-0.1))*(1+Tunjangan_Pct)),Plafon_JP)*Tarif_JP+MIN(MAX((($C17*(1+-0.1))*(1+Tunjangan_Pct)),IF($D17="Padang",UMP_Padang,UMK_Pekanbaru)),Plafon_JKN)*Tarif_JKN -> 11768130 | L17: =(($C17*(1+0))*(1+Tunjangan_Pct))*(1+IF($E17="Lapangan",Tarif_JKK_Lapangan,Tarif_JKK_Kantor)+Tarif_JKM+Tarif_JHT+Tarif_THR)+MIN((($C17*(1+0))*(1+Tunjangan_Pct)),Plafon_JP)*Tarif_JP+MIN(MAX((($C17*(1+0))*(1+Tunjangan_Pct)),IF($D17="Padang",UMP_Padang,UMK_Pekanbaru)),Plafon_JKN)*Tarif_JKN -> 13075700 | M17: =(($C17*(1+0.1))*(1+Tunjangan_Pct))*(1+IF($E17="Lapangan",Tarif_JKK_Lapangan,Tarif_JKK_Kantor)+Tarif_JKM+Tarif_JHT+Tarif_THR)+MIN((($C17*(1+0.1))*(1+Tunjangan_Pct)),Plafon_JP)*Tarif_JP+MIN(MAX((($C17*(1+0.1))*(1+Tunjangan_Pct)),IF($D17="Padang",UMP_Padang,UMK_Pekanbaru)),Plafon_JKN)*Tarif_JKN -> 14358996 | N17: =(($C17*(1+0.2))*(1+Tunjangan_Pct))*(1+IF($E17="Lapangan",Tarif_JKK_Lapangan,Tarif_JKK_Kantor)+Tarif_JKM+Tarif_JHT+Tarif_THR)+MIN((($C17*(1+0.2))*(1+Tunjangan_Pct)),Plafon_JP)*Tarif_JP+MIN(MAX((($C17*(1+0.2))*(1+Tunjangan_Pct)),IF($D17="Padang",UMP_Padang,UMK_Pekanbaru)),Plafon_JKN)*Tarif_JKN -> 15600566 | O17: =$F17*MAX(0,MIN(3,4-MAX(1,$I17+-3)))+$G17*MAX(0,MIN(9,13-MAX(MAX(1,$I17+-3),4))) -> 9 | P17: =$F17*MAX(0,MIN(3,4-MAX(1,$I17+-2)))+$G17*MAX(0,MIN(9,13-MAX(MAX(1,$I17+-2),4))) -> 9 | Q17: =$F17*MAX(0,MIN(3,4-MAX(1,$I17+-1)))+$G17*MAX(0,MIN(9,13-MAX(MAX(1,$I17+-1),4))) -> 8 | R17: =$F17*MAX(0,MIN(3,4-MAX(1,$I17+0)))+$G17*MAX(0,MIN(9,13-MAX(MAX(1,$I17+0),4))) -> 7 | S17: =$F17*MAX(0,MIN(3,4-MAX(1,$I17+1)))+$G17*MAX(0,MIN(9,13-MAX(MAX(1,$I17+1),4))) -> 6 | T17: =$F17*MAX(0,MIN(3,4-MAX(1,$I17+2)))+$G17*MAX(0,MIN(9,13-MAX(MAX(1,$I17+2),4))) -> 5 | U17: =$F17*MAX(0,MIN(3,4-MAX(1,$I17+3)))+$G17*MAX(0,MIN(9,13-MAX(MAX(1,$I17+3),4))) -> 4 | V17: =O17+$H17*MAX(0,MIN(12,25-MAX(MAX(1,$I17+-3),13))) -> 21 | W17: =P17+$H17*MAX(0,MIN(12,25-MAX(MAX(1,$I17+-2),13))) -> 21 | X17: =Q17+$H17*MAX(0,MIN(12,25-MAX(MAX(1,$I17+-1),13))) -> 20 | Y17: =R17+$H17*MAX(0,MIN(12,25-MAX(MAX(1,$I17+0),13))) -> 19 | Z17: =S17+$H17*MAX(0,MIN(12,25-MAX(MAX(1,$I17+1),13))) -> 18 | AA17: =T17+$H17*MAX(0,MIN(12,25-MAX(MAX(1,$I17+2),13))) -> 17 | AB17: =U17+$H17*MAX(0,MIN(12,25-MAX(MAX(1,$I17+3),13))) -> 16
A18: 13 | B18: ='Biaya Bulanan'!$C$38 -> QA Engineer - gelombang 2 | C18: ='Biaya Bulanan'!$K$38 -> 10000000 | D18: ='Biaya Bulanan'!$E$38 -> Pekanbaru | E18: ='Biaya Bulanan'!$H$38 -> Kantor | F18: ='Biaya Bulanan'!$V$38 -> 0 | G18: ='Biaya Bulanan'!$W$38 -> 0 | H18: ='Biaya Bulanan'!$X$38 -> 1 | I18: ='Biaya Bulanan'!$I$38 -> 15 | J18: =(($C18*(1+-0.2))*(1+Tunjangan_Pct))*(1+IF($E18="Lapangan",Tarif_JKK_Lapangan,Tarif_JKK_Kantor)+Tarif_JKM+Tarif_JHT+Tarif_THR)+MIN((($C18*(1+-0.2))*(1+Tunjangan_Pct)),Plafon_JP)*Tarif_JP+MIN(MAX((($C18*(1+-0.2))*(1+Tunjangan_Pct)),IF($D18="Padang",UMP_Padang,UMK_Pekanbaru)),Plafon_JKN)*Tarif_JKN -> 10460560 | K18: =(($C18*(1+-0.1))*(1+Tunjangan_Pct))*(1+IF($E18="Lapangan",Tarif_JKK_Lapangan,Tarif_JKK_Kantor)+Tarif_JKM+Tarif_JHT+Tarif_THR)+MIN((($C18*(1+-0.1))*(1+Tunjangan_Pct)),Plafon_JP)*Tarif_JP+MIN(MAX((($C18*(1+-0.1))*(1+Tunjangan_Pct)),IF($D18="Padang",UMP_Padang,UMK_Pekanbaru)),Plafon_JKN)*Tarif_JKN -> 11768130 | L18: =(($C18*(1+0))*(1+Tunjangan_Pct))*(1+IF($E18="Lapangan",Tarif_JKK_Lapangan,Tarif_JKK_Kantor)+Tarif_JKM+Tarif_JHT+Tarif_THR)+MIN((($C18*(1+0))*(1+Tunjangan_Pct)),Plafon_JP)*Tarif_JP+MIN(MAX((($C18*(1+0))*(1+Tunjangan_Pct)),IF($D18="Padang",UMP_Padang,UMK_Pekanbaru)),Plafon_JKN)*Tarif_JKN -> 13075700 | M18: =(($C18*(1+0.1))*(1+Tunjangan_Pct))*(1+IF($E18="Lapangan",Tarif_JKK_Lapangan,Tarif_JKK_Kantor)+Tarif_JKM+Tarif_JHT+Tarif_THR)+MIN((($C18*(1+0.1))*(1+Tunjangan_Pct)),Plafon_JP)*Tarif_JP+MIN(MAX((($C18*(1+0.1))*(1+Tunjangan_Pct)),IF($D18="Padang",UMP_Padang,UMK_Pekanbaru)),Plafon_JKN)*Tarif_JKN -> 14358996 | N18: =(($C18*(1+0.2))*(1+Tunjangan_Pct))*(1+IF($E18="Lapangan",Tarif_JKK_Lapangan,Tarif_JKK_Kantor)+Tarif_JKM+Tarif_JHT+Tarif_THR)+MIN((($C18*(1+0.2))*(1+Tunjangan_Pct)),Plafon_JP)*Tarif_JP+MIN(MAX((($C18*(1+0.2))*(1+Tunjangan_Pct)),IF($D18="Padang",UMP_Padang,UMK_Pekanbaru)),Plafon_JKN)*Tarif_JKN -> 15600566 | O18: =$F18*MAX(0,MIN(3,4-MAX(1,$I18+-3)))+$G18*MAX(0,MIN(9,13-MAX(MAX(1,$I18+-3),4))) -> 0 | P18: =$F18*MAX(0,MIN(3,4-MAX(1,$I18+-2)))+$G18*MAX(0,MIN(9,13-MAX(MAX(1,$I18+-2),4))) -> 0 | Q18: =$F18*MAX(0,MIN(3,4-MAX(1,$I18+-1)))+$G18*MAX(0,MIN(9,13-MAX(MAX(1,$I18+-1),4))) -> 0 | R18: =$F18*MAX(0,MIN(3,4-MAX(1,$I18+0)))+$G18*MAX(0,MIN(9,13-MAX(MAX(1,$I18+0),4))) -> 0 | S18: =$F18*MAX(0,MIN(3,4-MAX(1,$I18+1)))+$G18*MAX(0,MIN(9,13-MAX(MAX(1,$I18+1),4))) -> 0 | T18: =$F18*MAX(0,MIN(3,4-MAX(1,$I18+2)))+$G18*MAX(0,MIN(9,13-MAX(MAX(1,$I18+2),4))) -> 0 | U18: =$F18*MAX(0,MIN(3,4-MAX(1,$I18+3)))+$G18*MAX(0,MIN(9,13-MAX(MAX(1,$I18+3),4))) -> 0 | V18: =O18+$H18*MAX(0,MIN(12,25-MAX(MAX(1,$I18+-3),13))) -> 12 | W18: =P18+$H18*MAX(0,MIN(12,25-MAX(MAX(1,$I18+-2),13))) -> 12 | X18: =Q18+$H18*MAX(0,MIN(12,25-MAX(MAX(1,$I18+-1),13))) -> 11 | Y18: =R18+$H18*MAX(0,MIN(12,25-MAX(MAX(1,$I18+0),13))) -> 10 | Z18: =S18+$H18*MAX(0,MIN(12,25-MAX(MAX(1,$I18+1),13))) -> 9 | AA18: =T18+$H18*MAX(0,MIN(12,25-MAX(MAX(1,$I18+2),13))) -> 8 | AB18: =U18+$H18*MAX(0,MIN(12,25-MAX(MAX(1,$I18+3),13))) -> 7
A19: 14 | B19: ='Biaya Bulanan'!$C$39 -> Junior Software Engineer | C19: ='Biaya Bulanan'!$K$39 -> 7500000 | D19: ='Biaya Bulanan'!$E$39 -> Pekanbaru | E19: ='Biaya Bulanan'!$H$39 -> Kantor | F19: ='Biaya Bulanan'!$V$39 -> 0 | G19: ='Biaya Bulanan'!$W$39 -> 0 | H19: ='Biaya Bulanan'!$X$39 -> 1 | I19: ='Biaya Bulanan'!$I$39 -> 16 | J19: =(($C19*(1+-0.2))*(1+Tunjangan_Pct))*(1+IF($E19="Lapangan",Tarif_JKK_Lapangan,Tarif_JKK_Kantor)+Tarif_JKM+Tarif_JHT+Tarif_THR)+MIN((($C19*(1+-0.2))*(1+Tunjangan_Pct)),Plafon_JP)*Tarif_JP+MIN(MAX((($C19*(1+-0.2))*(1+Tunjangan_Pct)),IF($D19="Padang",UMP_Padang,UMK_Pekanbaru)),Plafon_JKN)*Tarif_JKN -> 7845420 | K19: =(($C19*(1+-0.1))*(1+Tunjangan_Pct))*(1+IF($E19="Lapangan",Tarif_JKK_Lapangan,Tarif_JKK_Kantor)+Tarif_JKM+Tarif_JHT+Tarif_THR)+MIN((($C19*(1+-0.1))*(1+Tunjangan_Pct)),Plafon_JP)*Tarif_JP+MIN(MAX((($C19*(1+-0.1))*(1+Tunjangan_Pct)),IF($D19="Padang",UMP_Padang,UMK_Pekanbaru)),Plafon_JKN)*Tarif_JKN -> 8826097.5 | L19: =(($C19*(1+0))*(1+Tunjangan_Pct))*(1+IF($E19="Lapangan",Tarif_JKK_Lapangan,Tarif_JKK_Kantor)+Tarif_JKM+Tarif_JHT+Tarif_THR)+MIN((($C19*(1+0))*(1+Tunjangan_Pct)),Plafon_JP)*Tarif_JP+MIN(MAX((($C19*(1+0))*(1+Tunjangan_Pct)),IF($D19="Padang",UMP_Padang,UMK_Pekanbaru)),Plafon_JKN)*Tarif_JKN -> 9806775 | M19: =(($C19*(1+0.1))*(1+Tunjangan_Pct))*(1+IF($E19="Lapangan",Tarif_JKK_Lapangan,Tarif_JKK_Kantor)+Tarif_JKM+Tarif_JHT+Tarif_THR)+MIN((($C19*(1+0.1))*(1+Tunjangan_Pct)),Plafon_JP)*Tarif_JP+MIN(MAX((($C19*(1+0.1))*(1+Tunjangan_Pct)),IF($D19="Padang",UMP_Padang,UMK_Pekanbaru)),Plafon_JKN)*Tarif_JKN -> 10787452 | N19: =(($C19*(1+0.2))*(1+Tunjangan_Pct))*(1+IF($E19="Lapangan",Tarif_JKK_Lapangan,Tarif_JKK_Kantor)+Tarif_JKM+Tarif_JHT+Tarif_THR)+MIN((($C19*(1+0.2))*(1+Tunjangan_Pct)),Plafon_JP)*Tarif_JP+MIN(MAX((($C19*(1+0.2))*(1+Tunjangan_Pct)),IF($D19="Padang",UMP_Padang,UMK_Pekanbaru)),Plafon_JKN)*Tarif_JKN -> 11768130 | O19: =$F19*MAX(0,MIN(3,4-MAX(1,$I19+-3)))+$G19*MAX(0,MIN(9,13-MAX(MAX(1,$I19+-3),4))) -> 0 | P19: =$F19*MAX(0,MIN(3,4-MAX(1,$I19+-2)))+$G19*MAX(0,MIN(9,13-MAX(MAX(1,$I19+-2),4))) -> 0 | Q19: =$F19*MAX(0,MIN(3,4-MAX(1,$I19+-1)))+$G19*MAX(0,MIN(9,13-MAX(MAX(1,$I19+-1),4))) -> 0 | R19: =$F19*MAX(0,MIN(3,4-MAX(1,$I19+0)))+$G19*MAX(0,MIN(9,13-MAX(MAX(1,$I19+0),4))) -> 0 | S19: =$F19*MAX(0,MIN(3,4-MAX(1,$I19+1)))+$G19*MAX(0,MIN(9,13-MAX(MAX(1,$I19+1),4))) -> 0 | T19: =$F19*MAX(0,MIN(3,4-MAX(1,$I19+2)))+$G19*MAX(0,MIN(9,13-MAX(MAX(1,$I19+2),4))) -> 0 | U19: =$F19*MAX(0,MIN(3,4-MAX(1,$I19+3)))+$G19*MAX(0,MIN(9,13-MAX(MAX(1,$I19+3),4))) -> 0 | V19: =O19+$H19*MAX(0,MIN(12,25-MAX(MAX(1,$I19+-3),13))) -> 12 | W19: =P19+$H19*MAX(0,MIN(12,25-MAX(MAX(1,$I19+-2),13))) -> 11 | X19: =Q19+$H19*MAX(0,MIN(12,25-MAX(MAX(1,$I19+-1),13))) -> 10 | Y19: =R19+$H19*MAX(0,MIN(12,25-MAX(MAX(1,$I19+0),13))) -> 9 | Z19: =S19+$H19*MAX(0,MIN(12,25-MAX(MAX(1,$I19+1),13))) -> 8 | AA19: =T19+$H19*MAX(0,MIN(12,25-MAX(MAX(1,$I19+2),13))) -> 7 | AB19: =U19+$H19*MAX(0,MIN(12,25-MAX(MAX(1,$I19+3),13))) -> 6
A20: 15 | B20: ='Biaya Bulanan'!$C$40 -> Junior Software Engineer - Padang | C20: ='Biaya Bulanan'!$K$40 -> 7000000 | D20: ='Biaya Bulanan'!$E$40 -> Padang | E20: ='Biaya Bulanan'!$H$40 -> Kantor | F20: ='Biaya Bulanan'!$V$40 -> 0 | G20: ='Biaya Bulanan'!$W$40 -> 0 | H20: ='Biaya Bulanan'!$X$40 -> 1 | I20: ='Biaya Bulanan'!$I$40 -> 18 | J20: =(($C20*(1+-0.2))*(1+Tunjangan_Pct))*(1+IF($E20="Lapangan",Tarif_JKK_Lapangan,Tarif_JKK_Kantor)+Tarif_JKM+Tarif_JHT+Tarif_THR)+MIN((($C20*(1+-0.2))*(1+Tunjangan_Pct)),Plafon_JP)*Tarif_JP+MIN(MAX((($C20*(1+-0.2))*(1+Tunjangan_Pct)),IF($D20="Padang",UMP_Padang,UMK_Pekanbaru)),Plafon_JKN)*Tarif_JKN -> 7322392 | K20: =(($C20*(1+-0.1))*(1+Tunjangan_Pct))*(1+IF($E20="Lapangan",Tarif_JKK_Lapangan,Tarif_JKK_Kantor)+Tarif_JKM+Tarif_JHT+Tarif_THR)+MIN((($C20*(1+-0.1))*(1+Tunjangan_Pct)),Plafon_JP)*Tarif_JP+MIN(MAX((($C20*(1+-0.1))*(1+Tunjangan_Pct)),IF($D20="Padang",UMP_Padang,UMK_Pekanbaru)),Plafon_JKN)*Tarif_JKN -> 8237691 | L20: =(($C20*(1+0))*(1+Tunjangan_Pct))*(1+IF($E20="Lapangan",Tarif_JKK_Lapangan,Tarif_JKK_Kantor)+Tarif_JKM+Tarif_JHT+Tarif_THR)+MIN((($C20*(1+0))*(1+Tunjangan_Pct)),Plafon_JP)*Tarif_JP+MIN(MAX((($C20*(1+0))*(1+Tunjangan_Pct)),IF($D20="Padang",UMP_Padang,UMK_Pekanbaru)),Plafon_JKN)*Tarif_JKN -> 9152990 | M20: =(($C20*(1+0.1))*(1+Tunjangan_Pct))*(1+IF($E20="Lapangan",Tarif_JKK_Lapangan,Tarif_JKK_Kantor)+Tarif_JKM+Tarif_JHT+Tarif_THR)+MIN((($C20*(1+0.1))*(1+Tunjangan_Pct)),Plafon_JP)*Tarif_JP+MIN(MAX((($C20*(1+0.1))*(1+Tunjangan_Pct)),IF($D20="Padang",UMP_Padang,UMK_Pekanbaru)),Plafon_JKN)*Tarif_JKN -> 10068289 | N20: =(($C20*(1+0.2))*(1+Tunjangan_Pct))*(1+IF($E20="Lapangan",Tarif_JKK_Lapangan,Tarif_JKK_Kantor)+Tarif_JKM+Tarif_JHT+Tarif_THR)+MIN((($C20*(1+0.2))*(1+Tunjangan_Pct)),Plafon_JP)*Tarif_JP+MIN(MAX((($C20*(1+0.2))*(1+Tunjangan_Pct)),IF($D20="Padang",UMP_Padang,UMK_Pekanbaru)),Plafon_JKN)*Tarif_JKN -> 10983588 | O20: =$F20*MAX(0,MIN(3,4-MAX(1,$I20+-3)))+$G20*MAX(0,MIN(9,13-MAX(MAX(1,$I20+-3),4))) -> 0 | P20: =$F20*MAX(0,MIN(3,4-MAX(1,$I20+-2)))+$G20*MAX(0,MIN(9,13-MAX(MAX(1,$I20+-2),4))) -> 0 | Q20: =$F20*MAX(0,MIN(3,4-MAX(1,$I20+-1)))+$G20*MAX(0,MIN(9,13-MAX(MAX(1,$I20+-1),4))) -> 0 | R20: =$F20*MAX(0,MIN(3,4-MAX(1,$I20+0)))+$G20*MAX(0,MIN(9,13-MAX(MAX(1,$I20+0),4))) -> 0 | S20: =$F20*MAX(0,MIN(3,4-MAX(1,$I20+1)))+$G20*MAX(0,MIN(9,13-MAX(MAX(1,$I20+1),4))) -> 0 | T20: =$F20*MAX(0,MIN(3,4-MAX(1,$I20+2)))+$G20*MAX(0,MIN(9,13-MAX(MAX(1,$I20+2),4))) -> 0 | U20: =$F20*MAX(0,MIN(3,4-MAX(1,$I20+3)))+$G20*MAX(0,MIN(9,13-MAX(MAX(1,$I20+3),4))) -> 0 | V20: =O20+$H20*MAX(0,MIN(12,25-MAX(MAX(1,$I20+-3),13))) -> 10 | W20: =P20+$H20*MAX(0,MIN(12,25-MAX(MAX(1,$I20+-2),13))) -> 9 | X20: =Q20+$H20*MAX(0,MIN(12,25-MAX(MAX(1,$I20+-1),13))) -> 8 | Y20: =R20+$H20*MAX(0,MIN(12,25-MAX(MAX(1,$I20+0),13))) -> 7 | Z20: =S20+$H20*MAX(0,MIN(12,25-MAX(MAX(1,$I20+1),13))) -> 6 | AA20: =T20+$H20*MAX(0,MIN(12,25-MAX(MAX(1,$I20+2),13))) -> 5 | AB20: =U20+$H20*MAX(0,MIN(12,25-MAX(MAX(1,$I20+3),13))) -> 4
A21: 16 | B21: ='Biaya Bulanan'!$C$41 -> Product Designer (UI/UX) | C21: ='Biaya Bulanan'!$K$41 -> 13000000 | D21: ='Biaya Bulanan'!$E$41 -> Pekanbaru | E21: ='Biaya Bulanan'!$H$41 -> Kantor | F21: ='Biaya Bulanan'!$V$41 -> 1 | G21: ='Biaya Bulanan'!$W$41 -> 1 | H21: ='Biaya Bulanan'!$X$41 -> 1 | I21: ='Biaya Bulanan'!$I$41 -> 2 | J21: =(($C21*(1+-0.2))*(1+Tunjangan_Pct))*(1+IF($E21="Lapangan",Tarif_JKK_Lapangan,Tarif_JKK_Kantor)+Tarif_JKM+Tarif_JHT+Tarif_THR)+MIN((($C21*(1+-0.2))*(1+Tunjangan_Pct)),Plafon_JP)*Tarif_JP+MIN(MAX((($C21*(1+-0.2))*(1+Tunjangan_Pct)),IF($D21="Padang",UMP_Padang,UMK_Pekanbaru)),Plafon_JKN)*Tarif_JKN -> 13591654 | K21: =(($C21*(1+-0.1))*(1+Tunjangan_Pct))*(1+IF($E21="Lapangan",Tarif_JKK_Lapangan,Tarif_JKK_Kantor)+Tarif_JKM+Tarif_JHT+Tarif_THR)+MIN((($C21*(1+-0.1))*(1+Tunjangan_Pct)),Plafon_JP)*Tarif_JP+MIN(MAX((($C21*(1+-0.1))*(1+Tunjangan_Pct)),IF($D21="Padang",UMP_Padang,UMK_Pekanbaru)),Plafon_JKN)*Tarif_JKN -> 15228095 | L21: =(($C21*(1+0))*(1+Tunjangan_Pct))*(1+IF($E21="Lapangan",Tarif_JKK_Lapangan,Tarif_JKK_Kantor)+Tarif_JKM+Tarif_JHT+Tarif_THR)+MIN((($C21*(1+0))*(1+Tunjangan_Pct)),Plafon_JP)*Tarif_JP+MIN(MAX((($C21*(1+0))*(1+Tunjangan_Pct)),IF($D21="Padang",UMP_Padang,UMK_Pekanbaru)),Plafon_JKN)*Tarif_JKN -> 16842136 | M21: =(($C21*(1+0.1))*(1+Tunjangan_Pct))*(1+IF($E21="Lapangan",Tarif_JKK_Lapangan,Tarif_JKK_Kantor)+Tarif_JKM+Tarif_JHT+Tarif_THR)+MIN((($C21*(1+0.1))*(1+Tunjangan_Pct)),Plafon_JP)*Tarif_JP+MIN(MAX((($C21*(1+0.1))*(1+Tunjangan_Pct)),IF($D21="Padang",UMP_Padang,UMK_Pekanbaru)),Plafon_JKN)*Tarif_JKN -> 18456177 | N21: =(($C21*(1+0.2))*(1+Tunjangan_Pct))*(1+IF($E21="Lapangan",Tarif_JKK_Lapangan,Tarif_JKK_Kantor)+Tarif_JKM+Tarif_JHT+Tarif_THR)+MIN((($C21*(1+0.2))*(1+Tunjangan_Pct)),Plafon_JP)*Tarif_JP+MIN(MAX((($C21*(1+0.2))*(1+Tunjangan_Pct)),IF($D21="Padang",UMP_Padang,UMK_Pekanbaru)),Plafon_JKN)*Tarif_JKN -> 20070218 | O21: =$F21*MAX(0,MIN(3,4-MAX(1,$I21+-3)))+$G21*MAX(0,MIN(9,13-MAX(MAX(1,$I21+-3),4))) -> 12 | P21: =$F21*MAX(0,MIN(3,4-MAX(1,$I21+-2)))+$G21*MAX(0,MIN(9,13-MAX(MAX(1,$I21+-2),4))) -> 12 | Q21: =$F21*MAX(0,MIN(3,4-MAX(1,$I21+-1)))+$G21*MAX(0,MIN(9,13-MAX(MAX(1,$I21+-1),4))) -> 12 | R21: =$F21*MAX(0,MIN(3,4-MAX(1,$I21+0)))+$G21*MAX(0,MIN(9,13-MAX(MAX(1,$I21+0),4))) -> 11 | S21: =$F21*MAX(0,MIN(3,4-MAX(1,$I21+1)))+$G21*MAX(0,MIN(9,13-MAX(MAX(1,$I21+1),4))) -> 10 | T21: =$F21*MAX(0,MIN(3,4-MAX(1,$I21+2)))+$G21*MAX(0,MIN(9,13-MAX(MAX(1,$I21+2),4))) -> 9 | U21: =$F21*MAX(0,MIN(3,4-MAX(1,$I21+3)))+$G21*MAX(0,MIN(9,13-MAX(MAX(1,$I21+3),4))) -> 8 | V21: =O21+$H21*MAX(0,MIN(12,25-MAX(MAX(1,$I21+-3),13))) -> 24 | W21: =P21+$H21*MAX(0,MIN(12,25-MAX(MAX(1,$I21+-2),13))) -> 24 | X21: =Q21+$H21*MAX(0,MIN(12,25-MAX(MAX(1,$I21+-1),13))) -> 24 | Y21: =R21+$H21*MAX(0,MIN(12,25-MAX(MAX(1,$I21+0),13))) -> 23 | Z21: =S21+$H21*MAX(0,MIN(12,25-MAX(MAX(1,$I21+1),13))) -> 22 | AA21: =T21+$H21*MAX(0,MIN(12,25-MAX(MAX(1,$I21+2),13))) -> 21 | AB21: =U21+$H21*MAX(0,MIN(12,25-MAX(MAX(1,$I21+3),13))) -> 20
A22: 17 | B22: ='Biaya Bulanan'!$C$42 -> Product Designer (UI/UX) - gelombang 2 | C22: ='Biaya Bulanan'!$K$42 -> 13000000 | D22: ='Biaya Bulanan'!$E$42 -> Pekanbaru | E22: ='Biaya Bulanan'!$H$42 -> Kantor | F22: ='Biaya Bulanan'!$V$42 -> 0 | G22: ='Biaya Bulanan'!$W$42 -> 0 | H22: ='Biaya Bulanan'!$X$42 -> 1 | I22: ='Biaya Bulanan'!$I$42 -> 17 | J22: =(($C22*(1+-0.2))*(1+Tunjangan_Pct))*(1+IF($E22="Lapangan",Tarif_JKK_Lapangan,Tarif_JKK_Kantor)+Tarif_JKM+Tarif_JHT+Tarif_THR)+MIN((($C22*(1+-0.2))*(1+Tunjangan_Pct)),Plafon_JP)*Tarif_JP+MIN(MAX((($C22*(1+-0.2))*(1+Tunjangan_Pct)),IF($D22="Padang",UMP_Padang,UMK_Pekanbaru)),Plafon_JKN)*Tarif_JKN -> 13591654 | K22: =(($C22*(1+-0.1))*(1+Tunjangan_Pct))*(1+IF($E22="Lapangan",Tarif_JKK_Lapangan,Tarif_JKK_Kantor)+Tarif_JKM+Tarif_JHT+Tarif_THR)+MIN((($C22*(1+-0.1))*(1+Tunjangan_Pct)),Plafon_JP)*Tarif_JP+MIN(MAX((($C22*(1+-0.1))*(1+Tunjangan_Pct)),IF($D22="Padang",UMP_Padang,UMK_Pekanbaru)),Plafon_JKN)*Tarif_JKN -> 15228095 | L22: =(($C22*(1+0))*(1+Tunjangan_Pct))*(1+IF($E22="Lapangan",Tarif_JKK_Lapangan,Tarif_JKK_Kantor)+Tarif_JKM+Tarif_JHT+Tarif_THR)+MIN((($C22*(1+0))*(1+Tunjangan_Pct)),Plafon_JP)*Tarif_JP+MIN(MAX((($C22*(1+0))*(1+Tunjangan_Pct)),IF($D22="Padang",UMP_Padang,UMK_Pekanbaru)),Plafon_JKN)*Tarif_JKN -> 16842136 | M22: =(($C22*(1+0.1))*(1+Tunjangan_Pct))*(1+IF($E22="Lapangan",Tarif_JKK_Lapangan,Tarif_JKK_Kantor)+Tarif_JKM+Tarif_JHT+Tarif_THR)+MIN((($C22*(1+0.1))*(1+Tunjangan_Pct)),Plafon_JP)*Tarif_JP+MIN(MAX((($C22*(1+0.1))*(1+Tunjangan_Pct)),IF($D22="Padang",UMP_Padang,UMK_Pekanbaru)),Plafon_JKN)*Tarif_JKN -> 18456177 | N22: =(($C22*(1+0.2))*(1+Tunjangan_Pct))*(1+IF($E22="Lapangan",Tarif_JKK_Lapangan,Tarif_JKK_Kantor)+Tarif_JKM+Tarif_JHT+Tarif_THR)+MIN((($C22*(1+0.2))*(1+Tunjangan_Pct)),Plafon_JP)*Tarif_JP+MIN(MAX((($C22*(1+0.2))*(1+Tunjangan_Pct)),IF($D22="Padang",UMP_Padang,UMK_Pekanbaru)),Plafon_JKN)*Tarif_JKN -> 20070218 | O22: =$F22*MAX(0,MIN(3,4-MAX(1,$I22+-3)))+$G22*MAX(0,MIN(9,13-MAX(MAX(1,$I22+-3),4))) -> 0 | P22: =$F22*MAX(0,MIN(3,4-MAX(1,$I22+-2)))+$G22*MAX(0,MIN(9,13-MAX(MAX(1,$I22+-2),4))) -> 0 | Q22: =$F22*MAX(0,MIN(3,4-MAX(1,$I22+-1)))+$G22*MAX(0,MIN(9,13-MAX(MAX(1,$I22+-1),4))) -> 0 | R22: =$F22*MAX(0,MIN(3,4-MAX(1,$I22+0)))+$G22*MAX(0,MIN(9,13-MAX(MAX(1,$I22+0),4))) -> 0 | S22: =$F22*MAX(0,MIN(3,4-MAX(1,$I22+1)))+$G22*MAX(0,MIN(9,13-MAX(MAX(1,$I22+1),4))) -> 0 | T22: =$F22*MAX(0,MIN(3,4-MAX(1,$I22+2)))+$G22*MAX(0,MIN(9,13-MAX(MAX(1,$I22+2),4))) -> 0 | U22: =$F22*MAX(0,MIN(3,4-MAX(1,$I22+3)))+$G22*MAX(0,MIN(9,13-MAX(MAX(1,$I22+3),4))) -> 0 | V22: =O22+$H22*MAX(0,MIN(12,25-MAX(MAX(1,$I22+-3),13))) -> 11 | W22: =P22+$H22*MAX(0,MIN(12,25-MAX(MAX(1,$I22+-2),13))) -> 10 | X22: =Q22+$H22*MAX(0,MIN(12,25-MAX(MAX(1,$I22+-1),13))) -> 9 | Y22: =R22+$H22*MAX(0,MIN(12,25-MAX(MAX(1,$I22+0),13))) -> 8 | Z22: =S22+$H22*MAX(0,MIN(12,25-MAX(MAX(1,$I22+1),13))) -> 7 | AA22: =T22+$H22*MAX(0,MIN(12,25-MAX(MAX(1,$I22+2),13))) -> 6 | AB22: =U22+$H22*MAX(0,MIN(12,25-MAX(MAX(1,$I22+3),13))) -> 5
A23: 18 | B23: ='Biaya Bulanan'!$C$43 -> Data Analyst | C23: ='Biaya Bulanan'!$K$43 -> 11500000 | D23: ='Biaya Bulanan'!$E$43 -> Pekanbaru | E23: ='Biaya Bulanan'!$H$43 -> Kantor | F23: ='Biaya Bulanan'!$V$43 -> 0 | G23: ='Biaya Bulanan'!$W$43 -> 0 | H23: ='Biaya Bulanan'!$X$43 -> 1 | I23: ='Biaya Bulanan'!$I$43 -> 13 | J23: =(($C23*(1+-0.2))*(1+Tunjangan_Pct))*(1+IF($E23="Lapangan",Tarif_JKK_Lapangan,Tarif_JKK_Kantor)+Tarif_JKM+Tarif_JHT+Tarif_THR)+MIN((($C23*(1+-0.2))*(1+Tunjangan_Pct)),Plafon_JP)*Tarif_JP+MIN(MAX((($C23*(1+-0.2))*(1+Tunjangan_Pct)),IF($D23="Padang",UMP_Padang,UMK_Pekanbaru)),Plafon_JKN)*Tarif_JKN -> 12029644 | K23: =(($C23*(1+-0.1))*(1+Tunjangan_Pct))*(1+IF($E23="Lapangan",Tarif_JKK_Lapangan,Tarif_JKK_Kantor)+Tarif_JKM+Tarif_JHT+Tarif_THR)+MIN((($C23*(1+-0.1))*(1+Tunjangan_Pct)),Plafon_JP)*Tarif_JP+MIN(MAX((($C23*(1+-0.1))*(1+Tunjangan_Pct)),IF($D23="Padang",UMP_Padang,UMK_Pekanbaru)),Plafon_JKN)*Tarif_JKN -> 13527376 | L23: =(($C23*(1+0))*(1+Tunjangan_Pct))*(1+IF($E23="Lapangan",Tarif_JKK_Lapangan,Tarif_JKK_Kantor)+Tarif_JKM+Tarif_JHT+Tarif_THR)+MIN((($C23*(1+0))*(1+Tunjangan_Pct)),Plafon_JP)*Tarif_JP+MIN(MAX((($C23*(1+0))*(1+Tunjangan_Pct)),IF($D23="Padang",UMP_Padang,UMK_Pekanbaru)),Plafon_JKN)*Tarif_JKN -> 14979781 | M23: =(($C23*(1+0.1))*(1+Tunjangan_Pct))*(1+IF($E23="Lapangan",Tarif_JKK_Lapangan,Tarif_JKK_Kantor)+Tarif_JKM+Tarif_JHT+Tarif_THR)+MIN((($C23*(1+0.1))*(1+Tunjangan_Pct)),Plafon_JP)*Tarif_JP+MIN(MAX((($C23*(1+0.1))*(1+Tunjangan_Pct)),IF($D23="Padang",UMP_Padang,UMK_Pekanbaru)),Plafon_JKN)*Tarif_JKN -> 16407586 | N23: =(($C23*(1+0.2))*(1+Tunjangan_Pct))*(1+IF($E23="Lapangan",Tarif_JKK_Lapangan,Tarif_JKK_Kantor)+Tarif_JKM+Tarif_JHT+Tarif_THR)+MIN((($C23*(1+0.2))*(1+Tunjangan_Pct)),Plafon_JP)*Tarif_JP+MIN(MAX((($C23*(1+0.2))*(1+Tunjangan_Pct)),IF($D23="Padang",UMP_Padang,UMK_Pekanbaru)),Plafon_JKN)*Tarif_JKN -> 17835392 | O23: =$F23*MAX(0,MIN(3,4-MAX(1,$I23+-3)))+$G23*MAX(0,MIN(9,13-MAX(MAX(1,$I23+-3),4))) -> 0 | P23: =$F23*MAX(0,MIN(3,4-MAX(1,$I23+-2)))+$G23*MAX(0,MIN(9,13-MAX(MAX(1,$I23+-2),4))) -> 0 | Q23: =$F23*MAX(0,MIN(3,4-MAX(1,$I23+-1)))+$G23*MAX(0,MIN(9,13-MAX(MAX(1,$I23+-1),4))) -> 0 | R23: =$F23*MAX(0,MIN(3,4-MAX(1,$I23+0)))+$G23*MAX(0,MIN(9,13-MAX(MAX(1,$I23+0),4))) -> 0 | S23: =$F23*MAX(0,MIN(3,4-MAX(1,$I23+1)))+$G23*MAX(0,MIN(9,13-MAX(MAX(1,$I23+1),4))) -> 0 | T23: =$F23*MAX(0,MIN(3,4-MAX(1,$I23+2)))+$G23*MAX(0,MIN(9,13-MAX(MAX(1,$I23+2),4))) -> 0 | U23: =$F23*MAX(0,MIN(3,4-MAX(1,$I23+3)))+$G23*MAX(0,MIN(9,13-MAX(MAX(1,$I23+3),4))) -> 0 | V23: =O23+$H23*MAX(0,MIN(12,25-MAX(MAX(1,$I23+-3),13))) -> 12 | W23: =P23+$H23*MAX(0,MIN(12,25-MAX(MAX(1,$I23+-2),13))) -> 12 | X23: =Q23+$H23*MAX(0,MIN(12,25-MAX(MAX(1,$I23+-1),13))) -> 12 | Y23: =R23+$H23*MAX(0,MIN(12,25-MAX(MAX(1,$I23+0),13))) -> 12 | Z23: =S23+$H23*MAX(0,MIN(12,25-MAX(MAX(1,$I23+1),13))) -> 11 | AA23: =T23+$H23*MAX(0,MIN(12,25-MAX(MAX(1,$I23+2),13))) -> 10 | AB23: =U23+$H23*MAX(0,MIN(12,25-MAX(MAX(1,$I23+3),13))) -> 9
A24: 19 | B24: ='Biaya Bulanan'!$C$44 -> Direktur Operasi (COO) | C24: ='Biaya Bulanan'!$K$44 -> 20000000 | D24: ='Biaya Bulanan'!$E$44 -> Pekanbaru | E24: ='Biaya Bulanan'!$H$44 -> Kantor | F24: ='Biaya Bulanan'!$V$44 -> 1 | G24: ='Biaya Bulanan'!$W$44 -> 1 | H24: ='Biaya Bulanan'!$X$44 -> 1 | I24: ='Biaya Bulanan'!$I$44 -> 1 | J24: =(($C24*(1+-0.2))*(1+Tunjangan_Pct))*(1+IF($E24="Lapangan",Tarif_JKK_Lapangan,Tarif_JKK_Kantor)+Tarif_JKM+Tarif_JHT+Tarif_THR)+MIN((($C24*(1+-0.2))*(1+Tunjangan_Pct)),Plafon_JP)*Tarif_JP+MIN(MAX((($C24*(1+-0.2))*(1+Tunjangan_Pct)),IF($D24="Padang",UMP_Padang,UMK_Pekanbaru)),Plafon_JKN)*Tarif_JKN -> 20566846 | K24: =(($C24*(1+-0.1))*(1+Tunjangan_Pct))*(1+IF($E24="Lapangan",Tarif_JKK_Lapangan,Tarif_JKK_Kantor)+Tarif_JKM+Tarif_JHT+Tarif_THR)+MIN((($C24*(1+-0.1))*(1+Tunjangan_Pct)),Plafon_JP)*Tarif_JP+MIN(MAX((($C24*(1+-0.1))*(1+Tunjangan_Pct)),IF($D24="Padang",UMP_Padang,UMK_Pekanbaru)),Plafon_JKN)*Tarif_JKN -> 23049986 | L24: =(($C24*(1+0))*(1+Tunjangan_Pct))*(1+IF($E24="Lapangan",Tarif_JKK_Lapangan,Tarif_JKK_Kantor)+Tarif_JKM+Tarif_JHT+Tarif_THR)+MIN((($C24*(1+0))*(1+Tunjangan_Pct)),Plafon_JP)*Tarif_JP+MIN(MAX((($C24*(1+0))*(1+Tunjangan_Pct)),IF($D24="Padang",UMP_Padang,UMK_Pekanbaru)),Plafon_JKN)*Tarif_JKN -> 25533126 | M24: =(($C24*(1+0.1))*(1+Tunjangan_Pct))*(1+IF($E24="Lapangan",Tarif_JKK_Lapangan,Tarif_JKK_Kantor)+Tarif_JKM+Tarif_JHT+Tarif_THR)+MIN((($C24*(1+0.1))*(1+Tunjangan_Pct)),Plafon_JP)*Tarif_JP+MIN(MAX((($C24*(1+0.1))*(1+Tunjangan_Pct)),IF($D24="Padang",UMP_Padang,UMK_Pekanbaru)),Plafon_JKN)*Tarif_JKN -> 28016266 | N24: =(($C24*(1+0.2))*(1+Tunjangan_Pct))*(1+IF($E24="Lapangan",Tarif_JKK_Lapangan,Tarif_JKK_Kantor)+Tarif_JKM+Tarif_JHT+Tarif_THR)+MIN((($C24*(1+0.2))*(1+Tunjangan_Pct)),Plafon_JP)*Tarif_JP+MIN(MAX((($C24*(1+0.2))*(1+Tunjangan_Pct)),IF($D24="Padang",UMP_Padang,UMK_Pekanbaru)),Plafon_JKN)*Tarif_JKN -> 30499406 | O24: =$F24*MAX(0,MIN(3,4-MAX(1,$I24+-3)))+$G24*MAX(0,MIN(9,13-MAX(MAX(1,$I24+-3),4))) -> 12 | P24: =$F24*MAX(0,MIN(3,4-MAX(1,$I24+-2)))+$G24*MAX(0,MIN(9,13-MAX(MAX(1,$I24+-2),4))) -> 12 | Q24: =$F24*MAX(0,MIN(3,4-MAX(1,$I24+-1)))+$G24*MAX(0,MIN(9,13-MAX(MAX(1,$I24+-1),4))) -> 12 | R24: =$F24*MAX(0,MIN(3,4-MAX(1,$I24+0)))+$G24*MAX(0,MIN(9,13-MAX(MAX(1,$I24+0),4))) -> 12 | S24: =$F24*MAX(0,MIN(3,4-MAX(1,$I24+1)))+$G24*MAX(0,MIN(9,13-MAX(MAX(1,$I24+1),4))) -> 11 | T24: =$F24*MAX(0,MIN(3,4-MAX(1,$I24+2)))+$G24*MAX(0,MIN(9,13-MAX(MAX(1,$I24+2),4))) -> 10 | U24: =$F24*MAX(0,MIN(3,4-MAX(1,$I24+3)))+$G24*MAX(0,MIN(9,13-MAX(MAX(1,$I24+3),4))) -> 9 | V24: =O24+$H24*MAX(0,MIN(12,25-MAX(MAX(1,$I24+-3),13))) -> 24 | W24: =P24+$H24*MAX(0,MIN(12,25-MAX(MAX(1,$I24+-2),13))) -> 24 | X24: =Q24+$H24*MAX(0,MIN(12,25-MAX(MAX(1,$I24+-1),13))) -> 24 | Y24: =R24+$H24*MAX(0,MIN(12,25-MAX(MAX(1,$I24+0),13))) -> 24 | Z24: =S24+$H24*MAX(0,MIN(12,25-MAX(MAX(1,$I24+1),13))) -> 23 | AA24: =T24+$H24*MAX(0,MIN(12,25-MAX(MAX(1,$I24+2),13))) -> 22 | AB24: =U24+$H24*MAX(0,MIN(12,25-MAX(MAX(1,$I24+3),13))) -> 21
